Workbook

Sheet Payroll Calculations
A1: Basic Salary | B1: Position Allowance | C1: Meal Allowance | D1: Transport Allowance | E1: Overtime Pay | F1: THR (Religious Holiday Bonus) | G1: Bonus | H1: Gross Pay | I1: BPJS Kesehatan (Employee) | J1: BPJS TK JHT (Employee) | K1: BPJS TK JP (Employee) | L1: PPh 21 (Income Tax) | M1: Other Deductions | N1: Total Deductions | O1: Net Pay | P1: BPJS Kesehatan (Employer) | Q1: BPJS TK JHT (Employer) | R1: BPJS TK JP (Employer) | S1: BPJS TK JKK (Employer) | T1: BPJS TK JKM (Employer) | U1: Employer Contributions | V1: Cost to Company
A2: =5000000 -> 5000000 | B2: =A2*0.1 -> 500000 | C2: =20*25000 -> 500000 | D2: =20*20000 -> 400000 | E2: =1.5*(A2/173)*10 -> 433526.01 | F2: =A2 -> 5000000 | G2: =A2*0.2 -> 1000000 | H2: =SUM(A2:G2) -> 12833526 | I2: =H2*0.01 -> 128335.26 | J2: =H2*0.02 -> 256670.52 | K2: =H2*0.01 -> 128335.26 | L2: =H2*0.05 -> 641676.3 | M2: =100000 -> 100000 | N2: =SUM(I2:M2) -> 1255017.3 | O2: =H2-N2 -> 11578509 | P2: =H2*0.04 -> 513341.04 | Q2: =H2*0.037 -> 474840.46 | R2: =H2*0.02 -> 256670.52 | S2: =H2*0.0089 -> 114218.38 | T2: =H2*0.003 -> 38500.578 | U2: =SUM(Q2:U2) | V2: =H2+V2

Sheet Master Data
A1: Salary Slabs
A2: Min Salary | B2: Max Salary | C2: BPJS Kesehatan % | D2: PPh 21 %
A3: 0 | B3: 5000000 | C3: 0.01 | D3: 0.05
A4: 5000001 | B4: 10000000 | C4: 0.01 | D4: 0.1
A5: 10000001 | B5: 20000000 | C5: 0.01 | D5: 0.15
A7: Constants
A8: Item | B8: Value
A9: Meal Allowance Per Day | B9: 25000
A10: Transport Allowance Per Day | B10: 20000
A11: Standard Working Days | B11: 20
A12: Overtime Rate | B12: 1.5
A13: Working Hours Monthly | B13: 173

Sheet Employee Payroll
A1: Employee Name | B1: Basic Salary | C1: Position Allowance | D1: Meal Allowance | E1: Transport Allowance | F1: Overtime Pay | G1: Bonus | H1: Gross Pay | I1: BPJS Kesehatan | J1: PPh 21 | K1: Total Deductions | L1: Net Pay
A2: Alice | B2: 4500000 | C2: =B2*0.1 -> 450000 | D2: =20*25000 -> 500000 | E2: =20*20000 -> 400000 | F2: =1.5*(B2/173)*10 -> 390173.41 | G2: =B2*0.2 -> 900000 | H2: =SUM(B2:G2) -> 7140173.4 | I2: =_xludf.IFS( B2<=5000000, HLOOKUP(0, 'Master Data'!A3:D3, 3, TRUE)*H2, B2<=10000000, HLOOKUP(5000001, 'Master Data'!A4:D4, 3, TRUE)*H2, B2>10000000, HLOOKUP(10000001, 'Master Data'!A5:D5, 3, TRUE)*H2 ) -> #NAME? | J2: =_xludf.IFS( B2<=5000000, HLOOKUP(0, 'Master Data'!A3:D3, 4, TRUE)*H2, B2<=10000000, HLOOKUP(5000001, 'Master Data'!A4:D4, 4, TRUE)*H2, B2>10000000, HLOOKUP(10000001, 'Master Data'!A5:D5, 4, TRUE)*H2 ) -> #NAME? | K2: =SUM(I2:J2) -> #NAME? | L2: =H2-K2 -> #NAME?
A3: Bob | B3: 7000000 | C3: =B3*0.1 -> 700000 | D3: =20*25000 -> 500000 | E3: =20*20000 -> 400000 | F3: =1.5*(B3/173)*10 -> 606936.42 | G3: =B3*0.2 -> 1400000 | H3: =SUM(B3:G3) -> 10606936 | I3: =_xludf.IFS( B3<=5000000, HLOOKUP(0, 'Master Data'!A3:D3, 3, TRUE)*H3, B3<=10000000, HLOOKUP(5000001, 'Master Data'!A4:D4, 3, TRUE)*H3, B3>10000000, HLOOKUP(10000001, 'Master Data'!A5:D5, 3, TRUE)*H3 ) -> #NAME? | J3: =_xludf.IFS( B3<=5000000, HLOOKUP(0, 'Master Data'!A3:D3, 4, TRUE)*H3, B3<=10000000, HLOOKUP(5000001, 'Master Data'!A4:D4, 4, TRUE)*H3, B3>10000000, HLOOKUP(10000001, 'Master Data'!A5:D5, 4, TRUE)*H3 ) -> #NAME? | K3: =SUM(I3:J3) -> #NAME? | L3: =H3-K3 -> #NAME?
A4: Charlie | B4: 12000000 | C4: =B4*0.1 -> 1200000 | D4: =20*25000 -> 500000 | E4: =20*20000 -> 400000 | F4: =1.5*(B4/173)*10 -> 1040462.4 | G4: =B4*0.2 -> 2400000 | H4: =SUM(B4:G4) -> 17540462 | I4: =_xludf.IFS( B4<=5000000, HLOOKUP(0, 'Master Data'!A3:D3, 3, TRUE)*H4, B4<=10000000, HLOOKUP(5000001, 'Master Data'!A4:D4, 3, TRUE)*H4, B4>10000000, HLOOKUP(10000001, 'Master Data'!A5:D5, 3, TRUE)*H4 ) -> #NAME? | J4: =_xludf.IFS( B4<=5000000, HLOOKUP(0, 'Master Data'!A3:D3, 4, TRUE)*H4, B4<=10000000, HLOOKUP(5000001, 'Master Data'!A4:D4, 4, TRUE)*H4, B4>10000000, HLOOKUP(10000001, 'Master Data'!A5:D5, 4, TRUE)*H4 ) -> #NAME? | K4: =SUM(I4:J4) -> #NAME? | L4: =H4-K4 -> #NAME?
