Workbook

Sheet SHUI & PIT
A1: Taxable income | B1: PIT Rate | C1: PIT Deduct | E1: 0.1
A2: 0 | B2: 0.05 | C2: 0
A3: 5000000 | B3: 0.1 | C3: 250000
A4: 10000000 | B4: 0.15 | C4: 750000
A5: 18000000 | B5: 0.2 | C5: 1650000
A6: 32000000 | B6: 0.25 | C6: 3250000
A7: 52000000 | B7: 0.3 | C7: 5850000
A8: 80000000 | B8: 0.35 | C8: 9850000
B10: Statutory pay rate: | C10: 1800000 | D10: SI, HI | E10: Contribution rates | F10: SI | G10: HI | H10: UI | I10: TU
B11: Region-based minimum wages: | C11: 4160000 | D11: UI | E11: EE | F11: 0.08 | G11: 0.015 | H11: 0.01
B12: SHI salary contribution cap: | C12: =C10*20 -> 36000000 | E12: ER | F12: 0.175 | G12: 0.03 | H12: 0.01 | I12: 0.02
B13: UI salary contribution cap: | C13: =C11*20 -> 83200000
B16: SEIT | C16: Work location | D16: Total salary for Social Insurance, Health Insurance | E16: Total salary for Unemployment Insurance | F16: Social Insurance (Salary for SI x 25.5%) | G16: Health Insurance fee (Salary for HI x 4.5%) | H16: Unemployment Insurance (Salary for UI x 2%) | I16: Supplement payment (*) | K16: debt from last month | L16: Total of SI, HI, UI
I17: Supplement payment (*) | J17: HI
B18: 1 | C18: 2 | D18: 3 | E18: 4 | F18: 5 | G18: 6 | H18: 7 | I18: 8 | J18: 9 | K18: 10 | L18: 11
B19: 1 | C19: VNM - SEVN - HQ | D19: =SUMIF(#REF!,'SHUI & PIT'!$C19,#REF!)-D21 -> #REF! | E19: =SUMIF(#REF!,'SHUI & PIT'!$C19,#REF!)-E21 -> #REF! | F19: =SUMIF(#REF!,'SHUI & PIT'!$C19,#REF!)+SUMIF(#REF!,'SHUI & PIT'!$C19,#REF!)-F21 -> #REF! | G19: =SUMIF(#REF!,'SHUI & PIT'!$C19,#REF!)+SUMIF(#REF!,'SHUI & PIT'!$C19,#REF!)-G21 -> #REF! | H19: =SUMIF(#REF!,'SHUI & PIT'!$C19,#REF!)+SUMIF(#REF!,'SHUI & PIT'!$C19,#REF!)-H21 -> #REF! | L19: =ROUND(SUM(F19:H19),0) -> #REF!
B20: 2 | C20: VNM - Hanoi - Vinaconex Bldg. | D20: =SUMIF(#REF!,'SHUI & PIT'!$C20,#REF!) -> #REF! | E20: =SUMIF(#REF!,'SHUI & PIT'!$C20,#REF!) -> #REF! | F20: =SUMIF(#REF!,'SHUI & PIT'!$C20,#REF!)+SUMIF(#REF!,'SHUI & PIT'!$C20,#REF!) -> #REF! | G20: =SUMIF(#REF!,'SHUI & PIT'!$C20,#REF!)+SUMIF(#REF!,'SHUI & PIT'!$C20,#REF!) -> #REF! | H20: =SUMIF(#REF!,'SHUI & PIT'!$C20,#REF!)+SUMIF(#REF!,'SHUI & PIT'!$C20,#REF!) -> #REF! | L20: =ROUND(SUM(F20:H20),0) -> #REF!
B21: 3 | C21: 00247979 | D21: =SUMIF(#REF!,'SHUI & PIT'!$C$21,#REF!) -> #REF! | E21: =SUMIF(#REF!,'SHUI & PIT'!$C$21,#REF!) -> #REF! | F21: =SUMIF(#REF!,'SHUI & PIT'!$C21,#REF!)+SUMIF(#REF!,'SHUI & PIT'!$C21,#REF!) -> #REF! | G21: =SUMIF(#REF!,'SHUI & PIT'!$C21,#REF!)+SUMIF(#REF!,'SHUI & PIT'!$C21,#REF!) -> #REF! | H21: =SUMIF(#REF!,'SHUI & PIT'!$C21,#REF!)+SUMIF(#REF!,'SHUI & PIT'!$C21,#REF!) -> #REF! | L21: =ROUND(SUM(F21:H21),0) -> #REF!
B22: TOTAL PAID TO GOVERNEMNT | L22: =SUM(L19:L21) -> #REF!
B24: SEVL | C24: Work location | D24: Total salary for Social Insurance, Health Insurance | E24: Total salary for Unemployment Insurance | F24: Social Insurance (Salary for SI x 25.5%) | G24: Health Insurance fee (Salary for HI x 4.5%) | H24: Unemployment Insurance (Salary for UI x 2%) | I24: Supplement payment (*) | K24: debt from last month | L24: Total of SI, HI, UI
I25: Supplement payment (*) | J25: HI
B26: 1 | C26: 2 | D26: 3 | E26: 4 | F26: 5 | G26: 6 | H26: 7 | I26: 8 | J26: 9 | K26: 10 | L26: 11
B27: 1 | C27: VNM - SEVN - HQ | D27: =SUMIF(#REF!,'SHUI & PIT'!$C27,#REF!)-D29 -> #REF! | E27: =SUMIF(#REF!,'SHUI & PIT'!$C27,#REF!)-E29 -> #REF! | F27: =SUMIF(#REF!,'SHUI & PIT'!$C27,#REF!)+SUMIF(#REF!,'SHUI & PIT'!$C27,#REF!)-F29 -> #REF! | G27: =SUMIF(#REF!,'SHUI & PIT'!$C27,#REF!)+SUMIF(#REF!,'SHUI & PIT'!$C27,#REF!)-G29 -> #REF! | H27: =SUMIF(#REF!,'SHUI & PIT'!$C27,#REF!)+SUMIF(#REF!,'SHUI & PIT'!$C27,#REF!)-H29 -> #REF! | L27: =ROUND(SUM(F27:H27),0) -> #REF!
B28: 2 | C28: VNM - Hanoi - Vinaconex Bldg. | D28: =SUMIF(#REF!,'SHUI & PIT'!$C28,#REF!) -> #REF! | E28: =SUMIF(#REF!,'SHUI & PIT'!$C28,#REF!) -> #REF! | F28: =SUMIF(#REF!,'SHUI & PIT'!$C28,#REF!)+SUMIF(#REF!,'SHUI & PIT'!$C28,#REF!) -> #REF! | G28: =SUMIF(#REF!,'SHUI & PIT'!$C28,#REF!)+SUMIF(#REF!,'SHUI & PIT'!$C28,#REF!) -> #REF! | H28: =SUMIF(#REF!,'SHUI & PIT'!$C28,#REF!)+SUMIF(#REF!,'SHUI & PIT'!$C28,#REF!) -> #REF! | L28: =ROUND(SUM(F28:H28),0) -> #REF!
B29: 3 | C29: 00247979 | D29: =SUMIF(#REF!,'SHUI & PIT'!$C$21,#REF!) -> #REF! | E29: =SUMIF(#REF!,'SHUI & PIT'!$C$21,#REF!) -> #REF! | F29: =SUMIF(#REF!,'SHUI & PIT'!$C29,#REF!)+SUMIF(#REF!,'SHUI & PIT'!$C29,#REF!) -> #REF! | G29: =SUMIF(#REF!,'SHUI & PIT'!$C29,#REF!)+SUMIF(#REF!,'SHUI & PIT'!$C29,#REF!) -> #REF! | H29: =SUMIF(#REF!,'SHUI & PIT'!$C29,#REF!)+SUMIF(#REF!,'SHUI & PIT'!$C29,#REF!) -> #REF! | L29: =ROUND(SUM(F29:H29),0) -> #REF!
B30: TOTAL PAID TO GOVERNEMNT | L30: =SUM(L27:L29) -> #REF!
C38: Tính theo | D38: Căn cứ đóng BHXH | E38: Chịu thuế TNCN
B39: Responsibility | C39: Toàn bộ số tiền theo tháng | D39: Có | E39: Có
B40: Petrol | C40: Số ngày làm việc thực tế | D40: Không | E40: Có
B41: Parking | C41: Số ngày làm việc thực tế | D41: Không | E41: Có
B42: Support allowance | C42: Toàn bộ số tiền được gửi | D42: Không | E42: Có
B43: Retention allowance | C43: Toàn bộ số tiền được gửi | D43: Không | E43: Có
B44: Sales incentive | C44: Toàn bộ số tiền được gửi | D44: Không | E44: Có
B45: OT - PIT | C45: Số tiền được gửi theo Timesheet | D45: Không | E45: Có
B46: OT - Non PIT | C46: Số tiền được gửi theo Timesheet | D46: Không | E46: Không
B47: Meal allowance | C47: Số ngày làm việc thực tế | D47: Không | E47: Không
B48: Deduction of meal | C48: Số tiền được gửi theo Timesheet | D48: Không | E48: Không
B49: Phone | C49: Toàn bộ số tiền theo tháng | D49: Không | E49: Không
B50: Taxi | C50: Toàn bộ số tiền theo tháng | D50: Không | E50: Có
B51: Rewards | C51: Toàn bộ số tiền được gửi | D51: Không | E51: Có

Sheet SEVL
A1: 1 | B1: 2 | C1: 3 | D1: 4 | F1: 6 | G1: 7 | H1: 8 | I1: 9 | M1: 10 | N1: 11 | P1: 12 | W1: 17 | X1: 18 | Y1: 20 | Z1: 21 | AA1: 22 | AB1: 23 | AC1: 24 | AD1: 25 | AE1: 26 | AF1: 27 | AG1: 28 | AH1: 29 | AI1: 30 | AJ1: 31 | AK1: 32 | AL1: 33 | AM1: 34 | AN1: 35 | AV1: 36 | AW1: 37 | AX1: 38 | BC1: 39 | BD1: 40 | BE1: 41 | BF1: 42 | BG1: 43 | BH1: 44 | BI1: 45 | BJ1: 46 | BK1: 47 | BL1: 48 | BM1: 49 | BN1: 50 | BO1: 51 | BP1: 52 | BQ1: 53 | BR1: 54 | BS1: 55 | BT1: 56 | BU1: 57 | BV1: 58 | BW1: 59 | BX1: 60 | BY1: 61 | BZ1: 62 | CA1: 63 | CB1: 64 | CC1: 65 | CD1: 66 | CF1: 67 | CG1: 68 | CI1: 73 | CJ1: 69
Q2: Số ngày tt | R2: Total tháng | V2: Total tháng | BI2: =425700-29800000*1% -> 127700
C3: 45342 | G3: TN chịu thuế | H3: Miễn thuế TNCN | I3: 730k trở xuống thì miễn thuế | J3: TN chịu thuế | K3: TN chịu thuế | L3: TN chịu thuế | P3: Trả theo ngày thực tế làm việc | Q3: TN chịu thuế | R3: Miễn thuế TNCN | S3: 730k trở xuống thì miễn thuế | T3: TN chịu thuế | U3: TN chịu thuế | V3: TN chịu thuế | AF3: Công thức giống với cột TU ee -> bỏ thử | BN3: Thu nhập tính thuế | BO3: Thuế TNCN phải nộp | CJ3: Thu nhập chịu thuế
F4: =SUM(F7:F26) -> 371740000 | G4: =SUM(G7:G26) -> 12420000 | H4: =SUM(H7:H26) -> 9000000 | I4: =SUM(I7:I26) -> 8893000 | M4: =SUM(M7:M26) -> 3850 | N4: =SUM(N7:N26) -> 3726 | P4: =SUM(P7:P26) -> 364377500 | Q4: =SUM(Q7:Q26) -> 8981250 | R4: =SUM(R7:R26) -> 8677083.3 | S4: =SUM(S7:S26) -> 7001690.7 | W4: =SUM(W7:W26) -> 0 | X4: =SUM(X7:X26) -> 7125000 | Y4: =SUM(Y7:Y26) -> 0 | Z4: =SUM(Z7:Z26) -> 0 | AA4: =SUM(AA7:AA26) -> 0 | AB4: =SUM(AB7:AB26) -> 0 | AC4: =SUM(AC7:AC26) -> 0 | AD4: =SUM(AD7:AD26) -> 0 | ... AN4: =SUM(AN7:AN26) -> 0 | AO4: =SUM(AO7:AO139) -> 52.24 | AP4: =SUM(AP7:AP139) -> 15.17 | AQ4: =SUM(AQ7:AQ139) -> 10.08 | AR4: =SUM(AR7:AR139) -> 0 | AS4: =SUM(AS7:AS139) -> 0 | AT4: =SUM(AT7:AT139) -> 0 | AU4: =SUM(AU7:AU139) -> 0 | AV4: =SUM(AV7:AV26) -> 1723602.7 | AW4: =SUM(AW7:AW26) -> 1121649.5 | AX4: =SUM(AX7:AX26) -> 1989449.3 | BC4: =SUM(BC7:BC26) -> 5900702 | BD4: =SUM(BD7:BD26) -> 4.3475119e+08 | BE4: =SUM(BE7:BE26) -> 0 | BF4: =SUM(BF7:BF26) -> 0 | BG4: =SUM(BG7:BG26) -> 27135200 | BH4: =SUM(BH7:BH26) -> 5087850 | BI4: =SUM(BI7:BI26) -> 3781900 | BJ4: =SUM(BJ7:BJ26) -> 36004950 | ... CD4: =SUM(CD7:CD26) -> 2461658 | CF4: =SUM(CF7:CF105) -> 319000 | CG4: =SUM(CG7:CG26) -> 21.32 | CJ4: =SUM(CJ7:CJ26) -> 4.1661076e+08
A5: EMPLOYEE CODE | B5: EMPLOYEE NAME | C5: HIRE DATE | D5: NEW HIRE/ RESIGNEE/ LONG LEAVE | E5: Location | F5: Base Salary | G5: Gaz | H5: Phone Amount | I5: Meal | J5: Responsibility | K5: Parking | L5: Taxi allowance | M5: Standard whr | N5: Actual Working Hours incl. Paid leave | O5: Actual Working Hours. NOT incl. Paid leave | P5: Actual Basic salary | Q5: Gaz | R5: Phone Amount | S5: Meal | T5: Responsibility | U5: Parking | V5: Taxi allowance | W5: Recognition Bonus | X5: Other Income | Y5: Other Bonus | Z5: Bonus - STIP | AA5: Sign-on bonus | AB5: Retention Bonus | AC5: Marsh Insurance refund (Non-tax) | AD5: Adjustment | AE5: TU Participation | AF5: Trade Union Allowance | AG5: Goodwill | AH5: Sales Incentive | AI5: 13th month salary | AJ5: Referral Bonus | AK5: Severance allowance (Non-tax) | AL5: Notice Pay by ER | AM5: Reimbursement Payment | AN5: VN-Employer Tax | AO5: OT 1.5 Hours | AP5: OT 2 Hours | AQ5: OT 3 Hours | AR5: Night shif payment | AS5: OT Night shift wk day | AT5: OT Night shift off day | AU5: OT Ngiht shift Holiday | AV5: OT 1.5 Amount | AW5: OT 2 Amount | AX5: OT 3 Amount | AY5: Night shif amount | AZ5: OT Night shift wk day amount | BA5: OT Night shift off day amount | BB5: OT Ngiht shift Holiday amount | BC5: Total Overtime Amount | BD5: Actual Total Income | BE5: Unpaid Leave (Covid-19) | BF5: Ded. Outstanding A-Leave | BG5: Social Ins. - 8% | BH5: Medical Ins. - 1.5% | BI5: Unemployment Ins. - 1 % | BJ5: SI-HI-IU Total 10.5% | BK5: Employee Trade Union | BL5: Dependent No. | BM5: Dependent Amount | BN5: Tax Accessable Income | BO5: Monthly PIT | BP5: Other Deduction | BQ5: Reimbursement deduction | BR5: Marsh / Other Deduction | BS5: Total Deductions | BT5: Net Pay | BU5: Social Ins. - 17.5% | BV5: Medical Ins. - 3% | BW5: Unempt Ins. - 1% | BX5: MI 4.5% | BY5: SI-HI-UI Total 21.5% | BZ5: Trade Union ER 2% | CA5: Total Cost to Employer | CB5: Salary for SI | CC5: Salary for UI | CD5: OT Non-Taxable (Ref) | CE5: OT PIT for check | CF5: Meal allowance deduction for La Nga visit | CG5: OT Tài xế - giờ | CH5: OT tài xế tiền | CI5: La Nga không ăn cơm nhà máy | CJ5: Taxable Income
F6: =SUBTOTAL(9,F7:F55) -> 403960000 | G6: =SUBTOTAL(9,G7:G55) -> 12420000 | H6: =SUBTOTAL(9,H7:H55) -> 9700000 | I6: =SUBTOTAL(9,I7:I55) -> 8893000 | J6: =SUBTOTAL(9,J7:J55) -> 19170000 | K6: =SUBTOTAL(9,K7:K55) -> 4400000 | L6: =SUBTOTAL(9,L7:L55) -> 2500000 | M6: =SUBTOTAL(9,M7:M55) -> 4428 | ... CJ6: =SUBTOTAL(9,CJ7:CJ55) -> 4.5111397e+08
A7: 0639 | C7: 42461 | D7: =DATEDIF(C7,$C$3,"D") -> 2881 | E7: HCM | F7: 15710000 | G7: 0 | H7: 300000 | I7: 680000 | J7: 0 | K7: 0 | L7: 0 | M7: =_xlfn.XLOOKUP(A7,Main!$B$13:$B$1048576,Main!$D$13:$D$1048576,0,0)*8 -> 194 | N7: =_xlfn.XLOOKUP(A7,Main!$B$13:$B$1048576,Main!$BQ$13:$BQ$1048576,0,0) -> 194 | O7: =_xlfn.XLOOKUP(A7,Main!$B$13:$B$1048576,Main!$BR$13:$BR$1048576,0,0) -> 134 | P7: =ROUND(F7/M7*N7,0) -> 15710000 | Q7: =G7/M7*O7 -> 0 | R7: =IF(D7>=(M7/8),H7,H7/M7*N7) -> 300000 | S7: =IF(CI7="N",26500*(ROUND(O7/8,0)),(I7/M7*O7)-CF7) -> 150690.72 | T7: =J7 -> 0 | U7: =K7/M7*O7 -> 0 | V7: =IF(D7>=(M7/8),L7,L7/M7*N7) -> 0 | AE7: YES | AO7: =_xlfn.XLOOKUP($A7,Main!$B$13:$B$35,Main!BU$13:BU$35,0,0) -> 0 | AP7: =_xlfn.XLOOKUP($A7,Main!$B$13:$B$35,Main!BV$13:BV$35,0,0) -> 0 | AQ7: =_xlfn.XLOOKUP($A7,Main!$B$13:$B$35,Main!BW$13:BW$35,0,0) -> 0 | AR7: =_xlfn.XLOOKUP($A7,Main!$B$13:$B$35,Main!BX$13:BX$35,0,0) -> 0 | AS7: =_xlfn.XLOOKUP($A7,Main!$B$13:$B$35,Main!BY$13:BY$35,0,0) -> 0 | AT7: =_xlfn.XLOOKUP($A7,Main!$B$13:$B$35,Main!BZ$13:BZ$35,0,0) -> 0 | AU7: =_xlfn.XLOOKUP($A7,Main!$B$13:$B$35,Main!CA$13:CA$35,0,0) -> 0 | AV7: =$F7/$M7*AO7*150% -> 0 | AW7: =$F7/$M7*AP7*200% -> 0 | AX7: =$F7/$M7*AQ7*300% -> 0 | AY7: =$F7/$M7*AR7*30% -> 0 | AZ7: =$F7/$M7*AS7*210% -> 0 | BA7: =$F7/$M7*AT7*270% -> 0 | BB7: =$F7/$M7*AU7*390% -> 0 | BC7: =ROUND(SUM(AV7:BB7)+CH7,0) -> 558000 | BD7: =SUM(P7:AN7)+BC7 -> 16718691 | BG7: =ROUND($CB7*'SHUI & PIT'!$F$11,0) -> 1256800 | BH7: =ROUND($CB7*'SHUI & PIT'!$G$11,0) -> 235650 | BI7: =ROUND($CC7*'SHUI & PIT'!$H$11,0) -> 157100 | BJ7: =SUM(BG7:BI7) -> 1649550 | BK7: =IF(E7="La Nga",0,IF(E7="HCM",35000,IF(AE7="YES",IF($BG7>0,ROUND(MIN($CB7*1%,180000),0),0),0))) -> 35000 | BL7: =VLOOKUP(A7,'[1]Payroll master '!B$12:AD$160,29,0) -> 0 | BM7: =11000000+4400000*BL7 -> 11000000 | BN7: =ROUND(IF((CJ7-BJ7-BM7-BR7)<0,0,(CJ7-BJ7-BM7-BR7)),0) -> 3618450 | BO7: =ROUND((VLOOKUP(BN7,'SHUI & PIT'!$A$1:$C$8,2,1)*BN7-VLOOKUP(BN7,'SHUI & PIT'!$A$1:$C$8,3,1)),0) -> 180923 | BP7: =Y7 -> 0 | BS7: =BJ7+BO7+BP7+BR7+BE7+BF7+BQ7+BK7 -> 1865473 | BT7: =ROUND(IF((BD7-BS7)<0,0,(BD7-BS7)),0) -> 14853218 | BU7: =ROUND($CB7*'SHUI & PIT'!$F$12,0) -> 2749250 | BV7: =ROUND($CB7*'SHUI & PIT'!$G$12,0) -> 471300 | BW7: =ROUND($CC7*'SHUI & PIT'!$H$12,0) -> 157100 | BY7: =SUM(BU7:BX7) -> 3377650 | BZ7: =IF(BU7>0,ROUND($CB7*'SHUI & PIT'!$I$12,0),0) -> 314200 | CA7: =BD7+BY7-AC7+BZ7-BQ7 -> 20410541 | CB7: =IF(($F7+$T7)>='SHUI & PIT'!$C$12,'SHUI & PIT'!$C$12,($F7+$T7)) -> 15710000 | CC7: =IF(($F7+$T7)>='SHUI & PIT'!$C$13,'SHUI & PIT'!$C$13,($F7+$T7)) -> 15710000 | CD7: =ROUND(($F7/M7)*($AO7*0.5+$AP7+$AQ7*2+AR7*0.3+AS7*1.1+AT7*1.7+AU7*2.9),0) -> 0 | CE7: =BC7-CD7 -> 558000 | CF7: =_xlfn.XLOOKUP(A7,'[2]Termination and others'!B$12:B$33,'[2]Termination and others'!F$12:F$33,0,0) -> 319000 | CG7: =VLOOKUP(A7,Main!$B$13:$BN$405,65,0) -> 11.16 | CH7: =IF(50000<F7/M7,50000,F7/M7)*CG7 -> 558000 | CJ7: =BD7-R7-S7-AK7-CD7-AC7-BE7-BF7-BQ7 -> 16268000
A8: 11094 | C8: 43399 | D8: =DATEDIF(C8,$C$3,"D") -> 1943 | E8: HCM | F8: 19510000 | G8: 1200000 | H8: 500000 | I8: 680000 | J8: 0 | K8: 400000 | L8: 500000 | M8: =_xlfn.XLOOKUP(A8,Main!$B$13:$B$1048576,Main!$D$13:$D$1048576,0,0)*8 -> 192 | N8: =_xlfn.XLOOKUP(A8,Main!$B$13:$B$1048576,Main!$BQ$13:$BQ$1048576,0,0) -> 192 | O8: =_xlfn.XLOOKUP(A8,Main!$B$13:$B$1048576,Main!$BR$13:$BR$1048576,0,0) -> 152 | P8: =ROUND(F8/M8*N8,0) -> 19510000 | Q8: =G8/M8*O8 -> 950000 | R8: =IF(D8>=(M8/8),H8,H8/M8*N8) -> 500000 | S8: =IF(CI8="N",26500*(ROUND(O8/8,0)),(I8/M8*O8)-CF8) -> 538333.33 | T8: =J8 -> 0 | U8: =K8/M8*O8 -> 316666.67 | V8: =IF(D8>=(M8/8),L8,L8/M8*N8) -> 500000 | AE8: YES | AO8: =_xlfn.XLOOKUP($A8,Main!$B$13:$B$35,Main!BU$13:BU$35,0,0) -> 0 | AP8: =_xlfn.XLOOKUP($A8,Main!$B$13:$B$35,Main!BV$13:BV$35,0,0) -> 0 | AQ8: =_xlfn.XLOOKUP($A8,Main!$B$13:$B$35,Main!BW$13:BW$35,0,0) -> 0 | AR8: =_xlfn.XLOOKUP($A8,Main!$B$13:$B$35,Main!BX$13:BX$35,0,0) -> 0 | AS8: =_xlfn.XLOOKUP($A8,Main!$B$13:$B$35,Main!BY$13:BY$35,0,0) -> 0 | AT8: =_xlfn.XLOOKUP($A8,Main!$B$13:$B$35,Main!BZ$13:BZ$35,0,0) -> 0 | AU8: =_xlfn.XLOOKUP($A8,Main!$B$13:$B$35,Main!CA$13:CA$35,0,0) -> 0 | AV8: =$F8/$M8*AO8*150% -> 0 | AW8: =$F8/$M8*AP8*200% -> 0 | AX8: =$F8/$M8*AQ8*300% -> 0 | AY8: =$F8/$M8*AR8*30% -> 0 | AZ8: =$F8/$M8*AS8*210% -> 0 | BA8: =$F8/$M8*AT8*270% -> 0 | BB8: =$F8/$M8*AU8*390% -> 0 | BC8: =ROUND(SUM(AV8:BB8)+CH8,0) -> 0 | BD8: =SUM(P8:AN8)+BC8 -> 22315000 | BG8: =ROUND($CB8*'SHUI & PIT'!$F$11,0) -> 1560800 | BH8: =ROUND($CB8*'SHUI & PIT'!$G$11,0) -> 292650 | BI8: =ROUND($CC8*'SHUI & PIT'!$H$11,0) -> 195100 | BJ8: =SUM(BG8:BI8) -> 2048550 | BK8: =IF(E8="La Nga",0,IF(E8="HCM",35000,IF(AE8="YES",IF($BG8>0,ROUND(MIN($CB8*1%,180000),0),0),0))) -> 35000 | BL8: =VLOOKUP(A8,'[1]Payroll master '!B$12:AD$160,29,0) -> 4 | BM8: =11000000+4400000*BL8 -> 28600000 | BN8: =ROUND(IF((CJ8-BJ8-BM8-BR8)<0,0,(CJ8-BJ8-BM8-BR8)),0) -> 0 | BO8: =ROUND((VLOOKUP(BN8,'SHUI & PIT'!$A$1:$C$8,2,1)*BN8-VLOOKUP(BN8,'SHUI & PIT'!$A$1:$C$8,3,1)),0) -> 0 | BP8: =Y8 -> 0 | BS8: =BJ8+BO8+BP8+BR8+BE8+BF8+BQ8+BK8 -> 2083550 | BT8: =ROUND(IF((BD8-BS8)<0,0,(BD8-BS8)),0) -> 20231450 | BU8: =ROUND($CB8*'SHUI & PIT'!$F$12,0) -> 3414250 | BV8: =ROUND($CB8*'SHUI & PIT'!$G$12,0) -> 585300 | BW8: =ROUND($CC8*'SHUI & PIT'!$H$12,0) -> 195100 | BY8: =SUM(BU8:BX8) -> 4194650 | BZ8: =IF(BU8>0,ROUND($CB8*'SHUI & PIT'!$I$12,0),0) -> 390200 | CA8: =BD8+BY8-AC8+BZ8-BQ8 -> 26899850 | CB8: =IF(($F8+$T8)>='SHUI & PIT'!$C$12,'SHUI & PIT'!$C$12,($F8+$T8)) -> 19510000 | CC8: =IF(($F8+$T8)>='SHUI & PIT'!$C$13,'SHUI & PIT'!$C$13,($F8+$T8)) -> 19510000 | CD8: =ROUND(($F8/M8)*($AO8*0.5+$AP8+$AQ8*2+AR8*0.3+AS8*1.1+AT8*1.7+AU8*2.9),0) -> 0 | CE8: =BC8-CD8 -> 0 | CF8: =_xlfn.XLOOKUP(A8,'[2]Termination and others'!B$12:B$33,'[2]Termination and others'!F$12:F$33,0,0) -> 0 | CG8: =VLOOKUP(A8,Main!$B$13:$BN$405,65,0) -> 0 | CH8: =IF(50000<F8/M8,50000,F8/M8)*CG8 -> 0 | CJ8: =BD8-R8-S8-AK8-CD8-AC8-BE8-BF8-BQ8 -> 21276667
A9: 11126 | C9: 43479 | D9: =DATEDIF(C9,$C$3,"D") -> 1863 | E9: HCM | F9: 16690000 | G9: 1200000 | H9: 500000 | I9: 680000 | J9: 0 | K9: 400000 | L9: 500000 | M9: =_xlfn.XLOOKUP(A9,Main!$B$13:$B$1048576,Main!$D$13:$D$1048576,0,0)*8 -> 192 | N9: =_xlfn.XLOOKUP(A9,Main!$B$13:$B$1048576,Main!$BQ$13:$BQ$1048576,0,0) -> 192 | O9: =_xlfn.XLOOKUP(A9,Main!$B$13:$B$1048576,Main!$BR$13:$BR$1048576,0,0) -> 152 | P9: =ROUND(F9/M9*N9,0) -> 16690000 | Q9: =G9/M9*O9 -> 950000 | R9: =IF(D9>=(M9/8),H9,H9/M9*N9) -> 500000 | S9: =IF(CI9="N",26500*(ROUND(O9/8,0)),(I9/M9*O9)-CF9) -> 538333.33 | T9: =J9 -> 0 | U9: =K9/M9*O9 -> 316666.67 | V9: =IF(D9>=(M9/8),L9,L9/M9*N9) -> 500000 | AE9: YES | AO9: =_xlfn.XLOOKUP($A9,Main!$B$13:$B$35,Main!BU$13:BU$35,0,0) -> 0 | AP9: =_xlfn.XLOOKUP($A9,Main!$B$13:$B$35,Main!BV$13:BV$35,0,0) -> 0 | AQ9: =_xlfn.XLOOKUP($A9,Main!$B$13:$B$35,Main!BW$13:BW$35,0,0) -> 0 | AR9: =_xlfn.XLOOKUP($A9,Main!$B$13:$B$35,Main!BX$13:BX$35,0,0) -> 0 | AS9: =_xlfn.XLOOKUP($A9,Main!$B$13:$B$35,Main!BY$13:BY$35,0,0) -> 0 | AT9: =_xlfn.XLOOKUP($A9,Main!$B$13:$B$35,Main!BZ$13:BZ$35,0,0) -> 0 | AU9: =_xlfn.XLOOKUP($A9,Main!$B$13:$B$35,Main!CA$13:CA$35,0,0) -> 0 | AV9: =$F9/$M9*AO9*150% -> 0 | AW9: =$F9/$M9*AP9*200% -> 0 | AX9: =$F9/$M9*AQ9*300% -> 0 | AY9: =$F9/$M9*AR9*30% -> 0 | AZ9: =$F9/$M9*AS9*210% -> 0 | BA9: =$F9/$M9*AT9*270% -> 0 | BB9: =$F9/$M9*AU9*390% -> 0 | BC9: =ROUND(SUM(AV9:BB9)+CH9,0) -> 0 | BD9: =SUM(P9:AN9)+BC9 -> 19495000 | BG9: =ROUND($CB9*'SHUI & PIT'!$F$11,0) -> 1335200 | BH9: =ROUND($CB9*'SHUI & PIT'!$G$11,0) -> 250350 | BI9: =ROUND($CC9*'SHUI & PIT'!$H$11,0) -> 166900 | BJ9: =SUM(BG9:BI9) -> 1752450 | BK9: =IF(E9="La Nga",0,IF(E9="HCM",35000,IF(AE9="YES",IF($BG9>0,ROUND(MIN($CB9*1%,180000),0),0),0))) -> 35000 | BL9: =VLOOKUP(A9,'[1]Payroll master '!B$12:AD$160,29,0) -> 2 | BM9: =11000000+4400000*BL9 -> 19800000 | BN9: =ROUND(IF((CJ9-BJ9-BM9-BR9)<0,0,(CJ9-BJ9-BM9-BR9)),0) -> 0 | BO9: =ROUND((VLOOKUP(BN9,'SHUI & PIT'!$A$1:$C$8,2,1)*BN9-VLOOKUP(BN9,'SHUI & PIT'!$A$1:$C$8,3,1)),0) -> 0 | BP9: =Y9 -> 0 | BS9: =BJ9+BO9+BP9+BR9+BE9+BF9+BQ9+BK9 -> 1787450 | BT9: =ROUND(IF((BD9-BS9)<0,0,(BD9-BS9)),0) -> 17707550 | BU9: =ROUND($CB9*'SHUI & PIT'!$F$12,0) -> 2920750 | BV9: =ROUND($CB9*'SHUI & PIT'!$G$12,0) -> 500700 | BW9: =ROUND($CC9*'SHUI & PIT'!$H$12,0) -> 166900 | BY9: =SUM(BU9:BX9) -> 3588350 | BZ9: =IF(BU9>0,ROUND($CB9*'SHUI & PIT'!$I$12,0),0) -> 333800 | CA9: =BD9+BY9-AC9+BZ9-BQ9 -> 23417150 | CB9: =IF(($F9+$T9)>='SHUI & PIT'!$C$12,'SHUI & PIT'!$C$12,($F9+$T9)) -> 16690000 | CC9: =IF(($F9+$T9)>='SHUI & PIT'!$C$13,'SHUI & PIT'!$C$13,($F9+$T9)) -> 16690000 | CD9: =ROUND(($F9/M9)*($AO9*0.5+$AP9+$AQ9*2+AR9*0.3+AS9*1.1+AT9*1.7+AU9*2.9),0) -> 0 | CE9: =BC9-CD9 -> 0 | CF9: =_xlfn.XLOOKUP(A9,'[2]Termination and others'!B$12:B$33,'[2]Termination and others'!F$12:F$33,0,0) -> 0 | CG9: =VLOOKUP(A9,Main!$B$13:$BN$405,65,0) -> 0 | CH9: =IF(50000<F9/M9,50000,F9/M9)*CG9 -> 0 | CJ9: =BD9-R9-S9-AK9-CD9-AC9-BE9-BF9-BQ9 -> 18456667
A10: 11141 | C10: 43529 | D10: =DATEDIF(C10,$C$3,"D") -> 1813 | E10: HCM | F10: 12680000 | G10: 1200000 | H10: 500000 | I10: 680000 | J10: 1320000 | K10: 400000 | L10: 0 | M10: =_xlfn.XLOOKUP(A10,Main!$B$13:$B$1048576,Main!$D$13:$D$1048576,0,0)*8 -> 192 | N10: =_xlfn.XLOOKUP(A10,Main!$B$13:$B$1048576,Main!$BQ$13:$BQ$1048576,0,0) -> 192 | O10: =_xlfn.XLOOKUP(A10,Main!$B$13:$B$1048576,Main!$BR$13:$BR$1048576,0,0) -> 152 | P10: =ROUND(F10/M10*N10,0) -> 12680000 | Q10: =G10/M10*O10 -> 950000 | R10: =IF(D10>=(M10/8),H10,H10/M10*N10) -> 500000 | S10: =IF(CI10="N",26500*(ROUND(O10/8,0)),(I10/M10*O10)-CF10) -> 538333.33 | T10: =J10 -> 1320000 | U10: =K10/M10*O10 -> 316666.67 | V10: =IF(D10>=(M10/8),L10,L10/M10*N10) -> 0 | AE10: YES | AH10: 200000 | AO10: =_xlfn.XLOOKUP($A10,Main!$B$13:$B$35,Main!BU$13:BU$35,0,0) -> 0 | AP10: =_xlfn.XLOOKUP($A10,Main!$B$13:$B$35,Main!BV$13:BV$35,0,0) -> 0 | AQ10: =_xlfn.XLOOKUP($A10,Main!$B$13:$B$35,Main!BW$13:BW$35,0,0) -> 0 | AR10: =_xlfn.XLOOKUP($A10,Main!$B$13:$B$35,Main!BX$13:BX$35,0,0) -> 0 | AS10: =_xlfn.XLOOKUP($A10,Main!$B$13:$B$35,Main!BY$13:BY$35,0,0) -> 0 | AT10: =_xlfn.XLOOKUP($A10,Main!$B$13:$B$35,Main!BZ$13:BZ$35,0,0) -> 0 | AU10: =_xlfn.XLOOKUP($A10,Main!$B$13:$B$35,Main!CA$13:CA$35,0,0) -> 0 | AV10: =$F10/$M10*AO10*150% -> 0 | AW10: =$F10/$M10*AP10*200% -> 0 | AX10: =$F10/$M10*AQ10*300% -> 0 | AY10: =$F10/$M10*AR10*30% -> 0 | AZ10: =$F10/$M10*AS10*210% -> 0 | BA10: =$F10/$M10*AT10*270% -> 0 | BB10: =$F10/$M10*AU10*390% -> 0 | BC10: =ROUND(SUM(AV10:BB10)+CH10,0) -> 0 | BD10: =SUM(P10:AN10)+BC10 -> 16505000 | BG10: =ROUND($CB10*'SHUI & PIT'!$F$11,0) -> 1120000 | BH10: =ROUND($CB10*'SHUI & PIT'!$G$11,0) -> 210000 | BI10: =ROUND($CC10*'SHUI & PIT'!$H$11,0) -> 140000 | BJ10: =SUM(BG10:BI10) -> 1470000 | BK10: =IF(E10="La Nga",0,IF(E10="HCM",35000,IF(AE10="YES",IF($BG10>0,ROUND(MIN($CB10*1%,180000),0),0),0))) -> 35000 | BL10: =VLOOKUP(A10,'[1]Payroll master '!B$12:AD$160,29,0) -> 0 | BM10: =11000000+4400000*BL10 -> 11000000 | BN10: =ROUND(IF((CJ10-BJ10-BM10-BR10)<0,0,(CJ10-BJ10-BM10-BR10)),0) -> 2996667 | BO10: =ROUND((VLOOKUP(BN10,'SHUI & PIT'!$A$1:$C$8,2,1)*BN10-VLOOKUP(BN10,'SHUI & PIT'!$A$1:$C$8,3,1)),0) -> 149833 | BP10: =Y10 -> 0 | BS10: =BJ10+BO10+BP10+BR10+BE10+BF10+BQ10+BK10 -> 1654833 | BT10: =ROUND(IF((BD10-BS10)<0,0,(BD10-BS10)),0) -> 14850167 | BU10: =ROUND($CB10*'SHUI & PIT'!$F$12,0) -> 2450000 | BV10: =ROUND($CB10*'SHUI & PIT'!$G$12,0) -> 420000 | BW10: =ROUND($CC10*'SHUI & PIT'!$H$12,0) -> 140000 | BY10: =SUM(BU10:BX10) -> 3010000 | BZ10: =IF(BU10>0,ROUND($CB10*'SHUI & PIT'!$I$12,0),0) -> 280000 | CA10: =BD10+BY10-AC10+BZ10-BQ10 -> 19795000 | CB10: =IF(($F10+$T10)>='SHUI & PIT'!$C$12,'SHUI & PIT'!$C$12,($F10+$T10)) -> 14000000 | CC10: =IF(($F10+$T10)>='SHUI & PIT'!$C$13,'SHUI & PIT'!$C$13,($F10+$T10)) -> 14000000 | CD10: =ROUND(($F10/M10)*($AO10*0.5+$AP10+$AQ10*2+AR10*0.3+AS10*1.1+AT10*1.7+AU10*2.9),0) -> 0 | CE10: =BC10-CD10 -> 0 | CF10: =_xlfn.XLOOKUP(A10,'[2]Termination and others'!B$12:B$33,'[2]Termination and others'!F$12:F$33,0,0) -> 0 | CG10: =VLOOKUP(A10,Main!$B$13:$BN$405,65,0) -> 0 | CH10: =IF(50000<F10/M10,50000,F10/M10)*CG10 -> 0 | CJ10: =BD10-R10-S10-AK10-CD10-AC10-BE10-BF10-BQ10 -> 15466667
A11: 11168 | C11: 43558 | D11: =DATEDIF(C11,$C$3,"D") -> 1784 | E11: HCM | F11: 12780000 | G11: 1200000 | H11: 500000 | I11: 680000 | J11: 1320000 | K11: 400000 | L11: 0 | M11: =_xlfn.XLOOKUP(A11,Main!$B$13:$B$1048576,Main!$D$13:$D$1048576,0,0)*8 -> 192 | N11: =_xlfn.XLOOKUP(A11,Main!$B$13:$B$1048576,Main!$BQ$13:$BQ$1048576,0,0) -> 192 | O11: =_xlfn.XLOOKUP(A11,Main!$B$13:$B$1048576,Main!$BR$13:$BR$1048576,0,0) -> 152 | P11: =ROUND(F11/M11*N11,0) -> 12780000 | Q11: =G11/M11*O11 -> 950000 | R11: =IF(D11>=(M11/8),H11,H11/M11*N11) -> 500000 | S11: =IF(CI11="N",26500*(ROUND(O11/8,0)),(I11/M11*O11)-CF11) -> 538333.33 | T11: =J11 -> 1320000 | U11: =K11/M11*O11 -> 316666.67 | V11: =IF(D11>=(M11/8),L11,L11/M11*N11) -> 0 | AE11: YES | AH11: 1380000 | AO11: =_xlfn.XLOOKUP($A11,Main!$B$13:$B$35,Main!BU$13:BU$35,0,0) -> 0 | AP11: =_xlfn.XLOOKUP($A11,Main!$B$13:$B$35,Main!BV$13:BV$35,0,0) -> 0 | AQ11: =_xlfn.XLOOKUP($A11,Main!$B$13:$B$35,Main!BW$13:BW$35,0,0) -> 0 | AR11: =_xlfn.XLOOKUP($A11,Main!$B$13:$B$35,Main!BX$13:BX$35,0,0) -> 0 | AS11: =_xlfn.XLOOKUP($A11,Main!$B$13:$B$35,Main!BY$13:BY$35,0,0) -> 0 | AT11: =_xlfn.XLOOKUP($A11,Main!$B$13:$B$35,Main!BZ$13:BZ$35,0,0) -> 0 | AU11: =_xlfn.XLOOKUP($A11,Main!$B$13:$B$35,Main!CA$13:CA$35,0,0) -> 0 | AV11: =$F11/$M11*AO11*150% -> 0 | AW11: =$F11/$M11*AP11*200% -> 0 | AX11: =$F11/$M11*AQ11*300% -> 0 | AY11: =$F11/$M11*AR11*30% -> 0 | AZ11: =$F11/$M11*AS11*210% -> 0 | BA11: =$F11/$M11*AT11*270% -> 0 | BB11: =$F11/$M11*AU11*390% -> 0 | BC11: =ROUND(SUM(AV11:BB11)+CH11,0) -> 0 | BD11: =SUM(P11:AN11)+BC11 -> 17785000 | BG11: =ROUND($CB11*'SHUI & PIT'!$F$11,0) -> 1128000 | BH11: =ROUND($CB11*'SHUI & PIT'!$G$11,0) -> 211500 | BI11: =ROUND($CC11*'SHUI & PIT'!$H$11,0) -> 141000 | BJ11: =SUM(BG11:BI11) -> 1480500 | BK11: =IF(E11="La Nga",0,IF(E11="HCM",35000,IF(AE11="YES",IF($BG11>0,ROUND(MIN($CB11*1%,180000),0),0),0))) -> 35000 | BL11: =VLOOKUP(A11,'[1]Payroll master '!B$12:AD$160,29,0) -> 0 | BM11: =11000000+4400000*BL11 -> 11000000 | BN11: =ROUND(IF((CJ11-BJ11-BM11-BR11)<0,0,(CJ11-BJ11-BM11-BR11)),0) -> 4266167 | BO11: =ROUND((VLOOKUP(BN11,'SHUI & PIT'!$A$1:$C$8,2,1)*BN11-VLOOKUP(BN11,'SHUI & PIT'!$A$1:$C$8,3,1)),0) -> 213308 | BP11: =Y11 -> 0 | BS11: =BJ11+BO11+BP11+BR11+BE11+BF11+BQ11+BK11 -> 1728808 | BT11: =ROUND(IF((BD11-BS11)<0,0,(BD11-BS11)),0) -> 16056192 | BU11: =ROUND($CB11*'SHUI & PIT'!$F$12,0) -> 2467500 | BV11: =ROUND($CB11*'SHUI & PIT'!$G$12,0) -> 423000 | BW11: =ROUND($CC11*'SHUI & PIT'!$H$12,0) -> 141000 | BY11: =SUM(BU11:BX11) -> 3031500 | BZ11: =IF(BU11>0,ROUND($CB11*'SHUI & PIT'!$I$12,0),0) -> 282000 | CA11: =BD11+BY11-AC11+BZ11-BQ11 -> 21098500 | CB11: =IF(($F11+$T11)>='SHUI & PIT'!$C$12,'SHUI & PIT'!$C$12,($F11+$T11)) -> 14100000 | CC11: =IF(($F11+$T11)>='SHUI & PIT'!$C$13,'SHUI & PIT'!$C$13,($F11+$T11)) -> 14100000 | CD11: =ROUND(($F11/M11)*($AO11*0.5+$AP11+$AQ11*2+AR11*0.3+AS11*1.1+AT11*1.7+AU11*2.9),0) -> 0 | CE11: =BC11-CD11 -> 0 | CF11: =_xlfn.XLOOKUP(A11,'[2]Termination and others'!B$12:B$33,'[2]Termination and others'!F$12:F$33,0,0) -> 0 | CG11: =VLOOKUP(A11,Main!$B$13:$BN$405,65,0) -> 0 | CH11: =IF(50000<F11/M11,50000,F11/M11)*CG11 -> 0 | CJ11: =BD11-R11-S11-AK11-CD11-AC11-BE11-BF11-BQ11 -> 16746667
A12: 11188 | C12: 43620 | D12: =DATEDIF(C12,$C$3,"D") -> 1722 | E12: HCM | F12: 28780000 | G12: 810000 | H12: 1000000 | I12: 680000 | J12: 2750000 | K12: 400000 | L12: 500000 | M12: =_xlfn.XLOOKUP(A12,Main!$B$13:$B$1048576,Main!$D$13:$D$1048576,0,0)*8 -> 192 | N12: =_xlfn.XLOOKUP(A12,Main!$B$13:$B$1048576,Main!$BQ$13:$BQ$1048576,0,0) -> 192 | O12: =_xlfn.XLOOKUP(A12,Main!$B$13:$B$1048576,Main!$BR$13:$BR$1048576,0,0) -> 152 | P12: =ROUND(F12/M12*N12,0) -> 28780000 | Q12: =G12/M12*O12 -> 641250 | R12: =IF(D12>=(M12/8),H12,H12/M12*N12) -> 1000000 | S12: =IF(CI12="N",26500*(ROUND(O12/8,0)),(I12/M12*O12)-CF12) -> 538333.33 | T12: =J12 -> 2750000 | U12: =K12/M12*O12 -> 316666.67 | V12: =IF(D12>=(M12/8),L12,L12/M12*N12) -> 500000 | AE12: YES | AH12: 5024628 | AO12: =_xlfn.XLOOKUP($A12,Main!$B$13:$B$35,Main!BU$13:BU$35,0,0) -> 0 | AP12: =_xlfn.XLOOKUP($A12,Main!$B$13:$B$35,Main!BV$13:BV$35,0,0) -> 0 | AQ12: =_xlfn.XLOOKUP($A12,Main!$B$13:$B$35,Main!BW$13:BW$35,0,0) -> 0 | AR12: =_xlfn.XLOOKUP($A12,Main!$B$13:$B$35,Main!BX$13:BX$35,0,0) -> 0 | AS12: =_xlfn.XLOOKUP($A12,Main!$B$13:$B$35,Main!BY$13:BY$35,0,0) -> 0 | AT12: =_xlfn.XLOOKUP($A12,Main!$B$13:$B$35,Main!BZ$13:BZ$35,0,0) -> 0 | AU12: =_xlfn.XLOOKUP($A12,Main!$B$13:$B$35,Main!CA$13:CA$35,0,0) -> 0 | AV12: =$F12/$M12*AO12*150% -> 0 | AW12: =$F12/$M12*AP12*200% -> 0 | AX12: =$F12/$M12*AQ12*300% -> 0 | AY12: =$F12/$M12*AR12*30% -> 0 | AZ12: =$F12/$M12*AS12*210% -> 0 | BA12: =$F12/$M12*AT12*270% -> 0 | BB12: =$F12/$M12*AU12*390% -> 0 | BC12: =ROUND(SUM(AV12:BB12)+CH12,0) -> 0 | BD12: =SUM(P12:AN12)+BC12 -> 39550878 | BG12: =ROUND($CB12*'SHUI & PIT'!$F$11,0) -> 2522400 | BH12: =ROUND($CB12*'SHUI & PIT'!$G$11,0) -> 472950 | BI12: =ROUND($CC12*'SHUI & PIT'!$H$11,0) -> 315300 | BJ12: =SUM(BG12:BI12) -> 3310650 | BK12: =IF(E12="La Nga",0,IF(E12="HCM",35000,IF(AE12="YES",IF($BG12>0,ROUND(MIN($CB12*1%,180000),0),0),0))) -> 35000 | BL12: =VLOOKUP(A12,'[1]Payroll master '!B$12:AD$160,29,0) -> 3 | BM12: =11000000+4400000*BL12 -> 24200000 | BN12: =ROUND(IF((CJ12-BJ12-BM12-BR12)<0,0,(CJ12-BJ12-BM12-BR12)),0) -> 10501895 | BO12: =ROUND((VLOOKUP(BN12,'SHUI & PIT'!$A$1:$C$8,2,1)*BN12-VLOOKUP(BN12,'SHUI & PIT'!$A$1:$C$8,3,1)),0) -> 825284 | BP12: =Y12 -> 0 | BS12: =BJ12+BO12+BP12+BR12+BE12+BF12+BQ12+BK12 -> 4170934 | BT12: =ROUND(IF((BD12-BS12)<0,0,(BD12-BS12)),0) -> 35379944 | BU12: =ROUND($CB12*'SHUI & PIT'!$F$12,0) -> 5517750 | BV12: =ROUND($CB12*'SHUI & PIT'!$G$12,0) -> 945900 | BW12: =ROUND($CC12*'SHUI & PIT'!$H$12,0) -> 315300 | BY12: =SUM(BU12:BX12) -> 6778950 | BZ12: =IF(BU12>0,ROUND($CB12*'SHUI & PIT'!$I$12,0),0) -> 630600 | CA12: =BD12+BY12-AC12+BZ12-BQ12 -> 46960428 | CB12: =IF(($F12+$T12)>='SHUI & PIT'!$C$12,'SHUI & PIT'!$C$12,($F12+$T12)) -> 31530000 | CC12: =IF(($F12+$T12)>='SHUI & PIT'!$C$13,'SHUI & PIT'!$C$13,($F12+$T12)) -> 31530000 | CD12: =ROUND(($F12/M12)*($AO12*0.5+$AP12+$AQ12*2+AR12*0.3+AS12*1.1+AT12*1.7+AU12*2.9),0) -> 0 | CE12: =BC12-CD12 -> 0 | CF12: =_xlfn.XLOOKUP(A12,'[2]Termination and others'!B$12:B$33,'[2]Termination and others'!F$12:F$33,0,0) -> 0 | CG12: =VLOOKUP(A12,Main!$B$13:$BN$405,65,0) -> 0 | CH12: =IF(50000<F12/M12,50000,F12/M12)*CG12 -> 0 | CJ12: =BD12-R12-S12-AK12-CD12-AC12-BE12-BF12-BQ12 -> 38012545
A13: 11502 | C13: 44984 | D13: =DATEDIF(C13,$C$3,"D") -> 358 | E13: HCM | F13: 15610000 | G13: 1200000 | H13: 500000 | I13: 680000 | J13: 1320000 | K13: 400000 | L13: 0 | M13: =_xlfn.XLOOKUP(A13,Main!$B$13:$B$1048576,Main!$D$13:$D$1048576,0,0)*8 -> 192 | N13: =_xlfn.XLOOKUP(A13,Main!$B$13:$B$1048576,Main!$BQ$13:$BQ$1048576,0,0) -> 192 | O13: =_xlfn.XLOOKUP(A13,Main!$B$13:$B$1048576,Main!$BR$13:$BR$1048576,0,0) -> 152 | P13: =ROUND(F13/M13*N13,0) -> 15610000 | Q13: =G13/M13*O13 -> 950000 | R13: =IF(D13>=(M13/8),H13,H13/M13*N13) -> 500000 | S13: =IF(CI13="N",26500*(ROUND(O13/8,0)),(I13/M13*O13)-CF13) -> 538333.33 | T13: =J13 -> 1320000 | U13: =K13/M13*O13 -> 316666.67 | V13: =IF(D13>=(M13/8),L13,L13/M13*N13) -> 0 | AE13: YES | AO13: =_xlfn.XLOOKUP($A13,Main!$B$13:$B$35,Main!BU$13:BU$35,0,0) -> 0 | AP13: =_xlfn.XLOOKUP($A13,Main!$B$13:$B$35,Main!BV$13:BV$35,0,0) -> 0 | AQ13: =_xlfn.XLOOKUP($A13,Main!$B$13:$B$35,Main!BW$13:BW$35,0,0) -> 0 | AR13: =_xlfn.XLOOKUP($A13,Main!$B$13:$B$35,Main!BX$13:BX$35,0,0) -> 0 | AS13: =_xlfn.XLOOKUP($A13,Main!$B$13:$B$35,Main!BY$13:BY$35,0,0) -> 0 | AT13: =_xlfn.XLOOKUP($A13,Main!$B$13:$B$35,Main!BZ$13:BZ$35,0,0) -> 0 | AU13: =_xlfn.XLOOKUP($A13,Main!$B$13:$B$35,Main!CA$13:CA$35,0,0) -> 0 | AV13: =$F13/$M13*AO13*150% -> 0 | AW13: =$F13/$M13*AP13*200% -> 0 | AX13: =$F13/$M13*AQ13*300% -> 0 | AY13: =$F13/$M13*AR13*30% -> 0 | AZ13: =$F13/$M13*AS13*210% -> 0 | BA13: =$F13/$M13*AT13*270% -> 0 | BB13: =$F13/$M13*AU13*390% -> 0 | BC13: =ROUND(SUM(AV13:BB13)+CH13,0) -> 0 | BD13: =SUM(P13:AN13)+BC13 -> 19235000 | BG13: =ROUND($CB13*'SHUI & PIT'!$F$11,0) -> 1354400 | BH13: =ROUND($CB13*'SHUI & PIT'!$G$11,0) -> 253950 | BI13: =ROUND($CC13*'SHUI & PIT'!$H$11,0) -> 169300 | BJ13: =SUM(BG13:BI13) -> 1777650 | BK13: =IF(E13="La Nga",0,IF(E13="HCM",35000,IF(AE13="YES",IF($BG13>0,ROUND(MIN($CB13*1%,180000),0),0),0))) -> 35000 | BL13: =VLOOKUP(A13,'[1]Payroll master '!B$12:AD$160,29,0) -> 0 | BM13: =11000000+4400000*BL13 -> 11000000 | BN13: =ROUND(IF((CJ13-BJ13-BM13-BR13)<0,0,(CJ13-BJ13-BM13-BR13)),0) -> 5419017 | BO13: =ROUND((VLOOKUP(BN13,'SHUI & PIT'!$A$1:$C$8,2,1)*BN13-VLOOKUP(BN13,'SHUI & PIT'!$A$1:$C$8,3,1)),0) -> 291902 | BP13: =Y13 -> 0 | BS13: =BJ13+BO13+BP13+BR13+BE13+BF13+BQ13+BK13 -> 2104552 | BT13: =ROUND(IF((BD13-BS13)<0,0,(BD13-BS13)),0) -> 17130448 | BU13: =ROUND($CB13*'SHUI & PIT'!$F$12,0) -> 2962750 | BV13: =ROUND($CB13*'SHUI & PIT'!$G$12,0) -> 507900 | BW13: =ROUND($CC13*'SHUI & PIT'!$H$12,0) -> 169300 | BY13: =SUM(BU13:BX13) -> 3639950 | BZ13: =IF(BU13>0,ROUND($CB13*'SHUI & PIT'!$I$12,0),0) -> 338600 | CA13: =BD13+BY13-AC13+BZ13-BQ13 -> 23213550 | CB13: =IF(($F13+$T13)>='SHUI & PIT'!$C$12,'SHUI & PIT'!$C$12,($F13+$T13)) -> 16930000 | CC13: =IF(($F13+$T13)>='SHUI & PIT'!$C$13,'SHUI & PIT'!$C$13,($F13+$T13)) -> 16930000 | CD13: =ROUND(($F13/M13)*($AO13*0.5+$AP13+$AQ13*2+AR13*0.3+AS13*1.1+AT13*1.7+AU13*2.9),0) -> 0 | CE13: =BC13-CD13 -> 0 | CF13: =_xlfn.XLOOKUP(A13,'[2]Termination and others'!B$12:B$33,'[2]Termination and others'!F$12:F$33,0,0) -> 0 | CG13: =VLOOKUP(A13,Main!$B$13:$BN$405,65,0) -> 0 | CH13: =IF(50000<F13/M13,50000,F13/M13)*CG13 -> 0 | CJ13: =BD13-R13-S13-AK13-CD13-AC13-BE13-BF13-BQ13 -> 18196667
A14: 11587 | C14: 45166 | D14: =DATEDIF(C14,$C$3,"D") -> 176 | E14: HCM | F14: 75000000 | G14: 0 | H14: 1000000 | I14: 680000 | J14: 0 | K14: 0 | L14: 500000 | M14: =_xlfn.XLOOKUP(A14,Main!$B$13:$B$1048576,Main!$D$13:$D$1048576,0,0)*8 -> 192 | N14: =_xlfn.XLOOKUP(A14,Main!$B$13:$B$1048576,Main!$BQ$13:$BQ$1048576,0,0) -> 192 | O14: =_xlfn.XLOOKUP(A14,Main!$B$13:$B$1048576,Main!$BR$13:$BR$1048576,0,0) -> 152 | P14: =ROUND(F14/M14*N14,0) -> 75000000 | Q14: =G14/M14*O14 -> 0 | R14: =IF(D14>=(M14/8),H14,H14/M14*N14) -> 1000000 | S14: =IF(CI14="N",26500*(ROUND(O14/8,0)),(I14/M14*O14)-CF14) -> 538333.33 | T14: =J14 -> 0 | U14: =K14/M14*O14 -> 0 | V14: =IF(D14>=(M14/8),L14,L14/M14*N14) -> 500000 | AE14: YES | AH14: 750000 | AO14: =_xlfn.XLOOKUP($A14,Main!$B$13:$B$35,Main!BU$13:BU$35,0,0) -> 0 | AP14: =_xlfn.XLOOKUP($A14,Main!$B$13:$B$35,Main!BV$13:BV$35,0,0) -> 0 | AQ14: =_xlfn.XLOOKUP($A14,Main!$B$13:$B$35,Main!BW$13:BW$35,0,0) -> 0 | AR14: =_xlfn.XLOOKUP($A14,Main!$B$13:$B$35,Main!BX$13:BX$35,0,0) -> 0 | AS14: =_xlfn.XLOOKUP($A14,Main!$B$13:$B$35,Main!BY$13:BY$35,0,0) -> 0 | AT14: =_xlfn.XLOOKUP($A14,Main!$B$13:$B$35,Main!BZ$13:BZ$35,0,0) -> 0 | AU14: =_xlfn.XLOOKUP($A14,Main!$B$13:$B$35,Main!CA$13:CA$35,0,0) -> 0 | AV14: =$F14/$M14*AO14*150% -> 0 | AW14: =$F14/$M14*AP14*200% -> 0 | AX14: =$F14/$M14*AQ14*300% -> 0 | AY14: =$F14/$M14*AR14*30% -> 0 | AZ14: =$F14/$M14*AS14*210% -> 0 | BA14: =$F14/$M14*AT14*270% -> 0 | BB14: =$F14/$M14*AU14*390% -> 0 | BC14: =ROUND(SUM(AV14:BB14)+CH14,0) -> 0 | BD14: =SUM(P14:AN14)+BC14 -> 77788333 | BG14: =ROUND($CB14*'SHUI & PIT'!$F$11,0) -> 2880000 | BH14: =ROUND($CB14*'SHUI & PIT'!$G$11,0) -> 540000 | BI14: =ROUND($CC14*'SHUI & PIT'!$H$11,0) -> 750000 | BJ14: =SUM(BG14:BI14) -> 4170000 | BK14: =IF(E14="La Nga",0,IF(E14="HCM",35000,IF(AE14="YES",IF($BG14>0,ROUND(MIN($CB14*1%,180000),0),0),0))) -> 35000 | BL14: =VLOOKUP(A14,'[1]Payroll master '!B$12:AD$160,29,0) -> 4 | BM14: =11000000+4400000*BL14 -> 28600000 | BN14: =ROUND(IF((CJ14-BJ14-BM14-BR14)<0,0,(CJ14-BJ14-BM14-BR14)),0) -> 43480000 | BO14: =ROUND((VLOOKUP(BN14,'SHUI & PIT'!$A$1:$C$8,2,1)*BN14-VLOOKUP(BN14,'SHUI & PIT'!$A$1:$C$8,3,1)),0) -> 7620000 | BP14: =Y14 -> 0 | BS14: =BJ14+BO14+BP14+BR14+BE14+BF14+BQ14+BK14 -> 11825000 | BT14: =ROUND(IF((BD14-BS14)<0,0,(BD14-BS14)),0) -> 65963333 | BU14: =ROUND($CB14*'SHUI & PIT'!$F$12,0) -> 6300000 | BV14: =ROUND($CB14*'SHUI & PIT'!$G$12,0) -> 1080000 | BW14: =ROUND($CC14*'SHUI & PIT'!$H$12,0) -> 750000 | BY14: =SUM(BU14:BX14) -> 8130000 | BZ14: =IF(BU14>0,ROUND($CB14*'SHUI & PIT'!$I$12,0),0) -> 720000 | CA14: =BD14+BY14-AC14+BZ14-BQ14 -> 86638333 | CB14: =IF(($F14+$T14)>='SHUI & PIT'!$C$12,'SHUI & PIT'!$C$12,($F14+$T14)) -> 36000000 | CC14: =IF(($F14+$T14)>='SHUI & PIT'!$C$13,'SHUI & PIT'!$C$13,($F14+$T14)) -> 75000000 | CD14: =ROUND(($F14/M14)*($AO14*0.5+$AP14+$AQ14*2+AR14*0.3+AS14*1.1+AT14*1.7+AU14*2.9),0) -> 0 | CE14: =BC14-CD14 -> 0 | CF14: =_xlfn.XLOOKUP(A14,'[2]Termination and others'!B$12:B$33,'[2]Termination and others'!F$12:F$33,0,0) -> 0 | CG14: =VLOOKUP(A14,Main!$B$13:$BN$405,65,0) -> 0 | CH14: =IF(50000<F14/M14,50000,F14/M14)*CG14 -> 0 | CJ14: =BD14-R14-S14-AK14-CD14-AC14-BE14-BF14-BQ14 -> 76250000
A15: 11626 | C15: 45174 | D15: =DATEDIF(C15,$C$3,"D") -> 168 | E15: HCM | F15: 20000000 | G15: 1200000 | H15: 500000 | I15: 680000 | J15: 0 | K15: 400000 | L15: 0 | M15: =_xlfn.XLOOKUP(A15,Main!$B$13:$B$1048576,Main!$D$13:$D$1048576,0,0)*8 -> 192 | N15: =_xlfn.XLOOKUP(A15,Main!$B$13:$B$1048576,Main!$BQ$13:$BQ$1048576,0,0) -> 192 | O15: =_xlfn.XLOOKUP(A15,Main!$B$13:$B$1048576,Main!$BR$13:$BR$1048576,0,0) -> 116 | P15: =ROUND(F15/M15*N15,0) -> 20000000 | Q15: =G15/M15*O15 -> 725000 | R15: =IF(D15>=(M15/8),H15,H15/M15*N15) -> 500000 | S15: =IF(CI15="N",26500*(ROUND(O15/8,0)),(I15/M15*O15)-CF15) -> 410833.33 | T15: =J15 -> 0 | U15: =K15/M15*O15 -> 241666.67 | V15: =IF(D15>=(M15/8),L15,L15/M15*N15) -> 0 | AE15: YES | AH15: 200000 | AO15: =_xlfn.XLOOKUP($A15,Main!$B$13:$B$35,Main!BU$13:BU$35,0,0) -> 0 | AP15: =_xlfn.XLOOKUP($A15,Main!$B$13:$B$35,Main!BV$13:BV$35,0,0) -> 0 | AQ15: =_xlfn.XLOOKUP($A15,Main!$B$13:$B$35,Main!BW$13:BW$35,0,0) -> 0 | AR15: =_xlfn.XLOOKUP($A15,Main!$B$13:$B$35,Main!BX$13:BX$35,0,0) -> 0 | AS15: =_xlfn.XLOOKUP($A15,Main!$B$13:$B$35,Main!BY$13:BY$35,0,0) -> 0 | AT15: =_xlfn.XLOOKUP($A15,Main!$B$13:$B$35,Main!BZ$13:BZ$35,0,0) -> 0 | AU15: =_xlfn.XLOOKUP($A15,Main!$B$13:$B$35,Main!CA$13:CA$35,0,0) -> 0 | AV15: =$F15/$M15*AO15*150% -> 0 | AW15: =$F15/$M15*AP15*200% -> 0 | AX15: =$F15/$M15*AQ15*300% -> 0 | AY15: =$F15/$M15*AR15*30% -> 0 | AZ15: =$F15/$M15*AS15*210% -> 0 | BA15: =$F15/$M15*AT15*270% -> 0 | BB15: =$F15/$M15*AU15*390% -> 0 | BC15: =ROUND(SUM(AV15:BB15)+CH15,0) -> 0 | BD15: =SUM(P15:AN15)+BC15 -> 22077500 | BG15: =ROUND($CB15*'SHUI & PIT'!$F$11,0) -> 1600000 | BH15: =ROUND($CB15*'SHUI & PIT'!$G$11,0) -> 300000 | BI15: =ROUND($CC15*'SHUI & PIT'!$H$11,0) -> 200000 | BJ15: =SUM(BG15:BI15) -> 2100000 | BK15: =IF(E15="La Nga",0,IF(E15="HCM",35000,IF(AE15="YES",IF($BG15>0,ROUND(MIN($CB15*1%,180000),0),0),0))) -> 35000 | BL15: =VLOOKUP(A15,'[1]Payroll master '!B$12:AD$160,29,0) -> 0 | BM15: =11000000+4400000*BL15 -> 11000000 | BN15: =ROUND(IF((CJ15-BJ15-BM15-BR15)<0,0,(CJ15-BJ15-BM15-BR15)),0) -> 8066667 | BO15: =ROUND((VLOOKUP(BN15,'SHUI & PIT'!$A$1:$C$8,2,1)*BN15-VLOOKUP(BN15,'SHUI & PIT'!$A$1:$C$8,3,1)),0) -> 556667 | BP15: =Y15 -> 0 | BS15: =BJ15+BO15+BP15+BR15+BE15+BF15+BQ15+BK15 -> 2691667 | BT15: =ROUND(IF((BD15-BS15)<0,0,(BD15-BS15)),0) -> 19385833 | BU15: =ROUND($CB15*'SHUI & PIT'!$F$12,0) -> 3500000 | BV15: =ROUND($CB15*'SHUI & PIT'!$G$12,0) -> 600000 | BW15: =ROUND($CC15*'SHUI & PIT'!$H$12,0) -> 200000 | BY15: =SUM(BU15:BX15) -> 4300000 | BZ15: =IF(BU15>0,ROUND($CB15*'SHUI & PIT'!$I$12,0),0) -> 400000 | CA15: =BD15+BY15-AC15+BZ15-BQ15 -> 26777500 | CB15: =IF(($F15+$T15)>='SHUI & PIT'!$C$12,'SHUI & PIT'!$C$12,($F15+$T15)) -> 20000000 | CC15: =IF(($F15+$T15)>='SHUI & PIT'!$C$13,'SHUI & PIT'!$C$13,($F15+$T15)) -> 20000000 | CD15: =ROUND(($F15/M15)*($AO15*0.5+$AP15+$AQ15*2+AR15*0.3+AS15*1.1+AT15*1.7+AU15*2.9),0) -> 0 | CE15: =BC15-CD15 -> 0 | CF15: =_xlfn.XLOOKUP(A15,'[2]Termination and others'!B$12:B$33,'[2]Termination and others'!F$12:F$33,0,0) -> 0 | CG15: =VLOOKUP(A15,Main!$B$13:$BN$405,65,0) -> 0 | CH15: =IF(50000<F15/M15,50000,F15/M15)*CG15 -> 0 | CJ15: =BD15-R15-S15-AK15-CD15-AC15-BE15-BF15-BQ15 -> 21166667
A16: 4044 | C16: 37438 | D16: =DATEDIF(C16,$C$3,"D") -> 7904 | E16: HCM | F16: 16530000 | G16: 1200000 | H16: 500000 | I16: 680000 | J16: 1320000 | K16: 400000 | L16: 0 | M16: =_xlfn.XLOOKUP(A16,Main!$B$13:$B$1048576,Main!$D$13:$D$1048576,0,0)*8 -> 192 | N16: =_xlfn.XLOOKUP(A16,Main!$B$13:$B$1048576,Main!$BQ$13:$BQ$1048576,0,0) -> 192 | O16: =_xlfn.XLOOKUP(A16,Main!$B$13:$B$1048576,Main!$BR$13:$BR$1048576,0,0) -> 152 | P16: =ROUND(F16/M16*N16,0) -> 16530000 | Q16: =G16/M16*O16 -> 950000 | R16: =IF(D16>=(M16/8),H16,H16/M16*N16) -> 500000 | S16: =IF(CI16="N",26500*(ROUND(O16/8,0)),(I16/M16*O16)-CF16) -> 538333.33 | T16: =J16 -> 1320000 | U16: =K16/M16*O16 -> 316666.67 | V16: =IF(D16>=(M16/8),L16,L16/M16*N16) -> 0 | AE16: YES | AH16: 400000 | AO16: =_xlfn.XLOOKUP($A16,Main!$B$13:$B$35,Main!BU$13:BU$35,0,0) -> 0 | AP16: =_xlfn.XLOOKUP($A16,Main!$B$13:$B$35,Main!BV$13:BV$35,0,0) -> 0 | AQ16: =_xlfn.XLOOKUP($A16,Main!$B$13:$B$35,Main!BW$13:BW$35,0,0) -> 0 | AR16: =_xlfn.XLOOKUP($A16,Main!$B$13:$B$35,Main!BX$13:BX$35,0,0) -> 0 | AS16: =_xlfn.XLOOKUP($A16,Main!$B$13:$B$35,Main!BY$13:BY$35,0,0) -> 0 | AT16: =_xlfn.XLOOKUP($A16,Main!$B$13:$B$35,Main!BZ$13:BZ$35,0,0) -> 0 | AU16: =_xlfn.XLOOKUP($A16,Main!$B$13:$B$35,Main!CA$13:CA$35,0,0) -> 0 | AV16: =$F16/$M16*AO16*150% -> 0 | AW16: =$F16/$M16*AP16*200% -> 0 | AX16: =$F16/$M16*AQ16*300% -> 0 | AY16: =$F16/$M16*AR16*30% -> 0 | AZ16: =$F16/$M16*AS16*210% -> 0 | BA16: =$F16/$M16*AT16*270% -> 0 | BB16: =$F16/$M16*AU16*390% -> 0 | BC16: =ROUND(SUM(AV16:BB16)+CH16,0) -> 0 | BD16: =SUM(P16:AN16)+BC16 -> 20555000 | BG16: =ROUND($CB16*'SHUI & PIT'!$F$11,0) -> 1428000 | BH16: =ROUND($CB16*'SHUI & PIT'!$G$11,0) -> 267750 | BI16: =ROUND($CC16*'SHUI & PIT'!$H$11,0) -> 178500 | BJ16: =SUM(BG16:BI16) -> 1874250 | BK16: =IF(E16="La Nga",0,IF(E16="HCM",35000,IF(AE16="YES",IF($BG16>0,ROUND(MIN($CB16*1%,180000),0),0),0))) -> 35000 | BL16: =VLOOKUP(A16,'[1]Payroll master '!B$12:AD$160,29,0) -> 0 | BM16: =11000000+4400000*BL16 -> 11000000 | BN16: =ROUND(IF((CJ16-BJ16-BM16-BR16)<0,0,(CJ16-BJ16-BM16-BR16)),0) -> 6642417 | BO16: =ROUND((VLOOKUP(BN16,'SHUI & PIT'!$A$1:$C$8,2,1)*BN16-VLOOKUP(BN16,'SHUI & PIT'!$A$1:$C$8,3,1)),0) -> 414242 | BP16: =Y16 -> 0 | BS16: =BJ16+BO16+BP16+BR16+BE16+BF16+BQ16+BK16 -> 2323492 | BT16: =ROUND(IF((BD16-BS16)<0,0,(BD16-BS16)),0) -> 18231508 | BU16: =ROUND($CB16*'SHUI & PIT'!$F$12,0) -> 3123750 | BV16: =ROUND($CB16*'SHUI & PIT'!$G$12,0) -> 535500 | BW16: =ROUND($CC16*'SHUI & PIT'!$H$12,0) -> 178500 | BY16: =SUM(BU16:BX16) -> 3837750 | BZ16: =IF(BU16>0,ROUND($CB16*'SHUI & PIT'!$I$12,0),0) -> 357000 | CA16: =BD16+BY16-AC16+BZ16-BQ16 -> 24749750 | CB16: =IF(($F16+$T16)>='SHUI & PIT'!$C$12,'SHUI & PIT'!$C$12,($F16+$T16)) -> 17850000 | CC16: =IF(($F16+$T16)>='SHUI & PIT'!$C$13,'SHUI & PIT'!$C$13,($F16+$T16)) -> 17850000 | CD16: =ROUND(($F16/M16)*($AO16*0.5+$AP16+$AQ16*2+AR16*0.3+AS16*1.1+AT16*1.7+AU16*2.9),0) -> 0 | CE16: =BC16-CD16 -> 0 | CF16: =_xlfn.XLOOKUP(A16,'[2]Termination and others'!B$12:B$33,'[2]Termination and others'!F$12:F$33,0,0) -> 0 | CG16: =VLOOKUP(A16,Main!$B$13:$BN$405,65,0) -> 0 | CH16: =IF(50000<F16/M16,50000,F16/M16)*CG16 -> 0 | CJ16: =BD16-R16-S16-AK16-CD16-AC16-BE16-BF16-BQ16 -> 19516667
A17: 4045 | C17: 37867 | D17: =DATEDIF(C17,$C$3,"D") -> 7475 | E17: HCM | F17: 28550000 | G17: 810000 | H17: 1000000 | I17: 680000 | J17: 2750000 | K17: 400000 | L17: 500000 | M17: =_xlfn.XLOOKUP(A17,Main!$B$13:$B$1048576,Main!$D$13:$D$1048576,0,0)*8 -> 192 | N17: =_xlfn.XLOOKUP(A17,Main!$B$13:$B$1048576,Main!$BQ$13:$BQ$1048576,0,0) -> 192 | O17: =_xlfn.XLOOKUP(A17,Main!$B$13:$B$1048576,Main!$BR$13:$BR$1048576,0,0) -> 128 | P17: =ROUND(F17/M17*N17,0) -> 28550000 | Q17: =G17/M17*O17 -> 540000 | R17: =IF(D17>=(M17/8),H17,H17/M17*N17) -> 1000000 | S17: =IF(CI17="N",26500*(ROUND(O17/8,0)),(I17/M17*O17)-CF17) -> 453333.33 | T17: =J17 -> 2750000 | U17: =K17/M17*O17 -> 266666.67 | V17: =IF(D17>=(M17/8),L17,L17/M17*N17) -> 500000 | AE17: YES | AO17: =_xlfn.XLOOKUP($A17,Main!$B$13:$B$35,Main!BU$13:BU$35,0,0) -> 0 | AP17: =_xlfn.XLOOKUP($A17,Main!$B$13:$B$35,Main!BV$13:BV$35,0,0) -> 0 | AQ17: =_xlfn.XLOOKUP($A17,Main!$B$13:$B$35,Main!BW$13:BW$35,0,0) -> 0 | AR17: =_xlfn.XLOOKUP($A17,Main!$B$13:$B$35,Main!BX$13:BX$35,0,0) -> 0 | AS17: =_xlfn.XLOOKUP($A17,Main!$B$13:$B$35,Main!BY$13:BY$35,0,0) -> 0 | AT17: =_xlfn.XLOOKUP($A17,Main!$B$13:$B$35,Main!BZ$13:BZ$35,0,0) -> 0 | AU17: =_xlfn.XLOOKUP($A17,Main!$B$13:$B$35,Main!CA$13:CA$35,0,0) -> 0 | AV17: =$F17/$M17*AO17*150% -> 0 | AW17: =$F17/$M17*AP17*200% -> 0 | AX17: =$F17/$M17*AQ17*300% -> 0 | AY17: =$F17/$M17*AR17*30% -> 0 | AZ17: =$F17/$M17*AS17*210% -> 0 | BA17: =$F17/$M17*AT17*270% -> 0 | BB17: =$F17/$M17*AU17*390% -> 0 | BC17: =ROUND(SUM(AV17:BB17)+CH17,0) -> 0 | BD17: =SUM(P17:AN17)+BC17 -> 34060000 | BG17: =ROUND($CB17*'SHUI & PIT'!$F$11,0) -> 2504000 | BH17: =ROUND($CB17*'SHUI & PIT'!$G$11,0) -> 469500 | BI17: =ROUND($CC17*'SHUI & PIT'!$H$11,0) -> 313000 | BJ17: =SUM(BG17:BI17) -> 3286500 | BK17: =IF(E17="La Nga",0,IF(E17="HCM",35000,IF(AE17="YES",IF($BG17>0,ROUND(MIN($CB17*1%,180000),0),0),0))) -> 35000 | BL17: =VLOOKUP(A17,'[1]Payroll master '!B$12:AD$160,29,0) -> 0 | BM17: =11000000+4400000*BL17 -> 11000000 | BN17: =ROUND(IF((CJ17-BJ17-BM17-BR17)<0,0,(CJ17-BJ17-BM17-BR17)),0) -> 18320167 | BO17: =ROUND((VLOOKUP(BN17,'SHUI & PIT'!$A$1:$C$8,2,1)*BN17-VLOOKUP(BN17,'SHUI & PIT'!$A$1:$C$8,3,1)),0) -> 2014033 | BP17: =Y17 -> 0 | BS17: =BJ17+BO17+BP17+BR17+BE17+BF17+BQ17+BK17 -> 5335533 | BT17: =ROUND(IF((BD17-BS17)<0,0,(BD17-BS17)),0) -> 28724467 | BU17: =ROUND($CB17*'SHUI & PIT'!$F$12,0) -> 5477500 | BV17: =ROUND($CB17*'SHUI & PIT'!$G$12,0) -> 939000 | BW17: =ROUND($CC17*'SHUI & PIT'!$H$12,0) -> 313000 | BY17: =SUM(BU17:BX17) -> 6729500 | BZ17: =IF(BU17>0,ROUND($CB17*'SHUI & PIT'!$I$12,0),0) -> 626000 | CA17: =BD17+BY17-AC17+BZ17-BQ17 -> 41415500 | CB17: =IF(($F17+$T17)>='SHUI & PIT'!$C$12,'SHUI & PIT'!$C$12,($F17+$T17)) -> 31300000 | CC17: =IF(($F17+$T17)>='SHUI & PIT'!$C$13,'SHUI & PIT'!$C$13,($F17+$T17)) -> 31300000 | CD17: =ROUND(($F17/M17)*($AO17*0.5+$AP17+$AQ17*2+AR17*0.3+AS17*1.1+AT17*1.7+AU17*2.9),0) -> 0 | CE17: =BC17-CD17 -> 0 | CF17: =_xlfn.XLOOKUP(A17,'[2]Termination and others'!B$12:B$33,'[2]Termination and others'!F$12:F$33,0,0) -> 0 | CG17: =VLOOKUP(A17,Main!$B$13:$BN$405,65,0) -> 0 | CH17: =IF(50000<F17/M17,50000,F17/M17)*CG17 -> 0 | CJ17: =BD17-R17-S17-AK17-CD17-AC17-BE17-BF17-BQ17 -> 32606667
A18: 4047 | C18: 39204 | D18: =DATEDIF(C18,$C$3,"D") -> 6138 | E18: HCM | F18: 17630000 | G18: 1200000 | H18: 500000 | I18: 680000 | J18: 1320000 | K18: 400000 | L18: 0 | M18: =_xlfn.XLOOKUP(A18,Main!$B$13:$B$1048576,Main!$D$13:$D$1048576,0,0)*8 -> 192 | N18: =_xlfn.XLOOKUP(A18,Main!$B$13:$B$1048576,Main!$BQ$13:$BQ$1048576,0,0) -> 192 | O18: =_xlfn.XLOOKUP(A18,Main!$B$13:$B$1048576,Main!$BR$13:$BR$1048576,0,0) -> 152 | P18: =ROUND(F18/M18*N18,0) -> 17630000 | Q18: =G18/M18*O18 -> 950000 | R18: =IF(D18>=(M18/8),H18,H18/M18*N18) -> 500000 | S18: =IF(CI18="N",26500*(ROUND(O18/8,0)),(I18/M18*O18)-CF18) -> 538333.33 | T18: =J18 -> 1320000 | U18: =K18/M18*O18 -> 316666.67 | V18: =IF(D18>=(M18/8),L18,L18/M18*N18) -> 0 | AE18: YES | AH18: 600000 | AO18: =_xlfn.XLOOKUP($A18,Main!$B$13:$B$35,Main!BU$13:BU$35,0,0) -> 0 | AP18: =_xlfn.XLOOKUP($A18,Main!$B$13:$B$35,Main!BV$13:BV$35,0,0) -> 0 | AQ18: =_xlfn.XLOOKUP($A18,Main!$B$13:$B$35,Main!BW$13:BW$35,0,0) -> 0 | AR18: =_xlfn.XLOOKUP($A18,Main!$B$13:$B$35,Main!BX$13:BX$35,0,0) -> 0 | AS18: =_xlfn.XLOOKUP($A18,Main!$B$13:$B$35,Main!BY$13:BY$35,0,0) -> 0 | AT18: =_xlfn.XLOOKUP($A18,Main!$B$13:$B$35,Main!BZ$13:BZ$35,0,0) -> 0 | AU18: =_xlfn.XLOOKUP($A18,Main!$B$13:$B$35,Main!CA$13:CA$35,0,0) -> 0 | AV18: =$F18/$M18*AO18*150% -> 0 | AW18: =$F18/$M18*AP18*200% -> 0 | AX18: =$F18/$M18*AQ18*300% -> 0 | AY18: =$F18/$M18*AR18*30% -> 0 | AZ18: =$F18/$M18*AS18*210% -> 0 | BA18: =$F18/$M18*AT18*270% -> 0 | BB18: =$F18/$M18*AU18*390% -> 0 | BC18: =ROUND(SUM(AV18:BB18)+CH18,0) -> 0 | BD18: =SUM(P18:AN18)+BC18 -> 21855000 | BG18: =ROUND($CB18*'SHUI & PIT'!$F$11,0) -> 1516000 | BH18: =ROUND($CB18*'SHUI & PIT'!$G$11,0) -> 284250 | BI18: =ROUND($CC18*'SHUI & PIT'!$H$11,0) -> 189500 | BJ18: =SUM(BG18:BI18) -> 1989750 | BK18: =IF(E18="La Nga",0,IF(E18="HCM",35000,IF(AE18="YES",IF($BG18>0,ROUND(MIN($CB18*1%,180000),0),0),0))) -> 35000 | BL18: =VLOOKUP(A18,'[1]Payroll master '!B$12:AD$160,29,0) -> 2 | BM18: =11000000+4400000*BL18 -> 19800000 | BN18: =ROUND(IF((CJ18-BJ18-BM18-BR18)<0,0,(CJ18-BJ18-BM18-BR18)),0) -> 0 | BO18: =ROUND((VLOOKUP(BN18,'SHUI & PIT'!$A$1:$C$8,2,1)*BN18-VLOOKUP(BN18,'SHUI & PIT'!$A$1:$C$8,3,1)),0) -> 0 | BP18: =Y18 -> 0 | BS18: =BJ18+BO18+BP18+BR18+BE18+BF18+BQ18+BK18 -> 2024750 | BT18: =ROUND(IF((BD18-BS18)<0,0,(BD18-BS18)),0) -> 19830250 | BU18: =ROUND($CB18*'SHUI & PIT'!$F$12,0) -> 3316250 | BV18: =ROUND($CB18*'SHUI & PIT'!$G$12,0) -> 568500 | BW18: =ROUND($CC18*'SHUI & PIT'!$H$12,0) -> 189500 | BY18: =SUM(BU18:BX18) -> 4074250 | BZ18: =IF(BU18>0,ROUND($CB18*'SHUI & PIT'!$I$12,0),0) -> 379000 | CA18: =BD18+BY18-AC18+BZ18-BQ18 -> 26308250 | CB18: =IF(($F18+$T18)>='SHUI & PIT'!$C$12,'SHUI & PIT'!$C$12,($F18+$T18)) -> 18950000 | CC18: =IF(($F18+$T18)>='SHUI & PIT'!$C$13,'SHUI & PIT'!$C$13,($F18+$T18)) -> 18950000 | CD18: =ROUND(($F18/M18)*($AO18*0.5+$AP18+$AQ18*2+AR18*0.3+AS18*1.1+AT18*1.7+AU18*2.9),0) -> 0 | CE18: =BC18-CD18 -> 0 | CF18: =_xlfn.XLOOKUP(A18,'[2]Termination and others'!B$12:B$33,'[2]Termination and others'!F$12:F$33,0,0) -> 0 | CG18: =VLOOKUP(A18,Main!$B$13:$BN$405,65,0) -> 0 | CH18: =IF(50000<F18/M18,50000,F18/M18)*CG18 -> 0 | CJ18: =BD18-R18-S18-AK18-CD18-AC18-BE18-BF18-BQ18 -> 20816667
A19: 4145 | C19: 41855 | D19: 0 | E19: HCM | F19: 11400000 | G19: 1200000 | H19: 500000 | I19: 680000 | J19: 1320000 | K19: 400000 | L19: 0 | M19: =_xlfn.XLOOKUP(A19,Main!$B$13:$B$1048576,Main!$D$13:$D$1048576,0,0)*8 -> 192 | N19: =_xlfn.XLOOKUP(A19,Main!$B$13:$B$1048576,Main!$BQ$13:$BQ$1048576,0,0) -> 68 | O19: =_xlfn.XLOOKUP(A19,Main!$B$13:$B$1048576,Main!$BR$13:$BR$1048576,0,0) -> 68 | P19: =ROUND(F19/M19*N19,0) -> 4037500 | Q19: =G19/M19*O19 -> 425000 | R19: =IF(D19>=(M19/8),H19,H19/M19*N19) -> 177083.33 | S19: =IF(CI19="N",26500*(ROUND(O19/8,0)),(I19/M19*O19)-CF19) -> 240833.33 | T19: 0 | U19: =K19/M19*O19 -> 141666.67 | V19: =IF(D19>=(M19/8),L19,L19/M19*N19) -> 0 | X19: =F19/(M19/8)*15 -> 7125000 | AE19: YES | AH19: 600000 | AO19: =_xlfn.XLOOKUP($A19,Main!$B$13:$B$35,Main!BU$13:BU$35,0,0) -> 0 | AP19: =_xlfn.XLOOKUP($A19,Main!$B$13:$B$35,Main!BV$13:BV$35,0,0) -> 0 | AQ19: =_xlfn.XLOOKUP($A19,Main!$B$13:$B$35,Main!BW$13:BW$35,0,0) -> 0 | AR19: =_xlfn.XLOOKUP($A19,Main!$B$13:$B$35,Main!BX$13:BX$35,0,0) -> 0 | AS19: =_xlfn.XLOOKUP($A19,Main!$B$13:$B$35,Main!BY$13:BY$35,0,0) -> 0 | AT19: =_xlfn.XLOOKUP($A19,Main!$B$13:$B$35,Main!BZ$13:BZ$35,0,0) -> 0 | AU19: =_xlfn.XLOOKUP($A19,Main!$B$13:$B$35,Main!CA$13:CA$35,0,0) -> 0 | AV19: =$F19/$M19*AO19*150% -> 0 | AW19: =$F19/$M19*AP19*200% -> 0 | AX19: =$F19/$M19*AQ19*300% -> 0 | AY19: =$F19/$M19*AR19*30% -> 0 | AZ19: =$F19/$M19*AS19*210% -> 0 | BA19: =$F19/$M19*AT19*270% -> 0 | BB19: =$F19/$M19*AU19*390% -> 0 | BC19: =ROUND(SUM(AV19:BB19)+CH19,0) -> 0 | BD19: =SUM(P19:AN19)+BC19 -> 12747083 | BJ19: =SUM(BG19:BI19) -> 0 | BL19: =VLOOKUP(A19,'[1]Payroll master '!B$12:AD$160,29,0) -> 2 | BM19: =11000000+4400000*BL19 -> 19800000 | BN19: =ROUND(IF((CJ19-BJ19-BM19-BR19)<0,0,(CJ19-BJ19-BM19-BR19)),0) -> 0 | BO19: =ROUND((VLOOKUP(BN19,'SHUI & PIT'!$A$1:$C$8,2,1)*BN19-VLOOKUP(BN19,'SHUI & PIT'!$A$1:$C$8,3,1)),0) -> 0 | BP19: =Y19 -> 0 | BS19: =BJ19+BO19+BP19+BR19+BE19+BF19+BQ19+BK19 -> 0 | BT19: =ROUND(IF((BD19-BS19)<0,0,(BD19-BS19)),0) -> 12747083 | BY19: =SUM(BU19:BX19) -> 0 | BZ19: =IF(BU19>0,ROUND($CB19*'SHUI & PIT'!$I$12,0),0) -> 0 | CA19: =BD19+BY19-AC19+BZ19-BQ19 -> 12747083 | CB19: =IF(($F19+$T19)>='SHUI & PIT'!$C$12,'SHUI & PIT'!$C$12,($F19+$T19)) -> 11400000 | CC19: =IF(($F19+$T19)>='SHUI & PIT'!$C$13,'SHUI & PIT'!$C$13,($F19+$T19)) -> 11400000 | CD19: =ROUND(($F19/M19)*($AO19*0.5+$AP19+$AQ19*2+AR19*0.3+AS19*1.1+AT19*1.7+AU19*2.9),0) -> 0 | CE19: =BC19-CD19 -> 0 | CF19: =_xlfn.XLOOKUP(A19,'[2]Termination and others'!B$12:B$33,'[2]Termination and others'!F$12:F$33,0,0) -> 0 | CG19: =VLOOKUP(A19,Main!$B$13:$BN$405,65,0) -> 0 | CH19: =IF(50000<F19/M19,50000,F19/M19)*CG19 -> 0 | CJ19: =BD19-R19-S19-AK19-CD19-AC19-BE19-BF19-BQ19 -> 12329167
A20: 0014 | C20: 35690 | D20: =DATEDIF(C20,$C$3,"D") -> 9652 | E20: La Nga | F20: 15460000 | G20: 0 | H20: 300000 | I20: 0 | J20: 0 | K20: 0 | L20: 0 | M20: =_xlfn.XLOOKUP(A20,Main!$B$13:$B$1048576,Main!$D$13:$D$1048576,0,0)*8 -> 194 | N20: =_xlfn.XLOOKUP(A20,Main!$B$13:$B$1048576,Main!$BQ$13:$BQ$1048576,0,0) -> 194 | O20: =_xlfn.XLOOKUP(A20,Main!$B$13:$B$1048576,Main!$BR$13:$BR$1048576,0,0) -> 126 | P20: =ROUND(F20/M20*N20,0) -> 15460000 | Q20: =G20/M20*O20 -> 0 | R20: =IF(D20>=(M20/8),H20,H20/M20*N20) -> 300000 | S20: =IF(CI20="N",26500*(ROUND(O20/8,0)),(I20/M20*O20)-CF20) -> 0 | T20: =J20 -> 0 | U20: =K20/M20*O20 -> 0 | V20: =IF(D20>=(M20/8),L20,L20/M20*N20) -> 0 | AE20: YES | AF20: 0 | AG20: 0 | AJ20: 0 | AK20: 0 | AL20: 0 | AM20: 0 | AN20: 0 | AO20: =_xlfn.XLOOKUP($A20,Main!$B$13:$B$35,Main!BU$13:BU$35,0,0) -> 0 | AP20: =_xlfn.XLOOKUP($A20,Main!$B$13:$B$35,Main!BV$13:BV$35,0,0) -> 0 | AQ20: =_xlfn.XLOOKUP($A20,Main!$B$13:$B$35,Main!BW$13:BW$35,0,0) -> 0 | AR20: =_xlfn.XLOOKUP($A20,Main!$B$13:$B$35,Main!BX$13:BX$35,0,0) -> 0 | AS20: =_xlfn.XLOOKUP($A20,Main!$B$13:$B$35,Main!BY$13:BY$35,0,0) -> 0 | AT20: =_xlfn.XLOOKUP($A20,Main!$B$13:$B$35,Main!BZ$13:BZ$35,0,0) -> 0 | AU20: =_xlfn.XLOOKUP($A20,Main!$B$13:$B$35,Main!CA$13:CA$35,0,0) -> 0 | AV20: =$F20/$M20*AO20*150% -> 0 | AW20: =$F20/$M20*AP20*200% -> 0 | AX20: =$F20/$M20*AQ20*300% -> 0 | AY20: =$F20/$M20*AR20*30% -> 0 | AZ20: =$F20/$M20*AS20*210% -> 0 | BA20: =$F20/$M20*AT20*270% -> 0 | BB20: =$F20/$M20*AU20*390% -> 0 | BC20: =ROUND(SUM(AV20:BB20)+CH20,0) -> 508000 | BD20: =SUM(P20:AN20)+BC20 -> 16268000 | BG20: =ROUND($CB20*'SHUI & PIT'!$F$11,0) -> 1236800 | BH20: =ROUND($CB20*'SHUI & PIT'!$G$11,0) -> 231900 | BI20: =ROUND($CC20*'SHUI & PIT'!$H$11,0) -> 154600 | BJ20: =SUM(BG20:BI20) -> 1623300 | BK20: =IF(E20="La Nga",0,IF(E20="HCM",35000,IF(AE20="YES",IF($BG20>0,ROUND(MIN($CB20*1%,180000),0),0),0))) -> 0 | BL20: =VLOOKUP(A20,'[1]Payroll master '!B$12:AD$160,29,0) -> 2 | BM20: =11000000+4400000*BL20 -> 19800000 | BN20: =ROUND(IF((CJ20-BJ20-BM20-BR20)<0,0,(CJ20-BJ20-BM20-BR20)),0) -> 0 | BO20: =ROUND((VLOOKUP(BN20,'SHUI & PIT'!$A$1:$C$8,2,1)*BN20-VLOOKUP(BN20,'SHUI & PIT'!$A$1:$C$8,3,1)),0) -> 0 | BP20: =Y20 -> 0 | BS20: =BJ20+BO20+BP20+BR20+BE20+BF20+BQ20+BK20 -> 1623300 | BT20: =ROUND(IF((BD20-BS20)<0,0,(BD20-BS20)),0) -> 14644700 | BU20: =ROUND($CB20*'SHUI & PIT'!$F$12,0) -> 2705500 | BV20: =ROUND($CB20*'SHUI & PIT'!$G$12,0) -> 463800 | BW20: =ROUND($CC20*'SHUI & PIT'!$H$12,0) -> 154600 | BX20: 0 | BY20: =SUM(BU20:BX20) -> 3323900 | BZ20: =IF(BU20>0,ROUND($CB20*'SHUI & PIT'!$I$12,0),0) -> 309200 | CA20: =BD20+BY20-AC20+BZ20-BQ20 -> 19901100 | CB20: =IF(($F20+$T20)>='SHUI & PIT'!$C$12,'SHUI & PIT'!$C$12,($F20+$T20)) -> 15460000 | CC20: =IF(($F20+$T20)>='SHUI & PIT'!$C$13,'SHUI & PIT'!$C$13,($F20+$T20)) -> 15460000 | CD20: =ROUND(($F20/M20)*($AO20*0.5+$AP20+$AQ20*2+AR20*0.3+AS20*1.1+AT20*1.7+AU20*2.9),0) -> 0 | CE20: =BC20-CD20 -> 508000 | CF20: =_xlfn.XLOOKUP(A20,'[2]Termination and others'!B$12:B$33,'[2]Termination and others'!F$12:F$33,0,0) -> 0 | CG20: =VLOOKUP(A20,Main!$B$13:$BN$405,65,0) -> 10.16 | CH20: =IF(50000<F20/M20,50000,F20/M20)*CG20 -> 508000 | CJ20: =BD20-R20-S20-AK20-CD20-AC20-BE20-BF20-BQ20 -> 15968000
A21: 0016 | C21: 36342 | D21: =DATEDIF(C21,$C$3,"D") -> 9000 | E21: La Nga | F21: 6810000 | G21: 0 | H21: 0 | I21: 26500 | J21: 0 | K21: 0 | L21: 0 | M21: =_xlfn.XLOOKUP(A21,Main!$B$13:$B$1048576,Main!$D$13:$D$1048576,0,0)*8 -> 192 | N21: =_xlfn.XLOOKUP(A21,Main!$B$13:$B$1048576,Main!$BQ$13:$BQ$1048576,0,0) -> 192 | O21: =_xlfn.XLOOKUP(A21,Main!$B$13:$B$1048576,Main!$BR$13:$BR$1048576,0,0) -> 144 | P21: =ROUND(F21/M21*N21,0) -> 6810000 | Q21: =G21/M21*O21 -> 0 | R21: =IF(D21>=(M21/8),H21,H21/M21*N21) -> 0 | S21: =IF(CI21="N",26500*(ROUND(O21/8,0)),(I21/M21*O21)-CF21) -> 477000 | T21: =J21 -> 0 | U21: =K21/M21*O21 -> 0 | V21: =IF(D21>=(M21/8),L21,L21/M21*N21) -> 0 | AE21: YES | AF21: 0 | AG21: 0 | AJ21: 0 | AK21: 0 | AL21: 0 | AM21: 0 | AN21: 0 | AO21: =_xlfn.XLOOKUP($A21,Main!$B$13:$B$35,Main!BU$13:BU$35,0,0) -> 0 | AP21: =_xlfn.XLOOKUP($A21,Main!$B$13:$B$35,Main!BV$13:BV$35,0,0) -> 0 | AQ21: =_xlfn.XLOOKUP($A21,Main!$B$13:$B$35,Main!BW$13:BW$35,0,0) -> 0 | AR21: =_xlfn.XLOOKUP($A21,Main!$B$13:$B$35,Main!BX$13:BX$35,0,0) -> 0 | AS21: =_xlfn.XLOOKUP($A21,Main!$B$13:$B$35,Main!BY$13:BY$35,0,0) -> 0 | AT21: =_xlfn.XLOOKUP($A21,Main!$B$13:$B$35,Main!BZ$13:BZ$35,0,0) -> 0 | AU21: =_xlfn.XLOOKUP($A21,Main!$B$13:$B$35,Main!CA$13:CA$35,0,0) -> 0 | AV21: =$F21/$M21*AO21*150% -> 0 | AW21: =$F21/$M21*AP21*200% -> 0 | AX21: =$F21/$M21*AQ21*300% -> 0 | AY21: =$F21/$M21*AR21*30% -> 0 | AZ21: =$F21/$M21*AS21*210% -> 0 | BA21: =$F21/$M21*AT21*270% -> 0 | BB21: =$F21/$M21*AU21*390% -> 0 | BC21: =ROUND(SUM(AV21:BB21)+CH21,0) -> 0 | BD21: =SUM(P21:AN21)+BC21 -> 7287000 | BG21: =ROUND($CB21*'SHUI & PIT'!$F$11,0) -> 544800 | BH21: =ROUND($CB21*'SHUI & PIT'!$G$11,0) -> 102150 | BI21: =ROUND($CC21*'SHUI & PIT'!$H$11,0) -> 68100 | BJ21: =SUM(BG21:BI21) -> 715050 | BK21: =IF(E21="La Nga",0,IF(E21="HCM",35000,IF(AE21="YES",IF($BG21>0,ROUND(MIN($CB21*1%,180000),0),0),0))) -> 0 | BL21: =VLOOKUP(A21,'[1]Payroll master '!B$12:AD$160,29,0) -> 0 | BM21: =11000000+4400000*BL21 -> 11000000 | BN21: =ROUND(IF((CJ21-BJ21-BM21-BR21)<0,0,(CJ21-BJ21-BM21-BR21)),0) -> 0 | BO21: =ROUND((VLOOKUP(BN21,'SHUI & PIT'!$A$1:$C$8,2,1)*BN21-VLOOKUP(BN21,'SHUI & PIT'!$A$1:$C$8,3,1)),0) -> 0 | BP21: =Y21 -> 0 | BS21: =BJ21+BO21+BP21+BR21+BE21+BF21+BQ21+BK21 -> 715050 | BT21: =ROUND(IF((BD21-BS21)<0,0,(BD21-BS21)),0) -> 6571950 | BU21: =ROUND($CB21*'SHUI & PIT'!$F$12,0) -> 1191750 | BV21: =ROUND($CB21*'SHUI & PIT'!$G$12,0) -> 204300 | BW21: =ROUND($CC21*'SHUI & PIT'!$H$12,0) -> 68100 | BX21: 0 | BY21: =SUM(BU21:BX21) -> 1464150 | BZ21: =IF(BU21>0,ROUND($CB21*'SHUI & PIT'!$I$12,0),0) -> 136200 | CA21: =BD21+BY21-AC21+BZ21-BQ21 -> 8887350 | CB21: =IF(($F21+$T21)>='SHUI & PIT'!$C$12,'SHUI & PIT'!$C$12,($F21+$T21)) -> 6810000 | CC21: =IF(($F21+$T21)>='SHUI & PIT'!$C$13,'SHUI & PIT'!$C$13,($F21+$T21)) -> 6810000 | CD21: =ROUND(($F21/M21)*($AO21*0.5+$AP21+$AQ21*2+AR21*0.3+AS21*1.1+AT21*1.7+AU21*2.9),0) -> 0 | CE21: =BC21-CD21 -> 0 | CF21: =_xlfn.XLOOKUP(A21,'[2]Termination and others'!B$12:B$33,'[2]Termination and others'!F$12:F$33,0,0) -> 0 | CG21: =VLOOKUP(A21,Main!$B$13:$BN$405,65,0) -> 0 | CH21: =IF(50000<F21/M21,50000,F21/M21)*CG21 -> 0 | CI21: N | CJ21: =BD21-R21-S21-AK21-CD21-AC21-BE21-BF21-BQ21 -> 6810000
A22: 0020 | C22: 36122 | D22: =DATEDIF(C22,$C$3,"D") -> 9220 | E22: La Nga | F22: 7250000 | G22: 0 | H22: 0 | I22: 26500 | J22: 0 | K22: 0 | L22: 0 | M22: =_xlfn.XLOOKUP(A22,Main!$B$13:$B$1048576,Main!$D$13:$D$1048576,0,0)*8 -> 192 | N22: =_xlfn.XLOOKUP(A22,Main!$B$13:$B$1048576,Main!$BQ$13:$BQ$1048576,0,0) -> 192 | O22: =_xlfn.XLOOKUP(A22,Main!$B$13:$B$1048576,Main!$BR$13:$BR$1048576,0,0) -> 128 | P22: =ROUND(F22/M22*N22,0) -> 7250000 | Q22: =G22/M22*O22 -> 0 | R22: =IF(D22>=(M22/8),H22,H22/M22*N22) -> 0 | S22: =IF(CI22="N",26500*(ROUND(O22/8,0)),(I22/M22*O22)-CF22) -> 424000 | T22: =J22 -> 0 | U22: =K22/M22*O22 -> 0 | V22: =IF(D22>=(M22/8),L22,L22/M22*N22) -> 0 | AE22: YES | AF22: 0 | AG22: 0 | AJ22: 0 | AK22: 0 | AL22: 0 | AM22: 0 | AN22: 0 | AO22: =_xlfn.XLOOKUP($A22,Main!$B$13:$B$35,Main!BU$13:BU$35,0,0) -> 0 | AP22: =_xlfn.XLOOKUP($A22,Main!$B$13:$B$35,Main!BV$13:BV$35,0,0) -> 0 | AQ22: =_xlfn.XLOOKUP($A22,Main!$B$13:$B$35,Main!BW$13:BW$35,0,0) -> 0 | AR22: =_xlfn.XLOOKUP($A22,Main!$B$13:$B$35,Main!BX$13:BX$35,0,0) -> 0 | AS22: =_xlfn.XLOOKUP($A22,Main!$B$13:$B$35,Main!BY$13:BY$35,0,0) -> 0 | AT22: =_xlfn.XLOOKUP($A22,Main!$B$13:$B$35,Main!BZ$13:BZ$35,0,0) -> 0 | AU22: =_xlfn.XLOOKUP($A22,Main!$B$13:$B$35,Main!CA$13:CA$35,0,0) -> 0 | AV22: =$F22/$M22*AO22*150% -> 0 | AW22: =$F22/$M22*AP22*200% -> 0 | AX22: =$F22/$M22*AQ22*300% -> 0 | AY22: =$F22/$M22*AR22*30% -> 0 | AZ22: =$F22/$M22*AS22*210% -> 0 | BA22: =$F22/$M22*AT22*270% -> 0 | BB22: =$F22/$M22*AU22*390% -> 0 | BC22: =ROUND(SUM(AV22:BB22)+CH22,0) -> 0 | BD22: =SUM(P22:AN22)+BC22 -> 7674000 | BG22: =ROUND($CB22*'SHUI & PIT'!$F$11,0) -> 580000 | BH22: =ROUND($CB22*'SHUI & PIT'!$G$11,0) -> 108750 | BI22: =ROUND($CC22*'SHUI & PIT'!$H$11,0) -> 72500 | BJ22: =SUM(BG22:BI22) -> 761250 | BK22: =IF(E22="La Nga",0,IF(E22="HCM",35000,IF(AE22="YES",IF($BG22>0,ROUND(MIN($CB22*1%,180000),0),0),0))) -> 0 | BL22: =VLOOKUP(A22,'[1]Payroll master '!B$12:AD$160,29,0) -> 0 | BM22: =11000000+4400000*BL22 -> 11000000 | BN22: =ROUND(IF((CJ22-BJ22-BM22-BR22)<0,0,(CJ22-BJ22-BM22-BR22)),0) -> 0 | BO22: =ROUND((VLOOKUP(BN22,'SHUI & PIT'!$A$1:$C$8,2,1)*BN22-VLOOKUP(BN22,'SHUI & PIT'!$A$1:$C$8,3,1)),0) -> 0 | BP22: =Y22 -> 0 | BS22: =BJ22+BO22+BP22+BR22+BE22+BF22+BQ22+BK22 -> 761250 | BT22: =ROUND(IF((BD22-BS22)<0,0,(BD22-BS22)),0) -> 6912750 | BU22: =ROUND($CB22*'SHUI & PIT'!$F$12,0) -> 1268750 | BV22: =ROUND($CB22*'SHUI & PIT'!$G$12,0) -> 217500 | BW22: =ROUND($CC22*'SHUI & PIT'!$H$12,0) -> 72500 | BX22: 0 | BY22: =SUM(BU22:BX22) -> 1558750 | BZ22: =IF(BU22>0,ROUND($CB22*'SHUI & PIT'!$I$12,0),0) -> 145000 | CA22: =BD22+BY22-AC22+BZ22-BQ22 -> 9377750 | CB22: =IF(($F22+$T22)>='SHUI & PIT'!$C$12,'SHUI & PIT'!$C$12,($F22+$T22)) -> 7250000 | CC22: =IF(($F22+$T22)>='SHUI & PIT'!$C$13,'SHUI & PIT'!$C$13,($F22+$T22)) -> 7250000 | CD22: =ROUND(($F22/M22)*($AO22*0.5+$AP22+$AQ22*2+AR22*0.3+AS22*1.1+AT22*1.7+AU22*2.9),0) -> 0 | CE22: =BC22-CD22 -> 0 | CF22: =_xlfn.XLOOKUP(A22,'[2]Termination and others'!B$12:B$33,'[2]Termination and others'!F$12:F$33,0,0) -> 0 | CG22: =VLOOKUP(A22,Main!$B$13:$BN$405,65,0) -> 0 | CH22: =IF(50000<F22/M22,50000,F22/M22)*CG22 -> 0 | CI22: N | CJ22: =BD22-R22-S22-AK22-CD22-AC22-BE22-BF22-BQ22 -> 7250000
A23: 0023 | C23: 36122 | D23: =DATEDIF(C23,$C$3,"D") -> 9220 | E23: La Nga | F23: 11780000 | G23: 0 | H23: 200000 | I23: 0 | J23: 2000000 | K23: 0 | L23: 0 | M23: =_xlfn.XLOOKUP(A23,Main!$B$13:$B$1048576,Main!$D$13:$D$1048576,0,0)*8 -> 194 | N23: =_xlfn.XLOOKUP(A23,Main!$B$13:$B$1048576,Main!$BQ$13:$BQ$1048576,0,0) -> 194 | O23: =_xlfn.XLOOKUP(A23,Main!$B$13:$B$1048576,Main!$BR$13:$BR$1048576,0,0) -> 150 | P23: =ROUND(F23/M23*N23,0) -> 11780000 | Q23: =G23/M23*O23 -> 0 | R23: =IF(D23>=(M23/8),H23,H23/M23*N23) -> 200000 | S23: =IF(CI23="N",26500*(ROUND(O23/8,0)),(I23/M23*O23)-CF23) -> 0 | T23: =J23 -> 2000000 | U23: =K23/M23*O23 -> 0 | V23: =IF(D23>=(M23/8),L23,L23/M23*N23) -> 0 | AE23: YES | AF23: 0 | AG23: 0 | AJ23: 0 | AK23: 0 | AL23: 0 | AM23: 0 | AN23: 0 | AO23: =_xlfn.XLOOKUP($A23,Main!$B$13:$B$35,Main!BU$13:BU$35,0,0) -> 0 | AP23: =_xlfn.XLOOKUP($A23,Main!$B$13:$B$35,Main!BV$13:BV$35,0,0) -> 0 | AQ23: =_xlfn.XLOOKUP($A23,Main!$B$13:$B$35,Main!BW$13:BW$35,0,0) -> 0 | AR23: =_xlfn.XLOOKUP($A23,Main!$B$13:$B$35,Main!BX$13:BX$35,0,0) -> 0 | AS23: =_xlfn.XLOOKUP($A23,Main!$B$13:$B$35,Main!BY$13:BY$35,0,0) -> 0 | AT23: =_xlfn.XLOOKUP($A23,Main!$B$13:$B$35,Main!BZ$13:BZ$35,0,0) -> 0 | AU23: =_xlfn.XLOOKUP($A23,Main!$B$13:$B$35,Main!CA$13:CA$35,0,0) -> 0 | AV23: =$F23/$M23*AO23*150% -> 0 | AW23: =$F23/$M23*AP23*200% -> 0 | AX23: =$F23/$M23*AQ23*300% -> 0 | AY23: =$F23/$M23*AR23*30% -> 0 | AZ23: =$F23/$M23*AS23*210% -> 0 | BA23: =$F23/$M23*AT23*270% -> 0 | BB23: =$F23/$M23*AU23*390% -> 0 | BC23: =ROUND(SUM(AV23:BB23)+CH23,0) -> 0 | BD23: =SUM(P23:AN23)+BC23 -> 13980000 | BG23: =ROUND($CB23*'SHUI & PIT'!$F$11,0) -> 1102400 | BH23: =ROUND($CB23*'SHUI & PIT'!$G$11,0) -> 206700 | BI23: =ROUND($CC23*'SHUI & PIT'!$H$11,0) -> 137800 | BJ23: =SUM(BG23:BI23) -> 1446900 | BK23: =IF(E23="La Nga",0,IF(E23="HCM",35000,IF(AE23="YES",IF($BG23>0,ROUND(MIN($CB23*1%,180000),0),0),0))) -> 0 | BL23: =VLOOKUP(A23,'[1]Payroll master '!B$12:AD$160,29,0) -> 0 | BM23: =11000000+4400000*BL23 -> 11000000 | BN23: =ROUND(IF((CJ23-BJ23-BM23-BR23)<0,0,(CJ23-BJ23-BM23-BR23)),0) -> 1333100 | BO23: =ROUND((VLOOKUP(BN23,'SHUI & PIT'!$A$1:$C$8,2,1)*BN23-VLOOKUP(BN23,'SHUI & PIT'!$A$1:$C$8,3,1)),0) -> 66655 | BP23: =Y23 -> 0 | BS23: =BJ23+BO23+BP23+BR23+BE23+BF23+BQ23+BK23 -> 1513555 | BT23: =ROUND(IF((BD23-BS23)<0,0,(BD23-BS23)),0) -> 12466445 | BU23: =ROUND($CB23*'SHUI & PIT'!$F$12,0) -> 2411500 | BV23: =ROUND($CB23*'SHUI & PIT'!$G$12,0) -> 413400 | BW23: =ROUND($CC23*'SHUI & PIT'!$H$12,0) -> 137800 | BX23: 0 | BY23: =SUM(BU23:BX23) -> 2962700 | BZ23: =IF(BU23>0,ROUND($CB23*'SHUI & PIT'!$I$12,0),0) -> 275600 | CA23: =BD23+BY23-AC23+BZ23-BQ23 -> 17218300 | CB23: =IF(($F23+$T23)>='SHUI & PIT'!$C$12,'SHUI & PIT'!$C$12,($F23+$T23)) -> 13780000 | CC23: =IF(($F23+$T23)>='SHUI & PIT'!$C$13,'SHUI & PIT'!$C$13,($F23+$T23)) -> 13780000 | CD23: =ROUND(($F23/M23)*($AO23*0.5+$AP23+$AQ23*2+AR23*0.3+AS23*1.1+AT23*1.7+AU23*2.9),0) -> 0 | CE23: =BC23-CD23 -> 0 | CF23: =_xlfn.XLOOKUP(A23,'[2]Termination and others'!B$12:B$33,'[2]Termination and others'!F$12:F$33,0,0) -> 0 | CG23: =VLOOKUP(A23,Main!$B$13:$BN$405,65,0) -> 0 | CH23: =IF(50000<F23/M23,50000,F23/M23)*CG23 -> 0 | CJ23: =BD23-R23-S23-AK23-CD23-AC23-BE23-BF23-BQ23 -> 13780000
A24: 0024 | C24: 35200 | D24: =DATEDIF(C24,$C$3,"D") -> 10142 | E24: La Nga | F24: 12230000 | G24: 0 | H24: 200000 | I24: 0 | J24: =2000000+900000 -> 2900000 | K24: 0 | L24: 0 | M24: =_xlfn.XLOOKUP(A24,Main!$B$13:$B$1048576,Main!$D$13:$D$1048576,0,0)*8 -> 194 | N24: =_xlfn.XLOOKUP(A24,Main!$B$13:$B$1048576,Main!$BQ$13:$BQ$1048576,0,0) -> 194 | O24: =_xlfn.XLOOKUP(A24,Main!$B$13:$B$1048576,Main!$BR$13:$BR$1048576,0,0) -> 115 | P24: =ROUND(F24/M24*N24,0) -> 12230000 | Q24: =G24/M24*O24 -> 0 | R24: =IF(D24>=(M24/8),H24,H24/M24*N24) -> 200000 | S24: =IF(CI24="N",26500*(ROUND(O24/8,0)),(I24/M24*O24)-CF24) -> 0 | T24: =J24 -> 2900000 | U24: =K24/M24*O24 -> 0 | V24: =IF(D24>=(M24/8),L24,L24/M24*N24) -> 0 | AE24: YES | AF24: 0 | AO24: =_xlfn.XLOOKUP($A24,Main!$B$13:$B$35,Main!BU$13:BU$35,0,0) -> 0 | AP24: =_xlfn.XLOOKUP($A24,Main!$B$13:$B$35,Main!BV$13:BV$35,0,0) -> 0 | AQ24: =_xlfn.XLOOKUP($A24,Main!$B$13:$B$35,Main!BW$13:BW$35,0,0) -> 6.83 | AR24: =_xlfn.XLOOKUP($A24,Main!$B$13:$B$35,Main!BX$13:BX$35,0,0) -> 0 | AS24: =_xlfn.XLOOKUP($A24,Main!$B$13:$B$35,Main!BY$13:BY$35,0,0) -> 0 | AT24: =_xlfn.XLOOKUP($A24,Main!$B$13:$B$35,Main!BZ$13:BZ$35,0,0) -> 0 | AU24: =_xlfn.XLOOKUP($A24,Main!$B$13:$B$35,Main!CA$13:CA$35,0,0) -> 0 | AV24: =$F24/$M24*AO24*150% -> 0 | AW24: =$F24/$M24*AP24*200% -> 0 | AX24: =$F24/$M24*AQ24*300% -> 1291714.9 | AY24: =$F24/$M24*AR24*30% -> 0 | AZ24: =$F24/$M24*AS24*210% -> 0 | BA24: =$F24/$M24*AT24*270% -> 0 | BB24: =$F24/$M24*AU24*390% -> 0 | BC24: =ROUND(SUM(AV24:BB24)+CH24,0) -> 1291715 | BD24: =SUM(P24:AN24)+BC24 -> 16621715 | BG24: =ROUND($CB24*'SHUI & PIT'!$F$11,0) -> 1210400 | BH24: =ROUND($CB24*'SHUI & PIT'!$G$11,0) -> 226950 | BI24: =ROUND($CC24*'SHUI & PIT'!$H$11,0) -> 151300 | BJ24: =SUM(BG24:BI24) -> 1588650 | BK24: =IF(E24="La Nga",0,IF(E24="HCM",35000,IF(AE24="YES",IF($BG24>0,ROUND(MIN($CB24*1%,180000),0),0),0))) -> 0 | BL24: =VLOOKUP(A24,'[1]Payroll master '!B$12:AD$160,29,0) -> 1 | BM24: =11000000+4400000*BL24 -> 15400000 | BN24: =ROUND(IF((CJ24-BJ24-BM24-BR24)<0,0,(CJ24-BJ24-BM24-BR24)),0) -> 0 | BO24: =ROUND((VLOOKUP(BN24,'SHUI & PIT'!$A$1:$C$8,2,1)*BN24-VLOOKUP(BN24,'SHUI & PIT'!$A$1:$C$8,3,1)),0) -> 0 | BP24: =Y24 -> 0 | BS24: =BJ24+BO24+BP24+BR24+BE24+BF24+BQ24+BK24 -> 1588650 | BT24: =ROUND(IF((BD24-BS24)<0,0,(BD24-BS24)),0) -> 15033065 | BU24: =ROUND($CB24*'SHUI & PIT'!$F$12,0) -> 2647750 | BV24: =ROUND($CB24*'SHUI & PIT'!$G$12,0) -> 453900 | BW24: =ROUND($CC24*'SHUI & PIT'!$H$12,0) -> 151300 | BY24: =SUM(BU24:BX24) -> 3252950 | BZ24: =IF(BU24>0,ROUND($CB24*'SHUI & PIT'!$I$12,0),0) -> 302600 | CA24: =BD24+BY24-AC24+BZ24-BQ24 -> 20177265 | CB24: =IF(($F24+$T24)>='SHUI & PIT'!$C$12,'SHUI & PIT'!$C$12,($F24+$T24)) -> 15130000 | CC24: =IF(($F24+$T24)>='SHUI & PIT'!$C$13,'SHUI & PIT'!$C$13,($F24+$T24)) -> 15130000 | CD24: =ROUND(($F24/M24)*($AO24*0.5+$AP24+$AQ24*2+AR24*0.3+AS24*1.1+AT24*1.7+AU24*2.9),0) -> 861143 | CE24: =BC24-CD24 -> 430572 | CF24: =_xlfn.XLOOKUP(A24,'[2]Termination and others'!B$12:B$33,'[2]Termination and others'!F$12:F$33,0,0) -> 0 | CG24: =VLOOKUP(A24,Main!$B$13:$BN$405,65,0) -> 0 | CH24: =IF(50000<F24/M24,50000,F24/M24)*CG24 -> 0 | CJ24: =BD24-R24-S24-AK24-CD24-AC24-BE24-BF24-BQ24 -> 15560572
A25: 0242 | C25: 38020 | D25: =DATEDIF(C25,$C$3,"D") -> 7322 | E25: La Nga | F25: 13600000 | G25: 0 | H25: 200000 | I25: 0 | J25: 0 | K25: 0 | L25: 0 | M25: =_xlfn.XLOOKUP(A25,Main!$B$13:$B$1048576,Main!$D$13:$D$1048576,0,0)*8 -> 194 | N25: =_xlfn.XLOOKUP(A25,Main!$B$13:$B$1048576,Main!$BQ$13:$BQ$1048576,0,0) -> 194 | O25: =_xlfn.XLOOKUP(A25,Main!$B$13:$B$1048576,Main!$BR$13:$BR$1048576,0,0) -> 146 | P25: =ROUND(F25/M25*N25,0) -> 13600000 | Q25: =G25/M25*O25 -> 0 | R25: =IF(D25>=(M25/8),H25,H25/M25*N25) -> 200000 | S25: =IF(CI25="N",26500*(ROUND(O25/8,0)),(I25/M25*O25)-CF25) -> 0 | T25: =J25 -> 0 | U25: =K25/M25*O25 -> 0 | V25: =IF(D25>=(M25/8),L25,L25/M25*N25) -> 0 | AE25: YES | AO25: =_xlfn.XLOOKUP($A25,Main!$B$13:$B$35,Main!BU$13:BU$35,0,0) -> 8 | AP25: =_xlfn.XLOOKUP($A25,Main!$B$13:$B$35,Main!BV$13:BV$35,0,0) -> 8 | AQ25: =_xlfn.XLOOKUP($A25,Main!$B$13:$B$35,Main!BW$13:BW$35,0,0) -> 0 | AR25: =_xlfn.XLOOKUP($A25,Main!$B$13:$B$35,Main!BX$13:BX$35,0,0) -> 0 | AS25: =_xlfn.XLOOKUP($A25,Main!$B$13:$B$35,Main!BY$13:BY$35,0,0) -> 0 | AT25: =_xlfn.XLOOKUP($A25,Main!$B$13:$B$35,Main!BZ$13:BZ$35,0,0) -> 0 | AU25: =_xlfn.XLOOKUP($A25,Main!$B$13:$B$35,Main!CA$13:CA$35,0,0) -> 0 | AV25: =$F25/$M25*AO25*150% -> 841237.11 | AW25: =$F25/$M25*AP25*200% -> 1121649.5 | AX25: =$F25/$M25*AQ25*300% -> 0 | AY25: =$F25/$M25*AR25*30% -> 0 | AZ25: =$F25/$M25*AS25*210% -> 0 | BA25: =$F25/$M25*AT25*270% -> 0 | BB25: =$F25/$M25*AU25*390% -> 0 | BC25: =ROUND(SUM(AV25:BB25)+CH25,0) -> 1962887 | BD25: =SUM(P25:AN25)+BC25 -> 15762887 | BG25: =ROUND($CB25*'SHUI & PIT'!$F$11,0) -> 1088000 | BH25: =ROUND($CB25*'SHUI & PIT'!$G$11,0) -> 204000 | BI25: =ROUND($CC25*'SHUI & PIT'!$H$11,0) -> 136000 | BJ25: =SUM(BG25:BI25) -> 1428000 | BK25: =IF(E25="La Nga",0,IF(E25="HCM",35000,IF(AE25="YES",IF($BG25>0,ROUND(MIN($CB25*1%,180000),0),0),0))) -> 0 | BL25: =VLOOKUP(A25,'[1]Payroll master '!B$12:AD$160,29,0) -> 1 | BM25: =11000000+4400000*BL25 -> 15400000 | BN25: =ROUND(IF((CJ25-BJ25-BM25-BR25)<0,0,(CJ25-BJ25-BM25-BR25)),0) -> 0 | BO25: =ROUND((VLOOKUP(BN25,'SHUI & PIT'!$A$1:$C$8,2,1)*BN25-VLOOKUP(BN25,'SHUI & PIT'!$A$1:$C$8,3,1)),0) -> 0 | BP25: =Y25 -> 0 | BS25: =BJ25+BO25+BP25+BR25+BE25+BF25+BQ25+BK25 -> 1428000 | BT25: =ROUND(IF((BD25-BS25)<0,0,(BD25-BS25)),0) -> 14334887 | BU25: =ROUND($CB25*'SHUI & PIT'!$F$12,0) -> 2380000 | BV25: =ROUND($CB25*'SHUI & PIT'!$G$12,0) -> 408000 | BW25: =ROUND($CC25*'SHUI & PIT'!$H$12,0) -> 136000 | BY25: =SUM(BU25:BX25) -> 2924000 | BZ25: =IF(BU25>0,ROUND($CB25*'SHUI & PIT'!$I$12,0),0) -> 272000 | CA25: =BD25+BY25-AC25+BZ25-BQ25 -> 18958887 | CB25: =IF(($F25+$T25)>='SHUI & PIT'!$C$12,'SHUI & PIT'!$C$12,($F25+$T25)) -> 13600000 | CC25: =IF(($F25+$T25)>='SHUI & PIT'!$C$13,'SHUI & PIT'!$C$13,($F25+$T25)) -> 13600000 | CD25: =ROUND(($F25/M25)*($AO25*0.5+$AP25+$AQ25*2+AR25*0.3+AS25*1.1+AT25*1.7+AU25*2.9),0) -> 841237 | CE25: =BC25-CD25 -> 1121650 | CF25: =_xlfn.XLOOKUP(A25,'[2]Termination and others'!B$12:B$33,'[2]Termination and others'!F$12:F$33,0,0) -> 0 | CG25: =VLOOKUP(A25,Main!$B$13:$BN$405,65,0) -> 0 | CH25: =IF(50000<F25/M25,50000,F25/M25)*CG25 -> 0 | CJ25: =BD25-R25-S25-AK25-CD25-AC25-BE25-BF25-BQ25 -> 14721650
A26: 0272 | C26: 38355 | D26: =DATEDIF(C26,$C$3,"D") -> 6987 | E26: La Nga | F26: 13740000 | G26: 0 | H26: 300000 | I26: 0 | J26: 850000 | K26: 0 | L26: 0 | M26: =_xlfn.XLOOKUP(A26,Main!$B$13:$B$1048576,Main!$D$13:$D$1048576,0,0)*8 -> 192 | N26: =_xlfn.XLOOKUP(A26,Main!$B$13:$B$1048576,Main!$BQ$13:$BQ$1048576,0,0) -> 192 | O26: =_xlfn.XLOOKUP(A26,Main!$B$13:$B$1048576,Main!$BR$13:$BR$1048576,0,0) -> 136.3 | P26: =ROUND(F26/M26*N26,0) -> 13740000 | Q26: =G26/M26*O26 -> 0 | R26: =IF(D26>=(M26/8),H26,H26/M26*N26) -> 300000 | S26: =IF(CI26="N",26500*(ROUND(O26/8,0)),(I26/M26*O26)-CF26) -> 0 | T26: =J26 -> 850000 | U26: =K26/M26*O26 -> 0 | V26: =IF(D26>=(M26/8),L26,L26/M26*N26) -> 0 | AE26: YES | AO26: =_xlfn.XLOOKUP($A26,Main!$B$13:$B$35,Main!BU$13:BU$35,0,0) -> 8.22 | AP26: =_xlfn.XLOOKUP($A26,Main!$B$13:$B$35,Main!BV$13:BV$35,0,0) -> 0 | AQ26: =_xlfn.XLOOKUP($A26,Main!$B$13:$B$35,Main!BW$13:BW$35,0,0) -> 3.25 | AR26: =_xlfn.XLOOKUP($A26,Main!$B$13:$B$35,Main!BX$13:BX$35,0,0) -> 0 | AS26: =_xlfn.XLOOKUP($A26,Main!$B$13:$B$35,Main!BY$13:BY$35,0,0) -> 0 | AT26: =_xlfn.XLOOKUP($A26,Main!$B$13:$B$35,Main!BZ$13:BZ$35,0,0) -> 0 | AU26: =_xlfn.XLOOKUP($A26,Main!$B$13:$B$35,Main!CA$13:CA$35,0,0) -> 0 | AV26: =$F26/$M26*AO26*150% -> 882365.62 | AW26: =$F26/$M26*AP26*200% -> 0 | AX26: =$F26/$M26*AQ26*300% -> 697734.38 | AY26: =$F26/$M26*AR26*30% -> 0 | AZ26: =$F26/$M26*AS26*210% -> 0 | BA26: =$F26/$M26*AT26*270% -> 0 | BB26: =$F26/$M26*AU26*390% -> 0 | BC26: =ROUND(SUM(AV26:BB26)+CH26,0) -> 1580100 | BD26: =SUM(P26:AN26)+BC26 -> 16470100 | BG26: =ROUND($CB26*'SHUI & PIT'!$F$11,0) -> 1167200 | BH26: =ROUND($CB26*'SHUI & PIT'!$G$11,0) -> 218850 | BI26: =ROUND($CC26*'SHUI & PIT'!$H$11,0) -> 145900 | BJ26: =SUM(BG26:BI26) -> 1531950 | BK26: =IF(E26="La Nga",0,IF(E26="HCM",35000,IF(AE26="YES",IF($BG26>0,ROUND(MIN($CB26*1%,180000),0),0),0))) -> 0 | BL26: =VLOOKUP(A26,'[1]Payroll master '!B$12:AD$160,29,0) -> 2 | BM26: =11000000+4400000*BL26 -> 19800000 | BN26: =ROUND(IF((CJ26-BJ26-BM26-BR26)<0,0,(CJ26-BJ26-BM26-BR26)),0) -> 0 | BO26: =ROUND((VLOOKUP(BN26,'SHUI & PIT'!$A$1:$C$8,2,1)*BN26-VLOOKUP(BN26,'SHUI & PIT'!$A$1:$C$8,3,1)),0) -> 0 | BP26: =Y26 -> 0 | BS26: =BJ26+BO26+BP26+BR26+BE26+BF26+BQ26+BK26 -> 1531950 | BT26: =ROUND(IF((BD26-BS26)<0,0,(BD26-BS26)),0) -> 14938150 | BU26: =ROUND($CB26*'SHUI & PIT'!$F$12,0) -> 2553250 | BV26: =ROUND($CB26*'SHUI & PIT'!$G$12,0) -> 437700 | BW26: =ROUND($CC26*'SHUI & PIT'!$H$12,0) -> 145900 | BY26: =SUM(BU26:BX26) -> 3136850 | BZ26: =IF(BU26>0,ROUND($CB26*'SHUI & PIT'!$I$12,0),0) -> 291800 | CA26: =BD26+BY26-AC26+BZ26-BQ26 -> 19898750 | CB26: =IF(($F26+$T26)>='SHUI & PIT'!$C$12,'SHUI & PIT'!$C$12,($F26+$T26)) -> 14590000 | CC26: =IF(($F26+$T26)>='SHUI & PIT'!$C$13,'SHUI & PIT'!$C$13,($F26+$T26)) -> 14590000 | CD26: =ROUND(($F26/M26)*($AO26*0.5+$AP26+$AQ26*2+AR26*0.3+AS26*1.1+AT26*1.7+AU26*2.9),0) -> 759278 | CE26: =BC26-CD26 -> 820822 | CF26: =_xlfn.XLOOKUP(A26,'[2]Termination and others'!B$12:B$33,'[2]Termination and others'!F$12:F$33,0,0) -> 0 | CG26: =VLOOKUP(A26,Main!$B$13:$BN$405,65,0) -> 0 | CH26: =IF(50000<F26/M26,50000,F26/M26)*CG26 -> 0 | CJ26: =BD26-R26-S26-AK26-CD26-AC26-BE26-BF26-BQ26 -> 15410822
A27: 0509 | C27: 39790 | D27: =DATEDIF(C27,$C$3,"D") -> 5552 | E27: La Nga | F27: 8980000 | G27: 0 | H27: 200000 | I27: 0 | J27: 0 | K27: 0 | L27: 0 | M27: =_xlfn.XLOOKUP(A27,Main!$B$13:$B$1048576,Main!$D$13:$D$1048576,0,0)*8 -> 192 | N27: =_xlfn.XLOOKUP(A27,Main!$B$13:$B$1048576,Main!$BQ$13:$BQ$1048576,0,0) -> 192 | O27: =_xlfn.XLOOKUP(A27,Main!$B$13:$B$1048576,Main!$BR$13:$BR$1048576,0,0) -> 148 | P27: =ROUND(F27/M27*N27,0) -> 8980000 | Q27: =G27/M27*O27 -> 0 | R27: =IF(D27>=(M27/8),H27,H27/M27*N27) -> 200000 | S27: =IF(CI27="N",26500*(ROUND(O27/8,0)),(I27/M27*O27)-CF27) -> 0 | T27: =J27 -> 0 | U27: =K27/M27*O27 -> 0 | V27: =IF(D27>=(M27/8),L27,L27/M27*N27) -> 0 | AE27: YES | AO27: =_xlfn.XLOOKUP($A27,Main!$B$13:$B$35,Main!BU$13:BU$35,0,0) -> 18.05 | AP27: =_xlfn.XLOOKUP($A27,Main!$B$13:$B$35,Main!BV$13:BV$35,0,0) -> 0 | AQ27: =_xlfn.XLOOKUP($A27,Main!$B$13:$B$35,Main!BW$13:BW$35,0,0) -> 0 | AR27: =_xlfn.XLOOKUP($A27,Main!$B$13:$B$35,Main!BX$13:BX$35,0,0) -> 0 | AS27: =_xlfn.XLOOKUP($A27,Main!$B$13:$B$35,Main!BY$13:BY$35,0,0) -> 0 | AT27: =_xlfn.XLOOKUP($A27,Main!$B$13:$B$35,Main!BZ$13:BZ$35,0,0) -> 0 | AU27: =_xlfn.XLOOKUP($A27,Main!$B$13:$B$35,Main!CA$13:CA$35,0,0) -> 0 | AV27: =$F27/$M27*AO27*150% -> 1266320.3 | AW27: =$F27/$M27*AP27*200% -> 0 | AX27: =$F27/$M27*AQ27*300% -> 0 | AY27: =$F27/$M27*AR27*30% -> 0 | AZ27: =$F27/$M27*AS27*210% -> 0 | BA27: =$F27/$M27*AT27*270% -> 0 | BB27: =$F27/$M27*AU27*390% -> 0 | BC27: =ROUND(SUM(AV27:BB27)+CH27,0) -> 1266320 | BD27: =SUM(P27:AN27)+BC27 -> 10446320 | BG27: =ROUND($CB27*'SHUI & PIT'!$F$11,0) -> 718400 | BH27: =ROUND($CB27*'SHUI & PIT'!$G$11,0) -> 134700 | BI27: =ROUND($CC27*'SHUI & PIT'!$H$11,0) -> 89800 | BJ27: =SUM(BG27:BI27) -> 942900 | BK27: =IF(E27="La Nga",0,IF(E27="HCM",35000,IF(AE27="YES",IF($BG27>0,ROUND(MIN($CB27*1%,180000),0),0),0))) -> 0 | BL27: =VLOOKUP(A27,'[1]Payroll master '!B$12:AD$160,29,0) -> 2 | BM27: =11000000+4400000*BL27 -> 19800000 | BN27: =ROUND(IF((CJ27-BJ27-BM27-BR27)<0,0,(CJ27-BJ27-BM27-BR27)),0) -> 0 | BO27: =ROUND((VLOOKUP(BN27,'SHUI & PIT'!$A$1:$C$8,2,1)*BN27-VLOOKUP(BN27,'SHUI & PIT'!$A$1:$C$8,3,1)),0) -> 0 | BP27: =Y27 -> 0 | BS27: =BJ27+BO27+BP27+BR27+BE27+BF27+BQ27+BK27 -> 942900 | BT27: =ROUND(IF((BD27-BS27)<0,0,(BD27-BS27)),0) -> 9503420 | BU27: =ROUND($CB27*'SHUI & PIT'!$F$12,0) -> 1571500 | BV27: =ROUND($CB27*'SHUI & PIT'!$G$12,0) -> 269400 | BW27: =ROUND($CC27*'SHUI & PIT'!$H$12,0) -> 89800 | BY27: =SUM(BU27:BX27) -> 1930700 | BZ27: =IF(BU27>0,ROUND($CB27*'SHUI & PIT'!$I$12,0),0) -> 179600 | CA27: =BD27+BY27-AC27+BZ27-BQ27 -> 12556620 | CB27: =IF(($F27+$T27)>='SHUI & PIT'!$C$12,'SHUI & PIT'!$C$12,($F27+$T27)) -> 8980000 | CC27: =IF(($F27+$T27)>='SHUI & PIT'!$C$13,'SHUI & PIT'!$C$13,($F27+$T27)) -> 8980000 | CD27: =ROUND(($F27/M27)*($AO27*0.5+$AP27+$AQ27*2+AR27*0.3+AS27*1.1+AT27*1.7+AU27*2.9),0) -> 422107 | CE27: =BC27-CD27 -> 844213 | CF27: =_xlfn.XLOOKUP(A27,'[2]Termination and others'!B$12:B$33,'[2]Termination and others'!F$12:F$33,0,0) -> 0 | CG27: =VLOOKUP(A27,Main!$B$13:$BN$405,65,0) -> 0 | CH27: =IF(50000<F27/M27,50000,F27/M27)*CG27 -> 0 | CJ27: =BD27-R27-S27-AK27-CD27-AC27-BE27-BF27-BQ27 -> 9824213
A28: 0539 | C28: 40600 | D28: =DATEDIF(C28,$C$3,"D") -> 4742 | E28: La Nga | F28: 9500000 | G28: 0 | H28: 200000 | I28: 0 | J28: 0 | K28: 0 | L28: 0 | M28: =_xlfn.XLOOKUP(A28,Main!$B$13:$B$1048576,Main!$D$13:$D$1048576,0,0)*8 -> 192 | N28: =_xlfn.XLOOKUP(A28,Main!$B$13:$B$1048576,Main!$BQ$13:$BQ$1048576,0,0) -> 192 | O28: =_xlfn.XLOOKUP(A28,Main!$B$13:$B$1048576,Main!$BR$13:$BR$1048576,0,0) -> 152 | P28: =ROUND(F28/M28*N28,0) -> 9500000 | Q28: =G28/M28*O28 -> 0 | R28: =IF(D28>=(M28/8),H28,H28/M28*N28) -> 200000 | S28: =IF(CI28="N",26500*(ROUND(O28/8,0)),(I28/M28*O28)-CF28) -> 0 | T28: =J28 -> 0 | U28: =K28/M28*O28 -> 0 | V28: =IF(D28>=(M28/8),L28,L28/M28*N28) -> 0 | AE28: YES | AO28: =_xlfn.XLOOKUP($A28,Main!$B$13:$B$35,Main!BU$13:BU$35,0,0) -> 16 | AP28: =_xlfn.XLOOKUP($A28,Main!$B$13:$B$35,Main!BV$13:BV$35,0,0) -> 0 | AQ28: =_xlfn.XLOOKUP($A28,Main!$B$13:$B$35,Main!BW$13:BW$35,0,0) -> 0 | AR28: =_xlfn.XLOOKUP($A28,Main!$B$13:$B$35,Main!BX$13:BX$35,0,0) -> 0 | AS28: =_xlfn.XLOOKUP($A28,Main!$B$13:$B$35,Main!BY$13:BY$35,0,0) -> 0 | AT28: =_xlfn.XLOOKUP($A28,Main!$B$13:$B$35,Main!BZ$13:BZ$35,0,0) -> 0 | AU28: =_xlfn.XLOOKUP($A28,Main!$B$13:$B$35,Main!CA$13:CA$35,0,0) -> 0 | AV28: =$F28/$M28*AO28*150% -> 1187500 | AW28: =$F28/$M28*AP28*200% -> 0 | AX28: =$F28/$M28*AQ28*300% -> 0 | AY28: =$F28/$M28*AR28*30% -> 0 | AZ28: =$F28/$M28*AS28*210% -> 0 | BA28: =$F28/$M28*AT28*270% -> 0 | BB28: =$F28/$M28*AU28*390% -> 0 | BC28: =ROUND(SUM(AV28:BB28)+CH28,0) -> 1187500 | BD28: =SUM(P28:AN28)+BC28 -> 10887500 | BG28: =ROUND($CB28*'SHUI & PIT'!$F$11,0) -> 760000 | BH28: =ROUND($CB28*'SHUI & PIT'!$G$11,0) -> 142500 | BI28: =ROUND($CC28*'SHUI & PIT'!$H$11,0) -> 95000 | BJ28: =SUM(BG28:BI28) -> 997500 | BK28: =IF(E28="La Nga",0,IF(E28="HCM",35000,IF(AE28="YES",IF($BG28>0,ROUND(MIN($CB28*1%,180000),0),0),0))) -> 0 | BL28: 2 | BM28: =11000000+4400000*BL28 -> 19800000 | BN28: =ROUND(IF((CJ28-BJ28-BM28-BR28)<0,0,(CJ28-BJ28-BM28-BR28)),0) -> 0 | BO28: =ROUND((VLOOKUP(BN28,'SHUI & PIT'!$A$1:$C$8,2,1)*BN28-VLOOKUP(BN28,'SHUI & PIT'!$A$1:$C$8,3,1)),0) -> 0 | BP28: =Y28 -> 0 | BS28: =BJ28+BO28+BP28+BR28+BE28+BF28+BQ28+BK28 -> 997500 | BT28: =ROUND(IF((BD28-BS28)<0,0,(BD28-BS28)),0) -> 9890000 | BU28: =ROUND($CB28*'SHUI & PIT'!$F$12,0) -> 1662500 | BV28: =ROUND($CB28*'SHUI & PIT'!$G$12,0) -> 285000 | BW28: =ROUND($CC28*'SHUI & PIT'!$H$12,0) -> 95000 | BY28: =SUM(BU28:BX28) -> 2042500 | BZ28: =IF(BU28>0,ROUND($CB28*'SHUI & PIT'!$I$12,0),0) -> 190000 | CA28: =BD28+BY28-AC28+BZ28-BQ28 -> 13120000 | CB28: =IF(($F28+$T28)>='SHUI & PIT'!$C$12,'SHUI & PIT'!$C$12,($F28+$T28)) -> 9500000 | CC28: =IF(($F28+$T28)>='SHUI & PIT'!$C$13,'SHUI & PIT'!$C$13,($F28+$T28)) -> 9500000 | CD28: =ROUND(($F28/M28)*($AO28*0.5+$AP28+$AQ28*2+AR28*0.3+AS28*1.1+AT28*1.7+AU28*2.9),0) -> 395833 | CE28: =BC28-CD28 -> 791667 | CF28: =_xlfn.XLOOKUP(A28,'[2]Termination and others'!B$12:B$33,'[2]Termination and others'!F$12:F$33,0,0) -> 0 | CG28: =VLOOKUP(A28,Main!$B$13:$BN$405,65,0) -> 0 | CH28: =IF(50000<F28/M28,50000,F28/M28)*CG28 -> 0 | CJ28: =BD28-R28-S28-AK28-CD28-AC28-BE28-BF28-BQ28 -> 10291667
A29: 11358 | C29: 43960 | D29: =DATEDIF(C29,$C$3,"D") -> 1382 | E29: La Nga | F29: 13740000 | G29: 0 | H29: 300000 | I29: 0 | J29: 0 | K29: 0 | L29: 0 | M29: =_xlfn.XLOOKUP(A29,Main!$B$13:$B$1048576,Main!$D$13:$D$1048576,0,0)*8 -> 194 | N29: =_xlfn.XLOOKUP(A29,Main!$B$13:$B$1048576,Main!$BQ$13:$BQ$1048576,0,0) -> 194 | O29: =_xlfn.XLOOKUP(A29,Main!$B$13:$B$1048576,Main!$BR$13:$BR$1048576,0,0) -> 133.33 | P29: =ROUND(F29/M29*N29,0) -> 13740000 | Q29: =G29/M29*O29 -> 0 | R29: =IF(D29>=(M29/8),H29,H29/M29*N29) -> 300000 | S29: =IF(CI29="N",26500*(ROUND(O29/8,0)),(I29/M29*O29)-CF29) -> 0 | T29: =J29 -> 0 | U29: =K29/M29*O29 -> 0 | V29: =IF(D29>=(M29/8),L29,L29/M29*N29) -> 0 | AE29: YES | AO29: =_xlfn.XLOOKUP($A29,Main!$B$13:$B$35,Main!BU$13:BU$35,0,0) -> 1.97 | AP29: =_xlfn.XLOOKUP($A29,Main!$B$13:$B$35,Main!BV$13:BV$35,0,0) -> 7.17 | AQ29: =_xlfn.XLOOKUP($A29,Main!$B$13:$B$35,Main!BW$13:BW$35,0,0) -> 0 | AR29: =_xlfn.XLOOKUP($A29,Main!$B$13:$B$35,Main!BX$13:BX$35,0,0) -> 0 | AS29: =_xlfn.XLOOKUP($A29,Main!$B$13:$B$35,Main!BY$13:BY$35,0,0) -> 0 | AT29: =_xlfn.XLOOKUP($A29,Main!$B$13:$B$35,Main!BZ$13:BZ$35,0,0) -> 0 | AU29: =_xlfn.XLOOKUP($A29,Main!$B$13:$B$35,Main!CA$13:CA$35,0,0) -> 0 | AV29: =$F29/$M29*AO29*150% -> 209287.11 | AW29: =$F29/$M29*AP29*200% -> 1015626.8 | AX29: =$F29/$M29*AQ29*300% -> 0 | AY29: =$F29/$M29*AR29*30% -> 0 | AZ29: =$F29/$M29*AS29*210% -> 0 | BA29: =$F29/$M29*AT29*270% -> 0 | BB29: =$F29/$M29*AU29*390% -> 0 | BC29: =ROUND(SUM(AV29:BB29)+CH29,0) -> 1224914 | BD29: =SUM(P29:AN29)+BC29 -> 15264914 | BG29: =ROUND($CB29*'SHUI & PIT'!$F$11,0) -> 1099200 | BH29: =ROUND($CB29*'SHUI & PIT'!$G$11,0) -> 206100 | BI29: =ROUND($CC29*'SHUI & PIT'!$H$11,0) -> 137400 | BJ29: =SUM(BG29:BI29) -> 1442700 | BK29: =IF(E29="La Nga",0,IF(E29="HCM",35000,IF(AE29="YES",IF($BG29>0,ROUND(MIN($CB29*1%,180000),0),0),0))) -> 0 | BL29: =VLOOKUP(A29,'[1]Payroll master '!B$12:AD$160,29,0) -> 1 | BM29: =11000000+4400000*BL29 -> 15400000 | BN29: =ROUND(IF((CJ29-BJ29-BM29-BR29)<0,0,(CJ29-BJ29-BM29-BR29)),0) -> 0 | BO29: =ROUND((VLOOKUP(BN29,'SHUI & PIT'!$A$1:$C$8,2,1)*BN29-VLOOKUP(BN29,'SHUI & PIT'!$A$1:$C$8,3,1)),0) -> 0 | BP29: =Y29 -> 0 | BS29: =BJ29+BO29+BP29+BR29+BE29+BF29+BQ29+BK29 -> 1442700 | BT29: =ROUND(IF((BD29-BS29)<0,0,(BD29-BS29)),0) -> 13822214 | BU29: =ROUND($CB29*'SHUI & PIT'!$F$12,0) -> 2404500 | BV29: =ROUND($CB29*'SHUI & PIT'!$G$12,0) -> 412200 | BW29: =ROUND($CC29*'SHUI & PIT'!$H$12,0) -> 137400 | BY29: =SUM(BU29:BX29) -> 2954100 | BZ29: =IF(BU29>0,ROUND($CB29*'SHUI & PIT'!$I$12,0),0) -> 274800 | CA29: =BD29+BY29-AC29+BZ29-BQ29 -> 18493814 | CB29: =IF(($F29+$T29)>='SHUI & PIT'!$C$12,'SHUI & PIT'!$C$12,($F29+$T29)) -> 13740000 | CC29: =IF(($F29+$T29)>='SHUI & PIT'!$C$13,'SHUI & PIT'!$C$13,($F29+$T29)) -> 13740000 | CD29: =ROUND(($F29/M29)*($AO29*0.5+$AP29+$AQ29*2+AR29*0.3+AS29*1.1+AT29*1.7+AU29*2.9),0) -> 577576 | CE29: =BC29-CD29 -> 647338 | CF29: =_xlfn.XLOOKUP(A29,'[2]Termination and others'!B$12:B$33,'[2]Termination and others'!F$12:F$33,0,0) -> 0 | CG29: =VLOOKUP(A29,Main!$B$13:$BN$405,65,0) -> 0 | CH29: =IF(50000<F29/M29,50000,F29/M29)*CG29 -> 0 | CJ29: =BD29-R29-S29-AK29-CD29-AC29-BE29-BF29-BQ29 -> 14387338
G31: BASIC | H31: BASIC | I31: BASIC | J31: BASIC | K31: BASIC | L31: BASIC | P31: Actual Basic Salary | R31: ACTPHONE | S31: ACTMEAL | T31: Actual Responsibility ATI1R | AV31: Overtime | AW31: Overtime | AX31: Overtime | AY31: Overtime | AZ31: Overtime | BA31: Overtime | BB31: Overtime | BC31: Total Overtime | BD31: Actual total Income | BG31: Deductions1 | BH31: Deductions1 | BI31: Deductions1 | BJ31: Deductions | BK31: Deductions | BM31: DEPAMT | BN31: Tax Accessable Income | BO31: Deductions | BP31: Deductions | BQ31: Deductions | BR31: Deductions | BS31: Total Deductions | BT31: Net Pay | BU31: Insurance 2 | BV31: Insurance 2 | BW31: Insurance 2 | BY31: Total Insurance 2 | CA31: Total Cost to employer | CD31: OTNT | CJ31: Taxable Income
CJ32: BD17-R17-S17-AK17-CD17-AC17-BE17-BF17-BQ17
Q33: Actual Total 1 | R33: Actual Total 1 | S33: Actual Total 1 | T33: Actual Total 1 | U33: Actual total 1 | V33: Actual total 1 | W33: Actual total 2 | X33: Actual total 2 | Y33: Actual total 2 | Z33: Actual total 2 | AC33: MARSH | AD33: Actual total 2 | AH33: Actual total 2 | AI33: Actual total 2 | AK33: Sever Allowance | AM33: Actual total 2 | BS33: BJ17+BO17+BP17+BR17+BE17+BF17+BQ17+BK17 | BW33: BD12-R12-S12-AK12-CD12-AC12-BE12-BF12-BQ12 | CA33: BD17+BY17-AC17+BZ17-BQ17
AC34: Actual total 2 | AK34: Actual total 2

Sheet Main
AS1: 2 | AT1: 2 | AU1: 2 | AV1: 2 | AW1: 2 | AX1: 2 | AY1: 2 | AZ1: 2 | BA1: 2 | BB1: 2 | BC1: 2 | BD1: 2 | BE1: 2 | BF1: 2 | BG1: 2 | BH1: 0 | BI1: 2 | BJ1: 2 | BK1: 2 | BL1: 2
A2: Công ty | E2: 45281 | F2: 31 | G2: Chủ nhật | H2: 45311 | I2: Thứ hai | J2: Thứ ba | K2: Thứ tư | L2: Thứ năm | M2: Thứ sáu | N2: Thứ bảy | O2: Chủ nhật
A3: CÔNG TY AB MAURI VIỆT NAM | BS3: B1: VLOOKUP SO SÁNH DS 2 BÊN
A4: Ấp 4, xã La Ngà, huyện Định Quán, tỉnh Đồng Nai | BS4: B2: CHECK GIỜ CÔNG BẤT THƯỜNG TRONG CỘT VÀNG
A5: http://abmauri.vn/ | BS5: NHỮNG TRƯỜNG HỢP ÂM LÀ DO NHÂN VIÊN MỚI HOẶC NGHỈ VIỆC
BS6: NHỮNG TRƯỜNG HỢP DƯƠNG CẦN CHECK LẠI TẠI SAO SỐ GIỜ LÀM VIỆC VƯỢT CÔNG CHUẨN
A7: BẢNG CHẤM CÔNG
A8: Từ ngày 21/12/2023 đến ngày 20/01/2024
A9: Tất cả các bộ phận
BU10: =SUBTOTAL(9,BU$13:BU$35) -> 52.24 | BV10: =SUBTOTAL(9,BV$13:BV$35) -> 15.17 | BW10: =SUBTOTAL(9,BW$13:BW$35) -> 10.08 | BX10: =SUBTOTAL(9,BX$13:BX$35) -> 0 | BY10: =SUBTOTAL(9,BY$13:BY$35) -> 0 | BZ10: =SUBTOTAL(9,BZ$13:BZ$35) -> 0 | CA10: =SUBTOTAL(9,CA$13:CA$35) -> 0
A11: Stt | B11: Mã nhân viên | C11: Họ và tên | D11: Ngày công chuẩn | E11: =IF($E$2+COLUMN()-5>$H$2, "", DAY($E$2+COLUMN()-5) & IF(DAY($E$2+COLUMN()-5)=1, "/" & MONTH($E$2+COLUMN()-5), "")) -> 21 | F11: =IF($E$2+COLUMN()-5>$H$2, "", DAY($E$2+COLUMN()-5) & IF(DAY($E$2+COLUMN()-5)=1, "/" & MONTH($E$2+COLUMN()-5), "")) -> 22 | G11: =IF($E$2+COLUMN()-5>$H$2, "", DAY($E$2+COLUMN()-5) & IF(DAY($E$2+COLUMN()-5)=1, "/" & MONTH($E$2+COLUMN()-5), "")) -> 23 | H11: =IF($E$2+COLUMN()-5>$H$2, "", DAY($E$2+COLUMN()-5) & IF(DAY($E$2+COLUMN()-5)=1, "/" & MONTH($E$2+COLUMN()-5), "")) -> 24 | I11: =IF($E$2+COLUMN()-5>$H$2, "", DAY($E$2+COLUMN()-5) & IF(DAY($E$2+COLUMN()-5)=1, "/" & MONTH($E$2+COLUMN()-5), "")) -> 25 | J11: =IF($E$2+COLUMN()-5>$H$2, "", DAY($E$2+COLUMN()-5) & IF(DAY($E$2+COLUMN()-5)=1, "/" & MONTH($E$2+COLUMN()-5), "")) -> 26 | K11: =IF($E$2+COLUMN()-5>$H$2, "", DAY($E$2+COLUMN()-5) & IF(DAY($E$2+COLUMN()-5)=1, "/" & MONTH($E$2+COLUMN()-5), "")) -> 27 | L11: =IF($E$2+COLUMN()-5>$H$2, "", DAY($E$2+COLUMN()-5) & IF(DAY($E$2+COLUMN()-5)=1, "/" & MONTH($E$2+COLUMN()-5), "")) -> 28 | ... AR11: =IF($E$2+COLUMN()-5>$H$2, "", DAY($E$2+COLUMN()-5) & IF(DAY($E$2+COLUMN()-5)=1, "/" & MONTH($E$2+COLUMN()-5), "")) | AS11: Số giờ làm việc ngày thường | AT11: Số giờ làm đêm ngày thường | AU11: Tăng ca thường | AV11: Tăng ca đêm | AW11: Đi làm ngày OFF | AX11: Đi làm đêm ngày OFF | AY11: Đi làm ngày lễ | AZ11: Đi làm đêm ngày lễ | BA11: Thời gian đi công tác | BB11: Nghỉ phép năm | BC11: Nghỉ bù | BD11: Nghỉ lễ | BE11: Nghỉ chế độ | BF11: Chờ việc | BG11: Ngừng việc | BH11: Làm việc tại nhà | BI11: Nghỉ ốm | BJ11: Nghỉ con ốm | BK11: Nghỉ thai sản | BL11: Nghỉ không lương | BM11: Tổng cộng thời gian
E12: =IF($E$2+COLUMN()-5>$H$2, "", IF(WEEKDAY($E$2+COLUMN()-5)=1, O2, IF(WEEKDAY($E$2+COLUMN()-5)=2, I2, IF(WEEKDAY($E$2+COLUMN()-5)=3, J2, IF(WEEKDAY($E$2+COLUMN()-5)=4, K2, IF(WEEKDAY($E$2+COLUMN()-5)=5, L2, IF(WEEKDAY($E$2+COLUMN()-5)=6, M2, N2))))))) -> Thứ năm | F12: =IF($E$2+COLUMN()-5>$H$2, "", IF(WEEKDAY($E$2+COLUMN()-5)=1, O2, IF(WEEKDAY($E$2+COLUMN()-5)=2, I2, IF(WEEKDAY($E$2+COLUMN()-5)=3, J2, IF(WEEKDAY($E$2+COLUMN()-5)=4, K2, IF(WEEKDAY($E$2+COLUMN()-5)=5, L2, IF(WEEKDAY($E$2+COLUMN()-5)=6, M2, N2))))))) -> Thứ sáu | G12: =IF($E$2+COLUMN()-5>$H$2, "", IF(WEEKDAY($E$2+COLUMN()-5)=1, O2, IF(WEEKDAY($E$2+COLUMN()-5)=2, I2, IF(WEEKDAY($E$2+COLUMN()-5)=3, J2, IF(WEEKDAY($E$2+COLUMN()-5)=4, K2, IF(WEEKDAY($E$2+COLUMN()-5)=5, L2, IF(WEEKDAY($E$2+COLUMN()-5)=6, M2, N2))))))) -> Thứ bảy | H12: =IF($E$2+COLUMN()-5>$H$2, "", IF(WEEKDAY($E$2+COLUMN()-5)=1, O2, IF(WEEKDAY($E$2+COLUMN()-5)=2, I2, IF(WEEKDAY($E$2+COLUMN()-5)=3, J2, IF(WEEKDAY($E$2+COLUMN()-5)=4, K2, IF(WEEKDAY($E$2+COLUMN()-5)=5, L2, IF(WEEKDAY($E$2+COLUMN()-5)=6, M2, N2))))))) -> Chủ nhật | I12: =IF($E$2+COLUMN()-5>$H$2, "", IF(WEEKDAY($E$2+COLUMN()-5)=1, O2, IF(WEEKDAY($E$2+COLUMN()-5)=2, I2, IF(WEEKDAY($E$2+COLUMN()-5)=3, J2, IF(WEEKDAY($E$2+COLUMN()-5)=4, K2, IF(WEEKDAY($E$2+COLUMN()-5)=5, L2, IF(WEEKDAY($E$2+COLUMN()-5)=6, M2, N2))))))) -> Thứ hai | J12: =IF($E$2+COLUMN()-5>$H$2, "", IF(WEEKDAY($E$2+COLUMN()-5)=1, O2, IF(WEEKDAY($E$2+COLUMN()-5)=2, I2, IF(WEEKDAY($E$2+COLUMN()-5)=3, J2, IF(WEEKDAY($E$2+COLUMN()-5)=4, K2, IF(WEEKDAY($E$2+COLUMN()-5)=5, L2, IF(WEEKDAY($E$2+COLUMN()-5)=6, M2, N2))))))) -> Thứ ba | K12: =IF($E$2+COLUMN()-5>$H$2, "", IF(WEEKDAY($E$2+COLUMN()-5)=1, O2, IF(WEEKDAY($E$2+COLUMN()-5)=2, I2, IF(WEEKDAY($E$2+COLUMN()-5)=3, J2, IF(WEEKDAY($E$2+COLUMN()-5)=4, K2, IF(WEEKDAY($E$2+COLUMN()-5)=5, L2, IF(WEEKDAY($E$2+COLUMN()-5)=6, M2, N2))))))) -> Thứ tư | L12: =IF($E$2+COLUMN()-5>$H$2, "", IF(WEEKDAY($E$2+COLUMN()-5)=1, O2, IF(WEEKDAY($E$2+COLUMN()-5)=2, I2, IF(WEEKDAY($E$2+COLUMN()-5)=3, J2, IF(WEEKDAY($E$2+COLUMN()-5)=4, K2, IF(WEEKDAY($E$2+COLUMN()-5)=5, L2, IF(WEEKDAY($E$2+COLUMN()-5)=6, M2, N2))))))) -> Thứ năm | M12: =IF($E$2+COLUMN()-5>$H$2, "", IF(WEEKDAY($E$2+COLUMN()-5)=1, O2, IF(WEEKDAY($E$2+COLUMN()-5)=2, I2, IF(WEEKDAY($E$2+COLUMN()-5)=3, J2, IF(WEEKDAY($E$2+COLUMN()-5)=4, K2, IF(WEEKDAY($E$2+COLUMN()-5)=5, L2, IF(WEEKDAY($E$2+COLUMN()-5)=6, M2, N2))))))) -> Thứ sáu | N12: =IF($E$2+COLUMN()-5>$H$2, "", IF(WEEKDAY($E$2+COLUMN()-5)=1, O2, IF(WEEKDAY($E$2+COLUMN()-5)=2, I2, IF(WEEKDAY($E$2+COLUMN()-5)=3, J2, IF(WEEKDAY($E$2+COLUMN()-5)=4, K2, IF(WEEKDAY($E$2+COLUMN()-5)=5, L2, IF(WEEKDAY($E$2+COLUMN()-5)=6, M2, N2))))))) -> Thứ bảy | O12: =IF($E$2+COLUMN()-5>$H$2, "", IF(WEEKDAY($E$2+COLUMN()-5)=1, O2, IF(WEEKDAY($E$2+COLUMN()-5)=2, I2, IF(WEEKDAY($E$2+COLUMN()-5)=3, J2, IF(WEEKDAY($E$2+COLUMN()-5)=4, K2, IF(WEEKDAY($E$2+COLUMN()-5)=5, L2, IF(WEEKDAY($E$2+COLUMN()-5)=6, M2, N2))))))) -> Chủ nhật | P12: =IF($E$2+COLUMN()-5>$H$2, "", IF(WEEKDAY($E$2+COLUMN()-5)=1, O2, IF(WEEKDAY($E$2+COLUMN()-5)=2, I2, IF(WEEKDAY($E$2+COLUMN()-5)=3, J2, IF(WEEKDAY($E$2+COLUMN()-5)=4, K2, IF(WEEKDAY($E$2+COLUMN()-5)=5, L2, IF(WEEKDAY($E$2+COLUMN()-5)=6, M2, N2))))))) -> Thứ hai | Q12: =IF($E$2+COLUMN()-5>$H$2, "", IF(WEEKDAY($E$2+COLUMN()-5)=1, O2, IF(WEEKDAY($E$2+COLUMN()-5)=2, I2, IF(WEEKDAY($E$2+COLUMN()-5)=3, J2, IF(WEEKDAY($E$2+COLUMN()-5)=4, K2, IF(WEEKDAY($E$2+COLUMN()-5)=5, L2, IF(WEEKDAY($E$2+COLUMN()-5)=6, M2, N2))))))) -> Thứ ba | R12: =IF($E$2+COLUMN()-5>$H$2, "", IF(WEEKDAY($E$2+COLUMN()-5)=1, O2, IF(WEEKDAY($E$2+COLUMN()-5)=2, I2, IF(WEEKDAY($E$2+COLUMN()-5)=3, J2, IF(WEEKDAY($E$2+COLUMN()-5)=4, K2, IF(WEEKDAY($E$2+COLUMN()-5)=5, L2, IF(WEEKDAY($E$2+COLUMN()-5)=6, M2, N2))))))) -> Thứ tư | S12: =IF($E$2+COLUMN()-5>$H$2, "", IF(WEEKDAY($E$2+COLUMN()-5)=1, O2, IF(WEEKDAY($E$2+COLUMN()-5)=2, I2, IF(WEEKDAY($E$2+COLUMN()-5)=3, J2, IF(WEEKDAY($E$2+COLUMN()-5)=4, K2, IF(WEEKDAY($E$2+COLUMN()-5)=5, L2, IF(WEEKDAY($E$2+COLUMN()-5)=6, M2, N2))))))) -> Thứ năm | T12: =IF($E$2+COLUMN()-5>$H$2, "", IF(WEEKDAY($E$2+COLUMN()-5)=1, O2, IF(WEEKDAY($E$2+COLUMN()-5)=2, I2, IF(WEEKDAY($E$2+COLUMN()-5)=3, J2, IF(WEEKDAY($E$2+COLUMN()-5)=4, K2, IF(WEEKDAY($E$2+COLUMN()-5)=5, L2, IF(WEEKDAY($E$2+COLUMN()-5)=6, M2, N2))))))) -> Thứ sáu | U12: =IF($E$2+COLUMN()-5>$H$2, "", IF(WEEKDAY($E$2+COLUMN()-5)=1, O2, IF(WEEKDAY($E$2+COLUMN()-5)=2, I2, IF(WEEKDAY($E$2+COLUMN()-5)=3, J2, IF(WEEKDAY($E$2+COLUMN()-5)=4, K2, IF(WEEKDAY($E$2+COLUMN()-5)=5, L2, IF(WEEKDAY($E$2+COLUMN()-5)=6, M2, N2))))))) -> Thứ bảy | V12: =IF($E$2+COLUMN()-5>$H$2, "", IF(WEEKDAY($E$2+COLUMN()-5)=1, O2, IF(WEEKDAY($E$2+COLUMN()-5)=2, I2, IF(WEEKDAY($E$2+COLUMN()-5)=3, J2, IF(WEEKDAY($E$2+COLUMN()-5)=4, K2, IF(WEEKDAY($E$2+COLUMN()-5)=5, L2, IF(WEEKDAY($E$2+COLUMN()-5)=6, M2, N2))))))) -> Chủ nhật | W12: =IF($E$2+COLUMN()-5>$H$2, "", IF(WEEKDAY($E$2+COLUMN()-5)=1, O2, IF(WEEKDAY($E$2+COLUMN()-5)=2, I2, IF(WEEKDAY($E$2+COLUMN()-5)=3, J2, IF(WEEKDAY($E$2+COLUMN()-5)=4, K2, IF(WEEKDAY($E$2+COLUMN()-5)=5, L2, IF(WEEKDAY($E$2+COLUMN()-5)=6, M2, N2))))))) -> Thứ hai | X12: =IF($E$2+COLUMN()-5>$H$2, "", IF(WEEKDAY($E$2+COLUMN()-5)=1, O2, IF(WEEKDAY($E$2+COLUMN()-5)=2, I2, IF(WEEKDAY($E$2+COLUMN()-5)=3, J2, IF(WEEKDAY($E$2+COLUMN()-5)=4, K2, IF(WEEKDAY($E$2+COLUMN()-5)=5, L2, IF(WEEKDAY($E$2+COLUMN()-5)=6, M2, N2))))))) -> Thứ ba | Y12: =IF($E$2+COLUMN()-5>$H$2, "", IF(WEEKDAY($E$2+COLUMN()-5)=1, O2, IF(WEEKDAY($E$2+COLUMN()-5)=2, I2, IF(WEEKDAY($E$2+COLUMN()-5)=3, J2, IF(WEEKDAY($E$2+COLUMN()-5)=4, K2, IF(WEEKDAY($E$2+COLUMN()-5)=5, L2, IF(WEEKDAY($E$2+COLUMN()-5)=6, M2, N2))))))) -> Thứ tư | Z12: =IF($E$2+COLUMN()-5>$H$2, "", IF(WEEKDAY($E$2+COLUMN()-5)=1, O2, IF(WEEKDAY($E$2+COLUMN()-5)=2, I2, IF(WEEKDAY($E$2+COLUMN()-5)=3, J2, IF(WEEKDAY($E$2+COLUMN()-5)=4, K2, IF(WEEKDAY($E$2+COLUMN()-5)=5, L2, IF(WEEKDAY($E$2+COLUMN()-5)=6, M2, N2))))))) -> Thứ năm | AA12: =IF($E$2+COLUMN()-5>$H$2, "", IF(WEEKDAY($E$2+COLUMN()-5)=1, O2, IF(WEEKDAY($E$2+COLUMN()-5)=2, I2, IF(WEEKDAY($E$2+COLUMN()-5)=3, J2, IF(WEEKDAY($E$2+COLUMN()-5)=4, K2, IF(WEEKDAY($E$2+COLUMN()-5)=5, L2, IF(WEEKDAY($E$2+COLUMN()-5)=6, M2, N2))))))) -> Thứ sáu | AB12: =IF($E$2+COLUMN()-5>$H$2, "", IF(WEEKDAY($E$2+COLUMN()-5)=1, O2, IF(WEEKDAY($E$2+COLUMN()-5)=2, I2, IF(WEEKDAY($E$2+COLUMN()-5)=3, J2, IF(WEEKDAY($E$2+COLUMN()-5)=4, K2, IF(WEEKDAY($E$2+COLUMN()-5)=5, L2, IF(WEEKDAY($E$2+COLUMN()-5)=6, M2, N2))))))) -> Thứ bảy | AC12: =IF($E$2+COLUMN()-5>$H$2, "", IF(WEEKDAY($E$2+COLUMN()-5)=1, O2, IF(WEEKDAY($E$2+COLUMN()-5)=2, I2, IF(WEEKDAY($E$2+COLUMN()-5)=3, J2, IF(WEEKDAY($E$2+COLUMN()-5)=4, K2, IF(WEEKDAY($E$2+COLUMN()-5)=5, L2, IF(WEEKDAY($E$2+COLUMN()-5)=6, M2, N2))))))) -> Chủ nhật | AD12: =IF($E$2+COLUMN()-5>$H$2, "", IF(WEEKDAY($E$2+COLUMN()-5)=1, O2, IF(WEEKDAY($E$2+COLUMN()-5)=2, I2, IF(WEEKDAY($E$2+COLUMN()-5)=3, J2, IF(WEEKDAY($E$2+COLUMN()-5)=4, K2, IF(WEEKDAY($E$2+COLUMN()-5)=5, L2, IF(WEEKDAY($E$2+COLUMN()-5)=6, M2, N2))))))) -> Thứ hai | AE12: =IF($E$2+COLUMN()-5>$H$2, "", IF(WEEKDAY($E$2+COLUMN()-5)=1, O2, IF(WEEKDAY($E$2+COLUMN()-5)=2, I2, IF(WEEKDAY($E$2+COLUMN()-5)=3, J2, IF(WEEKDAY($E$2+COLUMN()-5)=4, K2, IF(WEEKDAY($E$2+COLUMN()-5)=5, L2, IF(WEEKDAY($E$2+COLUMN()-5)=6, M2, N2))))))) -> Thứ ba | AF12: =IF($E$2+COLUMN()-5>$H$2, "", IF(WEEKDAY($E$2+COLUMN()-5)=1, O2, IF(WEEKDAY($E$2+COLUMN()-5)=2, I2, IF(WEEKDAY($E$2+COLUMN()-5)=3, J2, IF(WEEKDAY($E$2+COLUMN()-5)=4, K2, IF(WEEKDAY($E$2+COLUMN()-5)=5, L2, IF(WEEKDAY($E$2+COLUMN()-5)=6, M2, N2))))))) -> Thứ tư | AG12: =IF($E$2+COLUMN()-5>$H$2, "", IF(WEEKDAY($E$2+COLUMN()-5)=1, O2, IF(WEEKDAY($E$2+COLUMN()-5)=2, I2, IF(WEEKDAY($E$2+COLUMN()-5)=3, J2, IF(WEEKDAY($E$2+COLUMN()-5)=4, K2, IF(WEEKDAY($E$2+COLUMN()-5)=5, L2, IF(WEEKDAY($E$2+COLUMN()-5)=6, M2, N2))))))) -> Thứ năm | AH12: =IF($E$2+COLUMN()-5>$H$2, "", IF(WEEKDAY($E$2+COLUMN()-5)=1, O2, IF(WEEKDAY($E$2+COLUMN()-5)=2, I2, IF(WEEKDAY($E$2+COLUMN()-5)=3, J2, IF(WEEKDAY($E$2+COLUMN()-5)=4, K2, IF(WEEKDAY($E$2+COLUMN()-5)=5, L2, IF(WEEKDAY($E$2+COLUMN()-5)=6, M2, N2))))))) -> Thứ sáu | AI12: =IF($E$2+COLUMN()-5>$H$2, "", IF(WEEKDAY($E$2+COLUMN()-5)=1, O2, IF(WEEKDAY($E$2+COLUMN()-5)=2, I2, IF(WEEKDAY($E$2+COLUMN()-5)=3, J2, IF(WEEKDAY($E$2+COLUMN()-5)=4, K2, IF(WEEKDAY($E$2+COLUMN()-5)=5, L2, IF(WEEKDAY($E$2+COLUMN()-5)=6, M2, N2))))))) -> Thứ bảy | AJ12: =IF($E$2+COLUMN()-5>$H$2, "", IF(WEEKDAY($E$2+COLUMN()-5)=1, O2, IF(WEEKDAY($E$2+COLUMN()-5)=2, I2, IF(WEEKDAY($E$2+COLUMN()-5)=3, J2, IF(WEEKDAY($E$2+COLUMN()-5)=4, K2, IF(WEEKDAY($E$2+COLUMN()-5)=5, L2, IF(WEEKDAY($E$2+COLUMN()-5)=6, M2, N2))))))) | AK12: =IF($E$2+COLUMN()-5>$H$2, "", IF(WEEKDAY($E$2+COLUMN()-5)=1, O2, IF(WEEKDAY($E$2+COLUMN()-5)=2, I2, IF(WEEKDAY($E$2+COLUMN()-5)=3, J2, IF(WEEKDAY($E$2+COLUMN()-5)=4, K2, IF(WEEKDAY($E$2+COLUMN()-5)=5, L2, IF(WEEKDAY($E$2+COLUMN()-5)=6, M2, N2))))))) | AL12: =IF($E$2+COLUMN()-5>$H$2, "", IF(WEEKDAY($E$2+COLUMN()-5)=1, O2, IF(WEEKDAY($E$2+COLUMN()-5)=2, I2, IF(WEEKDAY($E$2+COLUMN()-5)=3, J2, IF(WEEKDAY($E$2+COLUMN()-5)=4, K2, IF(WEEKDAY($E$2+COLUMN()-5)=5, L2, IF(WEEKDAY($E$2+COLUMN()-5)=6, M2, N2))))))) | AM12: =IF($E$2+COLUMN()-5>$H$2, "", IF(WEEKDAY($E$2+COLUMN()-5)=1, O2, IF(WEEKDAY($E$2+COLUMN()-5)=2, I2, IF(WEEKDAY($E$2+COLUMN()-5)=3, J2, IF(WEEKDAY($E$2+COLUMN()-5)=4, K2, IF(WEEKDAY($E$2+COLUMN()-5)=5, L2, IF(WEEKDAY($E$2+COLUMN()-5)=6, M2, N2))))))) | AN12: =IF($E$2+COLUMN()-5>$H$2, "", IF(WEEKDAY($E$2+COLUMN()-5)=1, O2, IF(WEEKDAY($E$2+COLUMN()-5)=2, I2, IF(WEEKDAY($E$2+COLUMN()-5)=3, J2, IF(WEEKDAY($E$2+COLUMN()-5)=4, K2, IF(WEEKDAY($E$2+COLUMN()-5)=5, L2, IF(WEEKDAY($E$2+COLUMN()-5)=6, M2, N2))))))) | AO12: =IF($E$2+COLUMN()-5>$H$2, "", IF(WEEKDAY($E$2+COLUMN()-5)=1, O2, IF(WEEKDAY($E$2+COLUMN()-5)=2, I2, IF(WEEKDAY($E$2+COLUMN()-5)=3, J2, IF(WEEKDAY($E$2+COLUMN()-5)=4, K2, IF(WEEKDAY($E$2+COLUMN()-5)=5, L2, IF(WEEKDAY($E$2+COLUMN()-5)=6, M2, N2))))))) | AP12: =IF($E$2+COLUMN()-5>$H$2, "", IF(WEEKDAY($E$2+COLUMN()-5)=1, O2, IF(WEEKDAY($E$2+COLUMN()-5)=2, I2, IF(WEEKDAY($E$2+COLUMN()-5)=3, J2, IF(WEEKDAY($E$2+COLUMN()-5)=4, K2, IF(WEEKDAY($E$2+COLUMN()-5)=5, L2, IF(WEEKDAY($E$2+COLUMN()-5)=6, M2, N2))))))) | AQ12: =IF($E$2+COLUMN()-5>$H$2, "", IF(WEEKDAY($E$2+COLUMN()-5)=1, O2, IF(WEEKDAY($E$2+COLUMN()-5)=2, I2, IF(WEEKDAY($E$2+COLUMN()-5)=3, J2, IF(WEEKDAY($E$2+COLUMN()-5)=4, K2, IF(WEEKDAY($E$2+COLUMN()-5)=5, L2, IF(WEEKDAY($E$2+COLUMN()-5)=6, M2, N2))))))) | AR12: =IF($E$2+COLUMN()-5>$H$2, "", IF(WEEKDAY($E$2+COLUMN()-5)=1, O2, IF(WEEKDAY($E$2+COLUMN()-5)=2, I2, IF(WEEKDAY($E$2+COLUMN()-5)=3, J2, IF(WEEKDAY($E$2+COLUMN()-5)=4, K2, IF(WEEKDAY($E$2+COLUMN()-5)=5, L2, IF(WEEKDAY($E$2+COLUMN()-5)=6, M2, N2))))))) | BN12: OX Tai xe (hour) | BO12: Giờ công chuẩn tháng | BP12: Tổng giờ công trong tháng (trả lương, không lương) không gồm OT | BQ12: Gio cong thuc te trả lương trong tháng gồm ngày nghỉ | BR12: Giờ công thực tế trả lương không bao gồm các ngày nghỉ | BS12: SO SÁNH TỔNG GIỜ CÔNG K OT VỚI CÔNG CHUẨN | BU12: OT 1.5 Hours | BV12: OT 2 Hours | BW12: OT 3 Hours | BX12: Night shif payment | BY12: OT Night shift wk day | BZ12: OT Night shift off day | CA12: OT Ngiht shift Holiday
A13: 28 | B13: 0639 | D13: 24.25 | F13: X (9) | G13: X (9) | H13: X (9) | I13: X (9) | J13: X | M13: X (9) | N13: X (9) | O13: X (9) | P13: X (9) | Q13: X | T13: X (9) | U13: X (9) | V13: X (1), P | W13: H (9) | X13: H | Y13: H (9) | Z13: H (9) | AA13: H (9) | AD13: X (9) | AE13: P | AH13: X (9) | AI13: X (9) | AS13: 134 | BB13: 16 | BD13: 44 | BM13: 194 | BN13: 11.16 | BO13: =D13*8 -> 194 | BP13: =AS13+AT13+BA13+BB13+BC13+BD13+BE13+BF13+BG13+BH13+BI13+BJ13+BK13+BL13 -> 194 | BQ13: =AS13+AT13+BA13+BB13+BC13+BD13+BE13+BH13 -> 194 | BR13: =AS13+AT13+BA13+BH13 -> 134 | BS13: =BP13-BO13 -> 0 | BT13: =BO13-BQ13 -> 0 | BU13: =AU13 -> 0 | BV13: =AW13 -> 0 | BW13: =AY13 -> 0 | BX13: =AT13 -> 0 | BY13: =AV13 -> 0 | BZ13: =AX13 -> 0 | CA13: =AZ13 -> 0
A14: 34 | B14: 0014 | D14: 24.25 | F14: X (9) | G14: X (9) | H14: X (9) | I14: X (9) | J14: X | M14: X (9) | N14: X (9) | O14: X (9) | P14: X (9) | Q14: X | T14: X (9) | U14: X (9) | V14: X (1), P | W14: H (9) | X14: H | Y14: H (9) | Z14: H (9) | AA14: H (9) | AD14: X (1), P | AE14: P | AH14: X (9) | AI14: X (9) | AS14: 126 | BB14: 24 | BD14: 44 | BM14: 194 | BN14: 10.16 | BO14: =D14*8 -> 194 | BP14: =AS14+AT14+BA14+BB14+BC14+BD14+BE14+BF14+BG14+BH14+BI14+BJ14+BK14+BL14 -> 194 | BQ14: =AS14+AT14+BA14+BB14+BC14+BD14+BE14+BH14 -> 194 | BR14: =AS14+AT14+BA14+BH14 -> 126 | BS14: =BP14-BO14 -> 0 | BT14: =BO14-BQ14 -> 0 | BU14: =AU14 -> 0 | BV14: =AW14 -> 0 | BW14: =AY14 -> 0 | BX14: =AT14 -> 0 | BY14: =AV14 -> 0 | BZ14: =AX14 -> 0 | CA14: =AZ14 -> 0
A15: 35 | B15: 0023 | D15: 24.25 | F15: X (9) | G15: X (9) | H15: X (9) | I15: X (9) | J15: X | M15: X (9) | N15: X (9) | O15: X (9) | P15: X (9) | Q15: X | T15: X (9) | U15: X (9) | V15: X (9) | W15: H (9) | X15: H | Y15: H (9) | Z15: H (9) | AA15: H (9) | AD15: X (9) | AE15: X | AH15: X (9) | AI15: X (9) | AS15: 150 | BD15: 44 | BM15: 194 | BO15: =D15*8 -> 194 | BP15: =AS15+AT15+BA15+BB15+BC15+BD15+BE15+BF15+BG15+BH15+BI15+BJ15+BK15+BL15 -> 194 | BQ15: =AS15+AT15+BA15+BB15+BC15+BD15+BE15+BH15 -> 194 | BR15: =AS15+AT15+BA15+BH15 -> 150 | BS15: =BP15-BO15 -> 0 | BT15: =BO15-BQ15 -> 0 | BU15: =AU15 -> 0 | BV15: =AW15 -> 0 | BW15: =AY15 -> 0 | BX15: =AT15 -> 0 | BY15: =AV15 -> 0 | BZ15: =AX15 -> 0 | CA15: =AZ15 -> 0
A16: 39 | B16: 0539 | D16: 24 | F16: X | G16: X | H16: X | I16: X | J16: X | K16: X (4), OT(8) | M16: X | N16: X | O16: X | P16: X | Q16: X, OT(4) | R16: X (4), OT(4) | T16: X | U16: X | V16: X | W16: H | X16: H | Y16: H | Z16: H | AA16: H | AD16: X | AE16: X | AF16: X | AH16: X | AI16: X | AS16: 152 | AU16: 16 | BD16: 40 | BM16: 208 | BO16: =D16*8 -> 192 | BP16: =AS16+AT16+BA16+BB16+BC16+BD16+BE16+BF16+BG16+BH16+BI16+BJ16+BK16+BL16 -> 192 | BQ16: =AS16+AT16+BA16+BB16+BC16+BD16+BE16+BH16 -> 192 | BR16: =AS16+AT16+BA16+BH16 -> 152 | BS16: =BP16-BO16 -> 0 | BT16: =BO16-BQ16 -> 0 | BU16: =AU16 -> 16 | BV16: =AW16 -> 0 | BW16: =AY16 -> 0 | BX16: =AT16 -> 0 | BY16: =AV16 -> 0 | BZ16: =AX16 -> 0 | CA16: =AZ16 -> 0
A17: 40 | B17: 0242 | D17: 24.25 | F17: X (9) | G17: X (9) | H17: X (9) | I17: X (9) | J17: X(4), P(4) | M17: X (9) | N17: X (9) | O17: X (9) | P17: X (9) | Q17: X, OT(4) | T17: X (9) | U17: X (9) | V17: X (9) | W17: H (9) | X17: H | Y17: H (9) | Z17: H (9) | AA17: H (9) | AD17: X (9) | AE17: X | AF17: OW | AH17: X (9), OT(2) | AI17: X (9), OT(2) | AS17: 146 | AU17: 8 | AW17: 8 | BB17: 4 | BD17: 44 | BM17: 210 | BO17: =D17*8 -> 194 | BP17: =AS17+AT17+BA17+BB17+BC17+BD17+BE17+BF17+BG17+BH17+BI17+BJ17+BK17+BL17 -> 194 | BQ17: =AS17+AT17+BA17+BB17+BC17+BD17+BE17+BH17 -> 194 | BR17: =AS17+AT17+BA17+BH17 -> 146 | BS17: =BP17-BO17 -> 0 | BT17: =BO17-BQ17 -> 0 | BU17: =AU17 -> 8 | BV17: =AW17 -> 8 | BW17: =AY17 -> 0 | BX17: =AT17 -> 0 | BY17: =AV17 -> 0 | BZ17: =AX17 -> 0 | CA17: =AZ17 -> 0
A18: 68 | B18: 0016 | D18: 24 | F18: X | G18: X | H18: X | I18: X | J18: X | K18: X(4) | M18: X | N18: X (4), P(4) | O18: X | P18: X | Q18: X | R18: X(4) | T18: X | U18: X | V18: X | W18: H | X18: H | Y18: H | Z18: H | AA18: H | AC18: X(4) | AD18: X (4), P(4) | AE18: X | AF18: X(4) | AH18: X | AI18: X | AS18: 144 | BB18: 8 | BD18: 40 | BM18: 192 | BO18: =D18*8 -> 192 | BP18: =AS18+AT18+BA18+BB18+BC18+BD18+BE18+BF18+BG18+BH18+BI18+BJ18+BK18+BL18 -> 192 | BQ18: =AS18+AT18+BA18+BB18+BC18+BD18+BE18+BH18 -> 192 | BR18: =AS18+AT18+BA18+BH18 -> 144 | BS18: =BP18-BO18 -> 0 | BT18: =BO18-BQ18 -> 0 | BU18: =AU18 -> 0 | BV18: =AW18 -> 0 | BW18: =AY18 -> 0 | BX18: =AT18 -> 0 | BY18: =AV18 -> 0 | BZ18: =AX18 -> 0 | CA18: =AZ18 -> 0
A19: 69 | B19: 0020 | D19: 24 | F19: X | G19: X | H19: X | I19: X | J19: X | K19: X(4) | M19: X | N19: X | O19: X (4), P(4) | P19: X (4), P(4) | Q19: X (4), P(4) | R19: X(4) | T19: X (4), P(4) | U19: X (4), P(4) | V19: X | W19: H | X19: H | Y19: H | Z19: H | AA19: H | AC19: X(4) | AD19: X | AE19: X | AF19: X(4) | AH19: X (4), P(4) | AI19: X | AS19: 128 | BB19: 24 | BD19: 40 | BM19: 192 | BO19: =D19*8 -> 192 | BP19: =AS19+AT19+BA19+BB19+BC19+BD19+BE19+BF19+BG19+BH19+BI19+BJ19+BK19+BL19 -> 192 | BQ19: =AS19+AT19+BA19+BB19+BC19+BD19+BE19+BH19 -> 192 | BR19: =AS19+AT19+BA19+BH19 -> 128 | BS19: =BP19-BO19 -> 0 | BT19: =BO19-BQ19 -> 0 | BU19: =AU19 -> 0 | BV19: =AW19 -> 0 | BW19: =AY19 -> 0 | BX19: =AT19 -> 0 | BY19: =AV19 -> 0 | BZ19: =AX19 -> 0 | CA19: =AZ19 -> 0
A20: 87 | B20: 0024 | D20: 24.25 | F20: X (9) | G20: X (9) | H20: X (9) | I20: X (9) | J20: X | M20: X (9) | N20: X (9) | O20: X (9) | P20: X (9) | Q20: X | T20: NB(9) | U20: NB(9) | V20: X (9) | W20: OH(6.83), H (9) | X20: H | Y20: H (9) | Z20: H (9) | AA20: H (9) | AD20: NB(9) | AE20: NB | AH20: X (9) | AI20: X (9) | AS20: 115 | AY20: 6.83 | BC20: 35 | BD20: 44 | BM20: 200.83 | BO20: =D20*8 -> 194 | BP20: =AS20+AT20+BA20+BB20+BC20+BD20+BE20+BF20+BG20+BH20+BI20+BJ20+BK20+BL20 -> 194 | BQ20: =AS20+AT20+BA20+BB20+BC20+BD20+BE20+BH20 -> 194 | BR20: =AS20+AT20+BA20+BH20 -> 115 | BS20: =BP20-BO20 -> 0 | BT20: =BO20-BQ20 -> 0 | BU20: =AU20 -> 0 | BV20: =AW20 -> 0 | BW20: =AY20 -> 6.83 | BX20: =AT20 -> 0 | BY20: =AV20 -> 0 | BZ20: =AX20 -> 0 | CA20: =AZ20 -> 0
A21: 88 | B21: 0272 | D21: 24 | F21: X | G21: X | H21: X | I21: X | J21: X (4.3), P (3.7) | K21: X (4) | M21: X | N21: X | O21: X | P21: X | Q21: X , OT(1.72) | R21: X (4), OT(4) | T21: X | U21: X | V21: P | W21: H | X21: OH(3.25), H | Y21: H | Z21: H | AA21: H | AC21: P (4) | AD21: X | AE21: X | AF21: X (4), OT(2.5) | AH21: X | AI21: X | AS21: 136.3 | AU21: 8.22 | AY21: 3.25 | BB21: 15.7 | BD21: 40 | BM21: 203.47 | BO21: =D21*8 -> 192 | BP21: =AS21+AT21+BA21+BB21+BC21+BD21+BE21+BF21+BG21+BH21+BI21+BJ21+BK21+BL21 -> 192 | BQ21: =AS21+AT21+BA21+BB21+BC21+BD21+BE21+BH21 -> 192 | BR21: =AS21+AT21+BA21+BH21 -> 136.3 | BS21: =BP21-BO21 -> 0 | BT21: =BO21-BQ21 -> 0 | BU21: =AU21 -> 8.22 | BV21: =AW21 -> 0 | BW21: =AY21 -> 3.25 | BX21: =AT21 -> 0 | BY21: =AV21 -> 0 | BZ21: =AX21 -> 0 | CA21: =AZ21 -> 0
A22: 89 | B22: 0509 | D22: 24 | F22: X | G22: X | H22: X | I22: X | J22: X | K22: X (4), OT(4.5) | M22: X , OT(1.93) | N22: X | O22: X | P22: X | Q22: X | R22: X (4), OT(4.25) | T22: X | U22: X | V22: X , OT(2.37) | W22: H | X22: H | Y22: H | Z22: H | AA22: H | AC22: P (4) | AD22: X | AE22: X | AF22: X (4), OT(5) | AH22: X | AI22: X | AS22: 148 | AU22: 18.05 | BB22: 4 | BD22: 40 | BM22: 210.05 | BO22: =D22*8 -> 192 | BP22: =AS22+AT22+BA22+BB22+BC22+BD22+BE22+BF22+BG22+BH22+BI22+BJ22+BK22+BL22 -> 192 | BQ22: =AS22+AT22+BA22+BB22+BC22+BD22+BE22+BH22 -> 192 | BR22: =AS22+AT22+BA22+BH22 -> 148 | BS22: =BP22-BO22 -> 0 | BT22: =BO22-BQ22 -> 0 | BU22: =AU22 -> 18.05 | BV22: =AW22 -> 0 | BW22: =AY22 -> 0 | BX22: =AT22 -> 0 | BY22: =AV22 -> 0 | BZ22: =AX22 -> 0 | CA22: =AZ22 -> 0
A23: 91 | B23: 11358 | D23: 24.25 | F23: X (9) | G23: X (9) | H23: X (9), OT(1.97) | I23: X (9) | J23: X (5.23), NB(2.77) | M23: X (9) | N23: X (9) | O23: X (9) | P23: X (9) | Q23: X | R23: OW(7.17) | T23: X (9) | U23: X (8.83), NB(0.17) | V23: X (8.27), NB(0.73) | W23: H (9) | X23: H | Y23: H (9) | Z23: H (9) | AA23: H (9) | AD23: X (4), NB(5) | AE23: NB | AH23: X (9) | AI23: X (9) | AS23: 133.33 | AU23: 1.97 | AW23: 7.17 | BC23: 16.67 | BD23: 44 | BM23: 203.14 | BO23: =D23*8 -> 194 | BP23: =AS23+AT23+BA23+BB23+BC23+BD23+BE23+BF23+BG23+BH23+BI23+BJ23+BK23+BL23 -> 194 | BQ23: =AS23+AT23+BA23+BB23+BC23+BD23+BE23+BH23 -> 194 | BR23: =AS23+AT23+BA23+BH23 -> 133.33 | BS23: =BP23-BO23 -> 0 | BT23: =BO23-BQ23 -> 0 | BU23: =AU23 -> 1.97 | BV23: =AW23 -> 7.17 | BW23: =AY23 -> 0 | BX23: =AT23 -> 0 | BY23: =AV23 -> 0 | BZ23: =AX23 -> 0 | CA23: =AZ23 -> 0
A24: 94 | B24: 11094 | D24: 24 | F24: X | G24: X | H24: X | I24: X | J24: X | K24: X(4) | M24: X | N24: X | O24: X | P24: X | Q24: X | R24: X(4) | T24: X | U24: X | V24: X | W24: H | X24: H | Y24: H | Z24: H | AA24: H | AC24: X(4) | AD24: X | AE24: X | AF24: X(4) | AH24: X | AI24: X | AS24: 152 | BD24: 40 | BM24: 192 | BO24: =D24*8 -> 192 | BP24: =AS24+AT24+BA24+BB24+BC24+BD24+BE24+BF24+BG24+BH24+BI24+BJ24+BK24+BL24 -> 192 | BQ24: =AS24+AT24+BA24+BB24+BC24+BD24+BE24+BH24 -> 192 | BR24: =AS24+AT24+BA24+BH24 -> 152 | BS24: =BP24-BO24 -> 0 | BT24: =BO24-BQ24 -> 0 | BU24: =AU24 -> 0 | BV24: =AW24 -> 0 | BW24: =AY24 -> 0 | BX24: =AT24 -> 0 | BY24: =AV24 -> 0 | BZ24: =AX24 -> 0 | CA24: =AZ24 -> 0
A25: 95 | B25: 11126 | D25: 24 | F25: X | G25: X | H25: X | I25: X | J25: X | K25: X(4) | M25: X | N25: X | O25: X | P25: X | Q25: X | R25: X(4) | T25: X | U25: X | V25: X | W25: H | X25: H | Y25: H | Z25: H | AA25: H | AC25: X(4) | AD25: X | AE25: X | AF25: X(4) | AH25: X | AI25: X | AS25: 152 | BD25: 40 | BM25: 192 | BO25: =D25*8 -> 192 | BP25: =AS25+AT25+BA25+BB25+BC25+BD25+BE25+BF25+BG25+BH25+BI25+BJ25+BK25+BL25 -> 192 | BQ25: =AS25+AT25+BA25+BB25+BC25+BD25+BE25+BH25 -> 192 | BR25: =AS25+AT25+BA25+BH25 -> 152 | BS25: =BP25-BO25 -> 0 | BT25: =BO25-BQ25 -> 0 | BU25: =AU25 -> 0 | BV25: =AW25 -> 0 | BW25: =AY25 -> 0 | BX25: =AT25 -> 0 | BY25: =AV25 -> 0 | BZ25: =AX25 -> 0 | CA25: =AZ25 -> 0
A26: 96 | B26: 11141 | D26: 24 | F26: X | G26: X | H26: X | I26: X | J26: X | K26: X(4) | M26: X | N26: X | O26: X | P26: X | Q26: X | R26: X(4) | T26: X | U26: X | V26: X | W26: H | X26: H | Y26: H | Z26: H | AA26: H | AC26: X(4) | AD26: X | AE26: X | AF26: X(4) | AH26: X | AI26: X | AS26: 152 | BD26: 40 | BM26: 192 | BO26: =D26*8 -> 192 | BP26: =AS26+AT26+BA26+BB26+BC26+BD26+BE26+BF26+BG26+BH26+BI26+BJ26+BK26+BL26 -> 192 | BQ26: =AS26+AT26+BA26+BB26+BC26+BD26+BE26+BH26 -> 192 | BR26: =AS26+AT26+BA26+BH26 -> 152 | BS26: =BP26-BO26 -> 0 | BT26: =BO26-BQ26 -> 0 | BU26: =AU26 -> 0 | BV26: =AW26 -> 0 | BW26: =AY26 -> 0 | BX26: =AT26 -> 0 | BY26: =AV26 -> 0 | BZ26: =AX26 -> 0 | CA26: =AZ26 -> 0
A27: 97 | B27: 11168 | D27: 24 | F27: X | G27: X | H27: X | I27: X | J27: X | K27: X(4) | M27: X | N27: X | O27: X | P27: X | Q27: X | R27: X(4) | T27: X | U27: X | V27: X | W27: H | X27: H | Y27: H | Z27: H | AA27: H | AC27: X(4) | AD27: X | AE27: X | AF27: X(4) | AH27: X | AI27: X | AS27: 152 | BD27: 40 | BM27: 192 | BO27: =D27*8 -> 192 | BP27: =AS27+AT27+BA27+BB27+BC27+BD27+BE27+BF27+BG27+BH27+BI27+BJ27+BK27+BL27 -> 192 | BQ27: =AS27+AT27+BA27+BB27+BC27+BD27+BE27+BH27 -> 192 | BR27: =AS27+AT27+BA27+BH27 -> 152 | BS27: =BP27-BO27 -> 0 | BT27: =BO27-BQ27 -> 0 | BU27: =AU27 -> 0 | BV27: =AW27 -> 0 | BW27: =AY27 -> 0 | BX27: =AT27 -> 0 | BY27: =AV27 -> 0 | BZ27: =AX27 -> 0 | CA27: =AZ27 -> 0
A28: 98 | B28: 11188 | D28: 24 | F28: X | G28: X | H28: X | I28: X | J28: X | K28: X(4) | M28: X | N28: X | O28: X | P28: X | Q28: X | R28: X(4) | T28: X | U28: X | V28: X | W28: H | X28: H | Y28: H | Z28: H | AA28: H | AC28: X(4) | AD28: X | AE28: X | AF28: X(4) | AH28: X | AI28: X | AS28: 152 | BD28: 40 | BM28: 192 | BO28: =D28*8 -> 192 | BP28: =AS28+AT28+BA28+BB28+BC28+BD28+BE28+BF28+BG28+BH28+BI28+BJ28+BK28+BL28 -> 192 | BQ28: =AS28+AT28+BA28+BB28+BC28+BD28+BE28+BH28 -> 192 | BR28: =AS28+AT28+BA28+BH28 -> 152 | BS28: =BP28-BO28 -> 0 | BT28: =BO28-BQ28 -> 0 | BU28: =AU28 -> 0 | BV28: =AW28 -> 0 | BW28: =AY28 -> 0 | BX28: =AT28 -> 0 | BY28: =AV28 -> 0 | BZ28: =AX28 -> 0 | CA28: =AZ28 -> 0
A29: 99 | B29: 11502 | D29: 24 | F29: X | G29: X | H29: X | I29: X | J29: X | K29: X(4) | M29: X | N29: X | O29: X | P29: X | Q29: X | R29: X(4) | T29: X | U29: X | V29: X | W29: H | X29: H | Y29: H | Z29: H | AA29: H | AC29: X(4) | AD29: X | AE29: X | AF29: X(4) | AH29: X | AI29: X | AS29: 152 | BD29: 40 | BM29: 192 | BO29: =D29*8 -> 192 | BP29: =AS29+AT29+BA29+BB29+BC29+BD29+BE29+BF29+BG29+BH29+BI29+BJ29+BK29+BL29 -> 192 | BQ29: =AS29+AT29+BA29+BB29+BC29+BD29+BE29+BH29 -> 192 | BR29: =AS29+AT29+BA29+BH29 -> 152 | BS29: =BP29-BO29 -> 0 | BT29: =BO29-BQ29 -> 0 | BU29: =AU29 -> 0 | BV29: =AW29 -> 0 | BW29: =AY29 -> 0 | BX29: =AT29 -> 0 | BY29: =AV29 -> 0 | BZ29: =AX29 -> 0 | CA29: =AZ29 -> 0
A30: 101 | B30: 11587 | D30: 24 | F30: X | G30: X | H30: X | I30: X | J30: X | K30: X(4) | M30: X | N30: X | O30: X | P30: X | Q30: X | R30: X(4) | T30: X | U30: X | V30: X | W30: H | X30: H | Y30: H | Z30: H | AA30: H | AC30: X(4) | AD30: X | AE30: X | AF30: X(4) | AH30: X | AI30: X | AS30: 152 | BD30: 40 | BM30: 192 | BO30: =D30*8 -> 192 | BP30: =AS30+AT30+BA30+BB30+BC30+BD30+BE30+BF30+BG30+BH30+BI30+BJ30+BK30+BL30 -> 192 | BQ30: =AS30+AT30+BA30+BB30+BC30+BD30+BE30+BH30 -> 192 | BR30: =AS30+AT30+BA30+BH30 -> 152 | BS30: =BP30-BO30 -> 0 | BT30: =BO30-BQ30 -> 0 | BU30: =AU30 -> 0 | BV30: =AW30 -> 0 | BW30: =AY30 -> 0 | BX30: =AT30 -> 0 | BY30: =AV30 -> 0 | BZ30: =AX30 -> 0 | CA30: =AZ30 -> 0
A31: 102 | B31: 11626 | D31: 24 | F31: X | G31: X | H31: X | I31: X | J31: X | K31: X(4) | M31: X | N31: X | O31: X | P31: X | Q31: P | R31: P(4) | T31: P | U31: P | V31: P | W31: H | X31: H | Y31: H | Z31: H | AA31: H | AC31: X(4) | AD31: X | AE31: X | AF31: X(4) | AH31: X | AI31: X | AS31: 116 | BB31: 36 | BD31: 40 | BM31: 192 | BO31: =D31*8 -> 192 | BP31: =AS31+AT31+BA31+BB31+BC31+BD31+BE31+BF31+BG31+BH31+BI31+BJ31+BK31+BL31 -> 192 | BQ31: =AS31+AT31+BA31+BB31+BC31+BD31+BE31+BH31 -> 192 | BR31: =AS31+AT31+BA31+BH31 -> 116 | BS31: =BP31-BO31 -> 0 | BT31: =BO31-BQ31 -> 0 | BU31: =AU31 -> 0 | BV31: =AW31 -> 0 | BW31: =AY31 -> 0 | BX31: =AT31 -> 0 | BY31: =AV31 -> 0 | BZ31: =AX31 -> 0 | CA31: =AZ31 -> 0
A32: 106 | B32: 4044 | D32: 24 | F32: X | G32: X | H32: X | I32: X | J32: X | K32: X(4) | M32: X | N32: X | O32: X | P32: X | Q32: X | R32: X(4) | T32: X | U32: X | V32: X | W32: H | X32: H | Y32: H | Z32: H | AA32: H | AC32: X(4) | AD32: X | AE32: X | AF32: X(4) | AH32: X | AI32: X | AS32: 152 | BD32: 40 | BM32: 192 | BO32: =D32*8 -> 192 | BP32: =AS32+AT32+BA32+BB32+BC32+BD32+BE32+BF32+BG32+BH32+BI32+BJ32+BK32+BL32 -> 192 | BQ32: =AS32+AT32+BA32+BB32+BC32+BD32+BE32+BH32 -> 192 | BR32: =AS32+AT32+BA32+BH32 -> 152 | BS32: =BP32-BO32 -> 0 | BT32: =BO32-BQ32 -> 0 | BU32: =AU32 -> 0 | BV32: =AW32 -> 0 | BW32: =AY32 -> 0 | BX32: =AT32 -> 0 | BY32: =AV32 -> 0 | BZ32: =AX32 -> 0 | CA32: =AZ32 -> 0
A33: 107 | B33: 4045 | D33: 24 | F33: X | G33: X | H33: X | I33: X | J33: X | K33: X(4) | M33: X | N33: X | O33: X | P33: X | Q33: X | R33: X(4) | T33: X | U33: X | V33: P | W33: H | X33: H | Y33: H | Z33: H | AA33: H | AC33: X(4) | AD33: P | AE33: P | AF33: X(4) | AH33: X | AI33: X | AS33: 128 | BB33: 24 | BD33: 40 | BM33: 192 | BO33: =D33*8 -> 192 | BP33: =AS33+AT33+BA33+BB33+BC33+BD33+BE33+BF33+BG33+BH33+BI33+BJ33+BK33+BL33 -> 192 | BQ33: =AS33+AT33+BA33+BB33+BC33+BD33+BE33+BH33 -> 192 | BR33: =AS33+AT33+BA33+BH33 -> 128 | BS33: =BP33-BO33 -> 0 | BT33: =BO33-BQ33 -> 0 | BU33: =AU33 -> 0 | BV33: =AW33 -> 0 | BW33: =AY33 -> 0 | BX33: =AT33 -> 0 | BY33: =AV33 -> 0 | BZ33: =AX33 -> 0 | CA33: =AZ33 -> 0
A34: 108 | B34: 4047 | D34: 24 | F34: X | G34: X | H34: X | I34: X | J34: X | K34: X(4) | M34: X | N34: X | O34: X | P34: X | Q34: X | R34: X(4) | T34: X | U34: X | V34: X | W34: H | X34: H | Y34: H | Z34: H | AA34: H | AC34: X(4) | AD34: X | AE34: X | AF34: X(4) | AH34: X | AI34: X | AS34: 152 | BD34: 40 | BM34: 192 | BO34: =D34*8 -> 192 | BP34: =AS34+AT34+BA34+BB34+BC34+BD34+BE34+BF34+BG34+BH34+BI34+BJ34+BK34+BL34 -> 192 | BQ34: =AS34+AT34+BA34+BB34+BC34+BD34+BE34+BH34 -> 192 | BR34: =AS34+AT34+BA34+BH34 -> 152 | BS34: =BP34-BO34 -> 0 | BT34: =BO34-BQ34 -> 0 | BU34: =AU34 -> 0 | BV34: =AW34 -> 0 | BW34: =AY34 -> 0 | BX34: =AT34 -> 0 | BY34: =AV34 -> 0 | BZ34: =AX34 -> 0 | CA34: =AZ34 -> 0
A35: 110 | B35: 4145 | D35: 24 | F35: X | G35: X | H35: X | I35: X | J35: X | K35: X(4) | M35: X | N35: X | O35: X | AS35: 68 | BM35: 68 | BO35: =D35*8 -> 192 | BP35: =AS35+AT35+BA35+BB35+BC35+BD35+BE35+BF35+BG35+BH35+BI35+BJ35+BK35+BL35 -> 68 | BQ35: =AS35+AT35+BA35+BB35+BC35+BD35+BE35+BH35 -> 68 | BR35: =AS35+AT35+BA35+BH35 -> 68 | BS35: =BP35-BO35 -> -124 | BT35: =BO35-BQ35 -> 124 | BU35: =AU35 -> 0 | BV35: =AW35 -> 0 | BW35: =AY35 -> 0 | BX35: =AT35 -> 0 | BY35: =AV35 -> 0 | BZ35: =AX35 -> 0 | CA35: =AZ35 -> 0

Sheet CC
A1: 9200 | B1: Plant - HR & Admin
A2: 9260-1 | B2: Safety
A3: 9220-1 | B3: Plant - BI
A4: 9280 | B4: Warehouse
A5: 9220 | B5: Plant - BI
A6: 9240 | B6: QA/QC
A7: 9250 | B7: R&D
A8: 9260 | B8: Maintenance
A9: 9260-2 | B9: ETP
A10: 9410 | B10: HR & Admin
A11: 9100 | B11: Sales and Marketing
A12: 9420 | B12: Finance - Accounting - IT
... A14: 9430 | B14: Procurement
