Workbook
Name \0: #REF!
Name \a: #REF!
Name \a: #REF!
Name \a: #REF!
Name \b: #N/A
Name \c: #N/A
Name \d: #N/A
Name \e: #REF!
Name \f: #REF!
Name \g: #REF!
Name \h: #REF!
Name \i: #REF!
Name \j: #REF!
Name \k: #REF!
Name \l: #REF!
Name \m: #REF!
Name \n: #REF!
Name \o: #REF!
Name \p: #N/A
Name \T: #REF!
Name \T: #REF!
Name \T: #REF!
Name \T: #REF!
Name \T: #REF!
Name \T: #REF!
Name \z: #REF!
Name _: "SQRT"
Name _.._mik: #REF!
Name _?: #REF!
Name _?: #REF!
Name _??: #N/A
Name _??????: #REF!
Name _??????: #REF!
Name _?1: #N/A
Name _?271: #N/A
Name _?춑_TOTAL: #N/A
Name _?춮t2: #N/A
Name __?: #N/A
Name __??: #N/A
Name __??????: #REF!
Name __??????: #REF!
Name __?1: #N/A
Name __?271: #N/A
Name ___?: #REF!
Name ___?: #REF!
Name ___?: #REF!
Name ___?: #REF!
Name ___?: #REF!
Name ___?: #REF!
Name ___??????: #REF!
Name ___??????: #REF!
Name ___??????: #REF!
Name ___??????: #REF!
Name ___??????: #REF!
Name ___??????: #REF!
Name ___________________________________C45_EXC_M: #REF!
Name __________________________________C45_EXC_M: #REF!
Name _________________________________C45_EXC_M: #REF!
Name ________________________________C45_EXC_M: #REF!
Name _______________________________C45_EXC_M: #REF!

Sheet BANG LUONG VTĐB 
A1: CÔNG TY ................. | AU1: 5143077 | AY1: 4946923 | AZ1: =AU1-AY1 -> 196154
A2: Địa chỉ: ............
A3: BẢNG THANH TOÁN TIỀN LƯƠNG THÁNG 11 NĂM 2025 | CT3: THỐNG KÊ LƯƠNG KỲ 2
AZ5: Nam Bộ | BF5: Nam Bộ | BG5: 11 | CJ5: Công chuẩn
AZ6: Bắc Bộ | BF6: Bắc Bộ | BG6: 11 | BV6: THÔNG TIN VỀ TÍNH THUẾ TNCN | CJ6: 25
A7: TT | B7: MSNV | C7: Họ và tên | D7: TĐ | E7: Ngạch lương | F7: Ngày vào | G7: Mức lương HĐLĐ | H7: Mức lương HĐTV | I7: Định mức thưởng HQCV | J7: Phụ cấp | K7: Tổng định mức thưởng HQCV | L7: Tổng thu nhập (Mức lương + Định mức thưởng HQCV) | M7: Tỷ lệ % tạm ứng thưởng HQCV | N7: Mức lương tính chế độ ngừng việc | P7: Ngày công trong tháng | AG7: Các khoản được hưởng trong tháng | AV7: Tiền công giao xe 20% chi cùng lương kỳ 2/11 | AW7: Thu nhập hoàn thuế năm.. | AX7: Chi quà 1/6 | AY7: Thu nhập đã tạm ứng kỳ 1/11 | AZ7: Tổng thu nhập còn lại trong tháng 11 | BA7: Các khoản giám trừ kỳ trong tháng | BL7: Tổng giảm trừ | BM7: Thực nhận | BN7: Thu vào kỳ sau | BV7: THUẾ THU NHẬP CÁ NHÂN | CF7: Khoản đc giảm trừ trong thuế | CI7: BHXH | CL7: KỲ I | CT7: KỲ II | DA7: Chức vụ | DB7: Bộ phận | DC7: Mail | DD7: Khu vực đóng góp tang chế | DE7: TÀI KHOẢN NGÂN HÀNG | DJ7: GHI CHÚ
P8: Công chính | Q8: Công giao xe | R8: Công Tăng ca ngày thường | S8: Công Chủ nhật | T8: Công ngày lễ, tết | W8: Hiếu, hỉ | X8: Ngày PN thanh toán T11/2025 | Y8: Ngày ngừng việc | AA8: Ngày ngừng việc BKK | AB8: Công ngày thứ 7 | AD8: Công phụ cấp | AF8: Ngày PN chưa nghỉ năm 2025 | AG8: Lương Ngày thường | AH8: Lương Tăng ca thường | AI8: Lương chủ nhật | AJ8: Lương ngày lễ, tết | AL8: Lương Hiếu, Hỉ | AM8: Lương phép PN thanh toán T11 | AN8: Lương tạm ngừng việc | AO8: Lương chế độ T7 | AP8: Thu nhập phụ cấp | AR8: Phép năm chưa nghỉ năm 2025 | AS8: Tạm ứng thưởng HQCV | AT8: Thu nhập khác (Phép năm thôi việc, Hỗ trợ thôi việc,...) | AU8: Tổng thu nhập tháng 11 | BA8: BHXH | BB8: BHYT | BC8: BHTN | BD8: BHXH,BHYT, BHTN | BE8: Phí công đoàn | BF8: Phí đoàn thanh niên (dưới 30 tuổi) | BG8: Tiền phúng điếu | BH8: Cước điện thoại T10/2025 | BI8: Thuế TNCN T11 | BJ8: Thu thuế TNCN T1/2024 lần 1 | BK8: Giảm trừ khác (thu hộ tiền ủng hộ Nguyễn Tấn Dũng, thu nợ kỳ trước, thu hộ tiền bồi thường,...) | BO8: KIỂM TRA | BV8: Thu nhập ngoài bảng lương đưa vào tính thuế | BZ8: THU NHẬP CHỊU THUẾ TNCN | CA8: SỐ NGƯỜI PHỤ THUỘC | CB8: GIẢM TRỪ GIA CẢNH | CC8: GIẢM TRỪ BẢN THÂN | CD8: TỔNG GIẢM TRỪ | CE8: TỔNG THU NHẬP TÍNH THUẾ TNCN
N9: Tạm ngừng việc 14 ngày đầu | O9: Tạm ngừng việc từ 15 ngày trở đi | T9: Đi làm lễ, tết | U9: Tăng ca | V9: Nghỉ lễ, tết | Y9: 14 ngày đầu | Z9: Từ ngày 15 trở đi | AB9: Đi làm T7 | AC9: Nghỉ T7 | AD9: Phụ cấp ban đêm | AE9: Phụ cấp bồi dưỡng làm việc | AJ9: Làm việc ngày lễ, tết | AK9: Nghỉ lễ, tết | AP9: Phụ cấp ban đêm | AQ9: Phụ cấp bồi dưỡng làm việc | BA9: 8% | BB9: 1.5% | BC9: 1% | BD9: (LHĐLĐ *10.5%) | BE9: (LHĐLĐ*1%) | BF9: 5.000đ/ người | BG9: 23 | BO9: MA BH | BP9: Ma KPCD | BQ9: Kiểm tra đối tượng hưởng lương | BR9: Kiểm tra đối tượng hưởng tăng ca | BS9: BD PHSK | BT9: MỨC TIỀN | BU9: Trừ tiền tang chế | BV9: Tiền ăn vượt mức | BW9: Thu nhập còn phải chi tháng 1 | BX9: Tiền thưởng | BY9: Thu nhập 100% giao xe | CF9: Hỗ trợ thôi việc, trợ cấp thôi việc | CG9: Truy lĩnh PC ĐH cho LX trung chuyển làm việc MT ĐH T3-T6/2025 | CH9: Trả lại tiền thu ĐTDD Tháng 8 - Chi nhánh | CI9: Truy thu BH | CJ9: Truy lĩnh BHXH | CK9: BHXH đã thu (số trong bảng đóng BHXH) | CL9: Mức lương | CM9: PC ThN | CN9: PC chức danh | CO9: PC kiêm nhiệm | CP9: PC biệt phái | CQ9: Tổng PC | CR9: Tổng thu nhập | CT9: Mức lương | CU9: PC ThN | CV9: PC chức danh | CW9: PC kiêm nhiệm | CX9: PC biệt phái | CY9: Tổng PC | CZ9: Tổng thu nhập | DE9: ICB | DF9: VCB | DG9: BIDV | DH9: NH khác | DI9: CCCD
A10: A. | B10: ="KHU VỰC CHU LAI: "&"["&COUNT(A11:A23)&"]" -> KHU VỰC CHU LAI: [10] | G10: =G11+G22+G14+#REF!+#REF!+#REF!+#REF!+#REF!+#REF! -> #REF! | H10: =H11+H22+H14+#REF!+#REF!+#REF!+#REF!+#REF!+#REF! -> #REF! | I10: =I11+I22+I14+#REF!+#REF!+#REF!+#REF!+#REF!+#REF! -> #REF! | J10: =J11+J22+J14+#REF!+#REF!+#REF!+#REF!+#REF!+#REF! -> #REF! | K10: =K11+K22+K14+#REF!+#REF!+#REF!+#REF!+#REF!+#REF! -> #REF! | L10: =L11+L22+L14+#REF!+#REF!+#REF!+#REF!+#REF!+#REF! -> #REF! | N10: =N11+N22+N14+#REF!+#REF!+#REF!+#REF!+#REF!+#REF! -> #REF! | O10: =O11+O22+O14+#REF!+#REF!+#REF!+#REF!+#REF!+#REF! -> #REF! | P10: =P11+P22+P14+#REF!+#REF!+#REF!+#REF!+#REF!+#REF! -> #REF! | Q10: =Q11+Q22+Q14+#REF!+#REF!+#REF!+#REF!+#REF!+#REF! -> #REF! | R10: =R11+R22+R14+#REF!+#REF!+#REF!+#REF!+#REF!+#REF! -> #REF! | S10: =S11+S22+S14+#REF!+#REF!+#REF!+#REF!+#REF!+#REF! -> #REF! | T10: =T11+T22+T14+#REF!+#REF!+#REF!+#REF!+#REF!+#REF! -> #REF! | U10: =U11+U22+U14+#REF!+#REF!+#REF!+#REF!+#REF!+#REF! -> #REF! | ... CZ10: =CZ11+CZ22+CZ14+#REF!+#REF!+#REF!+#REF!+#REF!+#REF! -> #REF!
A11: I | B11: ="............: "&"["&COUNT(A13:A13)&"]" -> ............: [1] | G11: =SUM(G12:G13) -> 0 | H11: =SUM(H12:H13) -> 0 | I11: =SUM(I12:I13) -> 0 | J11: =SUM(J12:J13) -> 0 | K11: =SUM(K12:K13) -> 0 | L11: =SUM(L12:L13) -> 0 | N11: =SUM(N12:N13) -> 7280000 | O11: =SUM(O12:O13) -> 0 | P11: =SUM(P12:P13) -> 0 | Q11: =SUM(Q12:Q13) -> 0 | R11: =SUM(R12:R13) -> 0 | S11: =SUM(S12:S13) -> 0 | T11: =SUM(T12:T13) -> 0 | U11: =SUM(U12:U13) -> 0 | ... DC11: =SUM(DC12:DC13) -> 0 | DE11: =SUM(DE13:DE13) -> 0 | DF11: =SUM(DF13:DF13) -> 0 | DG11: =SUM(DG13:DG13) -> 0 | DH11: =SUM(DH13:DH13) -> 0 | DI11: =SUM(DI13:DI13) -> 0
A12: =SUBTOTAL(3,$C$11:C12) -> 0 | I12: =IF(G12>0,CT12-G12,CT12-H12) -> 0 | J12: =CY12 -> 0 | K12: =SUM(I12:J12) -> 0 | L12: =IF(G12>0,G12+K12,H12+K12) -> 0 | M12: 1 | N12: =ROUND(MAX(G12*70%,H12*70%,3640000),0) -> 3640000 | O12: 0 | AE12: =IF(OR(BS12="M1",BS12="M2",BS12="M3",BS12="M4"),P12+R12+S12+T12+U12,0) -> 0 | AG12: =MAX(ROUND(IF(P12=0,0,IF(AND(BQ12="Lương tháng",(AB12+AC12)=0),MAX(G12/26*P12*M12,H12/26*P12*M12),IF(BQ12="Lương tháng",MAX((G12-G12/26*($CJ$6-P12))*M12,(H12-H12/26*($CJ$6-P12))*M12),MAX(G12/26*P12*M12,H12/26*P12*M12)))),0),0) -> 0 | AH12: =ROUND(MAX((G12+I12)*M12/26*R12,(H12+I12)*M12/26*R12,G12/26*R12*150%,H12/26*R12*150%)*BR12,0) -> 0 | AI12: =ROUND(MAX((G12+I12)*M12/26*S12,(H12+I12)*M12/26*S12,G12/26*S12*200%,H12/26*S12*200%)*BR12,0) -> 0 | AJ12: =ROUND(IF(BQ12="Lương tháng",L12/26*T12,MAX((G12+I12)/26*(T12+U12)*200%+G12/26*T12,(H12+I12)/26*(T12+U12)*200%+H12/26*T12,G12/26*(T12+U12)*300%+G12/26*T12,H12/26*(T12+U12)*300%+H12/26*T12)),0) -> 0 | AK12: =ROUND(IF((P12+Q12)=0,0,IF(BQ12="Lương tháng",MAX((G12+I12)/26*V12,(H12+I12)/26*V12),MAX(G12/26*V12,H12/26*V12))),0) -> 0 | AL12: =ROUND(IF(G12>0,G12/26*W12,H12/26*W12),0) -> 0 | AM12: =ROUND((G12+50%*I12)/26*X12,0) -> 0 | AN12: =ROUND(N12/26*Y12+O12/26*Z12+MAX(G12/26*AA12,H12/26*AA12),0) -> 0 | AO12: =ROUND(IF(BQ12="Lương tháng",L12/26*AC12,L12/26*AC12+L12/26*AB12),0) -> 0 | AP12: =ROUND(IF(BQ12="lương tháng",0,MAX((G12+I12)/26*AD12*30%,(H12+I12)/26*AD12*30%)*BR12),0) -> 0 | AQ12: =ROUND(BT12*AE12,0) -> 0 | AR12: =ROUND((G12+I12)/26*AF12,0) -> 0 | AS12: =MAX(ROUND(IF(P12=0,0,IF(AND(BQ12="Lương tháng",(AB12+AC12)=0),K12/26*P12*M12,IF(BQ12="Lương tháng",(K12-K12/26*($CJ$6-P12))*M12,(K12/26*P12*M12)))),0),0)+ROUND(J12/26*Q12,0) -> 0 | AU12: =ROUND(SUM(AG12:AT12),0) -> 0 | AZ12: =ROUND(SUM(AU12:AX12)-AY12,0) -> 0 | BD12: =SUM(BA12:BC12) -> 0 | BE12: 0 | BG12: =IF(BU12="Xem lại",0,IF(CL12<11000000,5000,IF(AND(CL12>=11000000,CL12<25000000),10000,IF(AND(CL12>=25000000,CL12<40000000),15000,IF(AND(CL12>=40000000,CL12<120000000),20000,IF(AND(CL12>=120000000,CL12<240000000),25000,30000)))))*$BG$9) -> 0 | BI12: =IF(CE12>0,ROUND(IF(CE12>=80000000,CE12*35%-9850000,IF(CE12>=52000000,CE12*30%-5850000,IF(CE12>=32000000,CE12*25%-3250000,IF(CE12>=18000000,CE12*20%-1650000,IF(CE12>=10000000,CE12*15%-750000,IF(CE12>5000000,CE12*10%-250000,CE12*5%)))))),0),0) -> 0 | BL12: =ROUND(SUM(BD12:BK12),0) -> 0 | BM12: =ROUND(IF(AZ12>BL12,AZ12-BL12,0),0) -> 0 | BN12: =ROUND(IF(BL12>AZ12,BL12-AZ12,0),0) -> 0 | BO12: 1 | BP12: 1x | BQ12: =IF(AND(D12="QTNV CL",CT12>=11000000),"Lương tháng",IF(CT12>=18000000,"Lương tháng",0)) -> 0 | BR12: =IF(BQ12="Lương tháng",0,1) -> 1 | BS12: 0 | BT12: =IF(BS12="M1",13000,IF(BS12="M2",20000,IF(BS12="M3",26000,IF(BS12="M4",32000,0)))) -> 0 | BU12: =IF(AND(G12>0,(P12+Q12)>5),"Trừ tiền","Xem lại") -> Xem lại | BZ12: =AU12+SUM(BV12:BY12)-AL12-AP12-AQ12-SUM(CF12:CH12) -> 0 | CB12: =CA12*4400000 -> 0 | CC12: 11000000 | CD12: =CB12+CC12 -> 11000000 | CE12: =BZ12-SUM(CJ12:CK12)-CI12-BD12-CD12 -> -12798650 | CK12: 1798650 | CM12: 0 | CN12: 0 | CQ12: =SUM(CM12:CP12) -> 0 | CR12: =CL12+CQ12 -> 0 | CT12: =CL12 -> 0 | CU12: =CM12 -> 0 | CV12: =CN12 -> 0 | CW12: =CO12 -> 0 | CX12: =CP12 -> 0 | CY12: =SUM(CU12:CX12) -> 0 | CZ12: =CT12+CY12 -> 0
A13: =SUBTOTAL(3,$C$11:C13) -> 0 | I13: =IF(G13>0,CT13-G13,CT13-H13) -> 0 | J13: =CY13 -> 0 | K13: =SUM(I13:J13) -> 0 | L13: =IF(G13>0,G13+K13,H13+K13) -> 0 | M13: 1 | N13: =ROUND(MAX(G13*70%,H13*70%,3640000),0) -> 3640000 | O13: 0 | AE13: =IF(OR(BS13="M1",BS13="M2",BS13="M3",BS13="M4"),P13+R13+S13+T13+U13,0) -> 0 | AG13: =MAX(ROUND(IF(P13=0,0,IF(AND(BQ13="Lương tháng",(AB13+AC13)=0),MAX(G13/26*P13*M13,H13/26*P13*M13),IF(BQ13="Lương tháng",MAX((G13-G13/26*($CJ$6-P13))*M13,(H13-H13/26*($CJ$6-P13))*M13),MAX(G13/26*P13*M13,H13/26*P13*M13)))),0),0) -> 0 | AH13: =ROUND(MAX((G13+I13)*M13/26*R13,(H13+I13)*M13/26*R13,G13/26*R13*150%,H13/26*R13*150%)*BR13,0) -> 0 | AI13: =ROUND(MAX((G13+I13)*M13/26*S13,(H13+I13)*M13/26*S13,G13/26*S13*200%,H13/26*S13*200%)*BR13,0) -> 0 | AJ13: =ROUND(IF(BQ13="Lương tháng",L13/26*T13,MAX((G13+I13)/26*(T13+U13)*200%+G13/26*T13,(H13+I13)/26*(T13+U13)*200%+H13/26*T13,G13/26*(T13+U13)*300%+G13/26*T13,H13/26*(T13+U13)*300%+H13/26*T13)),0) -> 0 | AK13: =ROUND(IF((P13+Q13)=0,0,IF(BQ13="Lương tháng",MAX((G13+I13)/26*V13,(H13+I13)/26*V13),MAX(G13/26*V13,H13/26*V13))),0) -> 0 | AL13: =ROUND(IF(G13>0,G13/26*W13,H13/26*W13),0) -> 0 | AM13: =ROUND((G13+50%*I13)/26*X13,0) -> 0 | AN13: =ROUND(N13/26*Y13+O13/26*Z13+MAX(G13/26*AA13,H13/26*AA13),0) -> 0 | AO13: =ROUND(IF(BQ13="Lương tháng",L13/26*AC13,L13/26*AC13+L13/26*AB13),0) -> 0 | AP13: =ROUND(IF(BQ13="lương tháng",0,MAX((G13+I13)/26*AD13*30%,(H13+I13)/26*AD13*30%)*BR13),0) -> 0 | AQ13: =ROUND(BT13*AE13,0) -> 0 | AR13: =ROUND((G13+I13)/26*AF13,0) -> 0 | AS13: =MAX(ROUND(IF(P13=0,0,IF(AND(BQ13="Lương tháng",(AB13+AC13)=0),K13/26*P13*M13,IF(BQ13="Lương tháng",(K13-K13/26*($CJ$6-P13))*M13,(K13/26*P13*M13)))),0),0)+ROUND(J13/26*Q13,0) -> 0 | AU13: =ROUND(SUM(AG13:AT13),0) -> 0 | AZ13: =ROUND(SUM(AU13:AX13)-AY13,0) -> 0 | BD13: =SUM(BA13:BC13) -> 0 | BE13: 0 | BG13: =IF(BU13="Xem lại",0,IF(CL13<11000000,5000,IF(AND(CL13>=11000000,CL13<25000000),10000,IF(AND(CL13>=25000000,CL13<40000000),15000,IF(AND(CL13>=40000000,CL13<120000000),20000,IF(AND(CL13>=120000000,CL13<240000000),25000,30000)))))*$BG$9) -> 0 | BI13: =IF(CE13>0,ROUND(IF(CE13>=80000000,CE13*35%-9850000,IF(CE13>=52000000,CE13*30%-5850000,IF(CE13>=32000000,CE13*25%-3250000,IF(CE13>=18000000,CE13*20%-1650000,IF(CE13>=10000000,CE13*15%-750000,IF(CE13>5000000,CE13*10%-250000,CE13*5%)))))),0),0) -> 0 | BL13: =ROUND(SUM(BD13:BK13),0) -> 0 | BM13: =ROUND(IF(AZ13>BL13,AZ13-BL13,0),0) -> 0 | BN13: =ROUND(IF(BL13>AZ13,BL13-AZ13,0),0) -> 0 | BO13: 1 | BP13: 1x | BQ13: =IF(AND(D13="QTNV CL",CT13>=11000000),"Lương tháng",IF(CT13>=18000000,"Lương tháng",0)) -> 0 | BR13: =IF(BQ13="Lương tháng",0,1) -> 1 | BS13: 0 | BT13: =IF(BS13="M1",13000,IF(BS13="M2",20000,IF(BS13="M3",26000,IF(BS13="M4",32000,0)))) -> 0 | BU13: =IF(AND(G13>0,(P13+Q13)>5),"Trừ tiền","Xem lại") -> Xem lại | BV13: 0 | BZ13: =AU13+SUM(BV13:BY13)-AL13-AP13-AQ13-SUM(CF13:CH13) -> 0 | CB13: =CA13*4400000 -> 0 | CC13: 11000000 | CD13: =CB13+CC13 -> 11000000 | CE13: =BZ13-SUM(CJ13:CK13)-CI13-BD13-CD13 -> -12209600 | CK13: 1209600 | CM13: 0 | CN13: 0 | CQ13: =SUM(CM13:CP13) -> 0 | CR13: =CL13+CQ13 -> 0 | CT13: =CL13 -> 0 | CU13: =CM13 -> 0 | CV13: =CN13 -> 0 | CW13: =CO13 -> 0 | CX13: =CP13 -> 0 | CY13: =SUM(CU13:CX13) -> 0 | CZ13: =CT13+CY13 -> 0
A14: II | B14: ="...............: " &"["&COUNT(A15:A20)& "]" -> ...............: [6] | G14: =SUM(G15:G20) -> 29140000 | H14: =SUM(H15:H20) -> 0 | I14: =SUM(I15:I20) -> 35860000 | J14: =SUM(J15:J20) -> 3925000 | K14: =SUM(K15:K20) -> 39785000 | L14: =SUM(L15:L20) -> 68925000 | N14: =SUM(N15:N20) -> 22610000 | O14: =SUM(O15:O20) -> 0 | P14: =SUM(P15:P20) -> 123.5 | Q14: =SUM(Q15:Q20) -> 25 | R14: =SUM(R15:R20) -> 13.94 | S14: =SUM(S15:S20) -> 0 | T14: =SUM(T15:T20) -> 0 | U14: =SUM(U15:U20) -> 0 | ... DC14: =SUM(DC15:DC20) -> 0
A15: =SUBTOTAL(3,$C$11:C15) -> 1 | C15: Nguyễn Văn A | D15: THILOGI | E15: =IF(CL15>=400000000,"A1",IF(CL15>=300000000,"A2",IF(CL15>=240000000,"A3",IF(CL15>=180000000,"A4",IF(CL15>=120000000,"A5",IF(CL15>=80000000,"A6",IF(CL15>=40000000,"A7",IF(CL15>=25000000,"B1",IF(CL15>=12000000,"B2","B3"))))))))) -> B2 | F15: 45371 | G15: 6300000 | I15: =IF(G15>0,CT15-G15,CT15-H15) -> 5700000 | J15: =CY15 -> 0 | K15: =SUM(I15:J15) -> 5700000 | L15: =IF(G15>0,G15+K15,H15+K15) -> 12000000 | M15: 1 | N15: =ROUND(MAX(G15*70%,H15*70%,3640000),0) -> 4410000 | O15: 0 | P15: 22.5 | Q15: 0 | R15: 2 | S15: 0 | X15: 0.5 | AA15: 0 | AB15: 0 | AC15: 2 | AD15: 0 | AE15: 0 | AG15: =MAX(ROUND(IF(P15=0,0,IF(AND(BQ15="Lương tháng",(AB15+AC15)=0),MAX(G15/26*P15*M15,H15/26*P15*M15),IF(BQ15="Lương tháng",MAX((G15-G15/26*($CJ$6-P15))*M15,(H15-H15/26*($CJ$6-P15))*M15),MAX(G15/26*P15*M15,H15/26*P15*M15)))),0),0) -> 5451923 | AH15: =ROUND(MAX((G15+I15)*M15/26*R15,(H15+I15)*M15/26*R15,G15/26*R15*150%,H15/26*R15*150%)*BR15,0) -> 923077 | AI15: =ROUND(MAX((G15+I15)*M15/26*S15,(H15+I15)*M15/26*S15,G15/26*S15*200%,H15/26*S15*200%)*BR15,0) -> 0 | AJ15: =ROUND(IF(BQ15="Lương tháng",L15/26*T15,MAX((G15+I15)/26*(T15+U15)*200%+G15/26*T15,(H15+I15)/26*(T15+U15)*200%+H15/26*T15,G15/26*(T15+U15)*300%+G15/26*T15,H15/26*(T15+U15)*300%+H15/26*T15)),0) -> 0 | AK15: =ROUND(IF((P15+Q15)=0,0,IF(BQ15="Lương tháng",MAX((G15+I15)/26*V15,(H15+I15)/26*V15),MAX(G15/26*V15,H15/26*V15))),0) -> 0 | AL15: =ROUND(IF(G15>0,G15/26*W15,H15/26*W15),0) -> 0 | AM15: =ROUND((G15+50%*I15)/26*X15,0) -> 175962 | AN15: =ROUND(N15/26*Y15+O15/26*Z15+MAX(G15/26*AA15,H15/26*AA15),0) -> 0 | AO15: =ROUND(IF(BQ15="Lương tháng",L15/26*AC15,L15/26*AC15+L15/26*AB15),0) -> 923077 | AP15: =ROUND(IF(BQ15="lương tháng",0,MAX((G15+I15)/26*AD15*30%,(H15+I15)/26*AD15*30%)*BR15),0) -> 0 | AQ15: =ROUND(BT15*AE15,0) -> 0 | AR15: =ROUND((G15+I15)/26*AF15,0) -> 0 | AS15: =MAX(ROUND(IF(P15=0,0,IF(AND(BQ15="Lương tháng",(AB15+AC15)=0),K15/26*P15*M15,IF(BQ15="Lương tháng",(K15-K15/26*($CJ$6-P15))*M15,(K15/26*P15*M15)))),0),0)+ROUND(J15/26*Q15,0) -> 4932692 | AY15: =VLOOKUP(B15,'TAM UNG'!$B$12:$AQ$623,42,0) -> #N/A | AZ15: =ROUND(SUM(AU15:AX15)-AY15,0) -> #N/A | BD15: =SUM(BA15:BC15) -> 0 | BE15: 0 | BG15: =IF(BU15="Xem lại",0,IF(CL15<11000000,5000,IF(AND(CL15>=11000000,CL15<25000000),10000,IF(AND(CL15>=25000000,CL15<40000000),15000,IF(AND(CL15>=40000000,CL15<120000000),20000,IF(AND(CL15>=120000000,CL15<240000000),25000,30000)))))*$BG$9) -> 230000 | BI15: =IF(CE15>0,ROUND(IF(CE15>=80000000,CE15*35%-9850000,IF(CE15>=52000000,CE15*30%-5850000,IF(CE15>=32000000,CE15*25%-3250000,IF(CE15>=18000000,CE15*20%-1650000,IF(CE15>=10000000,CE15*15%-750000,IF(CE15>5000000,CE15*10%-250000,CE15*5%)))))),0),0) -> 0 | BL15: =ROUND(SUM(BD15:BK15),0) -> 230000 | BM15: =ROUND(IF(AZ15>BL15,AZ15-BL15,0),0) -> #N/A | BN15: =ROUND(IF(BL15>AZ15,BL15-AZ15,0),0) -> #N/A | BO15: 1 | BP15: 1x | BQ15: =IF(AND(D15="QTNV CL",CT15>=11000000),"Lương tháng",IF(CT15>=18000000,"Lương tháng",0)) -> 0 | BR15: =IF(BQ15="Lương tháng",0,1) -> 1 | BS15: 0 | BT15: =IF(BS15="M1",13000,IF(BS15="M2",20000,IF(BS15="M3",26000,IF(BS15="M4",32000,0)))) -> 0 | BU15: =IF(AND(G15>0,(P15+Q15)>5),"Trừ tiền","Xem lại") -> Trừ tiền | BZ15: =AU15+SUM(BV15:BY15)-AL15-AP15-AQ15-SUM(CF15:CH15) -> 0 | CB15: =CA15*4400000 -> 0 | CC15: 11000000 | CD15: =CB15+CC15 -> 11000000 | CE15: =BZ15-SUM(CJ15:CK15)-CI15-BD15-CD15 -> -11661500 | CK15: 661500 | CL15: 12000000 | CQ15: =SUM(CM15:CP15) -> 0 | CR15: =CL15+CQ15 -> 12000000 | CT15: =CL15 -> 12000000 | CU15: =CM15 -> 0 | CV15: =CN15 -> 0 | CW15: =CO15 -> 0 | CX15: =CP15 -> 0 | CY15: =SUM(CU15:CX15) -> 0 | CZ15: =CT15+CY15 -> 12000000 | DJ15: Nhân sự văn phòng
A16: =SUBTOTAL(3,$C$11:C16) -> 2 | C16: Nguyễn Văn B | D16: THILOGI | E16: =IF(CL16>=400000000,"A1",IF(CL16>=300000000,"A2",IF(CL16>=240000000,"A3",IF(CL16>=180000000,"A4",IF(CL16>=120000000,"A5",IF(CL16>=80000000,"A6",IF(CL16>=40000000,"A7",IF(CL16>=25000000,"B1",IF(CL16>=12000000,"B2","B3"))))))))) -> B3 | F16: 43570 | G16: 4520000 | I16: =IF(G16>0,CT16-G16,CT16-H16) -> 3980000 | J16: =CY16 -> 425000 | K16: =SUM(I16:J16) -> 4405000 | L16: =IF(G16>0,G16+K16,H16+K16) -> 8925000 | M16: 1 | N16: =ROUND(MAX(G16*70%,H16*70%,3640000),0) -> 3640000 | O16: 0 | P16: 25 | Q16: 0 | R16: 7.78 | S16: 0 | X16: 0 | AA16: 0 | AB16: 2 | AC16: 0 | AD16: 0.81 | AE16: 32.78 | AG16: =MAX(ROUND(IF(P16=0,0,IF(AND(BQ16="Lương tháng",(AB16+AC16)=0),MAX(G16/26*P16*M16,H16/26*P16*M16),IF(BQ16="Lương tháng",MAX((G16-G16/26*($CJ$6-P16))*M16,(H16-H16/26*($CJ$6-P16))*M16),MAX(G16/26*P16*M16,H16/26*P16*M16)))),0),0) -> 4346154 | AH16: =ROUND(MAX((G16+I16)*M16/26*R16,(H16+I16)*M16/26*R16,G16/26*R16*150%,H16/26*R16*150%)*BR16,0) -> 2543462 | AI16: =ROUND(MAX((G16+I16)*M16/26*S16,(H16+I16)*M16/26*S16,G16/26*S16*200%,H16/26*S16*200%)*BR16,0) -> 0 | AJ16: =ROUND(IF(BQ16="Lương tháng",L16/26*T16,MAX((G16+I16)/26*(T16+U16)*200%+G16/26*T16,(H16+I16)/26*(T16+U16)*200%+H16/26*T16,G16/26*(T16+U16)*300%+G16/26*T16,H16/26*(T16+U16)*300%+H16/26*T16)),0) -> 0 | AK16: =ROUND(IF((P16+Q16)=0,0,IF(BQ16="Lương tháng",MAX((G16+I16)/26*V16,(H16+I16)/26*V16),MAX(G16/26*V16,H16/26*V16))),0) -> 0 | AL16: =ROUND(IF(G16>0,G16/26*W16,H16/26*W16),0) -> 0 | AM16: =ROUND((G16+50%*I16)/26*X16,0) -> 0 | AN16: =ROUND(N16/26*Y16+O16/26*Z16+MAX(G16/26*AA16,H16/26*AA16),0) -> 0 | AO16: =ROUND(IF(BQ16="Lương tháng",L16/26*AC16,L16/26*AC16+L16/26*AB16),0) -> 686538 | AP16: =ROUND(IF(BQ16="lương tháng",0,MAX((G16+I16)/26*AD16*30%,(H16+I16)/26*AD16*30%)*BR16),0) -> 79442 | AQ16: =ROUND(BT16*AE16,0) -> 426140 | AR16: =ROUND((G16+I16)/26*AF16,0) -> 0 | AS16: =MAX(ROUND(IF(P16=0,0,IF(AND(BQ16="Lương tháng",(AB16+AC16)=0),K16/26*P16*M16,IF(BQ16="Lương tháng",(K16-K16/26*($CJ$6-P16))*M16,(K16/26*P16*M16)))),0),0)+ROUND(J16/26*Q16,0) -> 4235577 | AU16: =ROUND(SUM(AG16:AT16),0) -> 12317313 | AY16: 3000000 | AZ16: =ROUND(SUM(AU16:AX16)-AY16,0) -> 9317313 | BD16: =SUM(BA16:BC16) -> 0 | BE16: 0 | BG16: =IF(BU16="Xem lại",0,IF(CL16<11000000,5000,IF(AND(CL16>=11000000,CL16<25000000),10000,IF(AND(CL16>=25000000,CL16<40000000),15000,IF(AND(CL16>=40000000,CL16<120000000),20000,IF(AND(CL16>=120000000,CL16<240000000),25000,30000)))))*$BG$9) -> 115000 | BI16: =IF(CE16>0,ROUND(IF(CE16>=80000000,CE16*35%-9850000,IF(CE16>=52000000,CE16*30%-5850000,IF(CE16>=32000000,CE16*25%-3250000,IF(CE16>=18000000,CE16*20%-1650000,IF(CE16>=10000000,CE16*15%-750000,IF(CE16>5000000,CE16*10%-250000,CE16*5%)))))),0),0) -> 16857 | BL16: =ROUND(SUM(BD16:BK16),0) -> 131857 | BM16: =ROUND(IF(AZ16>BL16,AZ16-BL16,0),0) -> 9185456 | BN16: =ROUND(IF(BL16>AZ16,BL16-AZ16,0),0) -> 0 | BO16: 1 | BP16: Không | BQ16: =IF(AND(D16="QTNV CL",CT16>=11000000),"Lương tháng",IF(CT16>=18000000,"Lương tháng",0)) -> 0 | BR16: =IF(BQ16="Lương tháng",0,1) -> 1 | BS16: M1 | BT16: =IF(BS16="M1",13000,IF(BS16="M2",20000,IF(BS16="M3",26000,IF(BS16="M4",32000,0)))) -> 13000 | BU16: =IF(AND(G16>0,(P16+Q16)>5),"Trừ tiền","Xem lại") -> Trừ tiền | BV16: 0 | BZ16: =AU16+SUM(BV16:BY16)-AL16-AP16-AQ16-SUM(CF16:CH16) -> 11811731 | CA16: 0 | CB16: =CA16*4400000 -> 0 | CC16: 11000000 | CD16: =CB16+CC16 -> 11000000 | CE16: =BZ16-SUM(CJ16:CK16)-CI16-BD16-CD16 -> 337131 | CK16: 474600 | CL16: 8500000 | CM16: =CL16*5% -> 425000 | CN16: 0 | CO16: 0 | CQ16: =SUM(CM16:CP16) -> 425000 | CR16: =CL16+CQ16 -> 8925000 | CT16: =CL16 -> 8500000 | CU16: =CM16 -> 425000 | CV16: =CN16 -> 0 | CW16: =CO16 -> 0 | CX16: =CP16 -> 0 | CY16: =SUM(CU16:CX16) -> 425000 | CZ16: =CT16+CY16 -> 8925000 | DJ16: Công nhân kho bãi xe
A17: =SUBTOTAL(3,$C$11:C17) -> 3 | C17: Nguyễn Văn C | D17: THILOGI | E17: =IF(CL17>=400000000,"A1",IF(CL17>=300000000,"A2",IF(CL17>=240000000,"A3",IF(CL17>=180000000,"A4",IF(CL17>=120000000,"A5",IF(CL17>=80000000,"A6",IF(CL17>=40000000,"A7",IF(CL17>=25000000,"B1",IF(CL17>=12000000,"B2","B3"))))))))) -> B3 | F17: 42110 | G17: 4300000 | I17: =IF(G17>0,CT17-G17,CT17-H17) -> 3700000 | J17: =CY17 -> 800000 | K17: =SUM(I17:J17) -> 4500000 | L17: =IF(G17>0,G17+K17,H17+K17) -> 8800000 | M17: 1 | N17: =ROUND(MAX(G17*70%,H17*70%,3640000),0) -> 3640000 | O17: 0 | P17: 25 | Q17: 0 | R17: 0 | S17: 0 | X17: 0 | AA17: 0 | AB17: 0 | AC17: 0 | AD17: 0 | AE17: 0 | AG17: =MAX(ROUND(IF(P17=0,0,IF(AND(BQ17="Lương tháng",(AB17+AC17)=0),MAX(G17/26*P17*M17,H17/26*P17*M17),IF(BQ17="Lương tháng",MAX((G17-G17/26*($CJ$6-P17))*M17,(H17-H17/26*($CJ$6-P17))*M17),MAX(G17/26*P17*M17,H17/26*P17*M17)))),0),0) -> 4134615 | AH17: =ROUND(MAX((G17+I17)*M17/26*R17,(H17+I17)*M17/26*R17,G17/26*R17*150%,H17/26*R17*150%)*BR17,0) -> 0 | AI17: =ROUND(MAX((G17+I17)*M17/26*S17,(H17+I17)*M17/26*S17,G17/26*S17*200%,H17/26*S17*200%)*BR17,0) -> 0 | AJ17: =ROUND(IF(BQ17="Lương tháng",L17/26*T17,MAX((G17+I17)/26*(T17+U17)*200%+G17/26*T17,(H17+I17)/26*(T17+U17)*200%+H17/26*T17,G17/26*(T17+U17)*300%+G17/26*T17,H17/26*(T17+U17)*300%+H17/26*T17)),0) -> 0 | AK17: =ROUND(IF((P17+Q17)=0,0,IF(BQ17="Lương tháng",MAX((G17+I17)/26*V17,(H17+I17)/26*V17),MAX(G17/26*V17,H17/26*V17))),0) -> 0 | AL17: =ROUND(IF(G17>0,G17/26*W17,H17/26*W17),0) -> 0 | AM17: =ROUND((G17+50%*I17)/26*X17,0) -> 0 | AN17: =ROUND(N17/26*Y17+O17/26*Z17+MAX(G17/26*AA17,H17/26*AA17),0) -> 0 | AO17: =ROUND(IF(BQ17="Lương tháng",L17/26*AC17,L17/26*AC17+L17/26*AB17),0) -> 0 | AP17: =ROUND(IF(BQ17="lương tháng",0,MAX((G17+I17)/26*AD17*30%,(H17+I17)/26*AD17*30%)*BR17),0) -> 0 | AQ17: =ROUND(BT17*AE17,0) -> 0 | AR17: =ROUND((G17+I17)/26*AF17,0) -> 0 | AS17: =MAX(ROUND(IF(P17=0,0,IF(AND(BQ17="Lương tháng",(AB17+AC17)=0),K17/26*P17*M17,IF(BQ17="Lương tháng",(K17-K17/26*($CJ$6-P17))*M17,(K17/26*P17*M17)))),0),0)+ROUND(J17/26*Q17,0) -> 4326923 | AU17: =ROUND(SUM(AG17:AT17),0) -> 8461538 | AV17: 0 | AY17: 3000000 | AZ17: =ROUND(SUM(AU17:AX17)-AY17,0) -> 5461538 | BD17: =SUM(BA17:BC17) -> 0 | BE17: 0 | BG17: =IF(BU17="Xem lại",0,IF(CL17<11000000,5000,IF(AND(CL17>=11000000,CL17<25000000),10000,IF(AND(CL17>=25000000,CL17<40000000),15000,IF(AND(CL17>=40000000,CL17<120000000),20000,IF(AND(CL17>=120000000,CL17<240000000),25000,30000)))))*$BG$9) -> 115000 | BI17: =IF(CE17>0,ROUND(IF(CE17>=80000000,CE17*35%-9850000,IF(CE17>=52000000,CE17*30%-5850000,IF(CE17>=32000000,CE17*25%-3250000,IF(CE17>=18000000,CE17*20%-1650000,IF(CE17>=10000000,CE17*15%-750000,IF(CE17>5000000,CE17*10%-250000,CE17*5%)))))),0),0) -> 0 | BL17: =ROUND(SUM(BD17:BK17),0) -> 115000 | BM17: =ROUND(IF(AZ17>BL17,AZ17-BL17,0),0) -> 5346538 | BN17: =ROUND(IF(BL17>AZ17,BL17-AZ17,0),0) -> 0 | BO17: 1 | BP17: 1x | BQ17: =IF(AND(D17="QTNV CL",CT17>=11000000),"Lương tháng",IF(CT17>=18000000,"Lương tháng",0)) -> 0 | BR17: =IF(BQ17="Lương tháng",0,1) -> 1 | BS17: 0 | BT17: =IF(BS17="M1",13000,IF(BS17="M2",20000,IF(BS17="M3",26000,IF(BS17="M4",32000,0)))) -> 0 | BU17: =IF(AND(G17>0,(P17+Q17)>5),"Trừ tiền","Xem lại") -> Trừ tiền | BV17: 0 | BZ17: =AU17+SUM(BV17:BY17)-AL17-AP17-AQ17-SUM(CF17:CH17) -> 8461538 | CA17: 1 | CB17: =CA17*4400000 -> 4400000 | CC17: 11000000 | CD17: =CB17+CC17 -> 15400000 | CE17: =BZ17-SUM(CJ17:CK17)-CI17-BD17-CD17 -> -7389962 | CK17: 451500 | CL17: 8000000 | CM17: =CL17*10% -> 800000 | CN17: 0 | CO17: 0 | CQ17: =SUM(CM17:CP17) -> 800000 | CR17: =CL17+CQ17 -> 8800000 | CT17: =CL17 -> 8000000 | CU17: =CM17 -> 800000 | CV17: =CN17 -> 0 | CW17: =CO17 -> 0 | CX17: =CP17 -> 0 | CY17: =SUM(CU17:CX17) -> 800000 | CZ17: =CT17+CY17 -> 8800000 | DJ17: Công nhân lái xe chuyên dụng (lương khoán, ko tính lương chủ nhật, tăng ca, đi làm thứ 7, chỉ được bù)
A18: =SUBTOTAL(3,$C$11:C18) -> 4 | C18: Nguyễn Văn D | D18: THILOGI | E18: =IF(CL18>=400000000,"A1",IF(CL18>=300000000,"A2",IF(CL18>=240000000,"A3",IF(CL18>=180000000,"A4",IF(CL18>=120000000,"A5",IF(CL18>=80000000,"A6",IF(CL18>=40000000,"A7",IF(CL18>=25000000,"B1",IF(CL18>=12000000,"B2","B3"))))))))) -> B3 | F18: 42110 | G18: 4520000 | I18: =IF(G18>0,CT18-G18,CT18-H18) -> 3980000 | J18: =CY18 -> 1700000 | K18: =SUM(I18:J18) -> 5680000 | L18: =IF(G18>0,G18+K18,H18+K18) -> 10200000 | M18: 1 | N18: =ROUND(MAX(G18*70%,H18*70%,3640000),0) -> 3640000 | O18: 0 | P18: 1 | Q18: 25 | R18: 0 | S18: 0 | X18: 0 | AA18: 0 | AB18: 0 | AC18: 1 | AD18: 0 | AE18: 0 | AG18: =MAX(ROUND(IF(P18=0,0,IF(AND(BQ18="Lương tháng",(AB18+AC18)=0),MAX(G18/26*P18*M18,H18/26*P18*M18),IF(BQ18="Lương tháng",MAX((G18-G18/26*($CJ$6-P18))*M18,(H18-H18/26*($CJ$6-P18))*M18),MAX(G18/26*P18*M18,H18/26*P18*M18)))),0),0) -> 173846 | AH18: =ROUND(MAX((G18+I18)*M18/26*R18,(H18+I18)*M18/26*R18,G18/26*R18*150%,H18/26*R18*150%)*BR18,0) -> 0 | AI18: =ROUND(MAX((G18+I18)*M18/26*S18,(H18+I18)*M18/26*S18,G18/26*S18*200%,H18/26*S18*200%)*BR18,0) -> 0 | AJ18: =ROUND(IF(BQ18="Lương tháng",L18/26*T18,MAX((G18+I18)/26*(T18+U18)*200%+G18/26*T18,(H18+I18)/26*(T18+U18)*200%+H18/26*T18,G18/26*(T18+U18)*300%+G18/26*T18,H18/26*(T18+U18)*300%+H18/26*T18)),0) -> 0 | AK18: =ROUND(IF((P18+Q18)=0,0,IF(BQ18="Lương tháng",MAX((G18+I18)/26*V18,(H18+I18)/26*V18),MAX(G18/26*V18,H18/26*V18))),0) -> 0 | AL18: =ROUND(IF(G18>0,G18/26*W18,H18/26*W18),0) -> 0 | AM18: =ROUND((G18+50%*I18)/26*X18,0) -> 0 | AN18: =ROUND(N18/26*Y18+O18/26*Z18+MAX(G18/26*AA18,H18/26*AA18),0) -> 0 | AO18: =ROUND(IF(BQ18="Lương tháng",L18/26*AC18,L18/26*AC18+L18/26*AB18),0) -> 392308 | AP18: =ROUND(IF(BQ18="lương tháng",0,MAX((G18+I18)/26*AD18*30%,(H18+I18)/26*AD18*30%)*BR18),0) -> 0 | AQ18: =ROUND(BT18*AE18,0) -> 0 | AR18: =ROUND((G18+I18)/26*AF18,0) -> 0 | AS18: =MAX(ROUND(IF(P18=0,0,IF(AND(BQ18="Lương tháng",(AB18+AC18)=0),K18/26*P18*M18,IF(BQ18="Lương tháng",(K18-K18/26*($CJ$6-P18))*M18,(K18/26*P18*M18)))),0),0)+ROUND(J18/26*Q18,0) -> 1853077 | AU18: =ROUND(SUM(AG18:AT18),0) -> 2419231 | AV18: 1206000 | AY18: 1000000 | AZ18: =ROUND(SUM(AU18:AX18)-AY18,0) -> 2625231 | BD18: =SUM(BA18:BC18) -> 0 | BE18: 0 | BG18: =IF(BU18="Xem lại",0,IF(CL18<11000000,5000,IF(AND(CL18>=11000000,CL18<25000000),10000,IF(AND(CL18>=25000000,CL18<40000000),15000,IF(AND(CL18>=40000000,CL18<120000000),20000,IF(AND(CL18>=120000000,CL18<240000000),25000,30000)))))*$BG$9) -> 115000 | BI18: =IF(CE18>0,ROUND(IF(CE18>=80000000,CE18*35%-9850000,IF(CE18>=52000000,CE18*30%-5850000,IF(CE18>=32000000,CE18*25%-3250000,IF(CE18>=18000000,CE18*20%-1650000,IF(CE18>=10000000,CE18*15%-750000,IF(CE18>5000000,CE18*10%-250000,CE18*5%)))))),0),0) -> 0 | BL18: =ROUND(SUM(BD18:BK18),0) -> 115000 | BM18: =ROUND(IF(AZ18>BL18,AZ18-BL18,0),0) -> 2510231 | BN18: =ROUND(IF(BL18>AZ18,BL18-AZ18,0),0) -> 0 | BO18: 1 | BP18: 1x | BQ18: =IF(AND(D18="QTNV CL",CT18>=11000000),"Lương tháng",IF(CT18>=18000000,"Lương tháng",0)) -> 0 | BR18: =IF(BQ18="Lương tháng",0,1) -> 1 | BS18: 0 | BT18: =IF(BS18="M1",13000,IF(BS18="M2",20000,IF(BS18="M3",26000,IF(BS18="M4",32000,0)))) -> 0 | BU18: =IF(AND(G18>0,(P18+Q18)>5),"Trừ tiền","Xem lại") -> Trừ tiền | BV18: 0 | BZ18: =AU18+SUM(BV18:BY18)-AL18-AP18-AQ18-SUM(CF18:CH18) -> 2419231 | CA18: 2 | CB18: =CA18*4400000 -> 8800000 | CC18: 11000000 | CD18: =CB18+CC18 -> 19800000 | CE18: =BZ18-SUM(CJ18:CK18)-CI18-BD18-CD18 -> -17855369 | CK18: 474600 | CL18: 8500000 | CM18: =CL18*10% -> 850000 | CN18: =CL18*10% -> 850000 | CO18: 0 | CQ18: =SUM(CM18:CP18) -> 1700000 | CR18: =CL18+CQ18 -> 10200000 | CT18: =CL18 -> 8500000 | CU18: =CM18 -> 850000 | CV18: 850000 | CW18: =CO18 -> 0 | CX18: =CP18 -> 0 | CY18: =SUM(CU18:CX18) -> 1700000 | CZ18: =CT18+CY18 -> 10200000 | DJ18: Công nhân lái xe chuyên dụng (lương khoán, ko tính lương chủ nhật, tăng ca, đi làm thứ 7, chỉ được bù, ngày nào giao xe thì để công giao xe, còn làm tại cty thì chấm X bên công chính
A19: =SUBTOTAL(3,$C$11:C19) -> 5 | C19: Nguyễn Văn E | D19: THILOGI | E19: =IF(CL19>=400000000,"A1",IF(CL19>=300000000,"A2",IF(CL19>=240000000,"A3",IF(CL19>=180000000,"A4",IF(CL19>=120000000,"A5",IF(CL19>=80000000,"A6",IF(CL19>=40000000,"A7",IF(CL19>=25000000,"B1",IF(CL19>=12000000,"B2","B3"))))))))) -> B3 | F19: 42110 | G19: 4750000 | I19: =IF(G19>0,CT19-G19,CT19-H19) -> 5250000 | J19: =CY19 -> 1000000 | K19: =SUM(I19:J19) -> 6250000 | L19: =IF(G19>0,G19+K19,H19+K19) -> 11000000 | M19: 1 | N19: =ROUND(MAX(G19*70%,H19*70%,3640000),0) -> 3640000 | O19: 0 | P19: 25 | Q19: 0 | R19: 0 | S19: 0 | X19: 0 | AA19: 0 | AB19: 0 | AC19: 0 | AD19: 0 | AE19: 0 | AG19: =MAX(ROUND(IF(P19=0,0,IF(AND(BQ19="Lương tháng",(AB19+AC19)=0),MAX(G19/26*P19*M19,H19/26*P19*M19),IF(BQ19="Lương tháng",MAX((G19-G19/26*($CJ$6-P19))*M19,(H19-H19/26*($CJ$6-P19))*M19),MAX(G19/26*P19*M19,H19/26*P19*M19)))),0),0) -> 4567308 | AH19: =ROUND(MAX((G19+I19)*M19/26*R19,(H19+I19)*M19/26*R19,G19/26*R19*150%,H19/26*R19*150%)*BR19,0) -> 0 | AI19: =ROUND(MAX((G19+I19)*M19/26*S19,(H19+I19)*M19/26*S19,G19/26*S19*200%,H19/26*S19*200%)*BR19,0) -> 0 | AJ19: =ROUND(IF(BQ19="Lương tháng",L19/26*T19,MAX((G19+I19)/26*(T19+U19)*200%+G19/26*T19,(H19+I19)/26*(T19+U19)*200%+H19/26*T19,G19/26*(T19+U19)*300%+G19/26*T19,H19/26*(T19+U19)*300%+H19/26*T19)),0) -> 0 | AK19: =ROUND(IF((P19+Q19)=0,0,IF(BQ19="Lương tháng",MAX((G19+I19)/26*V19,(H19+I19)/26*V19),MAX(G19/26*V19,H19/26*V19))),0) -> 0 | AL19: =ROUND(IF(G19>0,G19/26*W19,H19/26*W19),0) -> 0 | AM19: =ROUND((G19+50%*I19)/26*X19,0) -> 0 | AN19: =ROUND(N19/26*Y19+O19/26*Z19+MAX(G19/26*AA19,H19/26*AA19),0) -> 0 | AO19: =ROUND(IF(BQ19="Lương tháng",L19/26*AC19,L19/26*AC19+L19/26*AB19),0) -> 0 | AP19: =ROUND(IF(BQ19="lương tháng",0,MAX((G19+I19)/26*AD19*30%,(H19+I19)/26*AD19*30%)*BR19),0) -> 0 | AQ19: =ROUND(BT19*AE19,0) -> 0 | AR19: =ROUND((G19+I19)/26*AF19,0) -> 0 | AS19: =MAX(ROUND(IF(P19=0,0,IF(AND(BQ19="Lương tháng",(AB19+AC19)=0),K19/26*P19*M19,IF(BQ19="Lương tháng",(K19-K19/26*($CJ$6-P19))*M19,(K19/26*P19*M19)))),0),0)+ROUND(J19/26*Q19,0) -> 6009615 | AU19: =ROUND(SUM(AG19:AT19),0) -> 10576923 | AV19: 0 | AY19: 3000000 | AZ19: =ROUND(SUM(AU19:AX19)-AY19,0) -> 7576923 | BD19: =SUM(BA19:BC19) -> 0 | BE19: 0 | BG19: =IF(BU19="Xem lại",0,IF(CL19<11000000,5000,IF(AND(CL19>=11000000,CL19<25000000),10000,IF(AND(CL19>=25000000,CL19<40000000),15000,IF(AND(CL19>=40000000,CL19<120000000),20000,IF(AND(CL19>=120000000,CL19<240000000),25000,30000)))))*$BG$9) -> 115000 | BI19: =IF(CE19>0,ROUND(IF(CE19>=80000000,CE19*35%-9850000,IF(CE19>=52000000,CE19*30%-5850000,IF(CE19>=32000000,CE19*25%-3250000,IF(CE19>=18000000,CE19*20%-1650000,IF(CE19>=10000000,CE19*15%-750000,IF(CE19>5000000,CE19*10%-250000,CE19*5%)))))),0),0) -> 0 | BL19: =ROUND(SUM(BD19:BK19),0) -> 115000 | BM19: =ROUND(IF(AZ19>BL19,AZ19-BL19,0),0) -> 7461923 | BN19: =ROUND(IF(BL19>AZ19,BL19-AZ19,0),0) -> 0 | BO19: 1 | BP19: 1x | BQ19: =IF(AND(D19="QTNV CL",CT19>=11000000),"Lương tháng",IF(CT19>=18000000,"Lương tháng",0)) -> 0 | BR19: =IF(BQ19="Lương tháng",0,1) -> 1 | BS19: 0 | BT19: =IF(BS19="M1",13000,IF(BS19="M2",20000,IF(BS19="M3",26000,IF(BS19="M4",32000,0)))) -> 0 | BU19: =IF(AND(G19>0,(P19+Q19)>5),"Trừ tiền","Xem lại") -> Trừ tiền | BV19: 0 | BZ19: =AU19+SUM(BV19:BY19)-AL19-AP19-AQ19-SUM(CF19:CH19) -> 10576923 | CA19: 2 | CB19: =CA19*4400000 -> 8800000 | CC19: 11000000 | CD19: =CB19+CC19 -> 19800000 | CE19: =BZ19-SUM(CJ19:CK19)-CI19-BD19-CD19 -> -9721827 | CK19: 498750 | CL19: 10000000 | CM19: =CL19*10% -> 1000000 | CN19: 0 | CO19: 0 | CQ19: =SUM(CM19:CP19) -> 1000000 | CR19: =CL19+CQ19 -> 11000000 | CT19: =CL19 -> 10000000 | CU19: =CM19 -> 1000000 | CV19: =CN19 -> 0 | CW19: =CO19 -> 0 | CX19: =CP19 -> 0 | CY19: =SUM(CU19:CX19) -> 1000000 | CZ19: =CT19+CY19 -> 11000000 | DJ19: Công nhân lái xe chuyên dụng (lương khoán, ko tính lương chủ nhật, tăng ca, đi làm thứ 7, chỉ được bù)
A20: =SUBTOTAL(3,$C$11:C20) -> 6 | C20: Nguyễn Văn F | D20: THILOGI | E20: =IF(CL20>=400000000,"A1",IF(CL20>=300000000,"A2",IF(CL20>=240000000,"A3",IF(CL20>=180000000,"A4",IF(CL20>=120000000,"A5",IF(CL20>=80000000,"A6",IF(CL20>=40000000,"A7",IF(CL20>=25000000,"B1",IF(CL20>=12000000,"B2","B3"))))))))) -> B2 | F20: 45721 | G20: 4750000 | I20: =IF(G20>0,CT20-G20,CT20-H20) -> 13250000 | J20: =CY20 -> 0 | K20: =SUM(I20:J20) -> 13250000 | L20: =IF(G20>0,G20+K20,H20+K20) -> 18000000 | M20: 1 | N20: =ROUND(MAX(G20*70%,H20*70%,3640000),0) -> 3640000 | O20: 0 | P20: 25 | R20: 4.16 | AG20: =MAX(ROUND(IF(P20=0,0,IF(AND(BQ20="Lương tháng",(AB20+AC20)=0),MAX(G20/26*P20*M20,H20/26*P20*M20),IF(BQ20="Lương tháng",MAX((G20-G20/26*($CJ$6-P20))*M20,(H20-H20/26*($CJ$6-P20))*M20),MAX(G20/26*P20*M20,H20/26*P20*M20)))),0),0) -> 4567308 | AH20: =ROUND(MAX((G20+I20)*M20/26*R20,(H20+I20)*M20/26*R20,G20/26*R20*150%,H20/26*R20*150%)*BR20,0) -> 2880000 | AI20: =ROUND(MAX((G20+I20)*M20/26*S20,(H20+I20)*M20/26*S20,G20/26*S20*200%,H20/26*S20*200%)*BR20,0) -> 0 | AJ20: =ROUND(IF(BQ20="Lương tháng",L20/26*T20,MAX((G20+I20)/26*(T20+U20)*200%+G20/26*T20,(H20+I20)/26*(T20+U20)*200%+H20/26*T20,G20/26*(T20+U20)*300%+G20/26*T20,H20/26*(T20+U20)*300%+H20/26*T20)),0) -> 0 | AK20: =ROUND(IF((P20+Q20)=0,0,IF(BQ20="Lương tháng",MAX((G20+I20)/26*V20,(H20+I20)/26*V20),MAX(G20/26*V20,H20/26*V20))),0) -> 0 | AL20: =ROUND(IF(G20>0,G20/26*W20,H20/26*W20),0) -> 0 | AM20: =ROUND((G20+50%*I20)/26*X20,0) -> 0 | AN20: =ROUND(N20/26*Y20+O20/26*Z20+MAX(G20/26*AA20,H20/26*AA20),0) -> 0 | AO20: =ROUND(IF(BQ20="Lương tháng",L20/26*AC20,L20/26*AC20+L20/26*AB20),0) -> 0 | AP20: =ROUND(IF(BQ20="lương tháng",0,MAX((G20+I20)/26*AD20*30%,(H20+I20)/26*AD20*30%)*BR20),0) -> 0 | AQ20: =ROUND(BT20*AE20,0) -> 0 | AR20: =ROUND((G20+I20)/26*AF20,0) -> 0 | AS20: =MAX(ROUND(IF(P20=0,0,IF(AND(BQ20="Lương tháng",(AB20+AC20)=0),K20/26*P20*M20,IF(BQ20="Lương tháng",(K20-K20/26*($CJ$6-P20))*M20,(K20/26*P20*M20)))),0),0)+ROUND(J20/26*Q20,0) -> 12740385 | AU20: =ROUND(SUM(AG20:AT20),0) -> 20187693 | AY20: 9819677 | AZ20: =ROUND(SUM(AU20:AX20)-AY20,0) -> 10368016 | BD20: =SUM(BA20:BC20) -> 0 | BE20: 0 | BG20: =IF(BU20="Xem lại",0,IF(CL20<11000000,5000,IF(AND(CL20>=11000000,CL20<25000000),10000,IF(AND(CL20>=25000000,CL20<40000000),15000,IF(AND(CL20>=40000000,CL20<120000000),20000,IF(AND(CL20>=120000000,CL20<240000000),25000,30000)))))*$BG$9) -> 230000 | BI20: =IF(CE20>0,ROUND(IF(CE20>=80000000,CE20*35%-9850000,IF(CE20>=52000000,CE20*30%-5850000,IF(CE20>=32000000,CE20*25%-3250000,IF(CE20>=18000000,CE20*20%-1650000,IF(CE20>=10000000,CE20*15%-750000,IF(CE20>5000000,CE20*10%-250000,CE20*5%)))))),0),0) -> 0 | BL20: =ROUND(SUM(BD20:BK20),0) -> 230000 | BM20: =ROUND(IF(AZ20>BL20,AZ20-BL20,0),0) -> 10138016 | BN20: =ROUND(IF(BL20>AZ20,BL20-AZ20,0),0) -> 0 | BO20: 1 | BQ20: =IF(AND(D20="QTNV CL",CT20>=11000000),"Lương tháng",IF(CT20>=18000000,"Lương tháng",0)) -> Lương tháng | BR20: 1 | BS20: 0 | BT20: =IF(BS20="M1",13000,IF(BS20="M2",20000,IF(BS20="M3",26000,IF(BS20="M4",32000,0)))) -> 0 | BU20: =IF(AND(G20>0,(P20+Q20)>5),"Trừ tiền","Xem lại") -> Trừ tiền | BZ20: =AU20+SUM(BV20:BY20)-AL20-AP20-AQ20-SUM(CF20:CH20) -> 20187693 | CA20: 2 | CB20: =CA20*4400000 -> 8800000 | CC20: 11000000 | CD20: =CB20+CC20 -> 19800000 | CE20: =BZ20-SUM(CJ20:CK20)-CI20-BD20-CD20 -> -111057 | CK20: 498750 | CL20: 18000000 | CN20: 0 | CO20: 0 | CQ20: =SUM(CM20:CP20) -> 0 | CR20: =CL20+CQ20 -> 18000000 | CT20: =CL20 -> 18000000 | CU20: =CM20 -> 0 | CV20: =CN20 -> 0 | CW20: =CO20 -> 0 | CX20: =CP20 -> 0 | CY20: =SUM(CU20:CX20) -> 0 | CZ20: =CT20+CY20 -> 18000000 | DJ20: Công nhân vận hành thiết bị năng (lương tháng nhưng được tính lương làm thêm giờ)
A21: =SUBTOTAL(3,$C$11:C21) -> 7 | C21: Nguyễn Văn K | D21: THILOGI | E21: =IF(CL21>=400000000,"A1",IF(CL21>=300000000,"A2",IF(CL21>=240000000,"A3",IF(CL21>=180000000,"A4",IF(CL21>=120000000,"A5",IF(CL21>=80000000,"A6",IF(CL21>=40000000,"A7",IF(CL21>=25000000,"B1",IF(CL21>=12000000,"B2","B3"))))))))) -> B2 | F21: 45721 | G21: 4750000 | I21: =IF(G21>0,CT21-G21,CT21-H21) -> 9250000 | J21: =CY21 -> 0 | K21: =SUM(I21:J21) -> 9250000 | L21: =IF(G21>0,G21+K21,H21+K21) -> 14000000 | M21: 1 | N21: =ROUND(MAX(G21*70%,H21*70%,3640000),0) -> 3640000 | O21: 0 | P21: 25 | S21: 0 | AD21: 0 | AE21: 0 | AG21: =MAX(ROUND(IF(P21=0,0,IF(AND(BQ21="Lương tháng",(AB21+AC21)=0),MAX(G21/26*P21*M21,H21/26*P21*M21),IF(BQ21="Lương tháng",MAX((G21-G21/26*($CJ$6-P21))*M21,(H21-H21/26*($CJ$6-P21))*M21),MAX(G21/26*P21*M21,H21/26*P21*M21)))),0),0) -> 4567308 | AH21: =ROUND(MAX((G21+I21)*M21/26*R21,(H21+I21)*M21/26*R21,G21/26*R21*150%,H21/26*R21*150%)*BR21,0) -> 0 | AI21: =ROUND(MAX((G21+I21)*M21/26*S21,(H21+I21)*M21/26*S21,G21/26*S21*200%,H21/26*S21*200%)*BR21,0) -> 0 | AJ21: =ROUND(IF(BQ21="Lương tháng",L21/26*T21,MAX((G21+I21)/26*(T21+U21)*200%+G21/26*T21,(H21+I21)/26*(T21+U21)*200%+H21/26*T21,G21/26*(T21+U21)*300%+G21/26*T21,H21/26*(T21+U21)*300%+H21/26*T21)),0) -> 0 | AK21: =ROUND(IF((P21+Q21)=0,0,IF(BQ21="Lương tháng",MAX((G21+I21)/26*V21,(H21+I21)/26*V21),MAX(G21/26*V21,H21/26*V21))),0) -> 0 | AL21: =ROUND(IF(G21>0,G21/26*W21,H21/26*W21),0) -> 0 | AM21: =ROUND((G21+50%*I21)/26*X21,0) -> 0 | AN21: =ROUND(N21/26*Y21+O21/26*Z21+MAX(G21/26*AA21,H21/26*AA21),0) -> 0 | AO21: =ROUND(IF(BQ21="Lương tháng",L21/26*AC21,L21/26*AC21+L21/26*AB21),0) -> 0 | AP21: =ROUND(IF(BQ21="lương tháng",0,MAX((G21+I21)/26*AD21*30%,(H21+I21)/26*AD21*30%)*BR21),0) -> 0 | AQ21: =ROUND(BT21*AE21,0) -> 0 | AR21: =ROUND((G21+I21)/26*AF21,0) -> 0 | AS21: =MAX(ROUND(IF(P21=0,0,IF(AND(BQ21="Lương tháng",(AB21+AC21)=0),K21/26*P21*M21,IF(BQ21="Lương tháng",(K21-K21/26*($CJ$6-P21))*M21,(K21/26*P21*M21)))),0),0)+ROUND(J21/26*Q21,0) -> 8894231 | AU21: =ROUND(SUM(AG21:AT21),0) -> 13461539 | AY21: 5720000 | AZ21: =ROUND(SUM(AU21:AX21)-AY21,0) -> 7741539 | BD21: =SUM(BA21:BC21) -> 0 | BE21: 0 | BG21: =IF(BU21="Xem lại",0,IF(CL21<11000000,5000,IF(AND(CL21>=11000000,CL21<25000000),10000,IF(AND(CL21>=25000000,CL21<40000000),15000,IF(AND(CL21>=40000000,CL21<120000000),20000,IF(AND(CL21>=120000000,CL21<240000000),25000,30000)))))*$BG$9) -> 230000 | BI21: =IF(CE21>0,ROUND(IF(CE21>=80000000,CE21*35%-9850000,IF(CE21>=52000000,CE21*30%-5850000,IF(CE21>=32000000,CE21*25%-3250000,IF(CE21>=18000000,CE21*20%-1650000,IF(CE21>=10000000,CE21*15%-750000,IF(CE21>5000000,CE21*10%-250000,CE21*5%)))))),0),0) -> 98139 | BL21: =ROUND(SUM(BD21:BK21),0) -> 328139 | BM21: =ROUND(IF(AZ21>BL21,AZ21-BL21,0),0) -> 7413400 | BN21: =ROUND(IF(BL21>AZ21,BL21-AZ21,0),0) -> 0 | BO21: 1 | BQ21: =IF(AND(D21="QTNV CL",CT21>=11000000),"Lương tháng",IF(CT21>=18000000,"Lương tháng",0)) -> 0 | BR21: =IF(BQ21="Lương tháng",0,1) -> 1 | BS21: 0 | BT21: =IF(BS21="M1",13000,IF(BS21="M2",20000,IF(BS21="M3",26000,IF(BS21="M4",32000,0)))) -> 0 | BU21: =IF(AND(G21>0,(P21+Q21)>5),"Trừ tiền","Xem lại") -> Trừ tiền | BZ21: =AU21+SUM(BV21:BY21)-AL21-AP21-AQ21-SUM(CF21:CH21) -> 13461539 | CB21: =CA21*4400000 -> 0 | CC21: 11000000 | CD21: =CB21+CC21 -> 11000000 | CE21: =BZ21-SUM(CJ21:CK21)-CI21-BD21-CD21 -> 1962789 | CK21: 498750 | CL21: 14000000 | CN21: 0 | CO21: 0 | CQ21: =SUM(CM21:CP21) -> 0 | CR21: =CL21+CQ21 -> 14000000 | CT21: =CL21 -> 14000000 | CU21: =CM21 -> 0 | CV21: =CN21 -> 0 | CW21: =CO21 -> 0 | CX21: =CP21 -> 0 | CY21: =SUM(CU21:CX21) -> 0 | CZ21: =CT21+CY21 -> 14000000 | DJ21: Thuyèn viên tàu lai (tính khoán theo công chuẩn hằng tháng)
A22: III | B22: ="Suất ăn công nghiệp: " &"["&COUNT(A23:A23)& "]" -> Suất ăn công nghiệp: [1] | G22: =SUM(G23:G23) -> 4090000 | H22: =SUM(H23:H23) -> 0 | I22: =SUM(I23:I23) -> 2410000 | J22: =SUM(J23:J23) -> 0 | K22: =SUM(K23:K23) -> 2410000 | L22: =SUM(L23:L23) -> 6500000 | N22: =SUM(N23:N23) -> 3640000 | O22: =SUM(O23:O23) -> 0 | P22: =SUM(P23:P23) -> 25 | Q22: =SUM(Q23:Q23) -> 0 | R22: =SUM(R23:R23) -> 0 | S22: =SUM(S23:S23) -> 0 | T22: =SUM(T23:T23) -> 0 | U22: =SUM(U23:U23) -> 0 | ... DC22: =SUM(DC23:DC23) -> 0
A23: =SUBTOTAL(3,$C$11:C23) -> 7 | D23: THILOGI | E23: =IF(CL23>=400000000,"A1",IF(CL23>=300000000,"A2",IF(CL23>=240000000,"A3",IF(CL23>=180000000,"A4",IF(CL23>=120000000,"A5",IF(CL23>=80000000,"A6",IF(CL23>=40000000,"A7",IF(CL23>=25000000,"B1",IF(CL23>=12000000,"B2","B3"))))))))) -> B3 | F23: 44256 | G23: 4090000 | I23: =IF(G23>0,CT23-G23,CT23-H23) -> 2410000 | J23: =CY23 -> 0 | K23: =SUM(I23:J23) -> 2410000 | L23: =IF(G23>0,G23+K23,H23+K23) -> 6500000 | M23: 1 | N23: =ROUND(MAX(G23*70%,H23*70%,3640000),0) -> 3640000 | O23: 0 | P23: 25 | AG23: =MAX(ROUND(IF(P23=0,0,IF(AND(BQ23="Lương tháng",(AB23+AC23)=0),MAX(G23/26*P23*M23,H23/26*P23*M23),IF(BQ23="Lương tháng",MAX((G23-G23/26*($CJ$6-P23))*M23,(H23-H23/26*($CJ$6-P23))*M23),MAX(G23/26*P23*M23,H23/26*P23*M23)))),0),0) -> 3932692 | AH23: =ROUND(MAX((G23+I23)*M23/26*R23,(H23+I23)*M23/26*R23,G23/26*R23*150%,H23/26*R23*150%)*BR23,0) -> 0 | AI23: =ROUND(MAX((G23+I23)*M23/26*S23,(H23+I23)*M23/26*S23,G23/26*S23*200%,H23/26*S23*200%)*BR23,0) -> 0 | AJ23: =ROUND(IF(BQ23="Lương tháng",L23/26*T23,MAX((G23+I23)/26*(T23+U23)*200%+G23/26*T23,(H23+I23)/26*(T23+U23)*200%+H23/26*T23,G23/26*(T23+U23)*300%+G23/26*T23,H23/26*(T23+U23)*300%+H23/26*T23)),0) -> 0 | AK23: =ROUND(IF((P23+Q23)=0,0,IF(BQ23="Lương tháng",MAX((G23+I23)/26*V23,(H23+I23)/26*V23),MAX(G23/26*V23,H23/26*V23))),0) -> 0 | AL23: =ROUND(IF(G23>0,G23/26*W23,H23/26*W23),0) -> 0 | AM23: =ROUND((G23+50%*I23)/26*X23,0) -> 0 | AN23: =ROUND(N23/26*Y23+O23/26*Z23+MAX(G23/26*AA23,H23/26*AA23),0) -> 0 | AO23: =ROUND(IF(BQ23="Lương tháng",L23/26*AC23,L23/26*AC23+L23/26*AB23),0) -> 0 | AP23: =ROUND(IF(BQ23="lương tháng",0,MAX((G23+I23)/26*AD23*30%,(H23+I23)/26*AD23*30%)*BR23),0) -> 0 | AQ23: =ROUND(BT23*AE23,0) -> 0 | AR23: =ROUND((G23+I23)/26*AF23,0) -> 0 | AS23: =MAX(ROUND(IF(P23=0,0,IF(AND(BQ23="Lương tháng",(AB23+AC23)=0),K23/26*P23*M23,IF(BQ23="Lương tháng",(K23-K23/26*($CJ$6-P23))*M23,(K23/26*P23*M23)))),0),0)+ROUND(J23/26*Q23,0) -> 2317308 | AU23: =ROUND(SUM(AG23:AT23),0) -> 6250000 | AY23: 2000000 | AZ23: =ROUND(SUM(AU23:AX23)-AY23,0) -> 4250000 | BD23: =SUM(BA23:BC23) -> 0 | BE23: 0 | BG23: =IF(BU23="Xem lại",0,IF(CL23<11000000,5000,IF(AND(CL23>=11000000,CL23<25000000),10000,IF(AND(CL23>=25000000,CL23<40000000),15000,IF(AND(CL23>=40000000,CL23<120000000),20000,IF(AND(CL23>=120000000,CL23<240000000),25000,30000)))))*$BG$9) -> 0 | BI23: =IF(CE23>0,ROUND(IF(CE23>=80000000,CE23*35%-9850000,IF(CE23>=52000000,CE23*30%-5850000,IF(CE23>=32000000,CE23*25%-3250000,IF(CE23>=18000000,CE23*20%-1650000,IF(CE23>=10000000,CE23*15%-750000,IF(CE23>5000000,CE23*10%-250000,CE23*5%)))))),0),0) -> 0 | BL23: =ROUND(SUM(BD23:BK23),0) -> 0 | BM23: =ROUND(IF(AZ23>BL23,AZ23-BL23,0),0) -> 4250000 | BN23: =ROUND(IF(BL23>AZ23,BL23-AZ23,0),0) -> 0 | BO23: 1 | BP23: Không | BQ23: =IF(AND(D23="QTNV CL",CT23>=11000000),"Lương tháng",IF(CT23>=18000000,"Lương tháng",0)) -> 0 | BR23: =IF(BQ23="Lương tháng",0,1) -> 1 | BS23: 0 | BT23: =IF(BS23="M1",13000,IF(BS23="M2",20000,IF(BS23="M3",26000,IF(BS23="M4",32000,0)))) -> 0 | BU23: Xem lại | BV23: 0 | BZ23: =AU23+SUM(BV23:BY23)-AL23-AP23-AQ23-SUM(CF23:CH23) -> 6250000 | CA23: 0 | CB23: =CA23*4400000 -> 0 | CC23: 11000000 | CD23: =CB23+CC23 -> 11000000 | CE23: =BZ23-SUM(CJ23:CK23)-CI23-BD23-CD23 -> -5179450 | CK23: 429450 | CL23: 6500000 | CM23: 0 | CN23: 0 | CO23: 0 | CQ23: =SUM(CM23:CP23) -> 0 | CR23: =CL23+CQ23 -> 6500000 | CT23: =CL23 -> 6500000 | CU23: =CM23 -> 0 | CV23: =CN23 -> 0 | CW23: =CO23 -> 0 | CX23: =CP23 -> 0 | CY23: =SUM(CU23:CX23) -> 0 | CZ23: =CT23+CY23 -> 6500000 | DA23: Nhân viên SACN | DB23: Dự án Suất ăn công nghiệp | DC23: 0 | DD23: Chu Lai | DH23: TM | DJ23: Suất ăn công nghiệp bên THIDICO (mặc định không thu tang chế)
O24: 0 | P24: =#REF!-#REF! -> #REF! | Q24: =#REF!-#REF! -> #REF! | R24: =#REF!-#REF! -> #REF! | S24: =#REF!-#REF! -> #REF! | T24: =#REF!-#REF! -> #REF! | U24: =#REF!-#REF! -> #REF! | V24: =#REF!-#REF! -> #REF! | W24: =#REF!-#REF! -> #REF! | X24: =#REF!-#REF! -> #REF! | AA24: =#REF!-#REF! -> #REF! | AB24: =#REF!-#REF! -> #REF! | AC24: =#REF!-#REF! -> #REF! | AD24: =#REF!-#REF! -> #REF! | AY24: 2137505812 | AZ24: =#REF!-AY24 -> #REF! | BY24: 3631871000
BI25: Núi Thành, ngày 01 tháng 12 năm 2025
C26: Giám đốc | R26: Phòng Kế toán | AO26: Phòng Nhân sự | BI26: Người lập
AW28: =#REF!-AW24 -> #REF! | AX28: =#REF!-AX24 -> #REF! | AY28: =#REF!-AY24 -> #REF! | AZ28: =#REF!-AZ24 -> #REF! | BA28: =#REF!-BA24 -> #REF! | BB28: =#REF!-BB24 -> #REF! | BC28: =#REF!-BC24 -> #REF! | BD28: =#REF!-BD24 -> #REF! | BE28: =#REF!-BE24 -> #REF! | BG28: =#REF!-BG24 -> #REF! | BH28: =#REF!-BH24 -> #REF! | BI28: =#REF!-BI24 -> #REF! | BJ28: =#REF!-BJ24 -> #REF! | BL28: =#REF!-BL24 -> #REF! | BM28: =#REF!-BM24 -> #REF!

Sheet TAM UNG
A1: CÔNG TY TNHH LIÊN VẬN ĐÔNG DƯƠNG THILOGI
A2: Địa chỉ: Khu công nghiệp Cảng và Hậu cần Cảng Chu Lai Trường Hải, xã Núi Thành, Thành phố Đà Nẵng
A3: BẢNG THANH TOÁN TIỀN LƯƠNG TẠM ỨNG THÁNG 11 NĂM 2025 | CM3: THỐNG KÊ LƯƠNG KỲ 2
BA5: Nam Bộ | BB5: 24 | CC5: Công chuẩn
BA6: Bắc Bộ | BB6: 24 | BO6: THÔNG TIN VỀ TÍNH THUẾ TNCN | CC6: 13
A7: TT | B7: MSNV | C7: Họ và tên | D7: TĐ | E7: Ngạch lương | F7: Ngày vào | G7: Mức lương HĐLĐ | H7: Mức lương HĐTV | I7: Định mức thưởng HQCV | J7: Phụ cấp | K7: Tổng định mức thưởng HQCV | L7: Tổng thu nhập (Mức lương + Định mức thưởng HQCV) | M7: Tỷ lệ % tạm ứng lương | N7: Mức lương tính chế độ ngừng việc | P7: Ngày công trong tháng | AF7: Các khoản được hưởng trong tháng | AR7: Thu nhập giao xe 20% kỳ 1/11 | AS7: Hoàn thuế TNCN | AT7: Chi quà 1/6 | AU7: Truy lĩnh | AV7: Tổng thu nhập tạm ứng kỳ 1/11 | AW7: Các khoản giám trừ kỳ trong tháng | BE7: Tổng giảm trừ | BF7: Thực nhận | BG7: Thu vào kỳ sau | BO7: THUẾ THU NHẬP CÁ NHÂN | BY7: Khoản đc giảm trừ trong thuế | CB7: BHXH | CE7: KỲ I | CM7: KỲ II | CT7: Chức vụ | CU7: Bộ phận | CV7: Mail | CW7: Khu vực
P8: Công chính | Q8: Công giao xe | R8: Công tăng ca ngày thường | S8: Công Chủ nhật | T8: Công nghỉ lễ, tết | W8: Hiếu, hỉ | X8: Ngày PN thanh toán T1/2024 | Y8: Ngày ngừng việc/ cách ly trong tháng | AA8: Ngừng việc BKK | AB8: Công ngày thứ 7 | AD8: Công phụ cấp | AF8: Tạm ứng Lương Ngày thường | AG8: Lương Tăng ca thường | AH8: Lương chủ nhật | AI8: Lương ngày lễ, tết | AK8: Lương Hiếu, Hỉ | AL8: Lương tạm ngừng việc (BKK) | AM8: Lương chế độ T7 | AN8: Thu nhập phụ cấp | AP8: Thu nhập khác (phép năm thôi việc) | AQ8: Tổng tiền lương tạm ứng kỳ 1/11 | AW8: BHXH | AX8: BHYT | AY8: BHTN | AZ8: BHXH,BHYT, BHTN | BA8: Phí công đoàn | BB8: Tiền phúng điếu | BC8: Tạm thu thuế | BD8: Giảm trừ khác (Thu hộ tiền mua xe, thu nợ kỳ trước) | BH8: KIỂM TRA | BO8: Thu nhập ngoài bảng lương đưa vào tính thuế | BS8: THU NHẬP CHỊU THUẾ TNCN | BT8: SỐ NGƯỜI PHỤ THUỘC | BU8: GIẢM TRỪ GIA CẢNH | BV8: GIẢM TRỪ BẢN THÂN | BW8: TỔNG GIẢM TRỪ | BX8: TỔNG THU NHẬP TÍNH THUẾ TNCN
N9: Tạm ngừng việc 14 ngày đầu | O9: Tạm ngừng việc từ 15 ngày trở đi | T9: Chính | U9: Tăng ca | V9: Nghỉ lễ, tết | Y9: 14 ngày đầu | Z9: Từ ngày 15 trở đi | AB9: Đi làm T7 | AC9: Nghỉ T7 | AD9: Phụ cấp ban đêm | AE9: Phụ cấp bồi dưỡng làm việc | AI9: Làm việc ngày lễ, tết | AJ9: Nghỉ lễ, tết | AN9: Phụ cấp ban đêm | AO9: Phụ cấp bồi dưỡng làm việc | AW9: 8% | AX9: 1.5% | AY9: 1% | AZ9: (LHĐLĐ*10.5%) | BA9: (LHĐLĐ*0.5%) | BB9: 22 | BH9: MA BH | BI9: Ma KPCD | BJ9: Kiểm tra đối tượng hưởng lương | BK9: Kiểm tra đối tượng hưởng tăng ca | BL9: BD PHSK | BM9: MỨC TIỀN | BN9: Trừ tiền tang chế | BO9: Nội dung thu nhập 1 | BP9: Nội dung thu nhập 2 | BQ9: Tiền thưởng | BR9: Thu nhập 100% giao xe | BY9: Nội dung giảm trừ 1 | BZ9: Nội dung 1 | CA9: Nội dung 1 | CB9: Truy thu BH | CC9: Truy lĩnh BHXH | CD9: BHXH đã thu đưa vào tính thuế (số bảng đóng BHXH) | CE9: Mức lương | CF9: PC ThN | CG9: PC chức danh | CH9: PC kiêm nhiệm | CI9: PC biệt phái | CJ9: Tổng PC | CK9: Tổng thu nhập | CM9: Mức lương | CN9: PC ThN | CO9: PC chức danh | CP9: PC kiêm nhiệm | CQ9: PC biệt phát | CR9: Tổng PC | CS9: Tổng thu nhập
A10: A. | B10: ="KHU VỰC CHU LAI: "&"["&COUNT(A11:A421)&"]" -> KHU VỰC CHU LAI: [377] | G10: =G11+G22+G14+G24+G27+G29+G268+G274+G398 -> 1757160000 | H10: =H11+H22+H14+H24+H27+H29+H268+H274+H398 -> 52250000 | I10: =I11+I22+I14+I24+I27+I29+I268+I274+I398 -> 2115390000 | J10: =J11+J22+J14+J24+J27+J29+J268+J274+J398 -> 225370000 | K10: =K11+K22+K14+K24+K27+K29+K268+K274+K398 -> 2340760000 | L10: =L11+L22+L14+L24+L27+L29+L268+L274+L398 -> 4150170000 | N10: =N11+N22+N14+N24+N27+N29+N268+N274+N398 -> 1436785000 | O10: =O11+O22+O14+O24+O27+O29+O268+O274+O398 -> 0 | P10: =P11+P22+P14+P24+P27+P29+P268+P274+P398 -> 3268 | Q10: =Q11+Q22+Q14+Q24+Q27+Q29+Q268+Q274+Q398 -> 1501 | R10: =R11+R22+R14+R24+R27+R29+R268+R274+R398 -> 84.25 | S10: =S11+S22+S14+S24+S27+S29+S268+S274+S398 -> 23.14 | T10: =T11+T22+T14+T24+T27+T29+T268+T274+T398 -> 0 | U10: =U11+U22+U14+U24+U27+U29+U268+U274+U398 -> 0 | ... BG10: =BG11+BG22+BG14+BG24+BG27+BG29+BG268+BG274+BG398 -> 2094700 | BI10: =BI11+BI22+BI14+BI24+BI27+BI29+BI268+BI274+BI398 -> 0 | BJ10: =BJ11+BJ22+BJ14+BJ24+BJ27+BJ29+BJ268+BJ274+BJ398 -> 0 | BK10: =BK11+BK22+BK14+BK24+BK27+BK29+BK268+BK274+BK398 -> 0 | BL10: =BL11+BL22+BL14+BL24+BL27+BL29+BL268+BL274+BL398 -> 0 | BM10: =BM11+BM22+BM14+BM24+BM27+BM29+BM268+BM274+BM398 -> 515000 | BN10: =BN11+BN22+BN14+BN24+BN27+BN29+BN268+BN274+BN398 -> 0 | BO10: =BO11+BO22+BO14+BO24+BO27+BO29+BO268+BO274+BO398 -> 0 | BP10: =BP11+BP22+BP14+BP24+BP27+BP29+BP268+BP274+BP398 -> 0 | ... CS10: =CS11+CS22+CS14+CS24+CS27+CS29+CS268+CS274+CS398 -> 4150170000 | CT10: =SUM(CT11:CT11) -> 0 | CU10: =SUM(CU11:CU11) -> 0 | CV10: =SUM(CV11:CV11) -> 0
A11: I | B11: ="Ban Lãnh đạo: "&"["&COUNT(A12:A13)&"]" -> Ban Lãnh đạo: [2] | G11: =SUM(G12:G13) -> 28650000 | H11: =SUM(H12:H13) -> 0 | I11: =SUM(I12:I13) -> 181350000 | J11: =SUM(J12:J13) -> 35000000 | K11: =SUM(K12:K13) -> 216350000 | L11: =SUM(L12:L13) -> 245000000 | N11: =SUM(N12:N13) -> 20055000 | O11: =SUM(O12:O13) -> 0 | P11: =SUM(P12:P13) -> 25.5 | Q11: =SUM(Q12:Q13) -> 0 | R11: =SUM(R12:R13) -> 0 | S11: =SUM(S12:S13) -> 0 | T11: =SUM(T12:T13) -> 0 | U11: =SUM(U12:U13) -> 0 | ... CV11: =SUM(CV12:CV13) -> 0
A12: =SUBTOTAL(3,$C$11:C12) -> 1 | B12: 0803006 | C12: Bùi Trần Nhân Trí | D12: THILOGI | E12: =IF(CM12>=400000000,"A1",IF(CM12>=300000000,"A2",IF(CM12>=240000000,"A3",IF(CM12>=180000000,"A4",IF(CM12>=120000000,"A5",IF(CM12>=80000000,"A6",IF(CM12>=40000000,"A7",IF(CM12>=25000000,"B1",IF(CM12>=12000000,"B2","B3"))))))))) -> A5 | F12: 39449 | G12: 17130000 | I12: =IF(G12>0,CM12-G12,CM12-H12) -> 132870000 | J12: =CR12 -> 30000000 | K12: =SUM(I12:J12) -> 162870000 | L12: =IF(G12>0,G12+K12,H12+K12) -> 180000000 | M12: =IF(CE12>=11000000,80%,100%) -> 0.8 | N12: =ROUND(MAX(G12*70%,H12*70%,3640000),0) -> 11991000 | O12: 0 | P12: 13 | Q12: 0 | R12: 0 | S12: 0 | AD12: 0 | AE12: =IF(OR(BL12="M1",BL12="M2",BL12="M3",BL12="M4"),P12+R12+S12+T12+U12,0) -> 0 | AF12: =ROUND(IF($P12=0,0,IF(OR($BJ12="lương tháng",$CE12>=11000000),($L12/2-$L12/26*($CC$6-$P12))*$M12,$L12/26*$P12*$M12)),0) -> 72000000 | AG12: =ROUND(MAX((G12+I12)*M12/26*R12,(H12+I12)*M12/26*R12,G12/26*R12*150%,H12/26*R12*150%)*BK12,0) -> 0 | AH12: =ROUND(MAX((G12+I12)*M12/26*S12,(H12+I12)*M12/26*S12,G12/26*S12*200%,H12/26*S12*200%)*BK12,0) -> 0 | AI12: =ROUND(IF(BJ12="Lương tháng",L12/26*T12,MAX((G12+I12)/26*(T12+U12)*200%+G12/26*T12,(H12+I12)/26*(T12+U12)*200%+H12/26*T12,G12/26*(T12+U12)*300%+G12/26*T12,H12/26*(T12+U12)*300%+H12/26*T12)),0) -> 0 | AJ12: =ROUND(IF((P12+Q12)=0,0,IF(BJ12="Lương tháng",MAX((G12+I12)/26*V12,(H12+I12)/26*V12),MAX(G12/26*V12,H12/26*V12))),0) -> 0 | AK12: =ROUND(IF(G12>0,G12/26*W12,H12/26*W12),0) -> 0 | AL12: =ROUND(N12/26*Y12+O12/26*Z12+MAX(G12/26*AA12,H12/26*AA12),0) -> 0 | AM12: =ROUND(IF(BJ12="Lương tháng",L12/26*AC12,L12/26*AC12+MAX((G12+I12)/26*AB12,(H12+I12)/26*AB12)),0) -> 0 | AN12: =ROUND(IF(BJ12="lương tháng",0,MAX((G12+I12)/26*AD12*30%,(H12+I12)/26*AD12*30%)*BK12),0) -> 0 | AO12: =ROUND(BM12*AE12,0) -> 0 | AP12: 0 | AQ12: =ROUND(SUM(AF12:AP12),0) -> 72000000 | AV12: =ROUND(SUM(AQ12:AT12)-AU12,0) -> 72000000 | AW12: =ROUND(IF($BH12=1,$G12*$AW$9,0),0) -> 1370400 | AX12: =ROUND(IF($BH12=1,$G12*$AX$9,0),0) -> 256950 | AY12: =ROUND(IF($BH12=1,$G12*$AY$9,0),0) -> 171300 | AZ12: =SUM(AW12:AY12) -> 1798650 | BA12: =ROUND(IF($BI12="1x",$G12*0.5%,0),0) -> 85650 | BB12: =IF(BN12="Xem lại",0,IF(CM12<11000000,5000,IF(AND(CM12>=11000000,CM12<25000000),10000,IF(AND(CM12>=25000000,CM12<40000000),15000,IF(AND(CM12>=40000000,CM12<120000000),20000,IF(AND(CM12>=120000000,CM12<240000000),25000,30000)))))*$BB$9) -> 550000 | BD12: 0 | BE12: =ROUND(SUM(AZ12:BD12),0) -> 2434300 | BF12: =ROUND(IF(AV12>BE12,AV12-BE12,0),0) -> 69565700 | BG12: =ROUND(IF(BE12>AV12,BE12-AV12,0),0) -> 0 | BH12: 1 | BI12: 1x | BJ12: =IF(AND(D12="QTNV CL",CM12>=11000000),"Lương tháng",IF(CM12>=18000000,"Lương tháng",0)) -> Lương tháng | BK12: =IF(BJ12="Lương tháng",0,1) -> 0 | BL12: 0 | BM12: =IF(BL12="M1",13000,IF(BL12="M2",20000,IF(BL12="M3",26000,IF(BL12="M4",32000,0)))) -> 0 | BN12: =IF(AND(G12>0,(P12+Q12)>=5),"Trừ tiền","Xem lại") -> Trừ tiền | BS12: =AQ12+SUM(BO12:BR12)-AN12-AO12-SUM(BY12:CA12) -> 72000000 | BT12: 2 | BU12: =BT12*4400000 -> 8800000 | BV12: 11000000 | BW12: =BU12+BV12 -> 19800000 | BX12: =BS12-SUM(CC12:CD12)-CB12-AZ12-BW12 -> 50401350 | CE12: 150000000 | CF12: 0 | CG12: 0 | CH12: 30000000 | CJ12: =SUM(CF12:CI12) -> 30000000 | CK12: =CE12+CJ12 -> 180000000 | CM12: =CE12 -> 150000000 | CN12: =CF12 -> 0 | CO12: =CG12 -> 0 | CP12: =CH12 -> 30000000 | CQ12: =CI12 -> 0 | CR12: =SUM(CN12:CQ12) -> 30000000 | CS12: =CM12+CR12 -> 180000000 | CT12: Giám đốc | CU12: Ban Lãnh đạo THILOGI | CV12: buitrannhantri@thilogi.com.vn | CW12: Chu Lai
A13: =SUBTOTAL(3,$C$11:C13) -> 2 | B13: 0708065 | C13: Bùi Vĩnh Vũ | D13: THILOGI | E13: =IF(CM13>=400000000,"A1",IF(CM13>=300000000,"A2",IF(CM13>=240000000,"A3",IF(CM13>=180000000,"A4",IF(CM13>=120000000,"A5",IF(CM13>=80000000,"A6",IF(CM13>=40000000,"A7",IF(CM13>=25000000,"B1",IF(CM13>=12000000,"B2","B3"))))))))) -> A7 | F13: 39314 | G13: 11520000 | I13: =IF(G13>0,CM13-G13,CM13-H13) -> 48480000 | J13: =CR13 -> 5000000 | K13: =SUM(I13:J13) -> 53480000 | L13: =IF(G13>0,G13+K13,H13+K13) -> 65000000 | M13: =IF(CE13>=11000000,80%,100%) -> 0.8 | N13: =ROUND(MAX(G13*70%,H13*70%,3640000),0) -> 8064000 | O13: 0 | P13: 12.5 | Q13: 0 | R13: 0 | S13: 0 | AD13: 0 | AE13: =IF(OR(BL13="M1",BL13="M2",BL13="M3",BL13="M4"),P13+R13+S13+T13+U13,0) -> 0 | AF13: =ROUND(IF($P13=0,0,IF(OR($BJ13="lương tháng",$CE13>=11000000),($L13/2-$L13/26*($CC$6-$P13))*$M13,$L13/26*$P13*$M13)),0) -> 25000000 | AG13: =ROUND(MAX((G13+I13)*M13/26*R13,(H13+I13)*M13/26*R13,G13/26*R13*150%,H13/26*R13*150%)*BK13,0) -> 0 | AH13: =ROUND(MAX((G13+I13)*M13/26*S13,(H13+I13)*M13/26*S13,G13/26*S13*200%,H13/26*S13*200%)*BK13,0) -> 0 | AI13: =ROUND(IF(BJ13="Lương tháng",L13/26*T13,MAX((G13+I13)/26*(T13+U13)*200%+G13/26*T13,(H13+I13)/26*(T13+U13)*200%+H13/26*T13,G13/26*(T13+U13)*300%+G13/26*T13,H13/26*(T13+U13)*300%+H13/26*T13)),0) -> 0 | AJ13: =ROUND(IF((P13+Q13)=0,0,IF(BJ13="Lương tháng",MAX((G13+I13)/26*V13,(H13+I13)/26*V13),MAX(G13/26*V13,H13/26*V13))),0) -> 0 | AK13: =ROUND(IF(G13>0,G13/26*W13,H13/26*W13),0) -> 0 | AL13: =ROUND(N13/26*Y13+O13/26*Z13+MAX(G13/26*AA13,H13/26*AA13),0) -> 0 | AM13: =ROUND(IF(BJ13="Lương tháng",L13/26*AC13,L13/26*AC13+MAX((G13+I13)/26*AB13,(H13+I13)/26*AB13)),0) -> 0 | AN13: =ROUND(IF(BJ13="lương tháng",0,MAX((G13+I13)/26*AD13*30%,(H13+I13)/26*AD13*30%)*BK13),0) -> 0 | AO13: =ROUND(BM13*AE13,0) -> 0 | AP13: 0 | AQ13: =ROUND(SUM(AF13:AP13),0) -> 25000000 | AV13: =ROUND(SUM(AQ13:AT13)-AU13,0) -> 25000000 | AW13: =ROUND(IF($BH13=1,$G13*$AW$9,0),0) -> 921600 | AX13: =ROUND(IF($BH13=1,$G13*$AX$9,0),0) -> 172800 | AY13: =ROUND(IF($BH13=1,$G13*$AY$9,0),0) -> 115200 | AZ13: =SUM(AW13:AY13) -> 1209600 | BA13: =ROUND(IF($BI13="1x",$G13*0.5%,0),0) -> 57600 | BB13: =IF(BN13="Xem lại",0,IF(CM13<11000000,5000,IF(AND(CM13>=11000000,CM13<25000000),10000,IF(AND(CM13>=25000000,CM13<40000000),15000,IF(AND(CM13>=40000000,CM13<120000000),20000,IF(AND(CM13>=120000000,CM13<240000000),25000,30000)))))*$BB$9) -> 440000 | BD13: 0 | BE13: =ROUND(SUM(AZ13:BD13),0) -> 1707200 | BF13: =ROUND(IF(AV13>BE13,AV13-BE13,0),0) -> 23292800 | BG13: =ROUND(IF(BE13>AV13,BE13-AV13,0),0) -> 0 | BH13: 1 | BI13: 1x | BJ13: =IF(AND(D13="QTNV CL",CM13>=11000000),"Lương tháng",IF(CM13>=18000000,"Lương tháng",0)) -> Lương tháng | BK13: =IF(BJ13="Lương tháng",0,1) -> 0 | BL13: 0 | BM13: =IF(BL13="M1",13000,IF(BL13="M2",20000,IF(BL13="M3",26000,IF(BL13="M4",32000,0)))) -> 0 | BN13: =IF(AND(G13>0,(P13+Q13)>=5),"Trừ tiền","Xem lại") -> Trừ tiền | BS13: =AQ13+SUM(BO13:BR13)-AN13-AO13-SUM(BY13:CA13) -> 25000000 | BT13: 3 | BU13: =BT13*4400000 -> 13200000 | BV13: 11000000 | BW13: =BU13+BV13 -> 24200000 | BX13: =BS13-SUM(CC13:CD13)-CB13-AZ13-BW13 -> -409600 | CE13: 60000000 | CF13: 0 | CG13: 0 | CH13: 5000000 | CJ13: =SUM(CF13:CI13) -> 5000000 | CK13: =CE13+CJ13 -> 65000000 | CM13: =CE13 -> 60000000 | CN13: =CF13 -> 0 | CO13: =CG13 -> 0 | CP13: =CH13 -> 5000000 | CQ13: =CI13 -> 0 | CR13: =SUM(CN13:CQ13) -> 5000000 | CS13: =CM13+CR13 -> 65000000 | CT13: Phó Giám đốc - Phụ trách ô tô, cơ khí & LKPT | CU13: Ban Lãnh đạo THILOGI | CV13: buivinhvu@thilogi.com.vn | CW13: Chu Lai
A14: II | B14: ="Phòng Kế toán: " &"["&COUNT(A15:A21)& "]" -> Phòng Kế toán: [7] | G14: =SUM(G15:G21) -> 42450000 | H14: =SUM(H15:H21) -> 0 | I14: =SUM(I15:I21) -> 73050000 | J14: =SUM(J15:J21) -> 1400000 | K14: =SUM(K15:K21) -> 74450000 | L14: =SUM(L15:L21) -> 116900000 | N14: =SUM(N15:N21) -> 30975000 | O14: =SUM(O15:O21) -> 0 | P14: =SUM(P15:P21) -> 88.5 | Q14: =SUM(Q15:Q21) -> 0 | R14: =SUM(R15:R21) -> 5.93 | S14: =SUM(S15:S21) -> 0 | T14: =SUM(T15:T21) -> 0 | U14: =SUM(U15:U21) -> 0 | ... BG14: =SUM(BG15:BG21) -> 0 | BI14: =SUM(BI15:BI21) -> 0 | BJ14: =SUM(BJ15:BJ21) -> 0 | BL14: =SUM(BL15:BL21) -> 0 | BM14: =SUM(BM15:BM21) -> 0 | BN14: =SUM(BN15:BN21) -> 0 | BO14: =SUM(BO15:BO21) -> 0 | BP14: =SUM(BP15:BP21) -> 0 | BQ14: =SUM(BQ15:BQ21) -> 0 | BR14: =SUM(BR15:BR21) -> 0 | BS14: =SUM(BS15:BS21) -> 52134692 | ... CV14: =SUM(CV15:CV21) -> 0
A15: =SUBTOTAL(3,$C$11:C15) -> 3 | B15: 1307041 | C15: Lê Thị Huệ | D15: THILOGI | E15: =IF(CL15>=400000000,"A1",IF(CL15>=300000000,"A2",IF(CL15>=240000000,"A3",IF(CL15>=180000000,"A4",IF(CL15>=120000000,"A5",IF(CL15>=80000000,"A6",IF(CL15>=40000000,"A7",IF(CL15>=25000000,"B1",IF(CL15>=12000000,"B2","B3"))))))))) -> B3 | F15: 41463 | G15: 8640000 | I15: =IF(G15>0,CM15-G15,CM15-H15) -> 26360000 | J15: =CR15 -> 0 | K15: =SUM(I15:J15) -> 26360000 | L15: =IF(G15>0,G15+K15,H15+K15) -> 35000000 | M15: =IF(CE15>=11000000,80%,100%) -> 0.8 | N15: =ROUND(MAX(G15*70%,H15*70%,3640000),0) -> 6048000 | O15: 0 | P15: 13 | Q15: 0 | R15: 0 | S15: 0 | AD15: 0 | AE15: =IF(OR(BL15="M1",BL15="M2",BL15="M3",BL15="M4"),P15+R15+S15+T15+U15,0) -> 0 | AF15: =ROUND(IF($P15=0,0,IF(OR($BJ15="lương tháng",$CE15>=11000000),($L15/2-$L15/26*($CC$6-$P15))*$M15,$L15/26*$P15*$M15)),0) -> 14000000 | AG15: =ROUND(MAX((G15+I15)*M15/26*R15,(H15+I15)*M15/26*R15,G15/26*R15*150%,H15/26*R15*150%)*BK15,0) -> 0 | AH15: =ROUND(MAX((G15+I15)*M15/26*S15,(H15+I15)*M15/26*S15,G15/26*S15*200%,H15/26*S15*200%)*BK15,0) -> 0 | AI15: =ROUND(IF(BJ15="Lương tháng",L15/26*T15,MAX((G15+I15)/26*(T15+U15)*200%+G15/26*T15,(H15+I15)/26*(T15+U15)*200%+H15/26*T15,G15/26*(T15+U15)*300%+G15/26*T15,H15/26*(T15+U15)*300%+H15/26*T15)),0) -> 0 | AJ15: =ROUND(IF((P15+Q15)=0,0,IF(BJ15="Lương tháng",MAX((G15+I15)/26*V15,(H15+I15)/26*V15),MAX(G15/26*V15,H15/26*V15))),0) -> 0 | AK15: =ROUND(IF(G15>0,G15/26*W15,H15/26*W15),0) -> 0 | AL15: =ROUND(N15/26*Y15+O15/26*Z15+MAX(G15/26*AA15,H15/26*AA15),0) -> 0 | AM15: =ROUND(IF(BJ15="Lương tháng",L15/26*AC15,L15/26*AC15+MAX((G15+I15)/26*AB15,(H15+I15)/26*AB15)),0) -> 0 | AN15: =ROUND(IF(BJ15="lương tháng",0,MAX((G15+I15)/26*AD15*30%,(H15+I15)/26*AD15*30%)*BK15),0) -> 0 | AO15: =ROUND(BM15*AE15,0) -> 0 | AP15: 0 | AQ15: =ROUND(SUM(AF15:AP15),0) -> 14000000 | AV15: =ROUND(SUM(AQ15:AT15)-AU15,0) -> 14000000 | AW15: =ROUND(IF($BH15=1,$G15*$AW$9,0),0) -> 691200 | AX15: =ROUND(IF($BH15=1,$G15*$AX$9,0),0) -> 129600 | AY15: =ROUND(IF($BH15=1,$G15*$AY$9,0),0) -> 86400 | AZ15: =SUM(AW15:AY15) -> 907200 | BA15: =ROUND(IF($BI15="1x",$G15*0.5%,0),0) -> 43200 | BB15: =IF(BN15="Xem lại",0,IF(CM15<11000000,5000,IF(AND(CM15>=11000000,CM15<25000000),10000,IF(AND(CM15>=25000000,CM15<40000000),15000,IF(AND(CM15>=40000000,CM15<120000000),20000,IF(AND(CM15>=120000000,CM15<240000000),25000,30000)))))*$BB$9) -> 330000 | BD15: 0 | BE15: =ROUND(SUM(AZ15:BD15),0) -> 1280400 | BF15: =ROUND(IF(AV15>BE15,AV15-BE15,0),0) -> 12719600 | BG15: =ROUND(IF(BE15>AV15,BE15-AV15,0),0) -> 0 | BH15: 1 | BI15: 1x | BJ15: =IF(AND(D15="QTNV CL",CM15>=11000000),"Lương tháng",IF(CM15>=18000000,"Lương tháng",0)) -> Lương tháng | BK15: =IF(BJ15="Lương tháng",0,1) -> 0 | BL15: 0 | BM15: =IF(BL15="M1",13000,IF(BL15="M2",20000,IF(BL15="M3",26000,IF(BL15="M4",32000,0)))) -> 0 | BN15: =IF(AND(G15>0,(P15+Q15)>=5),"Trừ tiền","Xem lại") -> Trừ tiền | BS15: =AQ15+SUM(BO15:BR15)-AN15-AO15-SUM(BY15:CA15) -> 14000000 | BT15: 4 | BU15: =BT15*4400000 -> 17600000 | BV15: 11000000 | BW15: =BU15+BV15 -> 28600000 | BX15: =BS15-SUM(CC15:CD15)-CB15-AZ15-BW15 -> -15507200 | CE15: 35000000 | CG15: 0 | CH15: 0 | CJ15: =SUM(CF15:CI15) -> 0 | CK15: =CE15+CJ15 -> 35000000 | CM15: =CE15 -> 35000000 | CN15: =CF15 -> 0 | CO15: =CG15 -> 0 | CP15: =CH15 -> 0 | CQ15: =CI15 -> 0 | CR15: =SUM(CN15:CQ15) -> 0 | CS15: =CM15+CR15 -> 35000000 | CT15: Kế toán trưởng | CU15: Phòng Kế toán | CV15: lethihue@thilogi.com.vn | CW15: Chu Lai
A16: =SUBTOTAL(3,$C$11:C16) -> 4 | B16: 24031119 | C16: Nguyễn Thế Hạ | D16: THILOGI | E16: =IF(CL16>=400000000,"A1",IF(CL16>=300000000,"A2",IF(CL16>=240000000,"A3",IF(CL16>=180000000,"A4",IF(CL16>=120000000,"A5",IF(CL16>=80000000,"A6",IF(CL16>=40000000,"A7",IF(CL16>=25000000,"B1",IF(CL16>=12000000,"B2","B3"))))))))) -> B3 | F16: 45371 | G16: 6300000 | I16: =IF(G16>0,CM16-G16,CM16-H16) -> 5700000 | J16: =CR16 -> 0 | K16: =SUM(I16:J16) -> 5700000 | L16: =IF(G16>0,G16+K16,H16+K16) -> 12000000 | M16: =IF(CE16>=11000000,80%,100%) -> 0.8 | N16: =ROUND(MAX(G16*70%,H16*70%,3640000),0) -> 4410000 | O16: 0 | P16: 12.5 | Q16: 0 | R16: 1.57 | S16: 0 | AD16: 0 | AE16: =IF(OR(BL16="M1",BL16="M2",BL16="M3",BL16="M4"),P16+R16+S16+T16+U16,0) -> 0 | AF16: =ROUND(IF($P16=0,0,IF(OR($BJ16="lương tháng",$CE16>=11000000),($L16/2-$L16/26*($CC$6-$P16))*$M16,$L16/26*$P16*$M16)),0) -> 4615385 | AG16: =ROUND(MAX((G16+I16)*M16/26*R16,(H16+I16)*M16/26*R16,G16/26*R16*150%,H16/26*R16*150%)*BK16,0) -> 579692 | AH16: =ROUND(MAX((G16+I16)*M16/26*S16,(H16+I16)*M16/26*S16,G16/26*S16*200%,H16/26*S16*200%)*BK16,0) -> 0 | AI16: =ROUND(IF(BJ16="Lương tháng",L16/26*T16,MAX((G16+I16)/26*(T16+U16)*200%+G16/26*T16,(H16+I16)/26*(T16+U16)*200%+H16/26*T16,G16/26*(T16+U16)*300%+G16/26*T16,H16/26*(T16+U16)*300%+H16/26*T16)),0) -> 0 | AJ16: =ROUND(IF((P16+Q16)=0,0,IF(BJ16="Lương tháng",MAX((G16+I16)/26*V16,(H16+I16)/26*V16),MAX(G16/26*V16,H16/26*V16))),0) -> 0 | AK16: =ROUND(IF(G16>0,G16/26*W16,H16/26*W16),0) -> 0 | AL16: =ROUND(N16/26*Y16+O16/26*Z16+MAX(G16/26*AA16,H16/26*AA16),0) -> 0 | AM16: =ROUND(IF(BJ16="Lương tháng",L16/26*AC16,L16/26*AC16+MAX((G16+I16)/26*AB16,(H16+I16)/26*AB16)),0) -> 0 | AN16: =ROUND(IF(BJ16="lương tháng",0,MAX((G16+I16)/26*AD16*30%,(H16+I16)/26*AD16*30%)*BK16),0) -> 0 | AO16: =ROUND(BM16*AE16,0) -> 0 | AP16: 0 | AQ16: =ROUND(SUM(AF16:AP16),0) -> 5195077 | AV16: =ROUND(SUM(AQ16:AT16)-AU16,0) -> 5195077 | AW16: =ROUND(IF($BH16=1,$G16*$AW$9,0),0) -> 504000 | AX16: =ROUND(IF($BH16=1,$G16*$AX$9,0),0) -> 94500 | AY16: =ROUND(IF($BH16=1,$G16*$AY$9,0),0) -> 63000 | AZ16: =SUM(AW16:AY16) -> 661500 | BA16: =ROUND(IF($BI16="1x",$G16*0.5%,0),0) -> 31500 | BB16: =IF(BN16="Xem lại",0,IF(CM16<11000000,5000,IF(AND(CM16>=11000000,CM16<25000000),10000,IF(AND(CM16>=25000000,CM16<40000000),15000,IF(AND(CM16>=40000000,CM16<120000000),20000,IF(AND(CM16>=120000000,CM16<240000000),25000,30000)))))*$BB$9) -> 220000 | BD16: 0 | BE16: =ROUND(SUM(AZ16:BD16),0) -> 913000 | BF16: =ROUND(IF(AV16>BE16,AV16-BE16,0),0) -> 4282077 | BG16: =ROUND(IF(BE16>AV16,BE16-AV16,0),0) -> 0 | BH16: 1 | BI16: 1x | BJ16: =IF(AND(D16="QTNV CL",CM16>=11000000),"Lương tháng",IF(CM16>=18000000,"Lương tháng",0)) -> 0 | BK16: =IF(BJ16="Lương tháng",0,1) -> 1 | BL16: 0 | BM16: =IF(BL16="M1",13000,IF(BL16="M2",20000,IF(BL16="M3",26000,IF(BL16="M4",32000,0)))) -> 0 | BN16: =IF(AND(G16>0,(P16+Q16)>=5),"Trừ tiền","Xem lại") -> Trừ tiền | BS16: =AQ16+SUM(BO16:BR16)-AN16-AO16-SUM(BY16:CA16) -> 5195077 | BT16: 0 | BU16: =BT16*4400000 -> 0 | BV16: 11000000 | BW16: =BU16+BV16 -> 11000000 | BX16: =BS16-SUM(CC16:CD16)-CB16-AZ16-BW16 -> -6466423 | CE16: 12000000 | CJ16: =SUM(CF16:CI16) -> 0 | CK16: =CE16+CJ16 -> 12000000 | CM16: =CE16 -> 12000000 | CN16: =CF16 -> 0 | CO16: =CG16 -> 0 | CP16: =CH16 -> 0 | CQ16: =CI16 -> 0 | CR16: =SUM(CN16:CQ16) -> 0 | CS16: =CM16+CR16 -> 12000000 | CT16: Chuyên viên Kế toán Giá thành | CU16: Phòng Kế toán | CV16: nguyentheha@thilogi.com.vn | CW16: Chu Lai
A17: =SUBTOTAL(3,$C$11:C17) -> 5 | B17: 2309463 | C17: Nguyễn Thế Sỹ | D17: THILOGI | E17: =IF(CL17>=400000000,"A1",IF(CL17>=300000000,"A2",IF(CL17>=240000000,"A3",IF(CL17>=180000000,"A4",IF(CL17>=120000000,"A5",IF(CL17>=80000000,"A6",IF(CL17>=40000000,"A7",IF(CL17>=25000000,"B1",IF(CL17>=12000000,"B2","B3"))))))))) -> B3 | F17: 45174 | G17: 4750000 | I17: =IF(G17>0,CM17-G17,CM17-H17) -> 5250000 | J17: =CR17 -> 0 | K17: =SUM(I17:J17) -> 5250000 | L17: =IF(G17>0,G17+K17,H17+K17) -> 10000000 | M17: =IF(CE17>=11000000,80%,100%) -> 1 | N17: =ROUND(MAX(G17*70%,H17*70%,3640000),0) -> 3640000 | O17: 0 | P17: 13 | Q17: 0 | R17: 1.07 | S17: 0 | AD17: 0 | AE17: =IF(OR(BL17="M1",BL17="M2",BL17="M3",BL17="M4"),P17+R17+S17+T17+U17,0) -> 0 | AF17: =ROUND(IF($P17=0,0,IF(OR($BJ17="lương tháng",$CE17>=11000000),($L17/2-$L17/26*($CC$6-$P17))*$M17,$L17/26*$P17*$M17)),0) -> 5000000 | AG17: =ROUND(MAX((G17+I17)*M17/26*R17,(H17+I17)*M17/26*R17,G17/26*R17*150%,H17/26*R17*150%)*BK17,0) -> 411538 | AH17: =ROUND(MAX((G17+I17)*M17/26*S17,(H17+I17)*M17/26*S17,G17/26*S17*200%,H17/26*S17*200%)*BK17,0) -> 0 | AI17: =ROUND(IF(BJ17="Lương tháng",L17/26*T17,MAX((G17+I17)/26*(T17+U17)*200%+G17/26*T17,(H17+I17)/26*(T17+U17)*200%+H17/26*T17,G17/26*(T17+U17)*300%+G17/26*T17,H17/26*(T17+U17)*300%+H17/26*T17)),0) -> 0 | AJ17: =ROUND(IF((P17+Q17)=0,0,IF(BJ17="Lương tháng",MAX((G17+I17)/26*V17,(H17+I17)/26*V17),MAX(G17/26*V17,H17/26*V17))),0) -> 0 | AK17: =ROUND(IF(G17>0,G17/26*W17,H17/26*W17),0) -> 0 | AL17: =ROUND(N17/26*Y17+O17/26*Z17+MAX(G17/26*AA17,H17/26*AA17),0) -> 0 | AM17: =ROUND(IF(BJ17="Lương tháng",L17/26*AC17,L17/26*AC17+MAX((G17+I17)/26*AB17,(H17+I17)/26*AB17)),0) -> 0 | AN17: =ROUND(IF(BJ17="lương tháng",0,MAX((G17+I17)/26*AD17*30%,(H17+I17)/26*AD17*30%)*BK17),0) -> 0 | AO17: =ROUND(BM17*AE17,0) -> 0 | AP17: 0 | AQ17: =ROUND(SUM(AF17:AP17),0) -> 5411538 | AV17: =ROUND(SUM(AQ17:AT17)-AU17,0) -> 5411538 | AW17: =ROUND(IF($BH17=1,$G17*$AW$9,0),0) -> 380000 | AX17: =ROUND(IF($BH17=1,$G17*$AX$9,0),0) -> 71250 | AY17: =ROUND(IF($BH17=1,$G17*$AY$9,0),0) -> 47500 | AZ17: =SUM(AW17:AY17) -> 498750 | BA17: =ROUND(IF($BI17="1x",$G17*0.5%,0),0) -> 0 | BB17: =IF(BN17="Xem lại",0,IF(CM17<11000000,5000,IF(AND(CM17>=11000000,CM17<25000000),10000,IF(AND(CM17>=25000000,CM17<40000000),15000,IF(AND(CM17>=40000000,CM17<120000000),20000,IF(AND(CM17>=120000000,CM17<240000000),25000,30000)))))*$BB$9) -> 110000 | BD17: 0 | BE17: =ROUND(SUM(AZ17:BD17),0) -> 608750 | BF17: =ROUND(IF(AV17>BE17,AV17-BE17,0),0) -> 4802788 | BG17: =ROUND(IF(BE17>AV17,BE17-AV17,0),0) -> 0 | BH17: 1 | BI17: 0 | BJ17: =IF(AND(D17="QTNV CL",CM17>=11000000),"Lương tháng",IF(CM17>=18000000,"Lương tháng",0)) -> 0 | BK17: =IF(BJ17="Lương tháng",0,1) -> 1 | BL17: 0 | BM17: =IF(BL17="M1",13000,IF(BL17="M2",20000,IF(BL17="M3",26000,IF(BL17="M4",32000,0)))) -> 0 | BN17: =IF(AND(G17>0,(P17+Q17)>=5),"Trừ tiền","Xem lại") -> Trừ tiền | BS17: =AQ17+SUM(BO17:BR17)-AN17-AO17-SUM(BY17:CA17) -> 5411538 | BT17: 0 | BU17: =BT17*4400000 -> 0 | BV17: 11000000 | BW17: =BU17+BV17 -> 11000000 | BX17: =BS17-SUM(CC17:CD17)-CB17-AZ17-BW17 -> -6087212 | CE17: 10000000 | CJ17: =SUM(CF17:CI17) -> 0 | CK17: =CE17+CJ17 -> 10000000 | CM17: =CE17 -> 10000000 | CN17: =CF17 -> 0 | CO17: =CG17 -> 0 | CP17: =CH17 -> 0 | CQ17: =CI17 -> 0 | CR17: =SUM(CN17:CQ17) -> 0 | CS17: =CM17+CR17 -> 10000000 | CT17: Chuyên viên Kế toán doanh thu | CU17: Phòng Kế toán | CV17: nguyenthesy@thilogi.com.vn | CW17: Chu Lai
A18: =SUBTOTAL(3,$C$11:C18) -> 6 | B18: 1104119 | C18: Huỳnh Thị Trinh | D18: THILOGI | E18: =IF(CL18>=400000000,"A1",IF(CL18>=300000000,"A2",IF(CL18>=240000000,"A3",IF(CL18>=180000000,"A4",IF(CL18>=120000000,"A5",IF(CL18>=80000000,"A6",IF(CL18>=40000000,"A7",IF(CL18>=25000000,"B1",IF(CL18>=12000000,"B2","B3"))))))))) -> B3 | F18: 40634 | G18: 8510000 | I18: =IF(G18>0,CM18-G18,CM18-H18) -> 19490000 | J18: =CR18 -> 1400000 | K18: =SUM(I18:J18) -> 20890000 | L18: =IF(G18>0,G18+K18,H18+K18) -> 29400000 | M18: =IF(CE18>=11000000,80%,100%) -> 0.8 | N18: =ROUND(MAX(G18*70%,H18*70%,3640000),0) -> 5957000 | O18: 0 | P18: 13 | Q18: 0 | R18: 0 | S18: 0 | AD18: 0 | AE18: =IF(OR(BL18="M1",BL18="M2",BL18="M3",BL18="M4"),P18+R18+S18+T18+U18,0) -> 0 | AF18: =ROUND(IF($P18=0,0,IF(OR($BJ18="lương tháng",$CE18>=11000000),($L18/2-$L18/26*($CC$6-$P18))*$M18,$L18/26*$P18*$M18)),0) -> 11760000 | AG18: =ROUND(MAX((G18+I18)*M18/26*R18,(H18+I18)*M18/26*R18,G18/26*R18*150%,H18/26*R18*150%)*BK18,0) -> 0 | AH18: =ROUND(MAX((G18+I18)*M18/26*S18,(H18+I18)*M18/26*S18,G18/26*S18*200%,H18/26*S18*200%)*BK18,0) -> 0 | AI18: =ROUND(IF(BJ18="Lương tháng",L18/26*T18,MAX((G18+I18)/26*(T18+U18)*200%+G18/26*T18,(H18+I18)/26*(T18+U18)*200%+H18/26*T18,G18/26*(T18+U18)*300%+G18/26*T18,H18/26*(T18+U18)*300%+H18/26*T18)),0) -> 0 | AJ18: =ROUND(IF((P18+Q18)=0,0,IF(BJ18="Lương tháng",MAX((G18+I18)/26*V18,(H18+I18)/26*V18),MAX(G18/26*V18,H18/26*V18))),0) -> 0 | AK18: =ROUND(IF(G18>0,G18/26*W18,H18/26*W18),0) -> 0 | AL18: =ROUND(N18/26*Y18+O18/26*Z18+MAX(G18/26*AA18,H18/26*AA18),0) -> 0 | AM18: =ROUND(IF(BJ18="Lương tháng",L18/26*AC18,L18/26*AC18+MAX((G18+I18)/26*AB18,(H18+I18)/26*AB18)),0) -> 0 | AN18: =ROUND(IF(BJ18="lương tháng",0,MAX((G18+I18)/26*AD18*30%,(H18+I18)/26*AD18*30%)*BK18),0) -> 0 | AO18: =ROUND(BM18*AE18,0) -> 0 | AP18: 0 | AQ18: =ROUND(SUM(AF18:AP18),0) -> 11760000 | AV18: =ROUND(SUM(AQ18:AT18)-AU18,0) -> 11760000 | AW18: =ROUND(IF($BH18=1,$G18*$AW$9,0),0) -> 680800 | AX18: =ROUND(IF($BH18=1,$G18*$AX$9,0),0) -> 127650 | AY18: =ROUND(IF($BH18=1,$G18*$AY$9,0),0) -> 85100 | AZ18: =SUM(AW18:AY18) -> 893550 | BA18: =ROUND(IF($BI18="1x",$G18*0.5%,0),0) -> 42550 | BB18: =IF(BN18="Xem lại",0,IF(CM18<11000000,5000,IF(AND(CM18>=11000000,CM18<25000000),10000,IF(AND(CM18>=25000000,CM18<40000000),15000,IF(AND(CM18>=40000000,CM18<120000000),20000,IF(AND(CM18>=120000000,CM18<240000000),25000,30000)))))*$BB$9) -> 330000 | BD18: 0 | BE18: =ROUND(SUM(AZ18:BD18),0) -> 1266100 | BF18: =ROUND(IF(AV18>BE18,AV18-BE18,0),0) -> 10493900 | BG18: =ROUND(IF(BE18>AV18,BE18-AV18,0),0) -> 0 | BH18: 1 | BI18: 1x | BJ18: =IF(AND(D18="QTNV CL",CM18>=11000000),"Lương tháng",IF(CM18>=18000000,"Lương tháng",0)) -> Lương tháng | BK18: =IF(BJ18="Lương tháng",0,1) -> 0 | BL18: 0 | BM18: =IF(BL18="M1",13000,IF(BL18="M2",20000,IF(BL18="M3",26000,IF(BL18="M4",32000,0)))) -> 0 | BN18: =IF(AND(G18>0,(P18+Q18)>=5),"Trừ tiền","Xem lại") -> Trừ tiền | BS18: =AQ18+SUM(BO18:BR18)-AN18-AO18-SUM(BY18:CA18) -> 11760000 | BT18: 3 | BU18: =BT18*4400000 -> 13200000 | BV18: 11000000 | BW18: =BU18+BV18 -> 24200000 | BX18: =BS18-SUM(CC18:CD18)-CB18-AZ18-BW18 -> -13333550 | CE18: 28000000 | CF18: =CE18*5% -> 1400000 | CG18: 0 | CH18: 0 | CJ18: =SUM(CF18:CI18) -> 1400000 | CK18: =CE18+CJ18 -> 29400000 | CM18: =CE18 -> 28000000 | CN18: =CF18 -> 1400000 | CO18: =CG18 -> 0 | CP18: =CH18 -> 0 | CQ18: =CI18 -> 0 | CR18: =SUM(CN18:CQ18) -> 1400000 | CS18: =CM18+CR18 -> 29400000 | CT18: Kế toán phó | CU18: Phòng Kế toán | CV18: huynhthitrinh@thilogi.com.vn | CW18: Chu Lai
A19: =SUBTOTAL(3,$C$11:C19) -> 7 | B19: 2107314 | C19: Nguyễn Thị Phượng | D19: THILOGI | E19: =IF(CL19>=400000000,"A1",IF(CL19>=300000000,"A2",IF(CL19>=240000000,"A3",IF(CL19>=180000000,"A4",IF(CL19>=120000000,"A5",IF(CL19>=80000000,"A6",IF(CL19>=40000000,"A7",IF(CL19>=25000000,"B1",IF(CL19>=12000000,"B2","B3"))))))))) -> B3 | F19: 44396 | G19: 4750000 | I19: =IF(G19>0,CM19-G19,CM19-H19) -> 5750000 | J19: =CR19 -> 0 | K19: =SUM(I19:J19) -> 5750000 | L19: =IF(G19>0,G19+K19,H19+K19) -> 10500000 | M19: =IF(CE19>=11000000,80%,100%) -> 1 | N19: =ROUND(MAX(G19*70%,H19*70%,3640000),0) -> 3640000 | O19: 0 | P19: 13 | Q19: 0 | R19: 1.14 | S19: 0 | AD19: 0 | AE19: =IF(OR(BL19="M1",BL19="M2",BL19="M3",BL19="M4"),P19+R19+S19+T19+U19,0) -> 0 | AF19: =ROUND(IF($P19=0,0,IF(OR($BJ19="lương tháng",$CE19>=11000000),($L19/2-$L19/26*($CC$6-$P19))*$M19,$L19/26*$P19*$M19)),0) -> 5250000 | AG19: =ROUND(MAX((G19+I19)*M19/26*R19,(H19+I19)*M19/26*R19,G19/26*R19*150%,H19/26*R19*150%)*BK19,0) -> 460385 | AH19: =ROUND(MAX((G19+I19)*M19/26*S19,(H19+I19)*M19/26*S19,G19/26*S19*200%,H19/26*S19*200%)*BK19,0) -> 0 | AI19: =ROUND(IF(BJ19="Lương tháng",L19/26*T19,MAX((G19+I19)/26*(T19+U19)*200%+G19/26*T19,(H19+I19)/26*(T19+U19)*200%+H19/26*T19,G19/26*(T19+U19)*300%+G19/26*T19,H19/26*(T19+U19)*300%+H19/26*T19)),0) -> 0 | AJ19: =ROUND(IF((P19+Q19)=0,0,IF(BJ19="Lương tháng",MAX((G19+I19)/26*V19,(H19+I19)/26*V19),MAX(G19/26*V19,H19/26*V19))),0) -> 0 | AK19: =ROUND(IF(G19>0,G19/26*W19,H19/26*W19),0) -> 0 | AL19: =ROUND(N19/26*Y19+O19/26*Z19+MAX(G19/26*AA19,H19/26*AA19),0) -> 0 | AM19: =ROUND(IF(BJ19="Lương tháng",L19/26*AC19,L19/26*AC19+MAX((G19+I19)/26*AB19,(H19+I19)/26*AB19)),0) -> 0 | AN19: =ROUND(IF(BJ19="lương tháng",0,MAX((G19+I19)/26*AD19*30%,(H19+I19)/26*AD19*30%)*BK19),0) -> 0 | AO19: =ROUND(BM19*AE19,0) -> 0 | AP19: 0 | AQ19: =ROUND(SUM(AF19:AP19),0) -> 5710385 | AV19: =ROUND(SUM(AQ19:AT19)-AU19,0) -> 5710385 | AW19: =ROUND(IF($BH19=1,$G19*$AW$9,0),0) -> 380000 | AX19: =ROUND(IF($BH19=1,$G19*$AX$9,0),0) -> 71250 | AY19: =ROUND(IF($BH19=1,$G19*$AY$9,0),0) -> 47500 | AZ19: =SUM(AW19:AY19) -> 498750 | BA19: =ROUND(IF($BI19="1x",$G19*0.5%,0),0) -> 23750 | BB19: =IF(BN19="Xem lại",0,IF(CM19<11000000,5000,IF(AND(CM19>=11000000,CM19<25000000),10000,IF(AND(CM19>=25000000,CM19<40000000),15000,IF(AND(CM19>=40000000,CM19<120000000),20000,IF(AND(CM19>=120000000,CM19<240000000),25000,30000)))))*$BB$9) -> 110000 | BD19: 0 | BE19: =ROUND(SUM(AZ19:BD19),0) -> 632500 | BF19: =ROUND(IF(AV19>BE19,AV19-BE19,0),0) -> 5077885 | BG19: =ROUND(IF(BE19>AV19,BE19-AV19,0),0) -> 0 | BH19: 1 | BI19: 1x | BJ19: =IF(AND(D19="QTNV CL",CM19>=11000000),"Lương tháng",IF(CM19>=18000000,"Lương tháng",0)) -> 0 | BK19: =IF(BJ19="Lương tháng",0,1) -> 1 | BL19: 0 | BM19: =IF(BL19="M1",13000,IF(BL19="M2",20000,IF(BL19="M3",26000,IF(BL19="M4",32000,0)))) -> 0 | BN19: =IF(AND(G19>0,(P19+Q19)>=5),"Trừ tiền","Xem lại") -> Trừ tiền | BS19: =AQ19+SUM(BO19:BR19)-AN19-AO19-SUM(BY19:CA19) -> 5710385 | BT19: 0 | BU19: =BT19*4400000 -> 0 | BV19: 11000000 | BW19: =BU19+BV19 -> 11000000 | BX19: =BS19-SUM(CC19:CD19)-CB19-AZ19-BW19 -> -5788365 | CE19: 10500000 | CF19: 0 | CG19: 0 | CH19: 0 | CJ19: =SUM(CF19:CI19) -> 0 | CK19: =CE19+CJ19 -> 10500000 | CM19: =CE19 -> 10500000 | CN19: =CF19 -> 0 | CO19: =CG19 -> 0 | CP19: =CH19 -> 0 | CQ19: =CI19 -> 0 | CR19: =SUM(CN19:CQ19) -> 0 | CS19: =CM19+CR19 -> 10500000 | CT19: Chuyên viên Kế toán ngân hàng | CU19: Phòng Kế toán | CV19: nguyenthiphuong@thilogi.com.vn | CW19: Chu Lai
A20: =SUBTOTAL(3,$C$11:C20) -> 8 | B20: 2312722 | C20: Hồ Tuấn Đạt | D20: THILOGI | E20: =IF(CL20>=400000000,"A1",IF(CL20>=300000000,"A2",IF(CL20>=240000000,"A3",IF(CL20>=180000000,"A4",IF(CL20>=120000000,"A5",IF(CL20>=80000000,"A6",IF(CL20>=40000000,"A7",IF(CL20>=25000000,"B1",IF(CL20>=12000000,"B2","B3"))))))))) -> B3 | F20: 45271 | G20: 4750000 | I20: =IF(G20>0,CM20-G20,CM20-H20) -> 5250000 | J20: =CR20 -> 0 | K20: =SUM(I20:J20) -> 5250000 | L20: =IF(G20>0,G20+K20,H20+K20) -> 10000000 | M20: =IF(CE20>=11000000,80%,100%) -> 1 | N20: =ROUND(MAX(G20*70%,H20*70%,3640000),0) -> 3640000 | O20: 0 | P20: 13 | Q20: 0 | R20: 0.79 | S20: 0 | AD20: 0 | AE20: =IF(OR(BL20="M1",BL20="M2",BL20="M3",BL20="M4"),P20+R20+S20+T20+U20,0) -> 0 | AF20: =ROUND(IF($P20=0,0,IF(OR($BJ20="lương tháng",$CE20>=11000000),($L20/2-$L20/26*($CC$6-$P20))*$M20,$L20/26*$P20*$M20)),0) -> 5000000 | AG20: =ROUND(MAX((G20+I20)*M20/26*R20,(H20+I20)*M20/26*R20,G20/26*R20*150%,H20/26*R20*150%)*BK20,0) -> 303846 | AH20: =ROUND(MAX((G20+I20)*M20/26*S20,(H20+I20)*M20/26*S20,G20/26*S20*200%,H20/26*S20*200%)*BK20,0) -> 0 | AI20: =ROUND(IF(BJ20="Lương tháng",L20/26*T20,MAX((G20+I20)/26*(T20+U20)*200%+G20/26*T20,(H20+I20)/26*(T20+U20)*200%+H20/26*T20,G20/26*(T20+U20)*300%+G20/26*T20,H20/26*(T20+U20)*300%+H20/26*T20)),0) -> 0 | AJ20: =ROUND(IF((P20+Q20)=0,0,IF(BJ20="Lương tháng",MAX((G20+I20)/26*V20,(H20+I20)/26*V20),MAX(G20/26*V20,H20/26*V20))),0) -> 0 | AK20: =ROUND(IF(G20>0,G20/26*W20,H20/26*W20),0) -> 0 | AL20: =ROUND(N20/26*Y20+O20/26*Z20+MAX(G20/26*AA20,H20/26*AA20),0) -> 0 | AM20: =ROUND(IF(BJ20="Lương tháng",L20/26*AC20,L20/26*AC20+MAX((G20+I20)/26*AB20,(H20+I20)/26*AB20)),0) -> 0 | AN20: =ROUND(IF(BJ20="lương tháng",0,MAX((G20+I20)/26*AD20*30%,(H20+I20)/26*AD20*30%)*BK20),0) -> 0 | AO20: =ROUND(BM20*AE20,0) -> 0 | AP20: 0 | AQ20: =ROUND(SUM(AF20:AP20),0) -> 5303846 | AV20: =ROUND(SUM(AQ20:AT20)-AU20,0) -> 5303846 | AW20: =ROUND(IF($BH20=1,$G20*$AW$9,0),0) -> 380000 | AX20: =ROUND(IF($BH20=1,$G20*$AX$9,0),0) -> 71250 | AY20: =ROUND(IF($BH20=1,$G20*$AY$9,0),0) -> 47500 | AZ20: =SUM(AW20:AY20) -> 498750 | BA20: =ROUND(IF($BI20="1x",$G20*0.5%,0),0) -> 0 | BB20: =IF(BN20="Xem lại",0,IF(CM20<11000000,5000,IF(AND(CM20>=11000000,CM20<25000000),10000,IF(AND(CM20>=25000000,CM20<40000000),15000,IF(AND(CM20>=40000000,CM20<120000000),20000,IF(AND(CM20>=120000000,CM20<240000000),25000,30000)))))*$BB$9) -> 110000 | BD20: 0 | BE20: =ROUND(SUM(AZ20:BD20),0) -> 608750 | BF20: =ROUND(IF(AV20>BE20,AV20-BE20,0),0) -> 4695096 | BG20: =ROUND(IF(BE20>AV20,BE20-AV20,0),0) -> 0 | BH20: 1 | BI20: 0 | BJ20: =IF(AND(D20="QTNV CL",CM20>=11000000),"Lương tháng",IF(CM20>=18000000,"Lương tháng",0)) -> 0 | BK20: =IF(BJ20="Lương tháng",0,1) -> 1 | BL20: 0 | BM20: =IF(BL20="M1",13000,IF(BL20="M2",20000,IF(BL20="M3",26000,IF(BL20="M4",32000,0)))) -> 0 | BN20: =IF(AND(G20>0,(P20+Q20)>=5),"Trừ tiền","Xem lại") -> Trừ tiền | BS20: =AQ20+SUM(BO20:BR20)-AN20-AO20-SUM(BY20:CA20) -> 5303846 | BT20: 0 | BU20: =BT20*4400000 -> 0 | BV20: 11000000 | BW20: =BU20+BV20 -> 11000000 | BX20: =BS20-SUM(CC20:CD20)-CB20-AZ20-BW20 -> -6194904 | CE20: 10000000 | CF20: 0 | CG20: 0 | CH20: 0 | CJ20: =SUM(CF20:CI20) -> 0 | CK20: =CE20+CJ20 -> 10000000 | CM20: =CE20 -> 10000000 | CN20: =CF20 -> 0 | CO20: =CG20 -> 0 | CP20: =CH20 -> 0 | CQ20: =CI20 -> 0 | CR20: =SUM(CN20:CQ20) -> 0 | CS20: =CM20+CR20 -> 10000000 | CT20: Chuyên viên Kế toán chi phí | CU20: Phòng Kế toán | CV20: hotuandat@thilogi.com.vn | CW20: Chu Lai
A21: =SUBTOTAL(3,$C$11:C21) -> 9 | B21: 25030894 | C21: Lê Tuấn Kiệt | D21: THILOGI | E21: =IF(CL21>=400000000,"A1",IF(CL21>=300000000,"A2",IF(CL21>=240000000,"A3",IF(CL21>=180000000,"A4",IF(CL21>=120000000,"A5",IF(CL21>=80000000,"A6",IF(CL21>=40000000,"A7",IF(CL21>=25000000,"B1",IF(CL21>=12000000,"B2","B3"))))))))) -> B3 | F21: 45721 | G21: 4750000 | I21: =IF(G21>0,CM21-G21,CM21-H21) -> 5250000 | J21: =CR21 -> 0 | K21: =SUM(I21:J21) -> 5250000 | L21: =IF(G21>0,G21+K21,H21+K21) -> 10000000 | M21: =IF(CE21>=11000000,80%,100%) -> 1 | N21: =ROUND(MAX(G21*70%,H21*70%,3640000),0) -> 3640000 | O21: 0 | P21: 11 | Q21: 0 | R21: 1.36 | S21: 0 | AD21: 0 | AE21: =IF(OR(BL21="M1",BL21="M2",BL21="M3",BL21="M4"),P21+R21+S21+T21+U21,0) -> 0 | AF21: =ROUND(IF($P21=0,0,IF(OR($BJ21="lương tháng",$CE21>=11000000),($L21/2-$L21/26*($CC$6-$P21))*$M21,$L21/26*$P21*$M21)),0) -> 4230769 | AG21: =ROUND(MAX((G21+I21)*M21/26*R21,(H21+I21)*M21/26*R21,G21/26*R21*150%,H21/26*R21*150%)*BK21,0) -> 523077 | AH21: =ROUND(MAX((G21+I21)*M21/26*S21,(H21+I21)*M21/26*S21,G21/26*S21*200%,H21/26*S21*200%)*BK21,0) -> 0 | AI21: =ROUND(IF(BJ21="Lương tháng",L21/26*T21,MAX((G21+I21)/26*(T21+U21)*200%+G21/26*T21,(H21+I21)/26*(T21+U21)*200%+H21/26*T21,G21/26*(T21+U21)*300%+G21/26*T21,H21/26*(T21+U21)*300%+H21/26*T21)),0) -> 0 | AJ21: =ROUND(IF((P21+Q21)=0,0,IF(BJ21="Lương tháng",MAX((G21+I21)/26*V21,(H21+I21)/26*V21),MAX(G21/26*V21,H21/26*V21))),0) -> 0 | AK21: =ROUND(IF(G21>0,G21/26*W21,H21/26*W21),0) -> 0 | AL21: =ROUND(N21/26*Y21+O21/26*Z21+MAX(G21/26*AA21,H21/26*AA21),0) -> 0 | AM21: =ROUND(IF(BJ21="Lương tháng",L21/26*AC21,L21/26*AC21+MAX((G21+I21)/26*AB21,(H21+I21)/26*AB21)),0) -> 0 | AN21: =ROUND(IF(BJ21="lương tháng",0,MAX((G21+I21)/26*AD21*30%,(H21+I21)/26*AD21*30%)*BK21),0) -> 0 | AO21: =ROUND(BM21*AE21,0) -> 0 | AP21: 0 | AQ21: =ROUND(SUM(AF21:AP21),0) -> 4753846 | AV21: =ROUND(SUM(AQ21:AT21)-AU21,0) -> 4753846 | AW21: =ROUND(IF($BH21=1,$G21*$AW$9,0),0) -> 380000 | AX21: =ROUND(IF($BH21=1,$G21*$AX$9,0),0) -> 71250 | AY21: =ROUND(IF($BH21=1,$G21*$AY$9,0),0) -> 47500 | AZ21: =SUM(AW21:AY21) -> 498750 | BA21: =ROUND(IF($BI21="1x",$G21*0.5%,0),0) -> 0 | BB21: =IF(BN21="Xem lại",0,IF(CM21<11000000,5000,IF(AND(CM21>=11000000,CM21<25000000),10000,IF(AND(CM21>=25000000,CM21<40000000),15000,IF(AND(CM21>=40000000,CM21<120000000),20000,IF(AND(CM21>=120000000,CM21<240000000),25000,30000)))))*$BB$9) -> 110000 | BD21: 0 | BE21: =ROUND(SUM(AZ21:BD21),0) -> 608750 | BF21: =ROUND(IF(AV21>BE21,AV21-BE21,0),0) -> 4145096 | BG21: =ROUND(IF(BE21>AV21,BE21-AV21,0),0) -> 0 | BH21: 1 | BI21: 0 | BJ21: =IF(AND(D21="QTNV CL",CM21>=11000000),"Lương tháng",IF(CM21>=18000000,"Lương tháng",0)) -> 0 | BK21: =IF(BJ21="Lương tháng",0,1) -> 1 | BL21: 0 | BM21: =IF(BL21="M1",13000,IF(BL21="M2",20000,IF(BL21="M3",26000,IF(BL21="M4",32000,0)))) -> 0 | BN21: =IF(AND(G21>0,(P21+Q21)>=5),"Trừ tiền","Xem lại") -> Trừ tiền | BS21: =AQ21+SUM(BO21:BR21)-AN21-AO21-SUM(BY21:CA21) -> 4753846 | BT21: 0 | BU21: =BT21*4400000 -> 0 | BV21: 11000000 | BW21: =BU21+BV21 -> 11000000 | BX21: =BS21-SUM(CC21:CD21)-CB21-AZ21-BW21 -> -6744904 | CE21: 10000000 | CG21: 0 | CH21: 0 | CJ21: =SUM(CF21:CI21) -> 0 | CK21: =CE21+CJ21 -> 10000000 | CM21: =CE21 -> 10000000 | CN21: =CF21 -> 0 | CO21: =CG21 -> 0 | CP21: =CH21 -> 0 | CQ21: =CI21 -> 0 | CR21: =SUM(CN21:CQ21) -> 0 | CS21: =CM21+CR21 -> 10000000 | CT21: Chuyên viên Kế toán | CU21: Phòng Kế toán | CV21: letuankiet6@thilogi.com.vn | CW21: Chu Lai
A22: III | B22: ="Suất ăn công nghiệp: " &"["&COUNT(A23:A23)& "]" -> Suất ăn công nghiệp: [1] | G22: =SUM(G23:G23) -> 4090000 | H22: =SUM(H23:H23) -> 0 | I22: =SUM(I23:I23) -> 2410000 | J22: =SUM(J23:J23) -> 0 | K22: =SUM(K23:K23) -> 2410000 | L22: =SUM(L23:L23) -> 6500000 | N22: =SUM(N23:N23) -> 3640000 | O22: =SUM(O23:O23) -> 0 | P22: =SUM(P23:P23) -> 12 | Q22: =SUM(Q23:Q23) -> 0 | R22: =SUM(R23:R23) -> 0 | S22: =SUM(S23:S23) -> 0 | T22: =SUM(T23:T23) -> 0 | U22: =SUM(U23:U23) -> 0 | ... BG22: =SUM(BG23:BG23) -> 0 | BI22: =SUM(BI23:BI23) -> 0 | BJ22: =SUM(BJ23:BJ23) -> 0 | BL22: =SUM(BL23:BL23) -> 0 | BM22: =SUM(BM23:BM23) -> 0 | BN22: =SUM(BN23:BN23) -> 0 | BO22: =SUM(BO23:BO23) -> 0 | BP22: =SUM(BP23:BP23) -> 0 | BQ22: =SUM(BQ23:BQ23) -> 0 | BR22: =SUM(BR23:BR23) -> 0 | BS22: =SUM(BS23:BS23) -> 3000000 | ... CV22: =SUM(CV23:CV23) -> 0
A23: =SUBTOTAL(3,$C$11:C23) -> 10 | B23: 2103590 | C23: Lê Thị Tâm | D23: THILOGI | E23: =IF(CL23>=400000000,"A1",IF(CL23>=300000000,"A2",IF(CL23>=240000000,"A3",IF(CL23>=180000000,"A4",IF(CL23>=120000000,"A5",IF(CL23>=80000000,"A6",IF(CL23>=40000000,"A7",IF(CL23>=25000000,"B1",IF(CL23>=12000000,"B2","B3"))))))))) -> B3 | F23: 44256 | G23: 4090000 | I23: =IF(G23>0,CM23-G23,CM23-H23) -> 2410000 | J23: =CR23 -> 0 | K23: =SUM(I23:J23) -> 2410000 | L23: =IF(G23>0,G23+K23,H23+K23) -> 6500000 | M23: =IF(CE23>=11000000,80%,100%) -> 1 | N23: =ROUND(MAX(G23*70%,H23*70%,3640000),0) -> 3640000 | O23: 0 | P23: 12 | Q23: 0 | R23: 0 | S23: 0 | AD23: 0 | AE23: =IF(OR(BL23="M1",BL23="M2",BL23="M3",BL23="M4"),P23+R23+S23+T23+U23,0) -> 0 | AF23: =ROUND(IF($P23=0,0,IF(OR($BJ23="lương tháng",$CE23>=11000000),($L23/2-$L23/26*($CC$6-$P23))*$M23,$L23/26*$P23*$M23)),0) -> 3000000 | AG23: =ROUND(MAX((G23+I23)*M23/26*R23,(H23+I23)*M23/26*R23,G23/26*R23*150%,H23/26*R23*150%)*BK23,0) -> 0 | AH23: =ROUND(MAX((G23+I23)*M23/26*S23,(H23+I23)*M23/26*S23,G23/26*S23*200%,H23/26*S23*200%)*BK23,0) -> 0 | AI23: =ROUND(IF(BJ23="Lương tháng",L23/26*T23,MAX((G23+I23)/26*(T23+U23)*200%+G23/26*T23,(H23+I23)/26*(T23+U23)*200%+H23/26*T23,G23/26*(T23+U23)*300%+G23/26*T23,H23/26*(T23+U23)*300%+H23/26*T23)),0) -> 0 | AJ23: =ROUND(IF((P23+Q23)=0,0,IF(BJ23="Lương tháng",MAX((G23+I23)/26*V23,(H23+I23)/26*V23),MAX(G23/26*V23,H23/26*V23))),0) -> 0 | AK23: =ROUND(IF(G23>0,G23/26*W23,H23/26*W23),0) -> 0 | AL23: =ROUND(N23/26*Y23+O23/26*Z23+MAX(G23/26*AA23,H23/26*AA23),0) -> 0 | AM23: =ROUND(IF(BJ23="Lương tháng",L23/26*AC23,L23/26*AC23+MAX((G23+I23)/26*AB23,(H23+I23)/26*AB23)),0) -> 0 | AN23: =ROUND(IF(BJ23="lương tháng",0,MAX((G23+I23)/26*AD23*30%,(H23+I23)/26*AD23*30%)*BK23),0) -> 0 | AO23: =ROUND(BM23*AE23,0) -> 0 | AP23: 0 | AQ23: =ROUND(SUM(AF23:AP23),0) -> 3000000 | AV23: =ROUND(SUM(AQ23:AT23)-AU23,0) -> 3000000 | AW23: =ROUND(IF($BH23=1,$G23*$AW$9,0),0) -> 327200 | AX23: =ROUND(IF($BH23=1,$G23*$AX$9,0),0) -> 61350 | AY23: =ROUND(IF($BH23=1,$G23*$AY$9,0),0) -> 40900 | AZ23: =SUM(AW23:AY23) -> 429450 | BA23: =ROUND(IF($BI23="1x",$G23*0.5%,0),0) -> 0 | BB23: =IF(BN23="Xem lại",0,IF(CM23<11000000,5000,IF(AND(CM23>=11000000,CM23<25000000),10000,IF(AND(CM23>=25000000,CM23<40000000),15000,IF(AND(CM23>=40000000,CM23<120000000),20000,IF(AND(CM23>=120000000,CM23<240000000),25000,30000)))))*$BB$9) -> 0 | BD23: 0 | BE23: =ROUND(SUM(AZ23:BD23),0) -> 429450 | BF23: =ROUND(IF(AV23>BE23,AV23-BE23,0),0) -> 2570550 | BG23: =ROUND(IF(BE23>AV23,BE23-AV23,0),0) -> 0 | BH23: 1 | BI23: 0 | BJ23: =IF(AND(D23="QTNV CL",CM23>=11000000),"Lương tháng",IF(CM23>=18000000,"Lương tháng",0)) -> 0 | BK23: =IF(BJ23="Lương tháng",0,1) -> 1 | BL23: 0 | BM23: =IF(BL23="M1",13000,IF(BL23="M2",20000,IF(BL23="M3",26000,IF(BL23="M4",32000,0)))) -> 0 | BN23: Xem lại | BS23: =AQ23+SUM(BO23:BR23)-AN23-AO23-SUM(BY23:CA23) -> 3000000 | BT23: 0 | BU23: =BT23*4400000 -> 0 | BV23: 11000000 | BW23: =BU23+BV23 -> 11000000 | BX23: =BS23-SUM(CC23:CD23)-CB23-AZ23-BW23 -> -8429450 | CE23: 6500000 | CF23: 0 | CG23: 0 | CH23: 0 | CJ23: =SUM(CF23:CI23) -> 0 | CK23: =CE23+CJ23 -> 6500000 | CM23: =CE23 -> 6500000 | CN23: =CF23 -> 0 | CO23: =CG23 -> 0 | CP23: =CH23 -> 0 | CQ23: =CI23 -> 0 | CR23: =SUM(CN23:CQ23) -> 0 | CS23: =CM23+CR23 -> 6500000 | CT23: Nhân viên bếp | CU23: Suất ăn công nghiệp | CV23: 0 | CW23: Chu Lai
A24: IV | B24: ="Bộ phận Hành chính &ATLĐ: " &"["&COUNT(A25:A26)& "]" -> Bộ phận Hành chính &ATLĐ: [2] | G24: =SUM(G25:G26) -> 9500000 | H24: =SUM(H25:H26) -> 0 | I24: =SUM(I25:I26) -> 11500000 | J24: =SUM(J25:J26) -> 0 | K24: =SUM(K25:K26) -> 11500000 | L24: =SUM(L25:L26) -> 21000000 | N24: =SUM(N25:N26) -> 7280000 | O24: =SUM(O25:O26) -> 0 | P24: =SUM(P25:P26) -> 24 | Q24: =SUM(Q25:Q26) -> 0 | R24: =SUM(R25:R26) -> 0.5 | S24: =SUM(S25:S26) -> 0 | T24: =SUM(T25:T26) -> 0 | U24: =SUM(U25:U26) -> 0 | ... BG24: =SUM(BG25:BG26) -> 0 | BI24: =SUM(BI25:BI26) -> 0 | BJ24: =SUM(BJ25:BJ26) -> 0 | BL24: =SUM(BL25:BL26) -> 0 | BM24: =SUM(BM25:BM26) -> 0 | BN24: =SUM(BN25:BN26) -> 0 | BO24: =SUM(BO25:BO26) -> 0 | BP24: =SUM(BP25:BP26) -> 0 | BQ24: =SUM(BQ25:BQ26) -> 0 | BR24: =SUM(BR25:BR26) -> 0 | BS24: =SUM(BS25:BS26) -> 8846154 | ... CV24: =SUM(CV25:CV26) -> 0
A25: =SUBTOTAL(3,$C$11:C25) -> 11 | B25: 24041185 | C25: Cao Thị Thùy Linh | D25: THILOGI | E25: =IF(CL25>=400000000,"A1",IF(CL25>=300000000,"A2",IF(CL25>=240000000,"A3",IF(CL25>=180000000,"A4",IF(CL25>=120000000,"A5",IF(CL25>=80000000,"A6",IF(CL25>=40000000,"A7",IF(CL25>=25000000,"B1",IF(CL25>=12000000,"B2","B3"))))))))) -> B3 | F25: 45399 | G25: 4750000 | I25: =IF(G25>0,CM25-G25,CM25-H25) -> 6250000 | J25: =CR25 -> 0 | K25: =SUM(I25:J25) -> 6250000 | L25: =IF(G25>0,G25+K25,H25+K25) -> 11000000 | M25: =IF(CE25>=11000000,80%,100%) -> 0.8 | N25: =ROUND(MAX(G25*70%,H25*70%,3640000),0) -> 3640000 | O25: 0 | P25: 12 | Q25: 0 | R25: 0.5 | S25: 0 | AD25: 0 | AE25: =IF(OR(BL25="M1",BL25="M2",BL25="M3",BL25="M4"),P25+R25+S25+T25+U25,0) -> 0 | AF25: =ROUND(IF($P25=0,0,IF(OR($BJ25="lương tháng",$CE25>=11000000),($L25/2-$L25/26*($CC$6-$P25))*$M25,$L25/26*$P25*$M25)),0) -> 4061538 | AG25: =ROUND(MAX((G25+I25)*M25/26*R25,(H25+I25)*M25/26*R25,G25/26*R25*150%,H25/26*R25*150%)*BK25,0) -> 169231 | AH25: =ROUND(MAX((G25+I25)*M25/26*S25,(H25+I25)*M25/26*S25,G25/26*S25*200%,H25/26*S25*200%)*BK25,0) -> 0 | AI25: =ROUND(IF(BJ25="Lương tháng",L25/26*T25,MAX((G25+I25)/26*(T25+U25)*200%+G25/26*T25,(H25+I25)/26*(T25+U25)*200%+H25/26*T25,G25/26*(T25+U25)*300%+G25/26*T25,H25/26*(T25+U25)*300%+H25/26*T25)),0) -> 0 | AJ25: =ROUND(IF((P25+Q25)=0,0,IF(BJ25="Lương tháng",MAX((G25+I25)/26*V25,(H25+I25)/26*V25),MAX(G25/26*V25,H25/26*V25))),0) -> 0 | AK25: =ROUND(IF(G25>0,G25/26*W25,H25/26*W25),0) -> 0 | AL25: =ROUND(N25/26*Y25+O25/26*Z25+MAX(G25/26*AA25,H25/26*AA25),0) -> 0 | AM25: =ROUND(IF(BJ25="Lương tháng",L25/26*AC25,L25/26*AC25+MAX((G25+I25)/26*AB25,(H25+I25)/26*AB25)),0) -> 0 | AN25: =ROUND(IF(BJ25="lương tháng",0,MAX((G25+I25)/26*AD25*30%,(H25+I25)/26*AD25*30%)*BK25),0) -> 0 | AO25: =ROUND(BM25*AE25,0) -> 0 | AP25: 0 | AQ25: =ROUND(SUM(AF25:AP25),0) -> 4230769 | AV25: =ROUND(SUM(AQ25:AT25)-AU25,0) -> 4230769 | AW25: =ROUND(IF($BH25=1,$G25*$AW$9,0),0) -> 380000 | AX25: =ROUND(IF($BH25=1,$G25*$AX$9,0),0) -> 71250 | AY25: =ROUND(IF($BH25=1,$G25*$AY$9,0),0) -> 47500 | AZ25: =SUM(AW25:AY25) -> 498750 | BA25: =ROUND(IF($BI25="1x",$G25*0.5%,0),0) -> 23750 | BB25: =IF(BN25="Xem lại",0,IF(CM25<11000000,5000,IF(AND(CM25>=11000000,CM25<25000000),10000,IF(AND(CM25>=25000000,CM25<40000000),15000,IF(AND(CM25>=40000000,CM25<120000000),20000,IF(AND(CM25>=120000000,CM25<240000000),25000,30000)))))*$BB$9) -> 220000 | BD25: 0 | BE25: =ROUND(SUM(AZ25:BD25),0) -> 742500 | BF25: =ROUND(IF(AV25>BE25,AV25-BE25,0),0) -> 3488269 | BG25: =ROUND(IF(BE25>AV25,BE25-AV25,0),0) -> 0 | BH25: 1 | BI25: 1x | BJ25: =IF(AND(D25="QTNV CL",CM25>=11000000),"Lương tháng",IF(CM25>=18000000,"Lương tháng",0)) -> 0 | BK25: =IF(BJ25="Lương tháng",0,1) -> 1 | BL25: 0 | BM25: =IF(BL25="M1",13000,IF(BL25="M2",20000,IF(BL25="M3",26000,IF(BL25="M4",32000,0)))) -> 0 | BN25: =IF(AND(G25>0,(P25+Q25)>=5),"Trừ tiền","Xem lại") -> Trừ tiền | BS25: =AQ25+SUM(BO25:BR25)-AN25-AO25-SUM(BY25:CA25) -> 4230769 | BT25: 1 | BU25: =BT25*4400000 -> 4400000 | BV25: 11000000 | BW25: =BU25+BV25 -> 15400000 | BX25: =BS25-SUM(CC25:CD25)-CB25-AZ25-BW25 -> -11667981 | CE25: 11000000 | CF25: 0 | CJ25: =SUM(CF25:CI25) -> 0 | CK25: =CE25+CJ25 -> 11000000 | CM25: =CE25 -> 11000000 | CN25: =CF25 -> 0 | CR25: =SUM(CN25:CQ25) -> 0 | CS25: =CM25+CR25 -> 11000000 | CT25: Chuyên viên Hành chính | CU25: Phòng Hành chính | CV25: caothithuylinh@thilogi.com.vn | CW25: Chu Lai
A26: =SUBTOTAL(3,$C$11:C26) -> 12 | B26: 2210271 | C26: Huỳnh Văn Nhựt | D26: THILOGI | E26: =IF(CL26>=400000000,"A1",IF(CL26>=300000000,"A2",IF(CL26>=240000000,"A3",IF(CL26>=180000000,"A4",IF(CL26>=120000000,"A5",IF(CL26>=80000000,"A6",IF(CL26>=40000000,"A7",IF(CL26>=25000000,"B1",IF(CL26>=12000000,"B2","B3"))))))))) -> B3 | F26: 44840 | G26: 4750000 | I26: =IF(G26>0,CM26-G26,CM26-H26) -> 5250000 | J26: =CR26 -> 0 | K26: =SUM(I26:J26) -> 5250000 | L26: =IF(G26>0,G26+K26,H26+K26) -> 10000000 | M26: =IF(CE26>=11000000,80%,100%) -> 1 | N26: =ROUND(MAX(G26*70%,H26*70%,3640000),0) -> 3640000 | O26: 0 | P26: 12 | Q26: 0 | R26: 0 | S26: 0 | AD26: 0 | AE26: =IF(OR(BL26="M1",BL26="M2",BL26="M3",BL26="M4"),P26+R26+S26+T26+U26,0) -> 0 | AF26: =ROUND(IF($P26=0,0,IF(OR($BJ26="lương tháng",$CE26>=11000000),($L26/2-$L26/26*($CC$6-$P26))*$M26,$L26/26*$P26*$M26)),0) -> 4615385 | AG26: =ROUND(MAX((G26+I26)*M26/26*R26,(H26+I26)*M26/26*R26,G26/26*R26*150%,H26/26*R26*150%)*BK26,0) -> 0 | AH26: =ROUND(MAX((G26+I26)*M26/26*S26,(H26+I26)*M26/26*S26,G26/26*S26*200%,H26/26*S26*200%)*BK26,0) -> 0 | AI26: =ROUND(IF(BJ26="Lương tháng",L26/26*T26,MAX((G26+I26)/26*(T26+U26)*200%+G26/26*T26,(H26+I26)/26*(T26+U26)*200%+H26/26*T26,G26/26*(T26+U26)*300%+G26/26*T26,H26/26*(T26+U26)*300%+H26/26*T26)),0) -> 0 | AJ26: =ROUND(IF((P26+Q26)=0,0,IF(BJ26="Lương tháng",MAX((G26+I26)/26*V26,(H26+I26)/26*V26),MAX(G26/26*V26,H26/26*V26))),0) -> 0 | AK26: =ROUND(IF(G26>0,G26/26*W26,H26/26*W26),0) -> 0 | AL26: =ROUND(N26/26*Y26+O26/26*Z26+MAX(G26/26*AA26,H26/26*AA26),0) -> 0 | AM26: =ROUND(IF(BJ26="Lương tháng",L26/26*AC26,L26/26*AC26+MAX((G26+I26)/26*AB26,(H26+I26)/26*AB26)),0) -> 0 | AN26: =ROUND(IF(BJ26="lương tháng",0,MAX((G26+I26)/26*AD26*30%,(H26+I26)/26*AD26*30%)*BK26),0) -> 0 | AO26: =ROUND(BM26*AE26,0) -> 0 | AP26: 0 | AQ26: =ROUND(SUM(AF26:AP26),0) -> 4615385 | AV26: =ROUND(SUM(AQ26:AT26)-AU26,0) -> 4615385 | AW26: =ROUND(IF($BH26=1,$G26*$AW$9,0),0) -> 380000 | AX26: =ROUND(IF($BH26=1,$G26*$AX$9,0),0) -> 71250 | AY26: =ROUND(IF($BH26=1,$G26*$AY$9,0),0) -> 47500 | AZ26: =SUM(AW26:AY26) -> 498750 | BA26: =ROUND(IF($BI26="1x",$G26*0.5%,0),0) -> 23750 | BB26: =IF(BN26="Xem lại",0,IF(CM26<11000000,5000,IF(AND(CM26>=11000000,CM26<25000000),10000,IF(AND(CM26>=25000000,CM26<40000000),15000,IF(AND(CM26>=40000000,CM26<120000000),20000,IF(AND(CM26>=120000000,CM26<240000000),25000,30000)))))*$BB$9) -> 110000 | BD26: 0 | BE26: =ROUND(SUM(AZ26:BD26),0) -> 632500 | BF26: =ROUND(IF(AV26>BE26,AV26-BE26,0),0) -> 3982885 | BG26: =ROUND(IF(BE26>AV26,BE26-AV26,0),0) -> 0 | BH26: 1 | BI26: 1x | BJ26: =IF(AND(D26="QTNV CL",CM26>=11000000),"Lương tháng",IF(CM26>=18000000,"Lương tháng",0)) -> 0 | BK26: =IF(BJ26="Lương tháng",0,1) -> 1 | BL26: 0 | BM26: =IF(BL26="M1",13000,IF(BL26="M2",20000,IF(BL26="M3",26000,IF(BL26="M4",32000,0)))) -> 0 | BN26: =IF(AND(G26>0,(P26+Q26)>=5),"Trừ tiền","Xem lại") -> Trừ tiền | BS26: =AQ26+SUM(BO26:BR26)-AN26-AO26-SUM(BY26:CA26) -> 4615385 | BT26: 2 | BU26: =BT26*4400000 -> 8800000 | BV26: 11000000 | BW26: =BU26+BV26 -> 19800000 | BX26: =BS26-SUM(CC26:CD26)-CB26-AZ26-BW26 -> -15683365 | CE26: 10000000 | CF26: 0 | CG26: 0 | CH26: 0 | CJ26: =SUM(CF26:CI26) -> 0 | CK26: =CE26+CJ26 -> 10000000 | CM26: =CE26 -> 10000000 | CN26: =CF26 -> 0 | CO26: =CG26 -> 0 | CP26: =CH26 -> 0 | CQ26: =CI26 -> 0 | CR26: =SUM(CN26:CQ26) -> 0 | CS26: =CM26+CR26 -> 10000000 | CT26: Nhân viên An toàn lao động | CU26: Phòng Quản lý phương tiện thiết bị & An toàn | CV26: huynhvannhut2@thilogi.com.vn | CW26: Chu Lai
A27: V | B27: ="Phòng Kế hoạch: " &"["&COUNT(A28:A28)& "]" -> Phòng Kế hoạch: [1] | G27: =SUM(G28:G28) -> 4750000 | H27: =SUM(H28:H28) -> 0 | I27: =SUM(I28:I28) -> 5750000 | J27: =SUM(J28:J28) -> 0 | K27: =SUM(K28:K28) -> 5750000 | L27: =SUM(L28:L28) -> 10500000 | N27: =SUM(N28:N28) -> 3640000 | O27: =SUM(O28:O28) -> 0 | P27: =SUM(P28:P28) -> 12 | Q27: =SUM(Q28:Q28) -> 0 | R27: =SUM(R28:R28) -> 0 | S27: =SUM(S28:S28) -> 0 | T27: =SUM(T28:T28) -> 0 | U27: =SUM(U28:U28) -> 0 | ... BG27: =SUM(BG28:BG28) -> 0 | BI27: =SUM(BI28:BI28) -> 0 | BJ27: =SUM(BJ28:BJ28) -> 0 | BL27: =SUM(BL28:BL28) -> 0 | BM27: =SUM(BM28:BM28) -> 0 | BN27: =SUM(BN28:BN28) -> 0 | BO27: =SUM(BO28:BO28) -> 0 | BP27: =SUM(BP28:BP28) -> 0 | BQ27: =SUM(BQ28:BQ28) -> 0 | BR27: =SUM(BR28:BR28) -> 0 | BS27: =SUM(BS28:BS28) -> 4846154 | ... CV27: =SUM(CV28:CV28) -> 0
A28: =SUBTOTAL(3,$C$11:C28) -> 13 | B28: 24110112 | C28: Lê Triệu My | D28: THILOGI | E28: =IF(CL28>=400000000,"A1",IF(CL28>=300000000,"A2",IF(CL28>=240000000,"A3",IF(CL28>=180000000,"A4",IF(CL28>=120000000,"A5",IF(CL28>=80000000,"A6",IF(CL28>=40000000,"A7",IF(CL28>=25000000,"B1",IF(CL28>=12000000,"B2","B3"))))))))) -> B3 | F28: 45597 | G28: 4750000 | I28: =IF(G28>0,CM28-G28,CM28-H28) -> 5750000 | J28: =CR28 -> 0 | K28: =SUM(I28:J28) -> 5750000 | L28: =IF(G28>0,G28+K28,H28+K28) -> 10500000 | M28: =IF(CE28>=11000000,80%,100%) -> 1 | N28: =ROUND(MAX(G28*70%,H28*70%,3640000),0) -> 3640000 | O28: 0 | P28: 12 | Q28: 0 | R28: 0 | S28: 0 | AD28: 0 | AE28: =IF(OR(BL28="M1",BL28="M2",BL28="M3",BL28="M4"),P28+R28+S28+T28+U28,0) -> 0 | AF28: =ROUND(IF($P28=0,0,IF(OR($BJ28="lương tháng",$CE28>=11000000),($L28/2-$L28/26*($CC$6-$P28))*$M28,$L28/26*$P28*$M28)),0) -> 4846154 | AG28: =ROUND(MAX((G28+I28)*M28/26*R28,(H28+I28)*M28/26*R28,G28/26*R28*150%,H28/26*R28*150%)*BK28,0) -> 0 | AH28: =ROUND(MAX((G28+I28)*M28/26*S28,(H28+I28)*M28/26*S28,G28/26*S28*200%,H28/26*S28*200%)*BK28,0) -> 0 | AI28: =ROUND(IF(BJ28="Lương tháng",L28/26*T28,MAX((G28+I28)/26*(T28+U28)*200%+G28/26*T28,(H28+I28)/26*(T28+U28)*200%+H28/26*T28,G28/26*(T28+U28)*300%+G28/26*T28,H28/26*(T28+U28)*300%+H28/26*T28)),0) -> 0 | AJ28: =ROUND(IF((P28+Q28)=0,0,IF(BJ28="Lương tháng",MAX((G28+I28)/26*V28,(H28+I28)/26*V28),MAX(G28/26*V28,H28/26*V28))),0) -> 0 | AK28: =ROUND(IF(G28>0,G28/26*W28,H28/26*W28),0) -> 0 | AL28: =ROUND(N28/26*Y28+O28/26*Z28+MAX(G28/26*AA28,H28/26*AA28),0) -> 0 | AM28: =ROUND(IF(BJ28="Lương tháng",L28/26*AC28,L28/26*AC28+MAX((G28+I28)/26*AB28,(H28+I28)/26*AB28)),0) -> 0 | AN28: =ROUND(IF(BJ28="lương tháng",0,MAX((G28+I28)/26*AD28*30%,(H28+I28)/26*AD28*30%)*BK28),0) -> 0 | AO28: =ROUND(BM28*AE28,0) -> 0 | AP28: 0 | AQ28: =ROUND(SUM(AF28:AP28),0) -> 4846154 | AV28: =ROUND(SUM(AQ28:AT28)-AU28,0) -> 4846154 | AW28: =ROUND(IF($BH28=1,$G28*$AW$9,0),0) -> 380000 | AX28: =ROUND(IF($BH28=1,$G28*$AX$9,0),0) -> 71250 | AY28: =ROUND(IF($BH28=1,$G28*$AY$9,0),0) -> 47500 | AZ28: =SUM(AW28:AY28) -> 498750 | BA28: =ROUND(IF($BI28="1x",$G28*0.5%,0),0) -> 23750 | BB28: =IF(BN28="Xem lại",0,IF(CM28<11000000,5000,IF(AND(CM28>=11000000,CM28<25000000),10000,IF(AND(CM28>=25000000,CM28<40000000),15000,IF(AND(CM28>=40000000,CM28<120000000),20000,IF(AND(CM28>=120000000,CM28<240000000),25000,30000)))))*$BB$9) -> 110000 | BD28: 0 | BE28: =ROUND(SUM(AZ28:BD28),0) -> 632500 | BF28: =ROUND(IF(AV28>BE28,AV28-BE28,0),0) -> 4213654 | BG28: =ROUND(IF(BE28>AV28,BE28-AV28,0),0) -> 0 | BH28: 1 | BI28: 1x | BJ28: =IF(AND(D28="QTNV CL",CM28>=11000000),"Lương tháng",IF(CM28>=18000000,"Lương tháng",0)) -> 0 | BK28: =IF(BJ28="Lương tháng",0,1) -> 1 | BL28: 0 | BM28: =IF(BL28="M1",13000,IF(BL28="M2",20000,IF(BL28="M3",26000,IF(BL28="M4",32000,0)))) -> 0 | BN28: =IF(AND(G28>0,(P28+Q28)>=5),"Trừ tiền","Xem lại") -> Trừ tiền | BS28: =AQ28+SUM(BO28:BR28)-AN28-AO28-SUM(BY28:CA28) -> 4846154 | BT28: 0 | BU28: =BT28*4400000 -> 0 | BV28: 11000000 | BW28: =BU28+BV28 -> 11000000 | BX28: =BS28-SUM(CC28:CD28)-CB28-AZ28-BW28 -> -6652596 | CE28: 10500000 | CJ28: =SUM(CF28:CI28) -> 0 | CK28: =CE28+CJ28 -> 10500000 | CM28: =CE28 -> 10500000 | CR28: =SUM(CN28:CQ28) -> 0 | CS28: =CM28+CR28 -> 10500000 | CT28: Chuyên viên Kế hoạch tổng hợp | CU28: Phòng Kế hoạch | CV28: letrieumy@thilogi.com.vn | CW28: Chu Lai
A29: VI | B29: ="GNVC Ô TÔ & LKPT: " &"["&COUNT(A30:A267)& "]" -> GNVC Ô TÔ & LKPT: [220] | G29: =G30+G43+G63 -> 980310000 | H29: =H30+H43+H63 -> 14250000 | I29: =I30+I43+I63 -> 984740000 | J29: =J30+J43+J63 -> 131470000 | K29: =K30+K43+K63 -> 1116210000 | L29: =L30+L43+L63 -> 2110770000 | N29: =N30+N43+N63 -> 814632000 | O29: =O30+O43+O63 -> 0 | P29: =P30+P43+P63 -> 1342.5 | Q29: =Q30+Q43+Q63 -> 1501 | R29: =R30+R43+R63 -> 67.27 | S29: =S30+S43+S63 -> 0 | T29: =T30+T43+T63 -> 0 | U29: =U30+U43+U63 -> 0 | ... BG29: =BG30+BG43+BG63 -> 1433200 | BI29: =BI30+BI43+BI63 -> 0 | BJ29: =BJ30+BJ43+BJ63 -> 0 | BL29: =BL30+BL43+BL63 -> 0 | BM29: =BM30+BM43+BM63 -> 476000 | BN29: =BN30+BN43+BN63 -> 0 | BO29: =BO30+BO43+BO63 -> 0 | BP29: =BP30+BP43+BP63 -> 0 | BQ29: =BQ30+BQ43+BQ63 -> 0 | BR29: =BR30+BR43+BR63 -> 0 | BS29: =BS30+BS43+BS63 -> 544595896 | ... CV29: =CV30+CV43+CV63 -> 0
A30: VI.1 | B30: ="Phòng Quản lý kho xe và hàng hóa: " &"["&COUNT(A31:A42)& "]" -> Phòng Quản lý kho xe và hàng hóa: [12] | G30: =SUM(G31:G42) -> 66670000 | H30: =SUM(H31:H42) -> 0 | I30: =SUM(I31:I42) -> 73030000 | J30: =SUM(J31:J42) -> 11320000 | K30: =SUM(K31:K42) -> 84350000 | L30: =SUM(L31:L42) -> 151020000 | N30: =SUM(N31:N42) -> 49805000 | O30: =SUM(O31:O42) -> 0 | P30: =SUM(P31:P42) -> 152 | Q30: =SUM(Q31:Q42) -> 0 | R30: =SUM(R31:R42) -> 27.39 | S30: =SUM(S31:S42) -> 0 | T30: =SUM(T31:T42) -> 0 | U30: =SUM(U31:U42) -> 0 | ... BG30: =SUM(BG31:BG42) -> 0 | BI30: =SUM(BI31:BI42) -> 0 | BJ30: =SUM(BJ31:BJ42) -> 0 | BL30: =SUM(BL31:BL42) -> 0 | BM30: =SUM(BM31:BM42) -> 130000 | BN30: =SUM(BN31:BN42) -> 0 | BO30: =SUM(BO31:BO42) -> 0 | BP30: =SUM(BP31:BP42) -> 0 | BQ30: =SUM(BQ31:BQ42) -> 0 | BR30: =SUM(BR31:BR42) -> 0 | BS30: =SUM(BS31:BS42) -> 73256808 | ... CV30: =SUM(CV31:CV42) -> 0
A31: =SUBTOTAL(3,$C$11:C31) -> 14 | B31: 0905265 | C31: Trương Bảo Sa | D31: THILOGI | E31: =IF(CL31>=400000000,"A1",IF(CL31>=300000000,"A2",IF(CL31>=240000000,"A3",IF(CL31>=180000000,"A4",IF(CL31>=120000000,"A5",IF(CL31>=80000000,"A6",IF(CL31>=40000000,"A7",IF(CL31>=25000000,"B1",IF(CL31>=12000000,"B2","B3"))))))))) -> B3 | F31: 39962 | G31: 7710000 | I31: =IF(G31>0,CM31-G31,CM31-H31) -> 12290000 | J31: =CR31 -> 1000000 | K31: =SUM(I31:J31) -> 13290000 | L31: =IF(G31>0,G31+K31,H31+K31) -> 21000000 | M31: =IF(CE31>=11000000,80%,100%) -> 0.8 | N31: =ROUND(MAX(G31*70%,H31*70%,3640000),0) -> 5397000 | O31: 0 | P31: 12 | Q31: 0 | R31: 0 | S31: 0 | AD31: 0 | AE31: =IF(OR(BL31="M1",BL31="M2",BL31="M3",BL31="M4"),P31+R31+S31+T31+U31,0) -> 0 | AF31: =ROUND(IF($P31=0,0,IF(OR($BJ31="lương tháng",$CE31>=11000000),($L31/2-$L31/26*($CC$6-$P31))*$M31,$L31/26*$P31*$M31)),0) -> 7753846 | AG31: =ROUND(MAX((G31+I31)*M31/26*R31,(H31+I31)*M31/26*R31,G31/26*R31*150%,H31/26*R31*150%)*BK31,0) -> 0 | AH31: =ROUND(MAX((G31+I31)*M31/26*S31,(H31+I31)*M31/26*S31,G31/26*S31*200%,H31/26*S31*200%)*BK31,0) -> 0 | AI31: =ROUND(IF(BJ31="Lương tháng",L31/26*T31,MAX((G31+I31)/26*(T31+U31)*200%+G31/26*T31,(H31+I31)/26*(T31+U31)*200%+H31/26*T31,G31/26*(T31+U31)*300%+G31/26*T31,H31/26*(T31+U31)*300%+H31/26*T31)),0) -> 0 | AJ31: =ROUND(IF((P31+Q31)=0,0,IF(BJ31="Lương tháng",MAX((G31+I31)/26*V31,(H31+I31)/26*V31),MAX(G31/26*V31,H31/26*V31))),0) -> 0 | AK31: =ROUND(IF(G31>0,G31/26*W31,H31/26*W31),0) -> 0 | AL31: =ROUND(N31/26*Y31+O31/26*Z31+MAX(G31/26*AA31,H31/26*AA31),0) -> 0 | AM31: =ROUND(IF(BJ31="Lương tháng",L31/26*AC31,L31/26*AC31+MAX((G31+I31)/26*AB31,(H31+I31)/26*AB31)),0) -> 0 | AN31: =ROUND(IF(BJ31="lương tháng",0,MAX((G31+I31)/26*AD31*30%,(H31+I31)/26*AD31*30%)*BK31),0) -> 0 | AO31: =ROUND(BM31*AE31,0) -> 0 | AP31: 0 | AQ31: =ROUND(SUM(AF31:AP31),0) -> 7753846 | AV31: =ROUND(SUM(AQ31:AT31)-AU31,0) -> 7753846 | AW31: =ROUND(IF($BH31=1,$G31*$AW$9,0),0) -> 616800 | AX31: =ROUND(IF($BH31=1,$G31*$AX$9,0),0) -> 115650 | AY31: =ROUND(IF($BH31=1,$G31*$AY$9,0),0) -> 77100 | AZ31: =SUM(AW31:AY31) -> 809550 | BA31: =ROUND(IF($BI31="1x",$G31*0.5%,0),0) -> 38550 | BB31: =IF(BN31="Xem lại",0,IF(CM31<11000000,5000,IF(AND(CM31>=11000000,CM31<25000000),10000,IF(AND(CM31>=25000000,CM31<40000000),15000,IF(AND(CM31>=40000000,CM31<120000000),20000,IF(AND(CM31>=120000000,CM31<240000000),25000,30000)))))*$BB$9) -> 220000 | BD31: 0 | BE31: =ROUND(SUM(AZ31:BD31),0) -> 1068100 | BF31: =ROUND(IF(AV31>BE31,AV31-BE31,0),0) -> 6685746 | BG31: =ROUND(IF(BE31>AV31,BE31-AV31,0),0) -> 0 | BH31: 1 | BI31: 1x | BJ31: =IF(AND(D31="QTNV CL",CM31>=11000000),"Lương tháng",IF(CM31>=18000000,"Lương tháng",0)) -> Lương tháng | BK31: =IF(BJ31="Lương tháng",0,1) -> 0 | BL31: 0 | BM31: =IF(BL31="M1",13000,IF(BL31="M2",20000,IF(BL31="M3",26000,IF(BL31="M4",32000,0)))) -> 0 | BN31: =IF(AND(G31>0,(P31+Q31)>=5),"Trừ tiền","Xem lại") -> Trừ tiền | BS31: =AQ31+SUM(BO31:BR31)-AN31-AO31-SUM(BY31:CA31) -> 7753846 | BT31: 2 | BU31: =BT31*4400000 -> 8800000 | BV31: 11000000 | BW31: =BU31+BV31 -> 19800000 | BX31: =BS31-SUM(CC31:CD31)-CB31-AZ31-BW31 -> -12855704 | CE31: 20000000 | CF31: =CE31*5% -> 1000000 | CG31: 0 | CH31: 0 | CJ31: =SUM(CF31:CI31) -> 1000000 | CK31: =CE31+CJ31 -> 21000000 | CM31: =CE31 -> 20000000 | CN31: =CF31 -> 1000000 | CO31: =CG31 -> 0 | CP31: =CH31 -> 0 | CQ31: =CI31 -> 0 | CR31: =SUM(CN31:CQ31) -> 1000000 | CS31: =CM31+CR31 -> 21000000 | CT31: Phó phòng Quản lý kho xe & LKPT | CU31: Phòng Nghiệp vụ vận tải | CV31: truongbaosa@thilogi.com.vn | CW31: Chu Lai
A32: =SUBTOTAL(3,$C$11:C32) -> 15 | B32: 0912056 | C32: Trần Văn Trung | D32: THILOGI | E32: =IF(CL32>=400000000,"A1",IF(CL32>=300000000,"A2",IF(CL32>=240000000,"A3",IF(CL32>=180000000,"A4",IF(CL32>=120000000,"A5",IF(CL32>=80000000,"A6",IF(CL32>=40000000,"A7",IF(CL32>=25000000,"B1",IF(CL32>=12000000,"B2","B3"))))))))) -> B3 | F32: 40154 | G32: 7340000 | I32: =IF(G32>0,CM32-G32,CM32-H32) -> 10660000 | J32: =CR32 -> 1800000 | K32: =SUM(I32:J32) -> 12460000 | L32: =IF(G32>0,G32+K32,H32+K32) -> 19800000 | M32: =IF(CE32>=11000000,80%,100%) -> 0.8 | N32: =ROUND(MAX(G32*70%,H32*70%,3640000),0) -> 5138000 | O32: 0 | P32: 12 | Q32: 0 | R32: 0 | S32: 0 | AD32: 0 | AE32: =IF(OR(BL32="M1",BL32="M2",BL32="M3",BL32="M4"),P32+R32+S32+T32+U32,0) -> 0 | AF32: =ROUND(IF($P32=0,0,IF(OR($BJ32="lương tháng",$CE32>=11000000),($L32/2-$L32/26*($CC$6-$P32))*$M32,$L32/26*$P32*$M32)),0) -> 7310769 | AG32: =ROUND(MAX((G32+I32)*M32/26*R32,(H32+I32)*M32/26*R32,G32/26*R32*150%,H32/26*R32*150%)*BK32,0) -> 0 | AH32: =ROUND(MAX((G32+I32)*M32/26*S32,(H32+I32)*M32/26*S32,G32/26*S32*200%,H32/26*S32*200%)*BK32,0) -> 0 | AI32: =ROUND(IF(BJ32="Lương tháng",L32/26*T32,MAX((G32+I32)/26*(T32+U32)*200%+G32/26*T32,(H32+I32)/26*(T32+U32)*200%+H32/26*T32,G32/26*(T32+U32)*300%+G32/26*T32,H32/26*(T32+U32)*300%+H32/26*T32)),0) -> 0 | AJ32: =ROUND(IF((P32+Q32)=0,0,IF(BJ32="Lương tháng",MAX((G32+I32)/26*V32,(H32+I32)/26*V32),MAX(G32/26*V32,H32/26*V32))),0) -> 0 | AK32: =ROUND(IF(G32>0,G32/26*W32,H32/26*W32),0) -> 0 | AL32: =ROUND(N32/26*Y32+O32/26*Z32+MAX(G32/26*AA32,H32/26*AA32),0) -> 0 | AM32: =ROUND(IF(BJ32="Lương tháng",L32/26*AC32,L32/26*AC32+MAX((G32+I32)/26*AB32,(H32+I32)/26*AB32)),0) -> 0 | AN32: =ROUND(IF(BJ32="lương tháng",0,MAX((G32+I32)/26*AD32*30%,(H32+I32)/26*AD32*30%)*BK32),0) -> 0 | AO32: =ROUND(BM32*AE32,0) -> 0 | AP32: 0 | AQ32: =ROUND(SUM(AF32:AP32),0) -> 7310769 | AV32: =ROUND(SUM(AQ32:AT32)-AU32,0) -> 7310769 | AW32: =ROUND(IF($BH32=1,$G32*$AW$9,0),0) -> 587200 | AX32: =ROUND(IF($BH32=1,$G32*$AX$9,0),0) -> 110100 | AY32: =ROUND(IF($BH32=1,$G32*$AY$9,0),0) -> 73400 | AZ32: =SUM(AW32:AY32) -> 770700 | BA32: =ROUND(IF($BI32="1x",$G32*0.5%,0),0) -> 36700 | BB32: =IF(BN32="Xem lại",0,IF(CM32<11000000,5000,IF(AND(CM32>=11000000,CM32<25000000),10000,IF(AND(CM32>=25000000,CM32<40000000),15000,IF(AND(CM32>=40000000,CM32<120000000),20000,IF(AND(CM32>=120000000,CM32<240000000),25000,30000)))))*$BB$9) -> 220000 | BD32: 0 | BE32: =ROUND(SUM(AZ32:BD32),0) -> 1027400 | BF32: =ROUND(IF(AV32>BE32,AV32-BE32,0),0) -> 6283369 | BG32: =ROUND(IF(BE32>AV32,BE32-AV32,0),0) -> 0 | BH32: 1 | BI32: 1x | BJ32: =IF(AND(D32="QTNV CL",CM32>=11000000),"Lương tháng",IF(CM32>=18000000,"Lương tháng",0)) -> Lương tháng | BK32: =IF(BJ32="Lương tháng",0,1) -> 0 | BL32: 0 | BM32: =IF(BL32="M1",13000,IF(BL32="M2",20000,IF(BL32="M3",26000,IF(BL32="M4",32000,0)))) -> 0 | BN32: =IF(AND(G32>0,(P32+Q32)>=5),"Trừ tiền","Xem lại") -> Trừ tiền | BS32: =AQ32+SUM(BO32:BR32)-AN32-AO32-SUM(BY32:CA32) -> 7310769 | BT32: 1 | BU32: =BT32*4400000 -> 4400000 | BV32: 11000000 | BW32: =BU32+BV32 -> 15400000 | BX32: =BS32-SUM(CC32:CD32)-CB32-AZ32-BW32 -> -8859931 | CE32: 18000000 | CF32: =CE32*10% -> 1800000 | CG32: 0 | CH32: 0 | CJ32: =SUM(CF32:CI32) -> 1800000 | CK32: =CE32+CJ32 -> 19800000 | CM32: =CE32 -> 18000000 | CN32: =CF32 -> 1800000 | CO32: =CG32 -> 0 | CP32: =CH32 -> 0 | CQ32: =CI32 -> 0 | CR32: =SUM(CN32:CQ32) -> 1800000 | CS32: =CM32+CR32 -> 19800000 | CT32: Trưởng bộ phận Giao nhận hàng hóa | CU32: Bộ phận GNVC Hàng hóa Thaco | CV32: tranvantrung1@thilogi.com.vn | CW32: Chu Lai
A33: =SUBTOTAL(3,$C$11:C33) -> 16 | B33: 0804029 | C33: Nguyễn Văn Tấn | D33: THILOGI | E33: =IF(CL33>=400000000,"A1",IF(CL33>=300000000,"A2",IF(CL33>=240000000,"A3",IF(CL33>=180000000,"A4",IF(CL33>=120000000,"A5",IF(CL33>=80000000,"A6",IF(CL33>=40000000,"A7",IF(CL33>=25000000,"B1",IF(CL33>=12000000,"B2","B3"))))))))) -> B3 | F33: 39547 | G33: 6640000 | I33: =IF(G33>0,CM33-G33,CM33-H33) -> 7860000 | J33: =CR33 -> 1450000 | K33: =SUM(I33:J33) -> 9310000 | L33: =IF(G33>0,G33+K33,H33+K33) -> 15950000 | M33: =IF(CE33>=11000000,80%,100%) -> 0.8 | N33: =ROUND(MAX(G33*70%,H33*70%,3640000),0) -> 4648000 | O33: 0 | P33: 13 | Q33: 0 | R33: 0.5 | S33: 0 | AD33: 0 | AE33: =IF(OR(BL33="M1",BL33="M2",BL33="M3",BL33="M4"),P33+R33+S33+T33+U33,0) -> 13.5 | AF33: =ROUND(IF($P33=0,0,IF(OR($BJ33="lương tháng",$CE33>=11000000),($L33/2-$L33/26*($CC$6-$P33))*$M33,$L33/26*$P33*$M33)),0) -> 6380000 | AG33: =ROUND(MAX((G33+I33)*M33/26*R33,(H33+I33)*M33/26*R33,G33/26*R33*150%,H33/26*R33*150%)*BK33,0) -> 223077 | AH33: =ROUND(MAX((G33+I33)*M33/26*S33,(H33+I33)*M33/26*S33,G33/26*S33*200%,H33/26*S33*200%)*BK33,0) -> 0 | AI33: =ROUND(IF(BJ33="Lương tháng",L33/26*T33,MAX((G33+I33)/26*(T33+U33)*200%+G33/26*T33,(H33+I33)/26*(T33+U33)*200%+H33/26*T33,G33/26*(T33+U33)*300%+G33/26*T33,H33/26*(T33+U33)*300%+H33/26*T33)),0) -> 0 | AJ33: =ROUND(IF((P33+Q33)=0,0,IF(BJ33="Lương tháng",MAX((G33+I33)/26*V33,(H33+I33)/26*V33),MAX(G33/26*V33,H33/26*V33))),0) -> 0 | AK33: =ROUND(IF(G33>0,G33/26*W33,H33/26*W33),0) -> 0 | AL33: =ROUND(N33/26*Y33+O33/26*Z33+MAX(G33/26*AA33,H33/26*AA33),0) -> 0 | AM33: =ROUND(IF(BJ33="Lương tháng",L33/26*AC33,L33/26*AC33+MAX((G33+I33)/26*AB33,(H33+I33)/26*AB33)),0) -> 0 | AN33: =ROUND(IF(BJ33="lương tháng",0,MAX((G33+I33)/26*AD33*30%,(H33+I33)/26*AD33*30%)*BK33),0) -> 0 | AO33: =ROUND(BM33*AE33,0) -> 175500 | AP33: 0 | AQ33: =ROUND(SUM(AF33:AP33),0) -> 6778577 | AV33: =ROUND(SUM(AQ33:AT33)-AU33,0) -> 6778577 | AW33: =ROUND(IF($BH33=1,$G33*$AW$9,0),0) -> 531200 | AX33: =ROUND(IF($BH33=1,$G33*$AX$9,0),0) -> 99600 | AY33: =ROUND(IF($BH33=1,$G33*$AY$9,0),0) -> 66400 | AZ33: =SUM(AW33:AY33) -> 697200 | BA33: =ROUND(IF($BI33="1x",$G33*0.5%,0),0) -> 33200 | BB33: =IF(BN33="Xem lại",0,IF(CM33<11000000,5000,IF(AND(CM33>=11000000,CM33<25000000),10000,IF(AND(CM33>=25000000,CM33<40000000),15000,IF(AND(CM33>=40000000,CM33<120000000),20000,IF(AND(CM33>=120000000,CM33<240000000),25000,30000)))))*$BB$9) -> 220000 | BD33: 0 | BE33: =ROUND(SUM(AZ33:BD33),0) -> 950400 | BF33: =ROUND(IF(AV33>BE33,AV33-BE33,0),0) -> 5828177 | BG33: =ROUND(IF(BE33>AV33,BE33-AV33,0),0) -> 0 | BH33: 1 | BI33: 1x | BJ33: =IF(AND(D33="QTNV CL",CM33>=11000000),"Lương tháng",IF(CM33>=18000000,"Lương tháng",0)) -> 0 | BK33: =IF(BJ33="Lương tháng",0,1) -> 1 | BL33: M1 | BM33: =IF(BL33="M1",13000,IF(BL33="M2",20000,IF(BL33="M3",26000,IF(BL33="M4",32000,0)))) -> 13000 | BN33: =IF(AND(G33>0,(P33+Q33)>=5),"Trừ tiền","Xem lại") -> Trừ tiền | BS33: =AQ33+SUM(BO33:BR33)-AN33-AO33-SUM(BY33:CA33) -> 6603077 | BT33: 3 | BU33: =BT33*4400000 -> 13200000 | BV33: 11000000 | BW33: =BU33+BV33 -> 24200000 | BX33: =BS33-SUM(CC33:CD33)-CB33-AZ33-BW33 -> -18294123 | CE33: 14500000 | CF33: =CE33*10% -> 1450000 | CG33: 0 | CH33: 0 | CJ33: =SUM(CF33:CI33) -> 1450000 | CK33: =CE33+CJ33 -> 15950000 | CM33: =CE33 -> 14500000 | CN33: =CF33 -> 1450000 | CO33: =CG33 -> 0 | CP33: =CH33 -> 0 | CQ33: =CI33 -> 0 | CR33: =SUM(CN33:CQ33) -> 1450000 | CS33: =CM33+CR33 -> 15950000 | CT33: Tổ trưởng giao nhận vận chuyển | CU33: Phòng Kho vận Auto | CV33: nguyenvantan1@thilogi.com.vn | CW33: Chu Lai
A34: =SUBTOTAL(3,$C$11:C34) -> 17 | B34: 1904446 | C34: Nguyễn Văn Thông | D34: THILOGI | E34: =IF(CL34>=400000000,"A1",IF(CL34>=300000000,"A2",IF(CL34>=240000000,"A3",IF(CL34>=180000000,"A4",IF(CL34>=120000000,"A5",IF(CL34>=80000000,"A6",IF(CL34>=40000000,"A7",IF(CL34>=25000000,"B1",IF(CL34>=12000000,"B2","B3"))))))))) -> B3 | F34: 43570 | G34: 4520000 | I34: =IF(G34>0,CM34-G34,CM34-H34) -> 3980000 | J34: =CR34 -> 425000 | K34: =SUM(I34:J34) -> 4405000 | L34: =IF(G34>0,G34+K34,H34+K34) -> 8925000 | M34: =IF(CE34>=11000000,80%,100%) -> 1 | N34: =ROUND(MAX(G34*70%,H34*70%,3640000),0) -> 3640000 | O34: 0 | P34: 13 | Q34: 0 | R34: 4.07 | S34: 0 | AD34: 0 | AE34: =IF(OR(BL34="M1",BL34="M2",BL34="M3",BL34="M4"),P34+R34+S34+T34+U34,0) -> 17.07 | AF34: =ROUND(IF($P34=0,0,IF(OR($BJ34="lương tháng",$CE34>=11000000),($L34/2-$L34/26*($CC$6-$P34))*$M34,$L34/26*$P34*$M34)),0) -> 4462500 | AG34: =ROUND(MAX((G34+I34)*M34/26*R34,(H34+I34)*M34/26*R34,G34/26*R34*150%,H34/26*R34*150%)*BK34,0) -> 1330577 | AH34: =ROUND(MAX((G34+I34)*M34/26*S34,(H34+I34)*M34/26*S34,G34/26*S34*200%,H34/26*S34*200%)*BK34,0) -> 0 | AI34: =ROUND(IF(BJ34="Lương tháng",L34/26*T34,MAX((G34+I34)/26*(T34+U34)*200%+G34/26*T34,(H34+I34)/26*(T34+U34)*200%+H34/26*T34,G34/26*(T34+U34)*300%+G34/26*T34,H34/26*(T34+U34)*300%+H34/26*T34)),0) -> 0 | AJ34: =ROUND(IF((P34+Q34)=0,0,IF(BJ34="Lương tháng",MAX((G34+I34)/26*V34,(H34+I34)/26*V34),MAX(G34/26*V34,H34/26*V34))),0) -> 0 | AK34: =ROUND(IF(G34>0,G34/26*W34,H34/26*W34),0) -> 0 | AL34: =ROUND(N34/26*Y34+O34/26*Z34+MAX(G34/26*AA34,H34/26*AA34),0) -> 0 | AM34: =ROUND(IF(BJ34="Lương tháng",L34/26*AC34,L34/26*AC34+MAX((G34+I34)/26*AB34,(H34+I34)/26*AB34)),0) -> 0 | AN34: =ROUND(IF(BJ34="lương tháng",0,MAX((G34+I34)/26*AD34*30%,(H34+I34)/26*AD34*30%)*BK34),0) -> 0 | AO34: =ROUND(BM34*AE34,0) -> 221910 | AP34: 0 | AQ34: =ROUND(SUM(AF34:AP34),0) -> 6014987 | AV34: =ROUND(SUM(AQ34:AT34)-AU34,0) -> 6014987 | AW34: =ROUND(IF($BH34=1,$G34*$AW$9,0),0) -> 361600 | AX34: =ROUND(IF($BH34=1,$G34*$AX$9,0),0) -> 67800 | AY34: =ROUND(IF($BH34=1,$G34*$AY$9,0),0) -> 45200 | AZ34: =SUM(AW34:AY34) -> 474600 | BA34: =ROUND(IF($BI34="1x",$G34*0.5%,0),0) -> 0 | BB34: =IF(BN34="Xem lại",0,IF(CM34<11000000,5000,IF(AND(CM34>=11000000,CM34<25000000),10000,IF(AND(CM34>=25000000,CM34<40000000),15000,IF(AND(CM34>=40000000,CM34<120000000),20000,IF(AND(CM34>=120000000,CM34<240000000),25000,30000)))))*$BB$9) -> 110000 | BD34: 0 | BE34: =ROUND(SUM(AZ34:BD34),0) -> 584600 | BF34: =ROUND(IF(AV34>BE34,AV34-BE34,0),0) -> 5430387 | BG34: =ROUND(IF(BE34>AV34,BE34-AV34,0),0) -> 0 | BH34: 1 | BI34: 0 | BJ34: =IF(AND(D34="QTNV CL",CM34>=11000000),"Lương tháng",IF(CM34>=18000000,"Lương tháng",0)) -> 0 | BK34: =IF(BJ34="Lương tháng",0,1) -> 1 | BL34: M1 | BM34: =IF(BL34="M1",13000,IF(BL34="M2",20000,IF(BL34="M3",26000,IF(BL34="M4",32000,0)))) -> 13000 | BN34: =IF(AND(G34>0,(P34+Q34)>=5),"Trừ tiền","Xem lại") -> Trừ tiền | BS34: =AQ34+SUM(BO34:BR34)-AN34-AO34-SUM(BY34:CA34) -> 5793077 | BT34: 0 | BU34: =BT34*4400000 -> 0 | BV34: 11000000 | BW34: =BU34+BV34 -> 11000000 | BX34: =BS34-SUM(CC34:CD34)-CB34-AZ34-BW34 -> -5681523 | CE34: 8500000 | CF34: =CE34*5% -> 425000 | CG34: 0 | CH34: 0 | CJ34: =SUM(CF34:CI34) -> 425000 | CK34: =CE34+CJ34 -> 8925000 | CM34: =CE34 -> 8500000 | CN34: =CF34 -> 425000 | CO34: =CG34 -> 0 | CP34: =CH34 -> 0 | CQ34: =CI34 -> 0 | CR34: =SUM(CN34:CQ34) -> 425000 | CS34: =CM34+CR34 -> 8925000 | CT34: Công nhân giao nhận xe | CU34: Phòng Kho vận Auto | CV34: thongnguyen011169@gmail.com | CW34: Chu Lai
A35: =SUBTOTAL(3,$C$11:C35) -> 18 | B35: 1005193 | C35: Trương Văn Phong | D35: THILOGI | E35: =IF(CL35>=400000000,"A1",IF(CL35>=300000000,"A2",IF(CL35>=240000000,"A3",IF(CL35>=180000000,"A4",IF(CL35>=120000000,"A5",IF(CL35>=80000000,"A6",IF(CL35>=40000000,"A7",IF(CL35>=25000000,"B1",IF(CL35>=12000000,"B2","B3"))))))))) -> B3 | F35: 40302 | G35: 5980000 | I35: =IF(G35>0,CM35-G35,CM35-H35) -> 5720000 | J35: =CR35 -> 1170000 | K35: =SUM(I35:J35) -> 6890000 | L35: =IF(G35>0,G35+K35,H35+K35) -> 12870000 | M35: =IF(CE35>=11000000,80%,100%) -> 0.8 | N35: =ROUND(MAX(G35*70%,H35*70%,3640000),0) -> 4186000 | O35: 0 | P35: 12 | Q35: 0 | R35: 3.5 | S35: 0 | AD35: 0 | AE35: =IF(OR(BL35="M1",BL35="M2",BL35="M3",BL35="M4"),P35+R35+S35+T35+U35,0) -> 15.5 | AF35: =ROUND(IF($P35=0,0,IF(OR($BJ35="lương tháng",$CE35>=11000000),($L35/2-$L35/26*($CC$6-$P35))*$M35,$L35/26*$P35*$M35)),0) -> 4752000 | AG35: =ROUND(MAX((G35+I35)*M35/26*R35,(H35+I35)*M35/26*R35,G35/26*R35*150%,H35/26*R35*150%)*BK35,0) -> 1260000 | AH35: =ROUND(MAX((G35+I35)*M35/26*S35,(H35+I35)*M35/26*S35,G35/26*S35*200%,H35/26*S35*200%)*BK35,0) -> 0 | AI35: =ROUND(IF(BJ35="Lương tháng",L35/26*T35,MAX((G35+I35)/26*(T35+U35)*200%+G35/26*T35,(H35+I35)/26*(T35+U35)*200%+H35/26*T35,G35/26*(T35+U35)*300%+G35/26*T35,H35/26*(T35+U35)*300%+H35/26*T35)),0) -> 0 | AJ35: =ROUND(IF((P35+Q35)=0,0,IF(BJ35="Lương tháng",MAX((G35+I35)/26*V35,(H35+I35)/26*V35),MAX(G35/26*V35,H35/26*V35))),0) -> 0 | AK35: =ROUND(IF(G35>0,G35/26*W35,H35/26*W35),0) -> 0 | AL35: =ROUND(N35/26*Y35+O35/26*Z35+MAX(G35/26*AA35,H35/26*AA35),0) -> 0 | AM35: =ROUND(IF(BJ35="Lương tháng",L35/26*AC35,L35/26*AC35+MAX((G35+I35)/26*AB35,(H35+I35)/26*AB35)),0) -> 0 | AN35: =ROUND(IF(BJ35="lương tháng",0,MAX((G35+I35)/26*AD35*30%,(H35+I35)/26*AD35*30%)*BK35),0) -> 0 | AO35: =ROUND(BM35*AE35,0) -> 201500 | AP35: 0 | AQ35: =ROUND(SUM(AF35:AP35),0) -> 6213500 | AV35: =ROUND(SUM(AQ35:AT35)-AU35,0) -> 6213500 | AW35: =ROUND(IF($BH35=1,$G35*$AW$9,0),0) -> 478400 | AX35: =ROUND(IF($BH35=1,$G35*$AX$9,0),0) -> 89700 | AY35: =ROUND(IF($BH35=1,$G35*$AY$9,0),0) -> 59800 | AZ35: =SUM(AW35:AY35) -> 627900 | BA35: =ROUND(IF($BI35="1x",$G35*0.5%,0),0) -> 29900 | BB35: =IF(BN35="Xem lại",0,IF(CM35<11000000,5000,IF(AND(CM35>=11000000,CM35<25000000),10000,IF(AND(CM35>=25000000,CM35<40000000),15000,IF(AND(CM35>=40000000,CM35<120000000),20000,IF(AND(CM35>=120000000,CM35<240000000),25000,30000)))))*$BB$9) -> 220000 | BD35: 0 | BE35: =ROUND(SUM(AZ35:BD35),0) -> 877800 | BF35: =ROUND(IF(AV35>BE35,AV35-BE35,0),0) -> 5335700 | BG35: =ROUND(IF(BE35>AV35,BE35-AV35,0),0) -> 0 | BH35: 1 | BI35: 1x | BJ35: =IF(AND(D35="QTNV CL",CM35>=11000000),"Lương tháng",IF(CM35>=18000000,"Lương tháng",0)) -> 0 | BK35: =IF(BJ35="Lương tháng",0,1) -> 1 | BL35: M1 | BM35: =IF(BL35="M1",13000,IF(BL35="M2",20000,IF(BL35="M3",26000,IF(BL35="M4",32000,0)))) -> 13000 | BN35: =IF(AND(G35>0,(P35+Q35)>=5),"Trừ tiền","Xem lại") -> Trừ tiền | BS35: =AQ35+SUM(BO35:BR35)-AN35-AO35-SUM(BY35:CA35) -> 6012000 | BT35: 2 | BU35: =BT35*4400000 -> 8800000 | BV35: 11000000 | BW35: =BU35+BV35 -> 19800000 | BX35: =BS35-SUM(CC35:CD35)-CB35-AZ35-BW35 -> -14415900 | CE35: 11700000 | CF35: =CE35*10% -> 1170000 | CG35: 0 | CH35: 0 | CJ35: =SUM(CF35:CI35) -> 1170000 | CK35: =CE35+CJ35 -> 12870000 | CM35: =CE35 -> 11700000 | CN35: =CF35 -> 1170000 | CO35: =CG35 -> 0 | CP35: =CH35 -> 0 | CQ35: =CI35 -> 0 | CR35: =SUM(CN35:CQ35) -> 1170000 | CS35: =CM35+CR35 -> 12870000 | CT35: Công nhân giao nhận xe | CU35: Phòng Kho vận Auto | CV35: truongvanphong.02121989@gmail.com | CW35: Chu Lai
A36: =SUBTOTAL(3,$C$11:C36) -> 19 | B36: 0912044 | C36: Nguyễn Hữu Việt | D36: THILOGI | E36: =IF(CL36>=400000000,"A1",IF(CL36>=300000000,"A2",IF(CL36>=240000000,"A3",IF(CL36>=180000000,"A4",IF(CL36>=120000000,"A5",IF(CL36>=80000000,"A6",IF(CL36>=40000000,"A7",IF(CL36>=25000000,"B1",IF(CL36>=12000000,"B2","B3"))))))))) -> B3 | F36: 40151 | G36: 6300000 | I36: =IF(G36>0,CM36-G36,CM36-H36) -> 5700000 | J36: =CR36 -> 1200000 | K36: =SUM(I36:J36) -> 6900000 | L36: =IF(G36>0,G36+K36,H36+K36) -> 13200000 | M36: =IF(CE36>=11000000,80%,100%) -> 0.8 | N36: =ROUND(MAX(G36*70%,H36*70%,3640000),0) -> 4410000 | O36: 0 | P36: 13 | Q36: 0 | R36: 3.5 | S36: 0 | AD36: 0 | AE36: =IF(OR(BL36="M1",BL36="M2",BL36="M3",BL36="M4"),P36+R36+S36+T36+U36,0) -> 16.5 | AF36: =ROUND(IF($P36=0,0,IF(OR($BJ36="lương tháng",$CE36>=11000000),($L36/2-$L36/26*($CC$6-$P36))*$M36,$L36/26*$P36*$M36)),0) -> 5280000 | AG36: =ROUND(MAX((G36+I36)*M36/26*R36,(H36+I36)*M36/26*R36,G36/26*R36*150%,H36/26*R36*150%)*BK36,0) -> 1292308 | AH36: =ROUND(MAX((G36+I36)*M36/26*S36,(H36+I36)*M36/26*S36,G36/26*S36*200%,H36/26*S36*200%)*BK36,0) -> 0 | AI36: =ROUND(IF(BJ36="Lương tháng",L36/26*T36,MAX((G36+I36)/26*(T36+U36)*200%+G36/26*T36,(H36+I36)/26*(T36+U36)*200%+H36/26*T36,G36/26*(T36+U36)*300%+G36/26*T36,H36/26*(T36+U36)*300%+H36/26*T36)),0) -> 0 | AJ36: =ROUND(IF((P36+Q36)=0,0,IF(BJ36="Lương tháng",MAX((G36+I36)/26*V36,(H36+I36)/26*V36),MAX(G36/26*V36,H36/26*V36))),0) -> 0 | AK36: =ROUND(IF(G36>0,G36/26*W36,H36/26*W36),0) -> 0 | AL36: =ROUND(N36/26*Y36+O36/26*Z36+MAX(G36/26*AA36,H36/26*AA36),0) -> 0 | AM36: =ROUND(IF(BJ36="Lương tháng",L36/26*AC36,L36/26*AC36+MAX((G36+I36)/26*AB36,(H36+I36)/26*AB36)),0) -> 0 | AN36: =ROUND(IF(BJ36="lương tháng",0,MAX((G36+I36)/26*AD36*30%,(H36+I36)/26*AD36*30%)*BK36),0) -> 0 | AO36: =ROUND(BM36*AE36,0) -> 214500 | AP36: 0 | AQ36: =ROUND(SUM(AF36:AP36),0) -> 6786808 | AV36: =ROUND(SUM(AQ36:AT36)-AU36,0) -> 6786808 | AW36: =ROUND(IF($BH36=1,$G36*$AW$9,0),0) -> 504000 | AX36: =ROUND(IF($BH36=1,$G36*$AX$9,0),0) -> 94500 | AY36: =ROUND(IF($BH36=1,$G36*$AY$9,0),0) -> 63000 | AZ36: =SUM(AW36:AY36) -> 661500 | BA36: =ROUND(IF($BI36="1x",$G36*0.5%,0),0) -> 31500 | BB36: =IF(BN36="Xem lại",0,IF(CM36<11000000,5000,IF(AND(CM36>=11000000,CM36<25000000),10000,IF(AND(CM36>=25000000,CM36<40000000),15000,IF(AND(CM36>=40000000,CM36<120000000),20000,IF(AND(CM36>=120000000,CM36<240000000),25000,30000)))))*$BB$9) -> 220000 | BD36: 0 | BE36: =ROUND(SUM(AZ36:BD36),0) -> 913000 | BF36: =ROUND(IF(AV36>BE36,AV36-BE36,0),0) -> 5873808 | BG36: =ROUND(IF(BE36>AV36,BE36-AV36,0),0) -> 0 | BH36: 1 | BI36: 1x | BJ36: =IF(AND(D36="QTNV CL",CM36>=11000000),"Lương tháng",IF(CM36>=18000000,"Lương tháng",0)) -> 0 | BK36: =IF(BJ36="Lương tháng",0,1) -> 1 | BL36: M1 | BM36: =IF(BL36="M1",13000,IF(BL36="M2",20000,IF(BL36="M3",26000,IF(BL36="M4",32000,0)))) -> 13000 | BN36: =IF(AND(G36>0,(P36+Q36)>=5),"Trừ tiền","Xem lại") -> Trừ tiền | BS36: =AQ36+SUM(BO36:BR36)-AN36-AO36-SUM(BY36:CA36) -> 6572308 | BT36: 2 | BU36: =BT36*4400000 -> 8800000 | BV36: 11000000 | BW36: =BU36+BV36 -> 19800000 | BX36: =BS36-SUM(CC36:CD36)-CB36-AZ36-BW36 -> -13889192 | CE36: 12000000 | CF36: =CE36*10% -> 1200000 | CG36: 0 | CH36: 0 | CJ36: =SUM(CF36:CI36) -> 1200000 | CK36: =CE36+CJ36 -> 13200000 | CM36: =CE36 -> 12000000 | CN36: =CF36 -> 1200000 | CO36: =CG36 -> 0 | CP36: =CH36 -> 0 | CQ36: =CI36 -> 0 | CR36: =SUM(CN36:CQ36) -> 1200000 | CS36: =CM36+CR36 -> 13200000 | CT36: Công nhân giao nhận xe | CU36: Phòng Kho vận Auto | CV36: nguyenhuuviet817@gmail.com | CW36: Chu Lai
A37: =SUBTOTAL(3,$C$11:C37) -> 20 | B37: 1108012 | C37: Võ Như Lĩnh | D37: THILOGI | E37: =IF(CL37>=400000000,"A1",IF(CL37>=300000000,"A2",IF(CL37>=240000000,"A3",IF(CL37>=180000000,"A4",IF(CL37>=120000000,"A5",IF(CL37>=80000000,"A6",IF(CL37>=40000000,"A7",IF(CL37>=25000000,"B1",IF(CL37>=12000000,"B2","B3"))))))))) -> B3 | F37: 40757 | G37: 5980000 | I37: =IF(G37>0,CM37-G37,CM37-H37) -> 5520000 | J37: =CR37 -> 1150000 | K37: =SUM(I37:J37) -> 6670000 | L37: =IF(G37>0,G37+K37,H37+K37) -> 12650000 | M37: =IF(CE37>=11000000,80%,100%) -> 0.8 | N37: =ROUND(MAX(G37*70%,H37*70%,3640000),0) -> 4186000 | O37: 0 | P37: 13 | Q37: 0 | R37: 1 | S37: 0 | AD37: 0 | AE37: =IF(OR(BL37="M1",BL37="M2",BL37="M3",BL37="M4"),P37+R37+S37+T37+U37,0) -> 14 | AF37: =ROUND(IF($P37=0,0,IF(OR($BJ37="lương tháng",$CE37>=11000000),($L37/2-$L37/26*($CC$6-$P37))*$M37,$L37/26*$P37*$M37)),0) -> 5060000 | AG37: =ROUND(MAX((G37+I37)*M37/26*R37,(H37+I37)*M37/26*R37,G37/26*R37*150%,H37/26*R37*150%)*BK37,0) -> 353846 | AH37: =ROUND(MAX((G37+I37)*M37/26*S37,(H37+I37)*M37/26*S37,G37/26*S37*200%,H37/26*S37*200%)*BK37,0) -> 0 | AI37: =ROUND(IF(BJ37="Lương tháng",L37/26*T37,MAX((G37+I37)/26*(T37+U37)*200%+G37/26*T37,(H37+I37)/26*(T37+U37)*200%+H37/26*T37,G37/26*(T37+U37)*300%+G37/26*T37,H37/26*(T37+U37)*300%+H37/26*T37)),0) -> 0 | AJ37: =ROUND(IF((P37+Q37)=0,0,IF(BJ37="Lương tháng",MAX((G37+I37)/26*V37,(H37+I37)/26*V37),MAX(G37/26*V37,H37/26*V37))),0) -> 0 | AK37: =ROUND(IF(G37>0,G37/26*W37,H37/26*W37),0) -> 0 | AL37: =ROUND(N37/26*Y37+O37/26*Z37+MAX(G37/26*AA37,H37/26*AA37),0) -> 0 | AM37: =ROUND(IF(BJ37="Lương tháng",L37/26*AC37,L37/26*AC37+MAX((G37+I37)/26*AB37,(H37+I37)/26*AB37)),0) -> 0 | AN37: =ROUND(IF(BJ37="lương tháng",0,MAX((G37+I37)/26*AD37*30%,(H37+I37)/26*AD37*30%)*BK37),0) -> 0 | AO37: =ROUND(BM37*AE37,0) -> 182000 | AP37: 0 | AQ37: =ROUND(SUM(AF37:AP37),0) -> 5595846 | AV37: =ROUND(SUM(AQ37:AT37)-AU37,0) -> 5595846 | AW37: =ROUND(IF($BH37=1,$G37*$AW$9,0),0) -> 478400 | AX37: =ROUND(IF($BH37=1,$G37*$AX$9,0),0) -> 89700 | AY37: =ROUND(IF($BH37=1,$G37*$AY$9,0),0) -> 59800 | AZ37: =SUM(AW37:AY37) -> 627900 | BA37: =ROUND(IF($BI37="1x",$G37*0.5%,0),0) -> 29900 | BB37: =IF(BN37="Xem lại",0,IF(CM37<11000000,5000,IF(AND(CM37>=11000000,CM37<25000000),10000,IF(AND(CM37>=25000000,CM37<40000000),15000,IF(AND(CM37>=40000000,CM37<120000000),20000,IF(AND(CM37>=120000000,CM37<240000000),25000,30000)))))*$BB$9) -> 220000 | BD37: 0 | BE37: =ROUND(SUM(AZ37:BD37),0) -> 877800 | BF37: =ROUND(IF(AV37>BE37,AV37-BE37,0),0) -> 4718046 | BG37: =ROUND(IF(BE37>AV37,BE37-AV37,0),0) -> 0 | BH37: 1 | BI37: 1x | BJ37: =IF(AND(D37="QTNV CL",CM37>=11000000),"Lương tháng",IF(CM37>=18000000,"Lương tháng",0)) -> 0 | BK37: =IF(BJ37="Lương tháng",0,1) -> 1 | BL37: M1 | BM37: =IF(BL37="M1",13000,IF(BL37="M2",20000,IF(BL37="M3",26000,IF(BL37="M4",32000,0)))) -> 13000 | BN37: =IF(AND(G37>0,(P37+Q37)>=5),"Trừ tiền","Xem lại") -> Trừ tiền | BS37: =AQ37+SUM(BO37:BR37)-AN37-AO37-SUM(BY37:CA37) -> 5413846 | BT37: 2 | BU37: =BT37*4400000 -> 8800000 | BV37: 11000000 | BW37: =BU37+BV37 -> 19800000 | BX37: =BS37-SUM(CC37:CD37)-CB37-AZ37-BW37 -> -15014054 | CE37: 11500000 | CF37: =CE37*10% -> 1150000 | CG37: 0 | CH37: 0 | CJ37: =SUM(CF37:CI37) -> 1150000 | CK37: =CE37+CJ37 -> 12650000 | CM37: =CE37 -> 11500000 | CN37: =CF37 -> 1150000 | CO37: =CG37 -> 0 | CP37: =CH37 -> 0 | CQ37: =CI37 -> 0 | CR37: =SUM(CN37:CQ37) -> 1150000 | CS37: =CM37+CR37 -> 12650000 | CT37: Công nhân giao nhận xe | CU37: Phòng Kho vận Auto | CV37: vonhulinhthaco@gmail.com | CW37: Chu Lai
A38: =SUBTOTAL(3,$C$11:C38) -> 21 | B38: 1505120 | C38: Nguyễn Văn Phi | D38: THILOGI | E38: =IF(CL38>=400000000,"A1",IF(CL38>=300000000,"A2",IF(CL38>=240000000,"A3",IF(CL38>=180000000,"A4",IF(CL38>=120000000,"A5",IF(CL38>=80000000,"A6",IF(CL38>=40000000,"A7",IF(CL38>=25000000,"B1",IF(CL38>=12000000,"B2","B3"))))))))) -> B3 | F38: 42110 | G38: 4300000 | I38: =IF(G38>0,CM38-G38,CM38-H38) -> 4200000 | J38: =CR38 -> 850000 | K38: =SUM(I38:J38) -> 5050000 | L38: =IF(G38>0,G38+K38,H38+K38) -> 9350000 | M38: =IF(CE38>=11000000,80%,100%) -> 1 | N38: =ROUND(MAX(G38*70%,H38*70%,3640000),0) -> 3640000 | O38: 0 | P38: 12 | Q38: 0 | R38: 3.5 | S38: 0 | AD38: 0 | AE38: =IF(OR(BL38="M1",BL38="M2",BL38="M3",BL38="M4"),P38+R38+S38+T38+U38,0) -> 15.5 | AF38: =ROUND(IF($P38=0,0,IF(OR($BJ38="lương tháng",$CE38>=11000000),($L38/2-$L38/26*($CC$6-$P38))*$M38,$L38/26*$P38*$M38)),0) -> 4315385 | AG38: =ROUND(MAX((G38+I38)*M38/26*R38,(H38+I38)*M38/26*R38,G38/26*R38*150%,H38/26*R38*150%)*BK38,0) -> 1144231 | AH38: =ROUND(MAX((G38+I38)*M38/26*S38,(H38+I38)*M38/26*S38,G38/26*S38*200%,H38/26*S38*200%)*BK38,0) -> 0 | AI38: =ROUND(IF(BJ38="Lương tháng",L38/26*T38,MAX((G38+I38)/26*(T38+U38)*200%+G38/26*T38,(H38+I38)/26*(T38+U38)*200%+H38/26*T38,G38/26*(T38+U38)*300%+G38/26*T38,H38/26*(T38+U38)*300%+H38/26*T38)),0) -> 0 | AJ38: =ROUND(IF((P38+Q38)=0,0,IF(BJ38="Lương tháng",MAX((G38+I38)/26*V38,(H38+I38)/26*V38),MAX(G38/26*V38,H38/26*V38))),0) -> 0 | AK38: =ROUND(IF(G38>0,G38/26*W38,H38/26*W38),0) -> 0 | AL38: =ROUND(N38/26*Y38+O38/26*Z38+MAX(G38/26*AA38,H38/26*AA38),0) -> 0 | AM38: =ROUND(IF(BJ38="Lương tháng",L38/26*AC38,L38/26*AC38+MAX((G38+I38)/26*AB38,(H38+I38)/26*AB38)),0) -> 0 | AN38: =ROUND(IF(BJ38="lương tháng",0,MAX((G38+I38)/26*AD38*30%,(H38+I38)/26*AD38*30%)*BK38),0) -> 0 | AO38: =ROUND(BM38*AE38,0) -> 201500 | AP38: 0 | AQ38: =ROUND(SUM(AF38:AP38),0) -> 5661116 | AR38: 0 | AV38: =ROUND(SUM(AQ38:AT38)-AU38,0) -> 5661116 | AW38: =ROUND(IF($BH38=1,$G38*$AW$9,0),0) -> 344000 | AX38: =ROUND(IF($BH38=1,$G38*$AX$9,0),0) -> 64500 | AY38: =ROUND(IF($BH38=1,$G38*$AY$9,0),0) -> 43000 | AZ38: =SUM(AW38:AY38) -> 451500 | BA38: =ROUND(IF($BI38="1x",$G38*0.5%,0),0) -> 21500 | BB38: =IF(BN38="Xem lại",0,IF(CM38<11000000,5000,IF(AND(CM38>=11000000,CM38<25000000),10000,IF(AND(CM38>=25000000,CM38<40000000),15000,IF(AND(CM38>=40000000,CM38<120000000),20000,IF(AND(CM38>=120000000,CM38<240000000),25000,30000)))))*$BB$9) -> 110000 | BD38: 0 | BE38: =ROUND(SUM(AZ38:BD38),0) -> 583000 | BF38: =ROUND(IF(AV38>BE38,AV38-BE38,0),0) -> 5078116 | BG38: =ROUND(IF(BE38>AV38,BE38-AV38,0),0) -> 0 | BH38: 1 | BI38: 1x | BJ38: =IF(AND(D38="QTNV CL",CM38>=11000000),"Lương tháng",IF(CM38>=18000000,"Lương tháng",0)) -> 0 | BK38: =IF(BJ38="Lương tháng",0,1) -> 1 | BL38: M1 | BM38: =IF(BL38="M1",13000,IF(BL38="M2",20000,IF(BL38="M3",26000,IF(BL38="M4",32000,0)))) -> 13000 | BN38: =IF(AND(G38>0,(P38+Q38)>=5),"Trừ tiền","Xem lại") -> Trừ tiền | BS38: =AQ38+SUM(BO38:BR38)-AN38-AO38-SUM(BY38:CA38) -> 5459616 | BT38: 2 | BU38: =BT38*4400000 -> 8800000 | BV38: 11000000 | BW38: =BU38+BV38 -> 19800000 | BX38: =BS38-SUM(CC38:CD38)-CB38-AZ38-BW38 -> -14791884 | CE38: 8500000 | CF38: =CE38*10% -> 850000 | CG38: 0 | CH38: 0 | CJ38: =SUM(CF38:CI38) -> 850000 | CK38: =CE38+CJ38 -> 9350000 | CM38: =CE38 -> 8500000 | CN38: =CF38 -> 850000 | CO38: =CG38 -> 0 | CP38: =CH38 -> 0 | CQ38: =CI38 -> 0 | CR38: =SUM(CN38:CQ38) -> 850000 | CS38: =CM38+CR38 -> 9350000 | CT38: Công nhân giao nhận xe | CU38: Phòng Kho vận Auto | CV38: phi483416@gmail.com | CW38: Chu Lai
A39: =SUBTOTAL(3,$C$11:C39) -> 22 | B39: 1604579 | C39: Bùi Vũ Dũng | D39: THILOGI | E39: =IF(CL39>=400000000,"A1",IF(CL39>=300000000,"A2",IF(CL39>=240000000,"A3",IF(CL39>=180000000,"A4",IF(CL39>=120000000,"A5",IF(CL39>=80000000,"A6",IF(CL39>=40000000,"A7",IF(CL39>=25000000,"B1",IF(CL39>=12000000,"B2","B3"))))))))) -> B3 | F39: 42486 | G39: 4090000 | I39: =IF(G39>0,CM39-G39,CM39-H39) -> 4410000 | J39: =CR39 -> 425000 | K39: =SUM(I39:J39) -> 4835000 | L39: =IF(G39>0,G39+K39,H39+K39) -> 8925000 | M39: =IF(CE39>=11000000,80%,100%) -> 1 | N39: =ROUND(MAX(G39*70%,H39*70%,3640000),0) -> 3640000 | O39: 0 | P39: 13 | Q39: 0 | R39: 3.5 | S39: 0 | AD39: 0 | AE39: =IF(OR(BL39="M1",BL39="M2",BL39="M3",BL39="M4"),P39+R39+S39+T39+U39,0) -> 16.5 | AF39: =ROUND(IF($P39=0,0,IF(OR($BJ39="lương tháng",$CE39>=11000000),($L39/2-$L39/26*($CC$6-$P39))*$M39,$L39/26*$P39*$M39)),0) -> 4462500 | AG39: =ROUND(MAX((G39+I39)*M39/26*R39,(H39+I39)*M39/26*R39,G39/26*R39*150%,H39/26*R39*150%)*BK39,0) -> 1144231 | AH39: =ROUND(MAX((G39+I39)*M39/26*S39,(H39+I39)*M39/26*S39,G39/26*S39*200%,H39/26*S39*200%)*BK39,0) -> 0 | AI39: =ROUND(IF(BJ39="Lương tháng",L39/26*T39,MAX((G39+I39)/26*(T39+U39)*200%+G39/26*T39,(H39+I39)/26*(T39+U39)*200%+H39/26*T39,G39/26*(T39+U39)*300%+G39/26*T39,H39/26*(T39+U39)*300%+H39/26*T39)),0) -> 0 | AJ39: =ROUND(IF((P39+Q39)=0,0,IF(BJ39="Lương tháng",MAX((G39+I39)/26*V39,(H39+I39)/26*V39),MAX(G39/26*V39,H39/26*V39))),0) -> 0 | AK39: =ROUND(IF(G39>0,G39/26*W39,H39/26*W39),0) -> 0 | AL39: =ROUND(N39/26*Y39+O39/26*Z39+MAX(G39/26*AA39,H39/26*AA39),0) -> 0 | AM39: =ROUND(IF(BJ39="Lương tháng",L39/26*AC39,L39/26*AC39+MAX((G39+I39)/26*AB39,(H39+I39)/26*AB39)),0) -> 0 | AN39: =ROUND(IF(BJ39="lương tháng",0,MAX((G39+I39)/26*AD39*30%,(H39+I39)/26*AD39*30%)*BK39),0) -> 0 | AO39: =ROUND(BM39*AE39,0) -> 214500 | AP39: 0 | AQ39: =ROUND(SUM(AF39:AP39),0) -> 5821231 | AR39: 0 | AV39: =ROUND(SUM(AQ39:AT39)-AU39,0) -> 5821231 | AW39: =ROUND(IF($BH39=1,$G39*$AW$9,0),0) -> 327200 | AX39: =ROUND(IF($BH39=1,$G39*$AX$9,0),0) -> 61350 | AY39: =ROUND(IF($BH39=1,$G39*$AY$9,0),0) -> 40900 | AZ39: =SUM(AW39:AY39) -> 429450 | BA39: =ROUND(IF($BI39="1x",$G39*0.5%,0),0) -> 20450 | BB39: =IF(BN39="Xem lại",0,IF(CM39<11000000,5000,IF(AND(CM39>=11000000,CM39<25000000),10000,IF(AND(CM39>=25000000,CM39<40000000),15000,IF(AND(CM39>=40000000,CM39<120000000),20000,IF(AND(CM39>=120000000,CM39<240000000),25000,30000)))))*$BB$9) -> 110000 | BD39: 0 | BE39: =ROUND(SUM(AZ39:BD39),0) -> 559900 | BF39: =ROUND(IF(AV39>BE39,AV39-BE39,0),0) -> 5261331 | BG39: =ROUND(IF(BE39>AV39,BE39-AV39,0),0) -> 0 | BH39: 1 | BI39: 1x | BJ39: =IF(AND(D39="QTNV CL",CM39>=11000000),"Lương tháng",IF(CM39>=18000000,"Lương tháng",0)) -> 0 | BK39: =IF(BJ39="Lương tháng",0,1) -> 1 | BL39: M1 | BM39: =IF(BL39="M1",13000,IF(BL39="M2",20000,IF(BL39="M3",26000,IF(BL39="M4",32000,0)))) -> 13000 | BN39: =IF(AND(G39>0,(P39+Q39)>=5),"Trừ tiền","Xem lại") -> Trừ tiền | BS39: =AQ39+SUM(BO39:BR39)-AN39-AO39-SUM(BY39:CA39) -> 5606731 | BT39: 0 | BU39: =BT39*4400000 -> 0 | BV39: 11000000 | BW39: =BU39+BV39 -> 11000000 | BX39: =BS39-SUM(CC39:CD39)-CB39-AZ39-BW39 -> -5822719 | CE39: 8500000 | CF39: =CE39*5% -> 425000 | CG39: 0 | CH39: 0 | CJ39: =SUM(CF39:CI39) -> 425000 | CK39: =CE39+CJ39 -> 8925000 | CM39: =CE39 -> 8500000 | CN39: =CF39 -> 425000 | CO39: =CG39 -> 0 | CP39: =CH39 -> 0 | CQ39: =CI39 -> 0 | CR39: =SUM(CN39:CQ39) -> 425000 | CS39: =CM39+CR39 -> 8925000 | CT39: Công nhân giao nhận xe | CU39: Phòng Kho vận Auto | CV39: buivudung1604579@gmail.com | CW39: Chu Lai
A40: =SUBTOTAL(3,$C$11:C40) -> 23 | B40: 1505354 | C40: Dương Quốc Việt | D40: THILOGI | E40: =IF(CL40>=400000000,"A1",IF(CL40>=300000000,"A2",IF(CL40>=240000000,"A3",IF(CL40>=180000000,"A4",IF(CL40>=120000000,"A5",IF(CL40>=80000000,"A6",IF(CL40>=40000000,"A7",IF(CL40>=25000000,"B1",IF(CL40>=12000000,"B2","B3"))))))))) -> B3 | F40: 42110 | G40: 4990000 | I40: =IF(G40>0,CM40-G40,CM40-H40) -> 5010000 | J40: =CR40 -> 1000000 | K40: =SUM(I40:J40) -> 6010000 | L40: =IF(G40>0,G40+K40,H40+K40) -> 11000000 | M40: =IF(CE40>=11000000,80%,100%) -> 1 | N40: =ROUND(MAX(G40*70%,H40*70%,3640000),0) -> 3640000 | O40: 0 | P40: 13 | Q40: 0 | R40: 1 | S40: 0 | AD40: 0 | AE40: =IF(OR(BL40="M1",BL40="M2",BL40="M3",BL40="M4"),P40+R40+S40+T40+U40,0) -> 14 | AF40: =ROUND(IF($P40=0,0,IF(OR($BJ40="lương tháng",$CE40>=11000000),($L40/2-$L40/26*($CC$6-$P40))*$M40,$L40/26*$P40*$M40)),0) -> 5500000 | AG40: =ROUND(MAX((G40+I40)*M40/26*R40,(H40+I40)*M40/26*R40,G40/26*R40*150%,H40/26*R40*150%)*BK40,0) -> 384615 | AH40: =ROUND(MAX((G40+I40)*M40/26*S40,(H40+I40)*M40/26*S40,G40/26*S40*200%,H40/26*S40*200%)*BK40,0) -> 0 | AI40: =ROUND(IF(BJ40="Lương tháng",L40/26*T40,MAX((G40+I40)/26*(T40+U40)*200%+G40/26*T40,(H40+I40)/26*(T40+U40)*200%+H40/26*T40,G40/26*(T40+U40)*300%+G40/26*T40,H40/26*(T40+U40)*300%+H40/26*T40)),0) -> 0 | AJ40: =ROUND(IF((P40+Q40)=0,0,IF(BJ40="Lương tháng",MAX((G40+I40)/26*V40,(H40+I40)/26*V40),MAX(G40/26*V40,H40/26*V40))),0) -> 0 | AK40: =ROUND(IF(G40>0,G40/26*W40,H40/26*W40),0) -> 0 | AL40: =ROUND(N40/26*Y40+O40/26*Z40+MAX(G40/26*AA40,H40/26*AA40),0) -> 0 | AM40: =ROUND(IF(BJ40="Lương tháng",L40/26*AC40,L40/26*AC40+MAX((G40+I40)/26*AB40,(H40+I40)/26*AB40)),0) -> 0 | AN40: =ROUND(IF(BJ40="lương tháng",0,MAX((G40+I40)/26*AD40*30%,(H40+I40)/26*AD40*30%)*BK40),0) -> 0 | AO40: =ROUND(BM40*AE40,0) -> 182000 | AP40: 0 | AQ40: =ROUND(SUM(AF40:AP40),0) -> 6066615 | AR40: 0 | AV40: =ROUND(SUM(AQ40:AT40)-AU40,0) -> 6066615 | AW40: =ROUND(IF($BH40=1,$G40*$AW$9,0),0) -> 399200 | AX40: =ROUND(IF($BH40=1,$G40*$AX$9,0),0) -> 74850 | AY40: =ROUND(IF($BH40=1,$G40*$AY$9,0),0) -> 49900 | AZ40: =SUM(AW40:AY40) -> 523950 | BA40: =ROUND(IF($BI40="1x",$G40*0.5%,0),0) -> 24950 | BB40: =IF(BN40="Xem lại",0,IF(CM40<11000000,5000,IF(AND(CM40>=11000000,CM40<25000000),10000,IF(AND(CM40>=25000000,CM40<40000000),15000,IF(AND(CM40>=40000000,CM40<120000000),20000,IF(AND(CM40>=120000000,CM40<240000000),25000,30000)))))*$BB$9) -> 110000 | BD40: 0 | BE40: =ROUND(SUM(AZ40:BD40),0) -> 658900 | BF40: =ROUND(IF(AV40>BE40,AV40-BE40,0),0) -> 5407715 | BG40: =ROUND(IF(BE40>AV40,BE40-AV40,0),0) -> 0 | BH40: 1 | BI40: 1x | BJ40: =IF(AND(D40="QTNV CL",CM40>=11000000),"Lương tháng",IF(CM40>=18000000,"Lương tháng",0)) -> 0 | BK40: =IF(BJ40="Lương tháng",0,1) -> 1 | BL40: M1 | BM40: =IF(BL40="M1",13000,IF(BL40="M2",20000,IF(BL40="M3",26000,IF(BL40="M4",32000,0)))) -> 13000 | BN40: =IF(AND(G40>0,(P40+Q40)>=5),"Trừ tiền","Xem lại") -> Trừ tiền | BS40: =AQ40+SUM(BO40:BR40)-AN40-AO40-SUM(BY40:CA40) -> 5884615 | BT40: 1 | BU40: =BT40*4400000 -> 4400000 | BV40: 11000000 | BW40: =BU40+BV40 -> 15400000 | BX40: =BS40-SUM(CC40:CD40)-CB40-AZ40-BW40 -> -10039335 | CE40: 10000000 | CF40: =CE40*10% -> 1000000 | CG40: 0 | CH40: 0 | CJ40: =SUM(CF40:CI40) -> 1000000 | CK40: =CE40+CJ40 -> 11000000 | CM40: =CE40 -> 10000000 | CN40: =CF40 -> 1000000 | CO40: =CG40 -> 0 | CP40: =CH40 -> 0 | CQ40: =CI40 -> 0 | CR40: =SUM(CN40:CQ40) -> 1000000 | CS40: =CM40+CR40 -> 11000000 | CT40: Công nhân giao nhận xe | CU40: Phòng Kho vận Auto | CV40: duongquocviet1505354@gmail.com | CW40: Chu Lai
A41: =SUBTOTAL(3,$C$8:C41) -> 24 | B41: 22051632 | C41: Huỳnh Minh Phục | D41: THILOGI | E41: =IF(CM41>=400000000,"A1",IF(CM41>=300000000,"A2",IF(CM41>=240000000,"A3",IF(CM41>=180000000,"A4",IF(CM41>=120000000,"A5",IF(CM41>=80000000,"A6",IF(CM41>=40000000,"A7",IF(CM41>=25000000,"B1",IF(CM41>=12000000,"B2","B3"))))))))) -> B3 | F41: 44708 | G41: 4520000 | I41: =IF(G41>0,CM41-G41,CM41-H41) -> 3480000 | J41: =CR41 -> 0 | K41: =SUM(I41:J41) -> 3480000 | L41: =IF(G41>0,G41+K41,H41+K41) -> 8000000 | M41: =IF(CE41>=11000000,80%,100%) -> 1 | N41: =ROUND(MAX(G41*70%,H41*70%,3640000),0) -> 3640000 | O41: 0 | P41: 13 | Q41: 0 | R41: 3 | S41: 0 | AD41: 0 | AE41: =IF(OR(BL41="M1",BL41="M2",BL41="M3",BL41="M4"),P41+R41+S41+T41+U41,0) -> 16 | AF41: =ROUND(IF($P41=0,0,IF(OR($BJ41="lương tháng",$CE41>=11000000),($L41/2-$L41/26*($CC$6-$P41))*$M41,$L41/26*$P41*$M41)),0) -> 4000000 | AG41: =ROUND(MAX((G41+I41)*M41/26*R41,(H41+I41)*M41/26*R41,G41/26*R41*150%,H41/26*R41*150%)*BK41,0) -> 923077 | AH41: =ROUND(MAX((G41+I41)*M41/26*S41,(H41+I41)*M41/26*S41,G41/26*S41*200%,H41/26*S41*200%)*BK41,0) -> 0 | AI41: =ROUND(IF(BJ41="Lương tháng",L41/26*T41,MAX((G41+I41)/26*(T41+U41)*200%+G41/26*T41,(H41+I41)/26*(T41+U41)*200%+H41/26*T41,G41/26*(T41+U41)*300%+G41/26*T41,H41/26*(T41+U41)*300%+H41/26*T41)),0) -> 0 | AJ41: =ROUND(IF((P41+Q41)=0,0,IF(BJ41="Lương tháng",MAX((G41+I41)/26*V41,(H41+I41)/26*V41),MAX(G41/26*V41,H41/26*V41))),0) -> 0 | AK41: =ROUND(IF(G41>0,G41/26*W41,H41/26*W41),0) -> 0 | AL41: =ROUND(N41/26*Y41+O41/26*Z41+MAX(G41/26*AA41,H41/26*AA41),0) -> 0 | AM41: =ROUND(IF(BJ41="Lương tháng",L41/26*AC41,L41/26*AC41+L41/26*AB41),0) -> 0 | AN41: =ROUND(IF(BJ41="lương tháng",0,MAX((G41+I41)/26*AD41*30%,(H41+I41)/26*AD41*30%)*BK41),0) -> 0 | AO41: =ROUND(BM41*AE41,0) -> 208000 | AP41: 0 | AQ41: =ROUND(SUM(AF41:AP41),0) -> 5131077 | AV41: =ROUND(SUM(AQ41:AT41)-AU41,0) -> 5131077 | AW41: =ROUND(IF($BH41=1,$G41*$AW$9,0),0) -> 361600 | AX41: =ROUND(IF($BH41=1,$G41*$AX$9,0),0) -> 67800 | AY41: =ROUND(IF($BH41=1,$G41*$AY$9,0),0) -> 45200 | AZ41: =SUM(AW41:AY41) -> 474600 | BA41: =ROUND(IF($BI41="1x",$G41*0.5%,0),0) -> 22600 | BB41: =IF(BN41="Xem lại",0,IF(CM41<11000000,5000,IF(AND(CM41>=11000000,CM41<25000000),10000,IF(AND(CM41>=25000000,CM41<40000000),15000,IF(AND(CM41>=40000000,CM41<120000000),20000,IF(AND(CM41>=120000000,CM41<240000000),25000,30000)))))*$BB$9) -> 110000 | BD41: 0 | BE41: =ROUND(SUM(AZ41:BD41),0) -> 607200 | BF41: =ROUND(IF(AV41>BE41,AV41-BE41,0),0) -> 4523877 | BG41: =ROUND(IF(BE41>AV41,BE41-AV41,0),0) -> 0 | BH41: 1 | BI41: 1x | BJ41: =IF(AND(D41="QTNV CL",CM41>=11000000),"Lương tháng",IF(CM41>=18000000,"Lương tháng",0)) -> 0 | BK41: =IF(BJ41="Lương tháng",0,1) -> 1 | BL41: M1 | BM41: =IF(BL41="M1",13000,IF(BL41="M2",20000,IF(BL41="M3",26000,IF(BL41="M4",32000,0)))) -> 13000 | BN41: =IF(AND(G41>0,(P41+Q41)>=5),"Trừ tiền","Xem lại") -> Trừ tiền | BS41: =AQ41+SUM(BO41:BR41)-AN41-AO41-SUM(BY41:CA41) -> 4923077 | BT41: 0 | BU41: =BT41*4400000 -> 0 | BV41: 11000000 | BW41: =BU41+BV41 -> 11000000 | BX41: =BS41-SUM(CC41:CD41)-CB41-AZ41-BW41 -> -6551523 | CE41: 8000000 | CF41: 0 | CG41: 0 | CH41: 0 | CJ41: =SUM(CF41:CI41) -> 0 | CK41: =CE41+CJ41 -> 8000000 | CM41: =CE41 -> 8000000 | CN41: =CF41 -> 0 | CO41: =CG41 -> 0 | CP41: =CH41 -> 0 | CQ41: =CI41 -> 0 | CR41: =SUM(CN41:CQ41) -> 0 | CS41: =CM41+CR41 -> 8000000 | CT41: Công nhân giao nhận xe | CU41: Phòng Kho vận Auto | CV41: huynhminhphuc20071996@gmail.com | CW41: Chu Lai
A42: =SUBTOTAL(3,$C$11:C42) -> 25 | B42: 1505128 | C42: Nguyễn Thanh Bình | D42: THILOGI | E42: =IF(CL42>=400000000,"A1",IF(CL42>=300000000,"A2",IF(CL42>=240000000,"A3",IF(CL42>=180000000,"A4",IF(CL42>=120000000,"A5",IF(CL42>=80000000,"A6",IF(CL42>=40000000,"A7",IF(CL42>=25000000,"B1",IF(CL42>=12000000,"B2","B3"))))))))) -> B3 | F42: 42110 | G42: 4300000 | I42: =IF(G42>0,CM42-G42,CM42-H42) -> 4200000 | J42: =CR42 -> 850000 | K42: =SUM(I42:J42) -> 5050000 | L42: =IF(G42>0,G42+K42,H42+K42) -> 9350000 | M42: =IF(CE42>=11000000,80%,100%) -> 1 | N42: =ROUND(MAX(G42*70%,H42*70%,3640000),0) -> 3640000 | O42: 0 | P42: 13 | Q42: 0 | R42: 3.82 | S42: 0 | AD42: 0 | AE42: =IF(OR(BL42="M1",BL42="M2",BL42="M3",BL42="M4"),P42+R42+S42+T42+U42,0) -> 16.82 | AF42: =ROUND(IF($P42=0,0,IF(OR($BJ42="lương tháng",$CE42>=11000000),($L42/2-$L42/26*($CC$6-$P42))*$M42,$L42/26*$P42*$M42)),0) -> 4675000 | AG42: =ROUND(MAX((G42+I42)*M42/26*R42,(H42+I42)*M42/26*R42,G42/26*R42*150%,H42/26*R42*150%)*BK42,0) -> 1248846 | AH42: =ROUND(MAX((G42+I42)*M42/26*S42,(H42+I42)*M42/26*S42,G42/26*S42*200%,H42/26*S42*200%)*BK42,0) -> 0 | AI42: =ROUND(IF(BJ42="Lương tháng",L42/26*T42,MAX((G42+I42)/26*(T42+U42)*200%+G42/26*T42,(H42+I42)/26*(T42+U42)*200%+H42/26*T42,G42/26*(T42+U42)*300%+G42/26*T42,H42/26*(T42+U42)*300%+H42/26*T42)),0) -> 0 | AJ42: =ROUND(IF((P42+Q42)=0,0,IF(BJ42="Lương tháng",MAX((G42+I42)/26*V42,(H42+I42)/26*V42),MAX(G42/26*V42,H42/26*V42))),0) -> 0 | AK42: =ROUND(IF(G42>0,G42/26*W42,H42/26*W42),0) -> 0 | AL42: =ROUND(N42/26*Y42+O42/26*Z42+MAX(G42/26*AA42,H42/26*AA42),0) -> 0 | AM42: =ROUND(IF(BJ42="Lương tháng",L42/26*AC42,L42/26*AC42+MAX((G42+I42)/26*AB42,(H42+I42)/26*AB42)),0) -> 0 | AN42: =ROUND(IF(BJ42="lương tháng",0,MAX((G42+I42)/26*AD42*30%,(H42+I42)/26*AD42*30%)*BK42),0) -> 0 | AO42: =ROUND(BM42*AE42,0) -> 218660 | AP42: 0 | AQ42: =ROUND(SUM(AF42:AP42),0) -> 6142506 | AR42: 0 | AV42: =ROUND(SUM(AQ42:AT42)-AU42,0) -> 6142506 | AW42: =ROUND(IF($BH42=1,$G42*$AW$9,0),0) -> 344000 | AX42: =ROUND(IF($BH42=1,$G42*$AX$9,0),0) -> 64500 | AY42: =ROUND(IF($BH42=1,$G42*$AY$9,0),0) -> 43000 | AZ42: =SUM(AW42:AY42) -> 451500 | BA42: =ROUND(IF($BI42="1x",$G42*0.5%,0),0) -> 21500 | BB42: =IF(BN42="Xem lại",0,IF(CM42<11000000,5000,IF(AND(CM42>=11000000,CM42<25000000),10000,IF(AND(CM42>=25000000,CM42<40000000),15000,IF(AND(CM42>=40000000,CM42<120000000),20000,IF(AND(CM42>=120000000,CM42<240000000),25000,30000)))))*$BB$9) -> 110000 | BD42: 0 | BE42: =ROUND(SUM(AZ42:BD42),0) -> 583000 | BF42: =ROUND(IF(AV42>BE42,AV42-BE42,0),0) -> 5559506 | BG42: =ROUND(IF(BE42>AV42,BE42-AV42,0),0) -> 0 | BH42: 1 | BI42: 1x | BJ42: =IF(AND(D42="QTNV CL",CM42>=11000000),"Lương tháng",IF(CM42>=18000000,"Lương tháng",0)) -> 0 | BK42: =IF(BJ42="Lương tháng",0,1) -> 1 | BL42: M1 | BM42: =IF(BL42="M1",13000,IF(BL42="M2",20000,IF(BL42="M3",26000,IF(BL42="M4",32000,0)))) -> 13000 | BN42: =IF(AND(G42>0,(P42+Q42)>=5),"Trừ tiền","Xem lại") -> Trừ tiền | BS42: =AQ42+SUM(BO42:BR42)-AN42-AO42-SUM(BY42:CA42) -> 5923846 | BT42: 2 | BU42: =BT42*4400000 -> 8800000 | BV42: 11000000 | BW42: =BU42+BV42 -> 19800000 | BX42: =BS42-SUM(CC42:CD42)-CB42-AZ42-BW42 -> -14327654 | CE42: 8500000 | CF42: =CE42*10% -> 850000 | CG42: 0 | CH42: 0 | CJ42: =SUM(CF42:CI42) -> 850000 | CK42: =CE42+CJ42 -> 9350000 | CM42: =CE42 -> 8500000 | CN42: =CF42 -> 850000 | CO42: =CG42 -> 0 | CP42: =CH42 -> 0 | CQ42: =CI42 -> 0 | CR42: =SUM(CN42:CQ42) -> 850000 | CS42: =CM42+CR42 -> 9350000 | CT42: Công nhân giao nhận xe | CU42: Phòng Kho vận Auto | CV42: binhnguyen.161267@gmail.com | CW42: Chu Lai
A43: VI.2 | B43: ="Phòng GNVC xe thành phẩm: " &"["&COUNT(A44:A62)& "]" -> Phòng GNVC xe thành phẩm: [19] | G43: =SUM(G44:G62) -> 98600000 | H43: =SUM(H44:H62) -> 0 | I43: =SUM(I44:I62) -> 101000000 | J43: =SUM(J44:J62) -> 9300000 | K43: =SUM(K44:K62) -> 110300000 | L43: =SUM(L44:L62) -> 208900000 | N43: =SUM(N44:N62) -> 74543000 | O43: =SUM(O44:O62) -> 0 | P43: =SUM(P44:P62) -> 235 | Q43: =SUM(Q44:Q62) -> 0 | R43: =SUM(R44:R62) -> 39.31 | S43: =SUM(S44:S62) -> 0 | T43: =SUM(T44:T62) -> 0 | U43: =SUM(U44:U62) -> 0 | ... BG43: =SUM(BG44:BG62) -> 0 | BI43: =SUM(BI44:BI62) -> 0 | BJ43: =SUM(BJ44:BJ62) -> 0 | BL43: =SUM(BL44:BL62) -> 0 | BM43: =SUM(BM44:BM62) -> 346000 | BN43: =SUM(BN44:BN62) -> 0 | BO43: =SUM(BO44:BO62) -> 0 | BP43: =SUM(BP44:BP62) -> 0 | BQ43: =SUM(BQ44:BQ62) -> 0 | BR43: =SUM(BR44:BR62) -> 0 | BS43: =SUM(BS44:BS62) -> 105787346 | ... CV43: =SUM(CV44:CV62) -> 0
A44: =SUBTOTAL(3,$C$11:C44) -> 26 | B44: 1504663 | C44: Võ Thanh Quang | D44: THILOGI | E44: =IF(CL44>=400000000,"A1",IF(CL44>=300000000,"A2",IF(CL44>=240000000,"A3",IF(CL44>=180000000,"A4",IF(CL44>=120000000,"A5",IF(CL44>=80000000,"A6",IF(CL44>=40000000,"A7",IF(CL44>=25000000,"B1",IF(CL44>=12000000,"B2","B3"))))))))) -> B3 | F44: 42110 | G44: 8100000 | I44: =IF(G44>0,CM44-G44,CM44-H44) -> 13900000 | J44: =CR44 -> 1100000 | K44: =SUM(I44:J44) -> 15000000 | L44: =IF(G44>0,G44+K44,H44+K44) -> 23100000 | M44: =IF(CE44>=11000000,80%,100%) -> 0.8 | N44: =ROUND(MAX(G44*70%,H44*70%,3640000),0) -> 5670000 | O44: 0 | P44: 12.5 | Q44: 0 | R44: 0 | S44: 0 | AD44: 0 | AE44: =IF(OR(BL44="M1",BL44="M2",BL44="M3",BL44="M4"),P44+R44+S44+T44+U44,0) -> 0 | AF44: =ROUND(IF($P44=0,0,IF(OR($BJ44="lương tháng",$CE44>=11000000),($L44/2-$L44/26*($CC$6-$P44))*$M44,$L44/26*$P44*$M44)),0) -> 8884615 | AG44: =ROUND(MAX((G44+I44)*M44/26*R44,(H44+I44)*M44/26*R44,G44/26*R44*150%,H44/26*R44*150%)*BK44,0) -> 0 | AH44: =ROUND(MAX((G44+I44)*M44/26*S44,(H44+I44)*M44/26*S44,G44/26*S44*200%,H44/26*S44*200%)*BK44,0) -> 0 | AI44: =ROUND(IF(BJ44="Lương tháng",L44/26*T44,MAX((G44+I44)/26*(T44+U44)*200%+G44/26*T44,(H44+I44)/26*(T44+U44)*200%+H44/26*T44,G44/26*(T44+U44)*300%+G44/26*T44,H44/26*(T44+U44)*300%+H44/26*T44)),0) -> 0 | AJ44: =ROUND(IF((P44+Q44)=0,0,IF(BJ44="Lương tháng",MAX((G44+I44)/26*V44,(H44+I44)/26*V44),MAX(G44/26*V44,H44/26*V44))),0) -> 0 | AK44: =ROUND(IF(G44>0,G44/26*W44,H44/26*W44),0) -> 0 | AL44: =ROUND(N44/26*Y44+O44/26*Z44+MAX(G44/26*AA44,H44/26*AA44),0) -> 0 | AM44: =ROUND(IF(BJ44="Lương tháng",L44/26*AC44,L44/26*AC44+MAX((G44+I44)/26*AB44,(H44+I44)/26*AB44)),0) -> 0 | AN44: =ROUND(IF(BJ44="lương tháng",0,MAX((G44+I44)/26*AD44*30%,(H44+I44)/26*AD44*30%)*BK44),0) -> 0 | AO44: =ROUND(BM44*AE44,0) -> 0 | AP44: 0 | AQ44: =ROUND(SUM(AF44:AP44),0) -> 8884615 | AV44: =ROUND(SUM(AQ44:AT44)-AU44,0) -> 8884615 | AW44: =ROUND(IF($BH44=1,$G44*$AW$9,0),0) -> 648000 | AX44: =ROUND(IF($BH44=1,$G44*$AX$9,0),0) -> 121500 | AY44: =ROUND(IF($BH44=1,$G44*$AY$9,0),0) -> 81000 | AZ44: =SUM(AW44:AY44) -> 850500 | BA44: =ROUND(IF($BI44="1x",$G44*0.5%,0),0) -> 40500 | BB44: =IF(BN44="Xem lại",0,IF(CM44<11000000,5000,IF(AND(CM44>=11000000,CM44<25000000),10000,IF(AND(CM44>=25000000,CM44<40000000),15000,IF(AND(CM44>=40000000,CM44<120000000),20000,IF(AND(CM44>=120000000,CM44<240000000),25000,30000)))))*$BB$9) -> 220000 | BD44: 0 | BE44: =ROUND(SUM(AZ44:BD44),0) -> 1111000 | BF44: =ROUND(IF(AV44>BE44,AV44-BE44,0),0) -> 7773615 | BG44: =ROUND(IF(BE44>AV44,BE44-AV44,0),0) -> 0 | BH44: 1 | BI44: 1x | BJ44: =IF(AND(D44="QTNV CL",CM44>=11000000),"Lương tháng",IF(CM44>=18000000,"Lương tháng",0)) -> Lương tháng | BK44: =IF(BJ44="Lương tháng",0,1) -> 0 | BL44: 0 | BM44: =IF(BL44="M1",13000,IF(BL44="M2",20000,IF(BL44="M3",26000,IF(BL44="M4",32000,0)))) -> 0 | BN44: =IF(AND(G44>0,(P44+Q44)>=5),"Trừ tiền","Xem lại") -> Trừ tiền | BS44: =AQ44+SUM(BO44:BR44)-AN44-AO44-SUM(BY44:CA44) -> 8884615 | BT44: 1 | BU44: =BT44*4400000 -> 4400000 | BV44: 11000000 | BW44: =BU44+BV44 -> 15400000 | BX44: =BS44-SUM(CC44:CD44)-CB44-AZ44-BW44 -> -7365885 | CE44: 22000000 | CF44: =CE44*5% -> 1100000 | CG44: 0 | CH44: 0 | CJ44: =SUM(CF44:CI44) -> 1100000 | CK44: =CE44+CJ44 -> 23100000 | CM44: =CE44 -> 22000000 | CN44: =CF44 -> 1100000 | CO44: =CG44 -> 0 | CP44: =CH44 -> 0 | CQ44: =CI44 -> 0 | CR44: =SUM(CN44:CQ44) -> 1100000 | CS44: =CM44+CR44 -> 23100000 | CT44: Phó phòng Điều phối xe Du lịch | CU44: Phòng Kho vận Auto | CV44: vothanhquang@thilogi.com.vn | CW44: Chu Lai
A45: =SUBTOTAL(3,$C$11:C45) -> 27 | B45: 0803013 | C45: Trần Minh Phương | D45: THILOGI | E45: =IF(CL45>=400000000,"A1",IF(CL45>=300000000,"A2",IF(CL45>=240000000,"A3",IF(CL45>=180000000,"A4",IF(CL45>=120000000,"A5",IF(CL45>=80000000,"A6",IF(CL45>=40000000,"A7",IF(CL45>=25000000,"B1",IF(CL45>=12000000,"B2","B3"))))))))) -> B3 | F45: 39510 | G45: 6990000 | I45: =IF(G45>0,CM45-G45,CM45-H45) -> 10010000 | J45: =CR45 -> 1700000 | K45: =SUM(I45:J45) -> 11710000 | L45: =IF(G45>0,G45+K45,H45+K45) -> 18700000 | M45: =IF(CE45>=11000000,80%,100%) -> 0.8 | N45: =ROUND(MAX(G45*70%,H45*70%,3640000),0) -> 4893000 | O45: 0 | P45: 13 | Q45: 0 | R45: 1 | S45: 0 | AD45: 0 | AE45: =IF(OR(BL45="M1",BL45="M2",BL45="M3",BL45="M4"),P45+R45+S45+T45+U45,0) -> 14 | AF45: =ROUND(IF($P45=0,0,IF(OR($BJ45="lương tháng",$CE45>=11000000),($L45/2-$L45/26*($CC$6-$P45))*$M45,$L45/26*$P45*$M45)),0) -> 7480000 | AG45: =ROUND(MAX((G45+I45)*M45/26*R45,(H45+I45)*M45/26*R45,G45/26*R45*150%,H45/26*R45*150%)*BK45,0) -> 523077 | AH45: =ROUND(MAX((G45+I45)*M45/26*S45,(H45+I45)*M45/26*S45,G45/26*S45*200%,H45/26*S45*200%)*BK45,0) -> 0 | AI45: =ROUND(IF(BJ45="Lương tháng",L45/26*T45,MAX((G45+I45)/26*(T45+U45)*200%+G45/26*T45,(H45+I45)/26*(T45+U45)*200%+H45/26*T45,G45/26*(T45+U45)*300%+G45/26*T45,H45/26*(T45+U45)*300%+H45/26*T45)),0) -> 0 | AJ45: =ROUND(IF((P45+Q45)=0,0,IF(BJ45="Lương tháng",MAX((G45+I45)/26*V45,(H45+I45)/26*V45),MAX(G45/26*V45,H45/26*V45))),0) -> 0 | AK45: =ROUND(IF(G45>0,G45/26*W45,H45/26*W45),0) -> 0 | AL45: =ROUND(N45/26*Y45+O45/26*Z45+MAX(G45/26*AA45,H45/26*AA45),0) -> 0 | AM45: =ROUND(IF(BJ45="Lương tháng",L45/26*AC45,L45/26*AC45+MAX((G45+I45)/26*AB45,(H45+I45)/26*AB45)),0) -> 0 | AN45: =ROUND(IF(BJ45="lương tháng",0,MAX((G45+I45)/26*AD45*30%,(H45+I45)/26*AD45*30%)*BK45),0) -> 0 | AO45: =ROUND(BM45*AE45,0) -> 182000 | AP45: 0 | AQ45: =ROUND(SUM(AF45:AP45),0) -> 8185077 | AV45: =ROUND(SUM(AQ45:AT45)-AU45,0) -> 8185077 | AW45: =ROUND(IF($BH45=1,$G45*$AW$9,0),0) -> 559200 | AX45: =ROUND(IF($BH45=1,$G45*$AX$9,0),0) -> 104850 | AY45: =ROUND(IF($BH45=1,$G45*$AY$9,0),0) -> 69900 | AZ45: =SUM(AW45:AY45) -> 733950 | BA45: =ROUND(IF($BI45="1x",$G45*0.5%,0),0) -> 34950 | BB45: =IF(BN45="Xem lại",0,IF(CM45<11000000,5000,IF(AND(CM45>=11000000,CM45<25000000),10000,IF(AND(CM45>=25000000,CM45<40000000),15000,IF(AND(CM45>=40000000,CM45<120000000),20000,IF(AND(CM45>=120000000,CM45<240000000),25000,30000)))))*$BB$9) -> 220000 | BD45: 0 | BE45: =ROUND(SUM(AZ45:BD45),0) -> 988900 | BF45: =ROUND(IF(AV45>BE45,AV45-BE45,0),0) -> 7196177 | BG45: =ROUND(IF(BE45>AV45,BE45-AV45,0),0) -> 0 | BH45: 1 | BI45: 1x | BJ45: =IF(AND(D45="QTNV CL",CM45>=11000000),"Lương tháng",IF(CM45>=18000000,"Lương tháng",0)) -> 0 | BK45: =IF(BJ45="Lương tháng",0,1) -> 1 | BL45: M1 | BM45: =IF(BL45="M1",13000,IF(BL45="M2",20000,IF(BL45="M3",26000,IF(BL45="M4",32000,0)))) -> 13000 | BN45: =IF(AND(G45>0,(P45+Q45)>=5),"Trừ tiền","Xem lại") -> Trừ tiền | BS45: =AQ45+SUM(BO45:BR45)-AN45-AO45-SUM(BY45:CA45) -> 8003077 | BT45: 3 | BU45: =BT45*4400000 -> 13200000 | BV45: 11000000 | BW45: =BU45+BV45 -> 24200000 | BX45: =BS45-SUM(CC45:CD45)-CB45-AZ45-BW45 -> -16930873 | CE45: 17000000 | CF45: =CE45*10% -> 1700000 | CG45: 0 | CH45: 0 | CJ45: =SUM(CF45:CI45) -> 1700000 | CK45: =CE45+CJ45 -> 18700000 | CM45: =CE45 -> 17000000 | CN45: =CF45 -> 1700000 | CO45: =CG45 -> 0 | CP45: =CH45 -> 0 | CQ45: =CI45 -> 0 | CR45: =SUM(CN45:CQ45) -> 1700000 | CS45: =CM45+CR45 -> 18700000 | CT45: Trưởng bộ phận đóng xe vào container | CU45: Phòng Kho vận Auto | CV45: tranminhphuong@thilogi.com.vn | CW45: Chu Lai
A46: =SUBTOTAL(3,$C$11:C46) -> 28 | B46: 0509015 | C46: Vũ Hoài Nhơn | D46: THILOGI | E46: =IF(CL46>=400000000,"A1",IF(CL46>=300000000,"A2",IF(CL46>=240000000,"A3",IF(CL46>=180000000,"A4",IF(CL46>=120000000,"A5",IF(CL46>=80000000,"A6",IF(CL46>=40000000,"A7",IF(CL46>=25000000,"B1",IF(CL46>=12000000,"B2","B3"))))))))) -> B3 | F46: 38616 | G46: 5980000 | I46: =IF(G46>0,CM46-G46,CM46-H46) -> 5520000 | J46: =CR46 -> 1150000 | K46: =SUM(I46:J46) -> 6670000 | L46: =IF(G46>0,G46+K46,H46+K46) -> 12650000 | M46: =IF(CE46>=11000000,80%,100%) -> 0.8 | N46: =ROUND(MAX(G46*70%,H46*70%,3640000),0) -> 4186000 | O46: 0 | P46: 13 | Q46: 0 | R46: 3.21 | S46: 0 | AD46: 1 | AE46: =IF(OR(BL46="M1",BL46="M2",BL46="M3",BL46="M4"),P46+R46+S46+T46+U46,0) -> 16.21 | AF46: =ROUND(IF($P46=0,0,IF(OR($BJ46="lương tháng",$CE46>=11000000),($L46/2-$L46/26*($CC$6-$P46))*$M46,$L46/26*$P46*$M46)),0) -> 5060000 | AG46: =ROUND(MAX((G46+I46)*M46/26*R46,(H46+I46)*M46/26*R46,G46/26*R46*150%,H46/26*R46*150%)*BK46,0) -> 1135846 | AH46: =ROUND(MAX((G46+I46)*M46/26*S46,(H46+I46)*M46/26*S46,G46/26*S46*200%,H46/26*S46*200%)*BK46,0) -> 0 | AI46: =ROUND(IF(BJ46="Lương tháng",L46/26*T46,MAX((G46+I46)/26*(T46+U46)*200%+G46/26*T46,(H46+I46)/26*(T46+U46)*200%+H46/26*T46,G46/26*(T46+U46)*300%+G46/26*T46,H46/26*(T46+U46)*300%+H46/26*T46)),0) -> 0 | AJ46: =ROUND(IF((P46+Q46)=0,0,IF(BJ46="Lương tháng",MAX((G46+I46)/26*V46,(H46+I46)/26*V46),MAX(G46/26*V46,H46/26*V46))),0) -> 0 | AK46: =ROUND(IF(G46>0,G46/26*W46,H46/26*W46),0) -> 0 | AL46: =ROUND(N46/26*Y46+O46/26*Z46+MAX(G46/26*AA46,H46/26*AA46),0) -> 0 | AM46: =ROUND(IF(BJ46="Lương tháng",L46/26*AC46,L46/26*AC46+MAX((G46+I46)/26*AB46,(H46+I46)/26*AB46)),0) -> 0 | AN46: =ROUND(IF(BJ46="lương tháng",0,MAX((G46+I46)/26*AD46*30%,(H46+I46)/26*AD46*30%)*BK46),0) -> 132692 | AO46: =ROUND(BM46*AE46,0) -> 324200 | AP46: 0 | AQ46: =ROUND(SUM(AF46:AP46),0) -> 6652738 | AR46: 0 | AV46: =ROUND(SUM(AQ46:AT46)-AU46,0) -> 6652738 | AW46: =ROUND(IF($BH46=1,$G46*$AW$9,0),0) -> 478400 | AX46: =ROUND(IF($BH46=1,$G46*$AX$9,0),0) -> 89700 | AY46: =ROUND(IF($BH46=1,$G46*$AY$9,0),0) -> 59800 | AZ46: =SUM(AW46:AY46) -> 627900 | BA46: =ROUND(IF($BI46="1x",$G46*0.5%,0),0) -> 29900 | BB46: =IF(BN46="Xem lại",0,IF(CM46<11000000,5000,IF(AND(CM46>=11000000,CM46<25000000),10000,IF(AND(CM46>=25000000,CM46<40000000),15000,IF(AND(CM46>=40000000,CM46<120000000),20000,IF(AND(CM46>=120000000,CM46<240000000),25000,30000)))))*$BB$9) -> 220000 | BD46: 0 | BE46: =ROUND(SUM(AZ46:BD46),0) -> 877800 | BF46: =ROUND(IF(AV46>BE46,AV46-BE46,0),0) -> 5774938 | BG46: =ROUND(IF(BE46>AV46,BE46-AV46,0),0) -> 0 | BH46: 1 | BI46: 1x | BJ46: =IF(AND(D46="QTNV CL",CM46>=11000000),"Lương tháng",IF(CM46>=18000000,"Lương tháng",0)) -> 0 | BK46: =IF(BJ46="Lương tháng",0,1) -> 1 | BL46: M2 | BM46: =IF(BL46="M1",13000,IF(BL46="M2",20000,IF(BL46="M3",26000,IF(BL46="M4",32000,0)))) -> 20000 | BN46: =IF(AND(G46>0,(P46+Q46)>=5),"Trừ tiền","Xem lại") -> Trừ tiền | BS46: =AQ46+SUM(BO46:BR46)-AN46-AO46-SUM(BY46:CA46) -> 6195846 | BT46: 2 | BU46: =BT46*4400000 -> 8800000 | BV46: 11000000 | BW46: =BU46+BV46 -> 19800000 | BX46: =BS46-SUM(CC46:CD46)-CB46-AZ46-BW46 -> -14232054 | CE46: 11500000 | CF46: =CE46*10% -> 1150000 | CG46: 0 | CH46: 0 | CJ46: =SUM(CF46:CI46) -> 1150000 | CK46: =CE46+CJ46 -> 12650000 | CM46: =CE46 -> 11500000 | CN46: =CF46 -> 1150000 | CO46: =CG46 -> 0 | CP46: =CH46 -> 0 | CQ46: =CI46 -> 0 | CR46: =SUM(CN46:CQ46) -> 1150000 | CS46: =CM46+CR46 -> 12650000 | CT46: Tổ trưởng tổ Đóng xe thành phẩm vào Container | CU46: Phòng Kho vận Auto | CV46: Vuhoainhon25101983@gmail.com | CW46: Chu Lai
A47: =SUBTOTAL(3,$C$11:C47) -> 29 | B47: 1505234 | C47: Nguyễn Đình Quốc | D47: THILOGI | E47: =IF(CL47>=400000000,"A1",IF(CL47>=300000000,"A2",IF(CL47>=240000000,"A3",IF(CL47>=180000000,"A4",IF(CL47>=120000000,"A5",IF(CL47>=80000000,"A6",IF(CL47>=40000000,"A7",IF(CL47>=25000000,"B1",IF(CL47>=12000000,"B2","B3"))))))))) -> B3 | F47: 42110 | G47: 4750000 | I47: =IF(G47>0,CM47-G47,CM47-H47) -> 4750000 | J47: =CR47 -> 950000 | K47: =SUM(I47:J47) -> 5700000 | L47: =IF(G47>0,G47+K47,H47+K47) -> 10450000 | M47: =IF(CE47>=11000000,80%,100%) -> 1 | N47: =ROUND(MAX(G47*70%,H47*70%,3640000),0) -> 3640000 | O47: 0 | P47: 13 | Q47: 0 | R47: 1 | S47: 0 | AD47: 0 | AE47: =IF(OR(BL47="M1",BL47="M2",BL47="M3",BL47="M4"),P47+R47+S47+T47+U47,0) -> 14 | AF47: =ROUND(IF($P47=0,0,IF(OR($BJ47="lương tháng",$CE47>=11000000),($L47/2-$L47/26*($CC$6-$P47))*$M47,$L47/26*$P47*$M47)),0) -> 5225000 | AG47: =ROUND(MAX((G47+I47)*M47/26*R47,(H47+I47)*M47/26*R47,G47/26*R47*150%,H47/26*R47*150%)*BK47,0) -> 365385 | AH47: =ROUND(MAX((G47+I47)*M47/26*S47,(H47+I47)*M47/26*S47,G47/26*S47*200%,H47/26*S47*200%)*BK47,0) -> 0 | AI47: =ROUND(IF(BJ47="Lương tháng",L47/26*T47,MAX((G47+I47)/26*(T47+U47)*200%+G47/26*T47,(H47+I47)/26*(T47+U47)*200%+H47/26*T47,G47/26*(T47+U47)*300%+G47/26*T47,H47/26*(T47+U47)*300%+H47/26*T47)),0) -> 0 | AJ47: =ROUND(IF((P47+Q47)=0,0,IF(BJ47="Lương tháng",MAX((G47+I47)/26*V47,(H47+I47)/26*V47),MAX(G47/26*V47,H47/26*V47))),0) -> 0 | AK47: =ROUND(IF(G47>0,G47/26*W47,H47/26*W47),0) -> 0 | AL47: =ROUND(N47/26*Y47+O47/26*Z47+MAX(G47/26*AA47,H47/26*AA47),0) -> 0 | AM47: =ROUND(IF(BJ47="Lương tháng",L47/26*AC47,L47/26*AC47+MAX((G47+I47)/26*AB47,(H47+I47)/26*AB47)),0) -> 0 | AN47: =ROUND(IF(BJ47="lương tháng",0,MAX((G47+I47)/26*AD47*30%,(H47+I47)/26*AD47*30%)*BK47),0) -> 0 | AO47: =ROUND(BM47*AE47,0) -> 182000 | AP47: 0 | AQ47: =ROUND(SUM(AF47:AP47),0) -> 5772385 | AR47: 0 | AV47: =ROUND(SUM(AQ47:AT47)-AU47,0) -> 5772385 | AW47: =ROUND(IF($BH47=1,$G47*$AW$9,0),0) -> 380000 | AX47: =ROUND(IF($BH47=1,$G47*$AX$9,0),0) -> 71250 | AY47: =ROUND(IF($BH47=1,$G47*$AY$9,0),0) -> 47500 | AZ47: =SUM(AW47:AY47) -> 498750 | BA47: =ROUND(IF($BI47="1x",$G47*0.5%,0),0) -> 23750 | BB47: =IF(BN47="Xem lại",0,IF(CM47<11000000,5000,IF(AND(CM47>=11000000,CM47<25000000),10000,IF(AND(CM47>=25000000,CM47<40000000),15000,IF(AND(CM47>=40000000,CM47<120000000),20000,IF(AND(CM47>=120000000,CM47<240000000),25000,30000)))))*$BB$9) -> 110000 | BD47: 0 | BE47: =ROUND(SUM(AZ47:BD47),0) -> 632500 | BF47: =ROUND(IF(AV47>BE47,AV47-BE47,0),0) -> 5139885 | BG47: =ROUND(IF(BE47>AV47,BE47-AV47,0),0) -> 0 | BH47: 1 | BI47: 1x | BJ47: =IF(AND(D47="QTNV CL",CM47>=11000000),"Lương tháng",IF(CM47>=18000000,"Lương tháng",0)) -> 0 | BK47: =IF(BJ47="Lương tháng",0,1) -> 1 | BL47: M1 | BM47: =IF(BL47="M1",13000,IF(BL47="M2",20000,IF(BL47="M3",26000,IF(BL47="M4",32000,0)))) -> 13000 | BN47: =IF(AND(G47>0,(P47+Q47)>=5),"Trừ tiền","Xem lại") -> Trừ tiền | BS47: =AQ47+SUM(BO47:BR47)-AN47-AO47-SUM(BY47:CA47) -> 5590385 | BT47: 2 | BU47: =BT47*4400000 -> 8800000 | BV47: 11000000 | BW47: =BU47+BV47 -> 19800000 | BX47: =BS47-SUM(CC47:CD47)-CB47-AZ47-BW47 -> -14708365 | CE47: 9500000 | CF47: =CE47*10% -> 950000 | CG47: 0 | CH47: 0 | CJ47: =SUM(CF47:CI47) -> 950000 | CK47: =CE47+CJ47 -> 10450000 | CM47: =CE47 -> 9500000 | CN47: =CF47 -> 950000 | CO47: =CG47 -> 0 | CP47: =CH47 -> 0 | CQ47: =CI47 -> 0 | CR47: =SUM(CN47:CQ47) -> 950000 | CS47: =CM47+CR47 -> 10450000 | CT47: Công nhân quản lý vật tư, công cụ dụng cụ | CU47: Phòng Kho vận Auto | CV47: nguyendinhquoc1984qn@gmail.com | CW47: Chu Lai
A48: =SUBTOTAL(3,$C$11:C48) -> 30 | B48: 2112689 | C48: Đặng Mậu Tĩnh | D48: THILOGI | E48: =IF(CL48>=400000000,"A1",IF(CL48>=300000000,"A2",IF(CL48>=240000000,"A3",IF(CL48>=180000000,"A4",IF(CL48>=120000000,"A5",IF(CL48>=80000000,"A6",IF(CL48>=40000000,"A7",IF(CL48>=25000000,"B1",IF(CL48>=12000000,"B2","B3"))))))))) -> B3 | F48: 44552 | G48: 4520000 | I48: =IF(G48>0,CM48-G48,CM48-H48) -> 4180000 | J48: =CR48 -> 0 | K48: =SUM(I48:J48) -> 4180000 | L48: =IF(G48>0,G48+K48,H48+K48) -> 8700000 | M48: =IF(CE48>=11000000,80%,100%) -> 1 | N48: =ROUND(MAX(G48*70%,H48*70%,3640000),0) -> 3640000 | O48: 0 | P48: 4.5 | Q48: 0 | R48: 0 | S48: 0 | AD48: 0 | AE48: =IF(OR(BL48="M1",BL48="M2",BL48="M3",BL48="M4"),P48+R48+S48+T48+U48,0) -> 4.5 | AF48: =ROUND(IF($P48=0,0,IF(OR($BJ48="lương tháng",$CE48>=11000000),($L48/2-$L48/26*($CC$6-$P48))*$M48,$L48/26*$P48*$M48)),0) -> 1505769 | AG48: =ROUND(MAX((G48+I48)*M48/26*R48,(H48+I48)*M48/26*R48,G48/26*R48*150%,H48/26*R48*150%)*BK48,0) -> 0 | AH48: =ROUND(MAX((G48+I48)*M48/26*S48,(H48+I48)*M48/26*S48,G48/26*S48*200%,H48/26*S48*200%)*BK48,0) -> 0 | AI48: =ROUND(IF(BJ48="Lương tháng",L48/26*T48,MAX((G48+I48)/26*(T48+U48)*200%+G48/26*T48,(H48+I48)/26*(T48+U48)*200%+H48/26*T48,G48/26*(T48+U48)*300%+G48/26*T48,H48/26*(T48+U48)*300%+H48/26*T48)),0) -> 0 | AJ48: =ROUND(IF((P48+Q48)=0,0,IF(BJ48="Lương tháng",MAX((G48+I48)/26*V48,(H48+I48)/26*V48),MAX(G48/26*V48,H48/26*V48))),0) -> 0 | AK48: =ROUND(IF(G48>0,G48/26*W48,H48/26*W48),0) -> 0 | AL48: =ROUND(N48/26*Y48+O48/26*Z48+MAX(G48/26*AA48,H48/26*AA48),0) -> 0 | AM48: =ROUND(IF(BJ48="Lương tháng",L48/26*AC48,L48/26*AC48+MAX((G48+I48)/26*AB48,(H48+I48)/26*AB48)),0) -> 0 | AN48: =ROUND(IF(BJ48="lương tháng",0,MAX((G48+I48)/26*AD48*30%,(H48+I48)/26*AD48*30%)*BK48),0) -> 0 | AO48: =ROUND(BM48*AE48,0) -> 90000 | AP48: 0 | AQ48: =ROUND(SUM(AF48:AP48),0) -> 1595769 | AV48: =ROUND(SUM(AQ48:AT48)-AU48,0) -> 1595769 | AW48: =ROUND(IF($BH48=1,$G48*$AW$9,0),0) -> 361600 | AX48: =ROUND(IF($BH48=1,$G48*$AX$9,0),0) -> 67800 | AY48: =ROUND(IF($BH48=1,$G48*$AY$9,0),0) -> 45200 | AZ48: =SUM(AW48:AY48) -> 474600 | BA48: =ROUND(IF($BI48="1x",$G48*0.5%,0),0) -> 22600 | BB48: =IF(BN48="Xem lại",0,IF(CM48<11000000,5000,IF(AND(CM48>=11000000,CM48<25000000),10000,IF(AND(CM48>=25000000,CM48<40000000),15000,IF(AND(CM48>=40000000,CM48<120000000),20000,IF(AND(CM48>=120000000,CM48<240000000),25000,30000)))))*$BB$9) -> 110000 | BD48: 0 | BE48: =ROUND(SUM(AZ48:BD48),0) -> 607200 | BF48: =ROUND(IF(AV48>BE48,AV48-BE48,0),0) -> 988569 | BG48: =ROUND(IF(BE48>AV48,BE48-AV48,0),0) -> 0 | BH48: 1 | BI48: 1x | BJ48: =IF(AND(D48="QTNV CL",CM48>=11000000),"Lương tháng",IF(CM48>=18000000,"Lương tháng",0)) -> 0 | BK48: =IF(BJ48="Lương tháng",0,1) -> 1 | BL48: M2 | BM48: =IF(BL48="M1",13000,IF(BL48="M2",20000,IF(BL48="M3",26000,IF(BL48="M4",32000,0)))) -> 20000 | BN48: Trừ tiền | BS48: =AQ48+SUM(BO48:BR48)-AN48-AO48-SUM(BY48:CA48) -> 1505769 | BT48: 0 | BU48: =BT48*4400000 -> 0 | BV48: 11000000 | BW48: =BU48+BV48 -> 11000000 | BX48: =BS48-SUM(CC48:CD48)-CB48-AZ48-BW48 -> -9968831 | CE48: 8700000 | CF48: 0 | CG48: 0 | CH48: 0 | CJ48: =SUM(CF48:CI48) -> 0 | CK48: =CE48+CJ48 -> 8700000 | CM48: =CE48 -> 8700000 | CN48: =CF48 -> 0 | CO48: =CG48 -> 0 | CP48: =CH48 -> 0 | CQ48: =CI48 -> 0 | CR48: =SUM(CN48:CQ48) -> 0 | CS48: =CM48+CR48 -> 8700000 | CT48: Công nhân Đóng xe thành phẩm vào container | CU48: Phòng Kho vận Auto | CV48: Dangmautinh1998@gmail.com | CW48: Chu Lai
A49: =SUBTOTAL(3,$C$11:C49) -> 31 | B49: 0506005 | C49: Võ Văn Vũ | D49: THILOGI | E49: =IF(CL49>=400000000,"A1",IF(CL49>=300000000,"A2",IF(CL49>=240000000,"A3",IF(CL49>=180000000,"A4",IF(CL49>=120000000,"A5",IF(CL49>=80000000,"A6",IF(CL49>=40000000,"A7",IF(CL49>=25000000,"B1",IF(CL49>=12000000,"B2","B3"))))))))) -> B3 | F49: 38510 | G49: 6640000 | I49: =IF(G49>0,CM49-G49,CM49-H49) -> 7360000 | J49: =CR49 -> 1400000 | K49: =SUM(I49:J49) -> 8760000 | L49: =IF(G49>0,G49+K49,H49+K49) -> 15400000 | M49: =IF(CE49>=11000000,80%,100%) -> 0.8 | N49: =ROUND(MAX(G49*70%,H49*70%,3640000),0) -> 4648000 | O49: 0 | P49: 13 | Q49: 0 | R49: 2.55 | S49: 0 | AD49: 0.31 | AE49: =IF(OR(BL49="M1",BL49="M2",BL49="M3",BL49="M4"),P49+R49+S49+T49+U49,0) -> 15.55 | AF49: =ROUND(IF($P49=0,0,IF(OR($BJ49="lương tháng",$CE49>=11000000),($L49/2-$L49/26*($CC$6-$P49))*$M49,$L49/26*$P49*$M49)),0) -> 6160000 | AG49: =ROUND(MAX((G49+I49)*M49/26*R49,(H49+I49)*M49/26*R49,G49/26*R49*150%,H49/26*R49*150%)*BK49,0) -> 1098462 | AH49: =ROUND(MAX((G49+I49)*M49/26*S49,(H49+I49)*M49/26*S49,G49/26*S49*200%,H49/26*S49*200%)*BK49,0) -> 0 | AI49: =ROUND(IF(BJ49="Lương tháng",L49/26*T49,MAX((G49+I49)/26*(T49+U49)*200%+G49/26*T49,(H49+I49)/26*(T49+U49)*200%+H49/26*T49,G49/26*(T49+U49)*300%+G49/26*T49,H49/26*(T49+U49)*300%+H49/26*T49)),0) -> 0 | AJ49: =ROUND(IF((P49+Q49)=0,0,IF(BJ49="Lương tháng",MAX((G49+I49)/26*V49,(H49+I49)/26*V49),MAX(G49/26*V49,H49/26*V49))),0) -> 0 | AK49: =ROUND(IF(G49>0,G49/26*W49,H49/26*W49),0) -> 0 | AL49: =ROUND(N49/26*Y49+O49/26*Z49+MAX(G49/26*AA49,H49/26*AA49),0) -> 0 | AM49: =ROUND(IF(BJ49="Lương tháng",L49/26*AC49,L49/26*AC49+MAX((G49+I49)/26*AB49,(H49+I49)/26*AB49)),0) -> 0 | AN49: =ROUND(IF(BJ49="lương tháng",0,MAX((G49+I49)/26*AD49*30%,(H49+I49)/26*AD49*30%)*BK49),0) -> 50077 | AO49: =ROUND(BM49*AE49,0) -> 311000 | AP49: 0 | AQ49: =ROUND(SUM(AF49:AP49),0) -> 7619539 | AV49: =ROUND(SUM(AQ49:AT49)-AU49,0) -> 7619539 | AW49: =ROUND(IF($BH49=1,$G49*$AW$9,0),0) -> 531200 | AX49: =ROUND(IF($BH49=1,$G49*$AX$9,0),0) -> 99600 | AY49: =ROUND(IF($BH49=1,$G49*$AY$9,0),0) -> 66400 | AZ49: =SUM(AW49:AY49) -> 697200 | BA49: =ROUND(IF($BI49="1x",$G49*0.5%,0),0) -> 33200 | BB49: =IF(BN49="Xem lại",0,IF(CM49<11000000,5000,IF(AND(CM49>=11000000,CM49<25000000),10000,IF(AND(CM49>=25000000,CM49<40000000),15000,IF(AND(CM49>=40000000,CM49<120000000),20000,IF(AND(CM49>=120000000,CM49<240000000),25000,30000)))))*$BB$9) -> 220000 | BD49: 0 | BE49: =ROUND(SUM(AZ49:BD49),0) -> 950400 | BF49: =ROUND(IF(AV49>BE49,AV49-BE49,0),0) -> 6669139 | BG49: =ROUND(IF(BE49>AV49,BE49-AV49,0),0) -> 0 | BH49: 1 | BI49: 1x | BJ49: =IF(AND(D49="QTNV CL",CM49>=11000000),"Lương tháng",IF(CM49>=18000000,"Lương tháng",0)) -> 0 | BK49: =IF(BJ49="Lương tháng",0,1) -> 1 | BL49: M2 | BM49: =IF(BL49="M1",13000,IF(BL49="M2",20000,IF(BL49="M3",26000,IF(BL49="M4",32000,0)))) -> 20000 | BN49: =IF(AND(G49>0,(P49+Q49)>=5),"Trừ tiền","Xem lại") -> Trừ tiền | BS49: =AQ49+SUM(BO49:BR49)-AN49-AO49-SUM(BY49:CA49) -> 7258462 | BT49: 1 | BU49: =BT49*4400000 -> 4400000 | BV49: 11000000 | BW49: =BU49+BV49 -> 15400000 | BX49: =BS49-SUM(CC49:CD49)-CB49-AZ49-BW49 -> -8838738 | CE49: 14000000 | CF49: =CE49*10% -> 1400000 | CG49: 0 | CH49: 0 | CJ49: =SUM(CF49:CI49) -> 1400000 | CK49: =CE49+CJ49 -> 15400000 | CM49: =CE49 -> 14000000 | CN49: =CF49 -> 1400000 | CO49: =CG49 -> 0 | CP49: =CH49 -> 0 | CQ49: =CI49 -> 0 | CR49: =SUM(CN49:CQ49) -> 1400000 | CS49: =CM49+CR49 -> 15400000 | CT49: Công nhân Đóng xe thành phẩm vào container | CU49: Phòng Kho vận Auto | CV49: vovanvu2411@gmail.com | CW49: Chu Lai
A50: =SUBTOTAL(3,$C$11:C50) -> 32 | B50: 0705026 | C50: Nguyễn Đình Vỹ | D50: THILOGI | E50: =IF(CL50>=400000000,"A1",IF(CL50>=300000000,"A2",IF(CL50>=240000000,"A3",IF(CL50>=180000000,"A4",IF(CL50>=120000000,"A5",IF(CL50>=80000000,"A6",IF(CL50>=40000000,"A7",IF(CL50>=25000000,"B1",IF(CL50>=12000000,"B2","B3"))))))))) -> B3 | F50: 39216 | G50: 5980000 | I50: =IF(G50>0,CM50-G50,CM50-H50) -> 5520000 | J50: =CR50 -> 1150000 | K50: =SUM(I50:J50) -> 6670000 | L50: =IF(G50>0,G50+K50,H50+K50) -> 12650000 | M50: =IF(CE50>=11000000,80%,100%) -> 0.8 | N50: =ROUND(MAX(G50*70%,H50*70%,3640000),0) -> 4186000 | O50: 0 | P50: 13 | Q50: 0 | R50: 1.29 | S50: 0 | AD50: 0 | AE50: =IF(OR(BL50="M1",BL50="M2",BL50="M3",BL50="M4"),P50+R50+S50+T50+U50,0) -> 14.29 | AF50: =ROUND(IF($P50=0,0,IF(OR($BJ50="lương tháng",$CE50>=11000000),($L50/2-$L50/26*($CC$6-$P50))*$M50,$L50/26*$P50*$M50)),0) -> 5060000 | AG50: =ROUND(MAX((G50+I50)*M50/26*R50,(H50+I50)*M50/26*R50,G50/26*R50*150%,H50/26*R50*150%)*BK50,0) -> 456462 | AH50: =ROUND(MAX((G50+I50)*M50/26*S50,(H50+I50)*M50/26*S50,G50/26*S50*200%,H50/26*S50*200%)*BK50,0) -> 0 | AI50: =ROUND(IF(BJ50="Lương tháng",L50/26*T50,MAX((G50+I50)/26*(T50+U50)*200%+G50/26*T50,(H50+I50)/26*(T50+U50)*200%+H50/26*T50,G50/26*(T50+U50)*300%+G50/26*T50,H50/26*(T50+U50)*300%+H50/26*T50)),0) -> 0 | AJ50: =ROUND(IF((P50+Q50)=0,0,IF(BJ50="Lương tháng",MAX((G50+I50)/26*V50,(H50+I50)/26*V50),MAX(G50/26*V50,H50/26*V50))),0) -> 0 | AK50: =ROUND(IF(G50>0,G50/26*W50,H50/26*W50),0) -> 0 | AL50: =ROUND(N50/26*Y50+O50/26*Z50+MAX(G50/26*AA50,H50/26*AA50),0) -> 0 | AM50: =ROUND(IF(BJ50="Lương tháng",L50/26*AC50,L50/26*AC50+MAX((G50+I50)/26*AB50,(H50+I50)/26*AB50)),0) -> 0 | AN50: =ROUND(IF(BJ50="lương tháng",0,MAX((G50+I50)/26*AD50*30%,(H50+I50)/26*AD50*30%)*BK50),0) -> 0 | AO50: =ROUND(BM50*AE50,0) -> 285800 | AP50: 0 | AQ50: =ROUND(SUM(AF50:AP50),0) -> 5802262 | AV50: =ROUND(SUM(AQ50:AT50)-AU50,0) -> 5802262 | AW50: =ROUND(IF($BH50=1,$G50*$AW$9,0),0) -> 478400 | AX50: =ROUND(IF($BH50=1,$G50*$AX$9,0),0) -> 89700 | AY50: =ROUND(IF($BH50=1,$G50*$AY$9,0),0) -> 59800 | AZ50: =SUM(AW50:AY50) -> 627900 | BA50: =ROUND(IF($BI50="1x",$G50*0.5%,0),0) -> 29900 | BB50: =IF(BN50="Xem lại",0,IF(CM50<11000000,5000,IF(AND(CM50>=11000000,CM50<25000000),10000,IF(AND(CM50>=25000000,CM50<40000000),15000,IF(AND(CM50>=40000000,CM50<120000000),20000,IF(AND(CM50>=120000000,CM50<240000000),25000,30000)))))*$BB$9) -> 220000 | BD50: 0 | BE50: =ROUND(SUM(AZ50:BD50),0) -> 877800 | BF50: =ROUND(IF(AV50>BE50,AV50-BE50,0),0) -> 4924462 | BG50: =ROUND(IF(BE50>AV50,BE50-AV50,0),0) -> 0 | BH50: 1 | BI50: 1x | BJ50: =IF(AND(D50="QTNV CL",CM50>=11000000),"Lương tháng",IF(CM50>=18000000,"Lương tháng",0)) -> 0 | BK50: =IF(BJ50="Lương tháng",0,1) -> 1 | BL50: M2 | BM50: =IF(BL50="M1",13000,IF(BL50="M2",20000,IF(BL50="M3",26000,IF(BL50="M4",32000,0)))) -> 20000 | BN50: =IF(AND(G50>0,(P50+Q50)>=5),"Trừ tiền","Xem lại") -> Trừ tiền | BS50: =AQ50+SUM(BO50:BR50)-AN50-AO50-SUM(BY50:CA50) -> 5516462 | BT50: 0 | BU50: =BT50*4400000 -> 0 | BV50: 11000000 | BW50: =BU50+BV50 -> 11000000 | BX50: =BS50-SUM(CC50:CD50)-CB50-AZ50-BW50 -> -6111438 | CE50: 11500000 | CF50: =CE50*10% -> 1150000 | CG50: 0 | CH50: 0 | CJ50: =SUM(CF50:CI50) -> 1150000 | CK50: =CE50+CJ50 -> 12650000 | CM50: =CE50 -> 11500000 | CN50: =CF50 -> 1150000 | CO50: =CG50 -> 0 | CP50: =CH50 -> 0 | CQ50: =CI50 -> 0 | CR50: =SUM(CN50:CQ50) -> 1150000 | CS50: =CM50+CR50 -> 12650000 | CT50: Công nhân Đóng xe thành phẩm vào container | CU50: Phòng Kho vận Auto | CV50: Nguyendinhvy2018@gmail.com | CW50: Chu Lai
A51: =SUBTOTAL(3,$C$11:C51) -> 33 | B51: 2210274 | C51: Dương Hoàng Vũ | D51: THILOGI | E51: =IF(CL51>=400000000,"A1",IF(CL51>=300000000,"A2",IF(CL51>=240000000,"A3",IF(CL51>=180000000,"A4",IF(CL51>=120000000,"A5",IF(CL51>=80000000,"A6",IF(CL51>=40000000,"A7",IF(CL51>=25000000,"B1",IF(CL51>=12000000,"B2","B3"))))))))) -> B3 | F51: 44840 | G51: 4750000 | I51: =IF(G51>0,CM51-G51,CM51-H51) -> 4250000 | J51: =CR51 -> 0 | K51: =SUM(I51:J51) -> 4250000 | L51: =IF(G51>0,G51+K51,H51+K51) -> 9000000 | M51: =IF(CE51>=11000000,80%,100%) -> 1 | N51: =ROUND(MAX(G51*70%,H51*70%,3640000),0) -> 3640000 | O51: 0 | P51: 12.5 | Q51: 0 | R51: 2.47 | S51: 0 | AD51: 0.31 | AE51: =IF(OR(BL51="M1",BL51="M2",BL51="M3",BL51="M4"),P51+R51+S51+T51+U51,0) -> 14.97 | AF51: =ROUND(IF($P51=0,0,IF(OR($BJ51="lương tháng",$CE51>=11000000),($L51/2-$L51/26*($CC$6-$P51))*$M51,$L51/26*$P51*$M51)),0) -> 4326923 | AG51: =ROUND(MAX((G51+I51)*M51/26*R51,(H51+I51)*M51/26*R51,G51/26*R51*150%,H51/26*R51*150%)*BK51,0) -> 855000 | AH51: =ROUND(MAX((G51+I51)*M51/26*S51,(H51+I51)*M51/26*S51,G51/26*S51*200%,H51/26*S51*200%)*BK51,0) -> 0 | AI51: =ROUND(IF(BJ51="Lương tháng",L51/26*T51,MAX((G51+I51)/26*(T51+U51)*200%+G51/26*T51,(H51+I51)/26*(T51+U51)*200%+H51/26*T51,G51/26*(T51+U51)*300%+G51/26*T51,H51/26*(T51+U51)*300%+H51/26*T51)),0) -> 0 | AJ51: =ROUND(IF((P51+Q51)=0,0,IF(BJ51="Lương tháng",MAX((G51+I51)/26*V51,(H51+I51)/26*V51),MAX(G51/26*V51,H51/26*V51))),0) -> 0 | AK51: =ROUND(IF(G51>0,G51/26*W51,H51/26*W51),0) -> 0 | AL51: =ROUND(N51/26*Y51+O51/26*Z51+MAX(G51/26*AA51,H51/26*AA51),0) -> 0 | AM51: =ROUND(IF(BJ51="Lương tháng",L51/26*AC51,L51/26*AC51+MAX((G51+I51)/26*AB51,(H51+I51)/26*AB51)),0) -> 0 | AN51: =ROUND(IF(BJ51="lương tháng",0,MAX((G51+I51)/26*AD51*30%,(H51+I51)/26*AD51*30%)*BK51),0) -> 32192 | AO51: =ROUND(BM51*AE51,0) -> 299400 | AP51: 0 | AQ51: =ROUND(SUM(AF51:AP51),0) -> 5513515 | AV51: =ROUND(SUM(AQ51:AT51)-AU51,0) -> 5513515 | AW51: =ROUND(IF($BH51=1,$G51*$AW$9,0),0) -> 380000 | AX51: =ROUND(IF($BH51=1,$G51*$AX$9,0),0) -> 71250 | AY51: =ROUND(IF($BH51=1,$G51*$AY$9,0),0) -> 47500 | AZ51: =SUM(AW51:AY51) -> 498750 | BA51: =ROUND(IF($BI51="1x",$G51*0.5%,0),0) -> 23750 | BB51: =IF(BN51="Xem lại",0,IF(CM51<11000000,5000,IF(AND(CM51>=11000000,CM51<25000000),10000,IF(AND(CM51>=25000000,CM51<40000000),15000,IF(AND(CM51>=40000000,CM51<120000000),20000,IF(AND(CM51>=120000000,CM51<240000000),25000,30000)))))*$BB$9) -> 110000 | BD51: 0 | BE51: =ROUND(SUM(AZ51:BD51),0) -> 632500 | BF51: =ROUND(IF(AV51>BE51,AV51-BE51,0),0) -> 4881015 | BG51: =ROUND(IF(BE51>AV51,BE51-AV51,0),0) -> 0 | BH51: 1 | BI51: 1x | BJ51: =IF(AND(D51="QTNV CL",CM51>=11000000),"Lương tháng",IF(CM51>=18000000,"Lương tháng",0)) -> 0 | BK51: =IF(BJ51="Lương tháng",0,1) -> 1 | BL51: M2 | BM51: =IF(BL51="M1",13000,IF(BL51="M2",20000,IF(BL51="M3",26000,IF(BL51="M4",32000,0)))) -> 20000 | BN51: =IF(AND(G51>0,(P51+Q51)>=5),"Trừ tiền","Xem lại") -> Trừ tiền | BS51: =AQ51+SUM(BO51:BR51)-AN51-AO51-SUM(BY51:CA51) -> 5181923 | BT51: 2 | BU51: =BT51*4400000 -> 8800000 | BV51: 11000000 | BW51: =BU51+BV51 -> 19800000 | BX51: =BS51-SUM(CC51:CD51)-CB51-AZ51-BW51 -> -15116827 | CE51: 9000000 | CF51: 0 | CG51: 0 | CH51: 0 | CJ51: =SUM(CF51:CI51) -> 0 | CK51: =CE51+CJ51 -> 9000000 | CM51: =CE51 -> 9000000 | CN51: =CF51 -> 0 | CO51: =CG51 -> 0 | CP51: =CH51 -> 0 | CQ51: =CI51 -> 0 | CR51: =SUM(CN51:CQ51) -> 0 | CS51: =CM51+CR51 -> 9000000 | CT51: Công nhân Đóng xe thành phẩm vào container | CU51: Phòng Kho vận Auto | CV51: hoangvu21082@gmail.com | CW51: Chu Lai
A52: =SUBTOTAL(3,$C$11:C52) -> 34 | B52: 2210283 | C52: Nguyễn Thanh Tùng | D52: THILOGI | E52: =IF(CL52>=400000000,"A1",IF(CL52>=300000000,"A2",IF(CL52>=240000000,"A3",IF(CL52>=180000000,"A4",IF(CL52>=120000000,"A5",IF(CL52>=80000000,"A6",IF(CL52>=40000000,"A7",IF(CL52>=25000000,"B1",IF(CL52>=12000000,"B2","B3"))))))))) -> B3 | F52: 44840 | G52: 4750000 | I52: =IF(G52>0,CM52-G52,CM52-H52) -> 4250000 | J52: =CR52 -> 0 | K52: =SUM(I52:J52) -> 4250000 | L52: =IF(G52>0,G52+K52,H52+K52) -> 9000000 | M52: =IF(CE52>=11000000,80%,100%) -> 1 | N52: =ROUND(MAX(G52*70%,H52*70%,3640000),0) -> 3640000 | O52: 0 | P52: 13 | Q52: 0 | R52: 2.45 | S52: 0 | AD52: 0.31 | AE52: =IF(OR(BL52="M1",BL52="M2",BL52="M3",BL52="M4"),P52+R52+S52+T52+U52,0) -> 15.45 | AF52: =ROUND(IF($P52=0,0,IF(OR($BJ52="lương tháng",$CE52>=11000000),($L52/2-$L52/26*($CC$6-$P52))*$M52,$L52/26*$P52*$M52)),0) -> 4500000 | AG52: =ROUND(MAX((G52+I52)*M52/26*R52,(H52+I52)*M52/26*R52,G52/26*R52*150%,H52/26*R52*150%)*BK52,0) -> 848077 | AH52: =ROUND(MAX((G52+I52)*M52/26*S52,(H52+I52)*M52/26*S52,G52/26*S52*200%,H52/26*S52*200%)*BK52,0) -> 0 | AI52: =ROUND(IF(BJ52="Lương tháng",L52/26*T52,MAX((G52+I52)/26*(T52+U52)*200%+G52/26*T52,(H52+I52)/26*(T52+U52)*200%+H52/26*T52,G52/26*(T52+U52)*300%+G52/26*T52,H52/26*(T52+U52)*300%+H52/26*T52)),0) -> 0 | AJ52: =ROUND(IF((P52+Q52)=0,0,IF(BJ52="Lương tháng",MAX((G52+I52)/26*V52,(H52+I52)/26*V52),MAX(G52/26*V52,H52/26*V52))),0) -> 0 | AK52: =ROUND(IF(G52>0,G52/26*W52,H52/26*W52),0) -> 0 | AL52: =ROUND(N52/26*Y52+O52/26*Z52+MAX(G52/26*AA52,H52/26*AA52),0) -> 0 | AM52: =ROUND(IF(BJ52="Lương tháng",L52/26*AC52,L52/26*AC52+MAX((G52+I52)/26*AB52,(H52+I52)/26*AB52)),0) -> 0 | AN52: =ROUND(IF(BJ52="lương tháng",0,MAX((G52+I52)/26*AD52*30%,(H52+I52)/26*AD52*30%)*BK52),0) -> 32192 | AO52: =ROUND(BM52*AE52,0) -> 309000 | AP52: 0 | AQ52: =ROUND(SUM(AF52:AP52),0) -> 5689269 | AV52: =ROUND(SUM(AQ52:AT52)-AU52,0) -> 5689269 | AW52: =ROUND(IF($BH52=1,$G52*$AW$9,0),0) -> 380000 | AX52: =ROUND(IF($BH52=1,$G52*$AX$9,0),0) -> 71250 | AY52: =ROUND(IF($BH52=1,$G52*$AY$9,0),0) -> 47500 | AZ52: =SUM(AW52:AY52) -> 498750 | BA52: =ROUND(IF($BI52="1x",$G52*0.5%,0),0) -> 23750 | BB52: =IF(BN52="Xem lại",0,IF(CM52<11000000,5000,IF(AND(CM52>=11000000,CM52<25000000),10000,IF(AND(CM52>=25000000,CM52<40000000),15000,IF(AND(CM52>=40000000,CM52<120000000),20000,IF(AND(CM52>=120000000,CM52<240000000),25000,30000)))))*$BB$9) -> 110000 | BD52: 0 | BE52: =ROUND(SUM(AZ52:BD52),0) -> 632500 | BF52: =ROUND(IF(AV52>BE52,AV52-BE52,0),0) -> 5056769 | BG52: =ROUND(IF(BE52>AV52,BE52-AV52,0),0) -> 0 | BH52: 1 | BI52: 1x | BJ52: =IF(AND(D52="QTNV CL",CM52>=11000000),"Lương tháng",IF(CM52>=18000000,"Lương tháng",0)) -> 0 | BK52: =IF(BJ52="Lương tháng",0,1) -> 1 | BL52: M2 | BM52: =IF(BL52="M1",13000,IF(BL52="M2",20000,IF(BL52="M3",26000,IF(BL52="M4",32000,0)))) -> 20000 | BN52: =IF(AND(G52>0,(P52+Q52)>=5),"Trừ tiền","Xem lại") -> Trừ tiền | BS52: =AQ52+SUM(BO52:BR52)-AN52-AO52-SUM(BY52:CA52) -> 5348077 | BT52: 0 | BU52: =BT52*4400000 -> 0 | BV52: 11000000 | BW52: =BU52+BV52 -> 11000000 | BX52: =BS52-SUM(CC52:CD52)-CB52-AZ52-BW52 -> -6150673 | CE52: 9000000 | CF52: 0 | CG52: 0 | CH52: 0 | CJ52: =SUM(CF52:CI52) -> 0 | CK52: =CE52+CJ52 -> 9000000 | CM52: =CE52 -> 9000000 | CN52: =CF52 -> 0 | CO52: =CG52 -> 0 | CP52: =CH52 -> 0 | CQ52: =CI52 -> 0 | CR52: =SUM(CN52:CQ52) -> 0 | CS52: =CM52+CR52 -> 9000000 | CT52: Công nhân Đóng xe thành phẩm vào container | CU52: Phòng Kho vận Auto | CV52: thanhtungnt1002@gmail.com | CW52: Chu Lai
A53: =SUBTOTAL(3,$C$11:C53) -> 35 | B53: 2011357 | C53: Nguyễn Đình May | D53: THILOGI | E53: =IF(CL53>=400000000,"A1",IF(CL53>=300000000,"A2",IF(CL53>=240000000,"A3",IF(CL53>=180000000,"A4",IF(CL53>=120000000,"A5",IF(CL53>=80000000,"A6",IF(CL53>=40000000,"A7",IF(CL53>=25000000,"B1",IF(CL53>=12000000,"B2","B3"))))))))) -> B3 | F53: 44147 | G53: 4750000 | I53: =IF(G53>0,CM53-G53,CM53-H53) -> 4250000 | J53: =CR53 -> 0 | K53: =SUM(I53:J53) -> 4250000 | L53: =IF(G53>0,G53+K53,H53+K53) -> 9000000 | M53: =IF(CE53>=11000000,80%,100%) -> 1 | N53: =ROUND(MAX(G53*70%,H53*70%,3640000),0) -> 3640000 | O53: 0 | P53: 12.5 | Q53: 0 | R53: 2.96 | S53: 0 | AD53: 1.31 | AE53: =IF(OR(BL53="M1",BL53="M2",BL53="M3",BL53="M4"),P53+R53+S53+T53+U53,0) -> 15.46 | AF53: =ROUND(IF($P53=0,0,IF(OR($BJ53="lương tháng",$CE53>=11000000),($L53/2-$L53/26*($CC$6-$P53))*$M53,$L53/26*$P53*$M53)),0) -> 4326923 | AG53: =ROUND(MAX((G53+I53)*M53/26*R53,(H53+I53)*M53/26*R53,G53/26*R53*150%,H53/26*R53*150%)*BK53,0) -> 1024615 | AH53: =ROUND(MAX((G53+I53)*M53/26*S53,(H53+I53)*M53/26*S53,G53/26*S53*200%,H53/26*S53*200%)*BK53,0) -> 0 | AI53: =ROUND(IF(BJ53="Lương tháng",L53/26*T53,MAX((G53+I53)/26*(T53+U53)*200%+G53/26*T53,(H53+I53)/26*(T53+U53)*200%+H53/26*T53,G53/26*(T53+U53)*300%+G53/26*T53,H53/26*(T53+U53)*300%+H53/26*T53)),0) -> 0 | AJ53: =ROUND(IF((P53+Q53)=0,0,IF(BJ53="Lương tháng",MAX((G53+I53)/26*V53,(H53+I53)/26*V53),MAX(G53/26*V53,H53/26*V53))),0) -> 0 | AK53: =ROUND(IF(G53>0,G53/26*W53,H53/26*W53),0) -> 0 | AL53: =ROUND(N53/26*Y53+O53/26*Z53+MAX(G53/26*AA53,H53/26*AA53),0) -> 0 | AM53: =ROUND(IF(BJ53="Lương tháng",L53/26*AC53,L53/26*AC53+MAX((G53+I53)/26*AB53,(H53+I53)/26*AB53)),0) -> 0 | AN53: =ROUND(IF(BJ53="lương tháng",0,MAX((G53+I53)/26*AD53*30%,(H53+I53)/26*AD53*30%)*BK53),0) -> 136038 | AO53: =ROUND(BM53*AE53,0) -> 309200 | AP53: 0 | AQ53: =ROUND(SUM(AF53:AP53),0) -> 5796776 | AV53: =ROUND(SUM(AQ53:AT53)-AU53,0) -> 5796776 | AW53: =ROUND(IF($BH53=1,$G53*$AW$9,0),0) -> 380000 | AX53: =ROUND(IF($BH53=1,$G53*$AX$9,0),0) -> 71250 | AY53: =ROUND(IF($BH53=1,$G53*$AY$9,0),0) -> 47500 | AZ53: =SUM(AW53:AY53) -> 498750 | BA53: =ROUND(IF($BI53="1x",$G53*0.5%,0),0) -> 23750 | BB53: =IF(BN53="Xem lại",0,IF(CM53<11000000,5000,IF(AND(CM53>=11000000,CM53<25000000),10000,IF(AND(CM53>=25000000,CM53<40000000),15000,IF(AND(CM53>=40000000,CM53<120000000),20000,IF(AND(CM53>=120000000,CM53<240000000),25000,30000)))))*$BB$9) -> 110000 | BD53: 0 | BE53: =ROUND(SUM(AZ53:BD53),0) -> 632500 | BF53: =ROUND(IF(AV53>BE53,AV53-BE53,0),0) -> 5164276 | BG53: =ROUND(IF(BE53>AV53,BE53-AV53,0),0) -> 0 | BH53: 1 | BI53: 1x | BJ53: =IF(AND(D53="QTNV CL",CM53>=11000000),"Lương tháng",IF(CM53>=18000000,"Lương tháng",0)) -> 0 | BK53: =IF(BJ53="Lương tháng",0,1) -> 1 | BL53: M2 | BM53: =IF(BL53="M1",13000,IF(BL53="M2",20000,IF(BL53="M3",26000,IF(BL53="M4",32000,0)))) -> 20000 | BN53: =IF(AND(G53>0,(P53+Q53)>=5),"Trừ tiền","Xem lại") -> Trừ tiền | BS53: =AQ53+SUM(BO53:BR53)-AN53-AO53-SUM(BY53:CA53) -> 5351538 | BT53: 0 | BU53: =BT53*4400000 -> 0 | BV53: 11000000 | BW53: =BU53+BV53 -> 11000000 | BX53: =BS53-SUM(CC53:CD53)-CB53-AZ53-BW53 -> -6147212 | CE53: 9000000 | CF53: 0 | CG53: 0 | CH53: 0 | CJ53: =SUM(CF53:CI53) -> 0 | CK53: =CE53+CJ53 -> 9000000 | CM53: =CE53 -> 9000000 | CN53: =CF53 -> 0 | CO53: =CG53 -> 0 | CP53: =CH53 -> 0 | CQ53: =CI53 -> 0 | CR53: =SUM(CN53:CQ53) -> 0 | CS53: =CM53+CR53 -> 9000000 | CT53: Công nhân Đóng xe thành phẩm vào container | CU53: Phòng Kho vận Auto | CV53: nguyenmay15041975@gmail.com | CW53: Chu Lai
A54: =SUBTOTAL(3,$C$11:C54) -> 36 | B54: 1505702 | C54: Nguyễn Đức Hạnh | D54: THILOGI | E54: =IF(CL54>=400000000,"A1",IF(CL54>=300000000,"A2",IF(CL54>=240000000,"A3",IF(CL54>=180000000,"A4",IF(CL54>=120000000,"A5",IF(CL54>=80000000,"A6",IF(CL54>=40000000,"A7",IF(CL54>=25000000,"B1",IF(CL54>=12000000,"B2","B3"))))))))) -> B3 | F54: 42140 | G54: 4990000 | I54: =IF(G54>0,CM54-G54,CM54-H54) -> 5010000 | J54: =CR54 -> 1000000 | K54: =SUM(I54:J54) -> 6010000 | L54: =IF(G54>0,G54+K54,H54+K54) -> 11000000 | M54: =IF(CE54>=11000000,80%,100%) -> 1 | N54: =ROUND(MAX(G54*70%,H54*70%,3640000),0) -> 3640000 | O54: 0 | P54: 13 | Q54: 0 | R54: 3.61 | S54: 0 | AD54: 1.31 | AE54: =IF(OR(BL54="M1",BL54="M2",BL54="M3",BL54="M4"),P54+R54+S54+T54+U54,0) -> 16.61 | AF54: =ROUND(IF($P54=0,0,IF(OR($BJ54="lương tháng",$CE54>=11000000),($L54/2-$L54/26*($CC$6-$P54))*$M54,$L54/26*$P54*$M54)),0) -> 5500000 | AG54: =ROUND(MAX((G54+I54)*M54/26*R54,(H54+I54)*M54/26*R54,G54/26*R54*150%,H54/26*R54*150%)*BK54,0) -> 1388462 | AH54: =ROUND(MAX((G54+I54)*M54/26*S54,(H54+I54)*M54/26*S54,G54/26*S54*200%,H54/26*S54*200%)*BK54,0) -> 0 | AI54: =ROUND(IF(BJ54="Lương tháng",L54/26*T54,MAX((G54+I54)/26*(T54+U54)*200%+G54/26*T54,(H54+I54)/26*(T54+U54)*200%+H54/26*T54,G54/26*(T54+U54)*300%+G54/26*T54,H54/26*(T54+U54)*300%+H54/26*T54)),0) -> 0 | AJ54: =ROUND(IF((P54+Q54)=0,0,IF(BJ54="Lương tháng",MAX((G54+I54)/26*V54,(H54+I54)/26*V54),MAX(G54/26*V54,H54/26*V54))),0) -> 0 | AK54: =ROUND(IF(G54>0,G54/26*W54,H54/26*W54),0) -> 0 | AL54: =ROUND(N54/26*Y54+O54/26*Z54+MAX(G54/26*AA54,H54/26*AA54),0) -> 0 | AM54: =ROUND(IF(BJ54="Lương tháng",L54/26*AC54,L54/26*AC54+MAX((G54+I54)/26*AB54,(H54+I54)/26*AB54)),0) -> 0 | AN54: =ROUND(IF(BJ54="lương tháng",0,MAX((G54+I54)/26*AD54*30%,(H54+I54)/26*AD54*30%)*BK54),0) -> 151154 | AO54: =ROUND(BM54*AE54,0) -> 332200 | AP54: 0 | AQ54: =ROUND(SUM(AF54:AP54),0) -> 7371816 | AV54: =ROUND(SUM(AQ54:AT54)-AU54,0) -> 7371816 | AW54: =ROUND(IF($BH54=1,$G54*$AW$9,0),0) -> 399200 | AX54: =ROUND(IF($BH54=1,$G54*$AX$9,0),0) -> 74850 | AY54: =ROUND(IF($BH54=1,$G54*$AY$9,0),0) -> 49900 | AZ54: =SUM(AW54:AY54) -> 523950 | BA54: =ROUND(IF($BI54="1x",$G54*0.5%,0),0) -> 24950 | BB54: =IF(BN54="Xem lại",0,IF(CM54<11000000,5000,IF(AND(CM54>=11000000,CM54<25000000),10000,IF(AND(CM54>=25000000,CM54<40000000),15000,IF(AND(CM54>=40000000,CM54<120000000),20000,IF(AND(CM54>=120000000,CM54<240000000),25000,30000)))))*$BB$9) -> 110000 | BD54: 0 | BE54: =ROUND(SUM(AZ54:BD54),0) -> 658900 | BF54: =ROUND(IF(AV54>BE54,AV54-BE54,0),0) -> 6712916 | BG54: =ROUND(IF(BE54>AV54,BE54-AV54,0),0) -> 0 | BH54: 1 | BI54: 1x | BJ54: =IF(AND(D54="QTNV CL",CM54>=11000000),"Lương tháng",IF(CM54>=18000000,"Lương tháng",0)) -> 0 | BK54: =IF(BJ54="Lương tháng",0,1) -> 1 | BL54: M2 | BM54: =IF(BL54="M1",13000,IF(BL54="M2",20000,IF(BL54="M3",26000,IF(BL54="M4",32000,0)))) -> 20000 | BN54: =IF(AND(G54>0,(P54+Q54)>=5),"Trừ tiền","Xem lại") -> Trừ tiền | BS54: =AQ54+SUM(BO54:BR54)-AN54-AO54-SUM(BY54:CA54) -> 6888462 | BT54: 0 | BU54: =BT54*4400000 -> 0 | BV54: 11000000 | BW54: =BU54+BV54 -> 11000000 | BX54: =BS54-SUM(CC54:CD54)-CB54-AZ54-BW54 -> -4635488 | CE54: 10000000 | CF54: =CE54*10% -> 1000000 | CG54: 0 | CH54: 0 | CJ54: =SUM(CF54:CI54) -> 1000000 | CK54: =CE54+CJ54 -> 11000000 | CM54: =CE54 -> 10000000 | CN54: =CF54 -> 1000000 | CO54: =CG54 -> 0 | CP54: =CH54 -> 0 | CQ54: =CI54 -> 0 | CR54: =SUM(CN54:CQ54) -> 1000000 | CS54: =CM54+CR54 -> 11000000 | CT54: Công nhân Đóng xe thành phẩm vào container | CU54: Phòng Kho vận Auto | CV54: nguyenduchanh010194@gmail.com | CW54: Chu Lai
A55: =SUBTOTAL(3,$C$11:C55) -> 37 | B55: 21051060 | C55: Lê Văn Phước | D55: THILOGI | E55: =IF(CL55>=400000000,"A1",IF(CL55>=300000000,"A2",IF(CL55>=240000000,"A3",IF(CL55>=180000000,"A4",IF(CL55>=120000000,"A5",IF(CL55>=80000000,"A6",IF(CL55>=40000000,"A7",IF(CL55>=25000000,"B1",IF(CL55>=12000000,"B2","B3"))))))))) -> B3 | F55: 44328 | G55: 4750000 | I55: =IF(G55>0,CM55-G55,CM55-H55) -> 4750000 | J55: =CR55 -> 0 | K55: =SUM(I55:J55) -> 4750000 | L55: =IF(G55>0,G55+K55,H55+K55) -> 9500000 | M55: =IF(CE55>=11000000,80%,100%) -> 1 | N55: =ROUND(MAX(G55*70%,H55*70%,3640000),0) -> 3640000 | O55: 0 | P55: 13 | Q55: 0 | R55: 1.5 | S55: 0 | AD55: 0 | AE55: =IF(OR(BL55="M1",BL55="M2",BL55="M3",BL55="M4"),P55+R55+S55+T55+U55,0) -> 14.5 | AF55: =ROUND(IF($P55=0,0,IF(OR($BJ55="lương tháng",$CE55>=11000000),($L55/2-$L55/26*($CC$6-$P55))*$M55,$L55/26*$P55*$M55)),0) -> 4750000 | AG55: =ROUND(MAX((G55+I55)*M55/26*R55,(H55+I55)*M55/26*R55,G55/26*R55*150%,H55/26*R55*150%)*BK55,0) -> 548077 | AH55: =ROUND(MAX((G55+I55)*M55/26*S55,(H55+I55)*M55/26*S55,G55/26*S55*200%,H55/26*S55*200%)*BK55,0) -> 0 | AI55: =ROUND(IF(BJ55="Lương tháng",L55/26*T55,MAX((G55+I55)/26*(T55+U55)*200%+G55/26*T55,(H55+I55)/26*(T55+U55)*200%+H55/26*T55,G55/26*(T55+U55)*300%+G55/26*T55,H55/26*(T55+U55)*300%+H55/26*T55)),0) -> 0 | AJ55: =ROUND(IF((P55+Q55)=0,0,IF(BJ55="Lương tháng",MAX((G55+I55)/26*V55,(H55+I55)/26*V55),MAX(G55/26*V55,H55/26*V55))),0) -> 0 | AK55: =ROUND(IF(G55>0,G55/26*W55,H55/26*W55),0) -> 0 | AL55: =ROUND(N55/26*Y55+O55/26*Z55+MAX(G55/26*AA55,H55/26*AA55),0) -> 0 | AM55: =ROUND(IF(BJ55="Lương tháng",L55/26*AC55,L55/26*AC55+MAX((G55+I55)/26*AB55,(H55+I55)/26*AB55)),0) -> 0 | AN55: =ROUND(IF(BJ55="lương tháng",0,MAX((G55+I55)/26*AD55*30%,(H55+I55)/26*AD55*30%)*BK55),0) -> 0 | AO55: =ROUND(BM55*AE55,0) -> 290000 | AP55: 0 | AQ55: =ROUND(SUM(AF55:AP55),0) -> 5588077 | AV55: =ROUND(SUM(AQ55:AT55)-AU55,0) -> 5588077 | AW55: =ROUND(IF($BH55=1,$G55*$AW$9,0),0) -> 380000 | AX55: =ROUND(IF($BH55=1,$G55*$AX$9,0),0) -> 71250 | AY55: =ROUND(IF($BH55=1,$G55*$AY$9,0),0) -> 47500 | AZ55: =SUM(AW55:AY55) -> 498750 | BA55: =ROUND(IF($BI55="1x",$G55*0.5%,0),0) -> 23750 | BB55: =IF(BN55="Xem lại",0,IF(CM55<11000000,5000,IF(AND(CM55>=11000000,CM55<25000000),10000,IF(AND(CM55>=25000000,CM55<40000000),15000,IF(AND(CM55>=40000000,CM55<120000000),20000,IF(AND(CM55>=120000000,CM55<240000000),25000,30000)))))*$BB$9) -> 0 | BD55: 0 | BE55: =ROUND(SUM(AZ55:BD55),0) -> 522500 | BF55: =ROUND(IF(AV55>BE55,AV55-BE55,0),0) -> 5065577 | BG55: =ROUND(IF(BE55>AV55,BE55-AV55,0),0) -> 0 | BH55: 1 | BI55: 1x | BJ55: =IF(AND(D55="QTNV CL",CM55>=11000000),"Lương tháng",IF(CM55>=18000000,"Lương tháng",0)) -> 0 | BK55: =IF(BJ55="Lương tháng",0,1) -> 1 | BL55: M2 | BM55: =IF(BL55="M1",13000,IF(BL55="M2",20000,IF(BL55="M3",26000,IF(BL55="M4",32000,0)))) -> 20000 | BN55: Xem lại | BS55: =AQ55+SUM(BO55:BR55)-AN55-AO55-SUM(BY55:CA55) -> 5298077 | BT55: 0 | BU55: =BT55*4400000 -> 0 | BV55: 11000000 | BW55: =BU55+BV55 -> 11000000 | BX55: =BS55-SUM(CC55:CD55)-CB55-AZ55-BW55 -> -6200673 | CE55: 9500000 | CJ55: =SUM(CF55:CI55) -> 0 | CK55: =CE55+CJ55 -> 9500000 | CM55: =CE55 -> 9500000 | CN55: =CF55 -> 0 | CO55: =CG55 -> 0 | CP55: =CH55 -> 0 | CQ55: =CI55 -> 0 | CR55: =SUM(CN55:CQ55) -> 0 | CS55: =CM55+CR55 -> 9500000 | CT55: Công nhân Đóng xe thành phẩm vào container | CU55: Phòng Kho vận Auto | CV55: levanphuoc06102022@gmail.com | CW55: Chu Lai
A56: =SUBTOTAL(3,$C$11:C56) -> 38 | B56: 1505216 | C56: Nguyễn Cường | D56: THILOGI | E56: =IF(CL56>=400000000,"A1",IF(CL56>=300000000,"A2",IF(CL56>=240000000,"A3",IF(CL56>=180000000,"A4",IF(CL56>=120000000,"A5",IF(CL56>=80000000,"A6",IF(CL56>=40000000,"A7",IF(CL56>=25000000,"B1",IF(CL56>=12000000,"B2","B3"))))))))) -> B3 | F56: 42110 | G56: 4300000 | I56: =IF(G56>0,CM56-G56,CM56-H56) -> 4200000 | J56: =CR56 -> 850000 | K56: =SUM(I56:J56) -> 5050000 | L56: =IF(G56>0,G56+K56,H56+K56) -> 9350000 | M56: =IF(CE56>=11000000,80%,100%) -> 1 | N56: =ROUND(MAX(G56*70%,H56*70%,3640000),0) -> 3640000 | O56: 0 | P56: 12.5 | Q56: 0 | R56: 2.39 | S56: 0 | AD56: 0.31 | AE56: =IF(OR(BL56="M1",BL56="M2",BL56="M3",BL56="M4"),P56+R56+S56+T56+U56,0) -> 14.89 | AF56: =ROUND(IF($P56=0,0,IF(OR($BJ56="lương tháng",$CE56>=11000000),($L56/2-$L56/26*($CC$6-$P56))*$M56,$L56/26*$P56*$M56)),0) -> 4495192 | AG56: =ROUND(MAX((G56+I56)*M56/26*R56,(H56+I56)*M56/26*R56,G56/26*R56*150%,H56/26*R56*150%)*BK56,0) -> 781346 | AH56: =ROUND(MAX((G56+I56)*M56/26*S56,(H56+I56)*M56/26*S56,G56/26*S56*200%,H56/26*S56*200%)*BK56,0) -> 0 | AI56: =ROUND(IF(BJ56="Lương tháng",L56/26*T56,MAX((G56+I56)/26*(T56+U56)*200%+G56/26*T56,(H56+I56)/26*(T56+U56)*200%+H56/26*T56,G56/26*(T56+U56)*300%+G56/26*T56,H56/26*(T56+U56)*300%+H56/26*T56)),0) -> 0 | AJ56: =ROUND(IF((P56+Q56)=0,0,IF(BJ56="Lương tháng",MAX((G56+I56)/26*V56,(H56+I56)/26*V56),MAX(G56/26*V56,H56/26*V56))),0) -> 0 | AK56: =ROUND(IF(G56>0,G56/26*W56,H56/26*W56),0) -> 0 | AL56: =ROUND(N56/26*Y56+O56/26*Z56+MAX(G56/26*AA56,H56/26*AA56),0) -> 0 | AM56: =ROUND(IF(BJ56="Lương tháng",L56/26*AC56,L56/26*AC56+MAX((G56+I56)/26*AB56,(H56+I56)/26*AB56)),0) -> 0 | AN56: =ROUND(IF(BJ56="lương tháng",0,MAX((G56+I56)/26*AD56*30%,(H56+I56)/26*AD56*30%)*BK56),0) -> 30404 | AO56: =ROUND(BM56*AE56,0) -> 297800 | AP56: 0 | AQ56: =ROUND(SUM(AF56:AP56),0) -> 5604742 | AR56: 0 | AV56: =ROUND(SUM(AQ56:AT56)-AU56,0) -> 5604742 | AW56: =ROUND(IF($BH56=1,$G56*$AW$9,0),0) -> 344000 | AX56: =ROUND(IF($BH56=1,$G56*$AX$9,0),0) -> 64500 | AY56: =ROUND(IF($BH56=1,$G56*$AY$9,0),0) -> 43000 | AZ56: =SUM(AW56:AY56) -> 451500 | BA56: =ROUND(IF($BI56="1x",$G56*0.5%,0),0) -> 21500 | BB56: =IF(BN56="Xem lại",0,IF(CM56<11000000,5000,IF(AND(CM56>=11000000,CM56<25000000),10000,IF(AND(CM56>=25000000,CM56<40000000),15000,IF(AND(CM56>=40000000,CM56<120000000),20000,IF(AND(CM56>=120000000,CM56<240000000),25000,30000)))))*$BB$9) -> 110000 | BD56: 0 | BE56: =ROUND(SUM(AZ56:BD56),0) -> 583000 | BF56: =ROUND(IF(AV56>BE56,AV56-BE56,0),0) -> 5021742 | BG56: =ROUND(IF(BE56>AV56,BE56-AV56,0),0) -> 0 | BH56: 1 | BI56: 1x | BJ56: =IF(AND(D56="QTNV CL",CM56>=11000000),"Lương tháng",IF(CM56>=18000000,"Lương tháng",0)) -> 0 | BK56: =IF(BJ56="Lương tháng",0,1) -> 1 | BL56: M2 | BM56: =IF(BL56="M1",13000,IF(BL56="M2",20000,IF(BL56="M3",26000,IF(BL56="M4",32000,0)))) -> 20000 | BN56: =IF(AND(G56>0,(P56+Q56)>=5),"Trừ tiền","Xem lại") -> Trừ tiền | BS56: =AQ56+SUM(BO56:BR56)-AN56-AO56-SUM(BY56:CA56) -> 5276538 | BT56: 0 | BU56: =BT56*4400000 -> 0 | BV56: 11000000 | BW56: =BU56+BV56 -> 11000000 | BX56: =BS56-SUM(CC56:CD56)-CB56-AZ56-BW56 -> -6174962 | CE56: 8500000 | CF56: =CE56*10% -> 850000 | CG56: 0 | CH56: 0 | CJ56: =SUM(CF56:CI56) -> 850000 | CK56: =CE56+CJ56 -> 9350000 | CM56: =CE56 -> 8500000 | CN56: =CF56 -> 850000 | CO56: =CG56 -> 0 | CP56: =CH56 -> 0 | CQ56: =CI56 -> 0 | CR56: =SUM(CN56:CQ56) -> 850000 | CS56: =CM56+CR56 -> 9350000 | CT56: Công nhân Đóng xe thành phẩm vào container | CU56: Phòng Kho vận Auto | CV56: nguyencuong070376@gmail.com | CW56: Chu Lai
A57: =SUBTOTAL(3,$C$11:C57) -> 39 | B57: 2210293 | C57: Trần Văn Lượng | D57: THILOGI | E57: =IF(CL57>=400000000,"A1",IF(CL57>=300000000,"A2",IF(CL57>=240000000,"A3",IF(CL57>=180000000,"A4",IF(CL57>=120000000,"A5",IF(CL57>=80000000,"A6",IF(CL57>=40000000,"A7",IF(CL57>=25000000,"B1",IF(CL57>=12000000,"B2","B3"))))))))) -> B3 | F57: 44840 | G57: 4520000 | I57: =IF(G57>0,CM57-G57,CM57-H57) -> 4180000 | J57: =CR57 -> 0 | K57: =SUM(I57:J57) -> 4180000 | L57: =IF(G57>0,G57+K57,H57+K57) -> 8700000 | M57: =IF(CE57>=11000000,80%,100%) -> 1 | N57: =ROUND(MAX(G57*70%,H57*70%,3640000),0) -> 3640000 | O57: 0 | P57: 13 | Q57: 0 | R57: 2.45 | S57: 0 | AD57: 0.31 | AE57: =IF(OR(BL57="M1",BL57="M2",BL57="M3",BL57="M4"),P57+R57+S57+T57+U57,0) -> 15.45 | AF57: =ROUND(IF($P57=0,0,IF(OR($BJ57="lương tháng",$CE57>=11000000),($L57/2-$L57/26*($CC$6-$P57))*$M57,$L57/26*$P57*$M57)),0) -> 4350000 | AG57: =ROUND(MAX((G57+I57)*M57/26*R57,(H57+I57)*M57/26*R57,G57/26*R57*150%,H57/26*R57*150%)*BK57,0) -> 819808 | AH57: =ROUND(MAX((G57+I57)*M57/26*S57,(H57+I57)*M57/26*S57,G57/26*S57*200%,H57/26*S57*200%)*BK57,0) -> 0 | AI57: =ROUND(IF(BJ57="Lương tháng",L57/26*T57,MAX((G57+I57)/26*(T57+U57)*200%+G57/26*T57,(H57+I57)/26*(T57+U57)*200%+H57/26*T57,G57/26*(T57+U57)*300%+G57/26*T57,H57/26*(T57+U57)*300%+H57/26*T57)),0) -> 0 | AJ57: =ROUND(IF((P57+Q57)=0,0,IF(BJ57="Lương tháng",MAX((G57+I57)/26*V57,(H57+I57)/26*V57),MAX(G57/26*V57,H57/26*V57))),0) -> 0 | AK57: =ROUND(IF(G57>0,G57/26*W57,H57/26*W57),0) -> 0 | AL57: =ROUND(N57/26*Y57+O57/26*Z57+MAX(G57/26*AA57,H57/26*AA57),0) -> 0 | AM57: =ROUND(IF(BJ57="Lương tháng",L57/26*AC57,L57/26*AC57+MAX((G57+I57)/26*AB57,(H57+I57)/26*AB57)),0) -> 0 | AN57: =ROUND(IF(BJ57="lương tháng",0,MAX((G57+I57)/26*AD57*30%,(H57+I57)/26*AD57*30%)*BK57),0) -> 31119 | AO57: =ROUND(BM57*AE57,0) -> 309000 | AP57: 0 | AQ57: =ROUND(SUM(AF57:AP57),0) -> 5509927 | AV57: =ROUND(SUM(AQ57:AT57)-AU57,0) -> 5509927 | AW57: =ROUND(IF($BH57=1,$G57*$AW$9,0),0) -> 361600 | AX57: =ROUND(IF($BH57=1,$G57*$AX$9,0),0) -> 67800 | AY57: =ROUND(IF($BH57=1,$G57*$AY$9,0),0) -> 45200 | AZ57: =SUM(AW57:AY57) -> 474600 | BA57: =ROUND(IF($BI57="1x",$G57*0.5%,0),0) -> 22600 | BB57: =IF(BN57="Xem lại",0,IF(CM57<11000000,5000,IF(AND(CM57>=11000000,CM57<25000000),10000,IF(AND(CM57>=25000000,CM57<40000000),15000,IF(AND(CM57>=40000000,CM57<120000000),20000,IF(AND(CM57>=120000000,CM57<240000000),25000,30000)))))*$BB$9) -> 110000 | BD57: 0 | BE57: =ROUND(SUM(AZ57:BD57),0) -> 607200 | BF57: =ROUND(IF(AV57>BE57,AV57-BE57,0),0) -> 4902727 | BG57: =ROUND(IF(BE57>AV57,BE57-AV57,0),0) -> 0 | BH57: 1 | BI57: 1x | BJ57: =IF(AND(D57="QTNV CL",CM57>=11000000),"Lương tháng",IF(CM57>=18000000,"Lương tháng",0)) -> 0 | BK57: =IF(BJ57="Lương tháng",0,1) -> 1 | BL57: M2 | BM57: =IF(BL57="M1",13000,IF(BL57="M2",20000,IF(BL57="M3",26000,IF(BL57="M4",32000,0)))) -> 20000 | BN57: =IF(AND(G57>0,(P57+Q57)>=5),"Trừ tiền","Xem lại") -> Trừ tiền | BS57: =AQ57+SUM(BO57:BR57)-AN57-AO57-SUM(BY57:CA57) -> 5169808 | BT57: 0 | BU57: =BT57*4400000 -> 0 | BV57: 11000000 | BW57: =BU57+BV57 -> 11000000 | BX57: =BS57-SUM(CC57:CD57)-CB57-AZ57-BW57 -> -6304792 | CE57: 8700000 | CF57: 0 | CG57: 0 | CH57: 0 | CJ57: =SUM(CF57:CI57) -> 0 | CK57: =CE57+CJ57 -> 8700000 | CM57: =CE57 -> 8700000 | CN57: =CF57 -> 0 | CO57: =CG57 -> 0 | CP57: =CH57 -> 0 | CQ57: =CI57 -> 0 | CR57: =SUM(CN57:CQ57) -> 0 | CS57: =CM57+CR57 -> 8700000 | CT57: Công nhân Đóng xe thành phẩm vào container | CU57: Phòng Kho vận Auto | CV57: luongtran.150793@gmail.com | CW57: Chu Lai
A58: =SUBTOTAL(3,$C$11:C58) -> 40 | B58: 24091138 | C58: Châu Ngọc Hiếu | D58: THILOGI | E58: =IF(CL58>=400000000,"A1",IF(CL58>=300000000,"A2",IF(CL58>=240000000,"A3",IF(CL58>=180000000,"A4",IF(CL58>=120000000,"A5",IF(CL58>=80000000,"A6",IF(CL58>=40000000,"A7",IF(CL58>=25000000,"B1",IF(CL58>=12000000,"B2","B3"))))))))) -> B3 | F58: 45541 | G58: 4520000 | I58: =IF(G58>0,CM58-G58,CM58-H58) -> 3480000 | J58: =CR58 -> 0 | K58: =SUM(I58:J58) -> 3480000 | L58: =IF(G58>0,G58+K58,H58+K58) -> 8000000 | M58: =IF(CE58>=11000000,80%,100%) -> 1 | N58: =ROUND(MAX(G58*70%,H58*70%,3640000),0) -> 3640000 | O58: 0 | P58: 12.5 | Q58: 0 | R58: 2.46 | S58: 0 | AD58: 0.31 | AE58: =IF(OR(BL58="M1",BL58="M2",BL58="M3",BL58="M4"),P58+R58+S58+T58+U58,0) -> 14.96 | AF58: =ROUND(IF($P58=0,0,IF(OR($BJ58="lương tháng",$CE58>=11000000),($L58/2-$L58/26*($CC$6-$P58))*$M58,$L58/26*$P58*$M58)),0) -> 3846154 | AG58: =ROUND(MAX((G58+I58)*M58/26*R58,(H58+I58)*M58/26*R58,G58/26*R58*150%,H58/26*R58*150%)*BK58,0) -> 756923 | AH58: =ROUND(MAX((G58+I58)*M58/26*S58,(H58+I58)*M58/26*S58,G58/26*S58*200%,H58/26*S58*200%)*BK58,0) -> 0 | AI58: =ROUND(IF(BJ58="Lương tháng",L58/26*T58,MAX((G58+I58)/26*(T58+U58)*200%+G58/26*T58,(H58+I58)/26*(T58+U58)*200%+H58/26*T58,G58/26*(T58+U58)*300%+G58/26*T58,H58/26*(T58+U58)*300%+H58/26*T58)),0) -> 0 | AJ58: =ROUND(IF((P58+Q58)=0,0,IF(BJ58="Lương tháng",MAX((G58+I58)/26*V58,(H58+I58)/26*V58),MAX(G58/26*V58,H58/26*V58))),0) -> 0 | AK58: =ROUND(IF(G58>0,G58/26*W58,H58/26*W58),0) -> 0 | AL58: =ROUND(N58/26*Y58+O58/26*Z58+MAX(G58/26*AA58,H58/26*AA58),0) -> 0 | AM58: =ROUND(IF(BJ58="Lương tháng",L58/26*AC58,L58/26*AC58+MAX((G58+I58)/26*AB58,(H58+I58)/26*AB58)),0) -> 0 | AN58: =ROUND(IF(BJ58="lương tháng",0,MAX((G58+I58)/26*AD58*30%,(H58+I58)/26*AD58*30%)*BK58),0) -> 28615 | AO58: =ROUND(BM58*AE58,0) -> 299200 | AP58: 0 | AQ58: =ROUND(SUM(AF58:AP58),0) -> 4930892 | AV58: =ROUND(SUM(AQ58:AT58)-AU58,0) -> 4930892 | AW58: =ROUND(IF($BH58=1,$G58*$AW$9,0),0) -> 361600 | AX58: =ROUND(IF($BH58=1,$G58*$AX$9,0),0) -> 67800 | AY58: =ROUND(IF($BH58=1,$G58*$AY$9,0),0) -> 45200 | AZ58: =SUM(AW58:AY58) -> 474600 | BA58: =ROUND(IF($BI58="1x",$G58*0.5%,0),0) -> 22600 | BB58: =IF(BN58="Xem lại",0,IF(CM58<11000000,5000,IF(AND(CM58>=11000000,CM58<25000000),10000,IF(AND(CM58>=25000000,CM58<40000000),15000,IF(AND(CM58>=40000000,CM58<120000000),20000,IF(AND(CM58>=120000000,CM58<240000000),25000,30000)))))*$BB$9) -> 110000 | BD58: 0 | BE58: =ROUND(SUM(AZ58:BD58),0) -> 607200 | BF58: =ROUND(IF(AV58>BE58,AV58-BE58,0),0) -> 4323692 | BG58: =ROUND(IF(BE58>AV58,BE58-AV58,0),0) -> 0 | BH58: 1 | BI58: 1x | BJ58: =IF(AND(D58="QTNV CL",CM58>=11000000),"Lương tháng",IF(CM58>=18000000,"Lương tháng",0)) -> 0 | BK58: =IF(BJ58="Lương tháng",0,1) -> 1 | BL58: M2 | BM58: =IF(BL58="M1",13000,IF(BL58="M2",20000,IF(BL58="M3",26000,IF(BL58="M4",32000,0)))) -> 20000 | BN58: =IF(AND(G58>0,(P58+Q58)>=5),"Trừ tiền","Xem lại") -> Trừ tiền | BS58: =AQ58+SUM(BO58:BR58)-AN58-AO58-SUM(BY58:CA58) -> 4603077 | BT58: 0 | BU58: =BT58*4400000 -> 0 | BV58: 11000000 | BW58: =BU58+BV58 -> 11000000 | BX58: =BS58-SUM(CC58:CD58)-CB58-AZ58-BW58 -> -6871523 | CE58: 8000000 | CJ58: =SUM(CF58:CI58) -> 0 | CK58: =CE58+CJ58 -> 8000000 | CM58: =CE58 -> 8000000 | CN58: =CF58 -> 0 | CO58: =CG58 -> 0 | CP58: =CH58 -> 0 | CQ58: =CI58 -> 0 | CR58: =SUM(CN58:CQ58) -> 0 | CS58: =CM58+CR58 -> 8000000 | CT58: Công nhân Đóng xe thành phẩm vào container | CU58: Phòng Kho vận Auto | CV58: Chaungochieu010175@gmail.com | CW58: Chu Lai
