Workbook
Name _: "SQRT"
Name _____KDX3: [1]!_____KDX3
Name ____KDX3: #N/A
Name ___a10: #N/A
Name ___atn1: #REF!
Name ___atn10: #REF!
Name ___atn2: #REF!
Name ___atn3: #REF!
Name ___atn4: #REF!
Name ___atn5: #REF!
Name ___atn6: #REF!
Name ___atn7: #REF!
Name ___atn8: #REF!
Name ___atn9: #REF!
Name ___Bia1: #N/A
Name ___Bia2: #N/A
Name ___boi1: #REF!
Name ___boi2: #REF!
Name ___BTM150: #REF!
Name ___BTM250: #REF!
Name ___BTM300: #REF!
Name ___cao1: #REF!
Name ___cao2: #REF!
Name ___cao3: #REF!
Name ___cao4: #REF!
Name ___cao5: #REF!
Name ___cao6: #REF!
Name ___coc250: #REF!
Name ___coc300: #REF!
Name ___coc350: #REF!
Name ___CON1: #REF!
Name ___CON2: #REF!
Name ___cpd1: #REF!
Name ___cpd2: #REF!
Name ___Cus1: #N/A
Name ___dai1: #REF!
Name ___dai2: #REF!
Name ___dai3: #REF!
Name ___dai4: #REF!
Name ___dai5: #REF!
Name ___dai6: #REF!
Name ___dan1: #REF!
Name ___dan2: #REF!
Name ___ddn400: #REF!
Name ___ddn600: #REF!
Name ___deo1: #REF!
Name ___deo10: #REF!
Name ___deo2: #REF!
Name ___deo3: #REF!
Name ___deo4: #REF!
Name ___deo5: #REF!
Name ___deo6: #REF!
Name ___deo7: #REF!
Name ___deo8: #REF!
Name ___deo9: #REF!
Name ___E99999: #REF!
Name ___gon4: #N/A
Name ___hom2: #N/A
Name ___KDX3: #N/A
Name ___lap1: #REF!

Sheet Template Payroll
A1: TEAMPLATE PAYROLL
A2: DATE: | D2: 45773
B3: A | D3: A | M3: A | AP3: 6200000 | AQ3: 0.08 | AR3: 0.015 | AS3: 0.01 | BA3: 0.17 | BB3: 0.03 | BC3: 0.01 | BD3: 0.005 | BF3: =2340000*20 -> 46800000 | BG3: =4960000*20 -> 99200000 | BH3: Truy thu BHYT 3% | BI3: Truy thu BHYT 1.5%
A4: No | B4: Emp. Code | C4: ID No | D4: Full name | E4: Joning Date | F4: Division | G4: Department | H4: Position | I4: Job title | J4: Income Salary | K4: Basic Salary | L4: Efficiency salary | M4: Standard working day | N4: Working day last month (21-25) | O4: Working day current month | P4: Actual Basic Salary last month (21-25) | Q4: Actual Basic Salary current month | R4: Total Actual Basic Salary | S4: Efficiency salary Advance last month (21-25) | T4: Efficiency salary Advance current month | U4: Total Efficiency salary Advance | V4: Responsibility Allows | W4: Transportation Allows | X4: Mob Allows | Y4: Meal Allows | Z4: Total Actual All Allows | AA4: Overtime | AB4: Night shift | AC4: Bonus | AD4: Acting Allowance | AE4: AL Remain | AF4: Rest of annual leave | AG4: Incentives | AH4: Other Allowance | AI4: Severance pay | AJ4: Total Gross Salary | AK4: OT untaxable | AL4: Night shift untaxable | AM4: Severance pay untaxable | AN4: Self- deduction | AO4: Qty. | AP4: AMT | AQ4: Social Ins. 8% | AR4: Health Ins. 1.5% | AS4: Jobless Ins. 1% | AT4: Total Ins. Employees paid 10.5% | AU4: Lunch Max (730,000đ) | AV4: Taxable income | AW4: Assessable income | AX4: Tax rate | AY4: Min Tax | AZ4: Monthly PIT 개인소득세 | BA4: Social Ins. 17% | BB4: Health Ins. 3% | BC4: Jobless Ins. 1% | BD4: Accident & occupational disease 0.5% | BE4: Total Ins. Employer paid 21.5% | BF4: Insurance salary (SI & HI) | BG4: Insurance salary (Jobless) | BH4: Obligation Health Insurance Employer | BI4: Obligation Health Insurance Employee | BJ4: Trade Union (Company) | BK4: Trade Union (Employee) | BL4: Support Funeral Fund | BM4: Net salary | BN4: Benefit TAX | BO4: PIT payable last year | BP4: Government funds | BQ4: Total Reduction | BR4: Total obligation of employee | BS4: Tham gia BHXH | BT4: Đối tượng tính thuế TNCN | BU4: Tham gia Công đoàn | BV4: Tham gia Tang chế | BW4: Số đám tang phát sinh trong kỳ | BX4: Email
A5: 1 | B5: SLA2500111 | D5: Nguyễn Thị Hà | E5: 27/07/2015 | F5: PVT - Store Manager | G5: Store Management | H5: Manager | I5: Store Manager - Emart Phan Van Tri | J5: 47000000 | K5: 10870000 | L5: =J5-K5 -> 36130000 | M5: 26 | N5: =IFERROR(VLOOKUP(B5,' TimeTB 1'!$B$4:$P$5,5,0),0) -> 0 | O5: =VLOOKUP(B5,'TimeTB 2'!$B$4:$O$11,14,0) -> 0 | P5: =ROUND(K5/M5*N5,0) -> 0 | Q5: =ROUND(K5/M5*O5,0) -> 0 | R5: =SUM(P5:Q5) -> 0 | S5: =ROUND(L5/26*N5,0) -> 0 | T5: =ROUND(L5/26*O5,0) -> 0 | U5: =SUM(S5:T5) -> 0 | V5: 0 | W5: 0 | X5: 0 | Y5: =VLOOKUP(B5,'PC cơm '!$A$3:$K$4,11,0) -> 0 | Z5: =SUM(V5:Y5) -> 0 | AA5: =VLOOKUP(B5,OT!A3:S15,17,0) -> 0 | AB5: =VLOOKUP(B5,NS!$A$2:$F$5,6,0) -> 135577 | AC5: 0 | AD5: 0 | AE5: 0 | AF5: =ROUND(J5/26*AE5,0) -> 0 | AG5: =IFERROR(VLOOKUP(B5,Incentive!$A$4:$G$6,7,0),0) -> 0 | AH5: =SUMIF(Others!$B$3:$B$9,$B5,Others!$F$3:$F$9) -> 0 | AI5: 0 | AJ5: =AI5+AH5+AG5+AF5+AD5+AC5+AB5+AA5+Z5+U5+R5+BN5 -> 335577 | AK5: =VLOOKUP(B5,OT!A3:S14,19,0) -> 0 | AL5: =VLOOKUP(B5,NS!$A$2:$H$5,8,0) -> 135577 | AM5: =AI5 -> 0 | AN5: =IF(BT5=1,0,15500000) -> 15500000 | AO5: 4 | AP5: =AO5*$AP$3 -> 24800000 | AQ5: =BF5*$AQ$3 -> 869600 | AR5: =BF5*$AR$3 -> 163050 | AS5: =BG5*$AS$3 -> 108700 | AT5: =+AS5+AR5+AQ5 -> 1141350 | AU5: =IF(BT5=1,0,MIN(Y5,730000)) -> 0 | AV5: =AJ5-AK5-AL5-AM5-AU5 -> 200000 | AW5: =MAX(AV5-AN5-AP5-AT5,0) -> 0 | AX5: =IF(BT5=1,10%,IF(AW5>0,IF(AW5>80000000,0.35,IF(AW5>52000000,0.3,IF(AW5>32000000,0.25,IF(AW5>18000000,0.2,IF(AW5>10000000,0.15,IF(AW5>5000000,0.1,0.05)))))),0)) -> 0 | AY5: =IF(BT5=1,0,IF(AW5>80000000,9850000,IF(AW5>52000000,5850000,IF(AW5>32000000,3250000,IF(AW5>18000000,1650000,IF(AW5>10000000,750000,IF(AW5>5000000,250000,0))))))) -> 0 | AZ5: =ROUND(AW5*AX5-AY5,0) -> 0 | BA5: =BF5*$BA$3 -> 1847900 | BB5: =BF5*$BB$3 -> 326100 | BC5: =BG5*$BC$3 -> 108700 | BD5: =BG5*$BD$3 -> 54350 | BE5: =SUM(BA5:BD5) -> 2337050 | BF5: =MIN((IF(BS5=1,K5,0)),$BF$3) -> 10870000 | BG5: =MIN((IF(BS5=1,K5,0)),$BG$3) -> 10870000 | BH5: 0 | BI5: 0 | BJ5: =IF(BS5=1,BF5*2%,0) -> 217400 | BK5: =IF(BU5=1,40000,0) -> 40000 | BL5: =IF(BV5=0,0,IF(J5<11000000,5000,IF(J5<25000000,10000,IF(J5<40000000,15000,20000)))*BW5) -> 0 | BM5: =AJ5-AT5-AZ5-BK5-BL5-BN5-BO5-BP5 -> -1045773 | BN5: =IFERROR(VLOOKUP(B5,'Benefit tính thuế'!$A$2:$G$5,7,0),0) -> 200000 | BO5: 0 | BP5: 0 | BQ5: =AN5+AP5+AU5 -> 40300000 | BR5: =+AZ5+AT5 -> 1141350 | BS5: 1 | BT5: 0 | BU5: 1 | BV5: 0 | BW5: 20
A6: 1 | B6: PHI2500112 | D6: Phùng Mạnh Hà | E6: 19/12/2022 | F6: PVT - Cooperate Function | G6: Cooperate Function | H6: Manager | I6: Corporate Function Manager | J6: 31000000 | K6: 8350000 | L6: =J6-K6 -> 22650000 | M6: 26 | N6: =IFERROR(VLOOKUP(B6,' TimeTB 1'!$B$4:$P$5,5,0),0) -> 0 | O6: =VLOOKUP(B6,'TimeTB 2'!$B$4:$O$11,14,0) -> 0 | P6: =ROUND((K6/M6*N6),0) -> 0 | Q6: =ROUND(K6/M6*O6,0) -> 0 | R6: =SUM(P6:Q6) -> 0 | S6: =ROUND(L6/26*N6,0) -> 0 | T6: =ROUND(L6/26*O6,0) -> 0 | U6: =SUM(S6:T6) -> 0 | V6: 0 | W6: 0 | X6: 0 | Y6: =VLOOKUP(B6,'[20]PC cơm '!$B$7:$L$15,11,0) -> 1120000 | Z6: =SUM(V6:Y6) -> 1120000 | AA6: =VLOOKUP(B6,'[20]OT '!$B$7:$R$14,17,0) -> 5827403 | AB6: =VLOOKUP(B6,[20]NS!$B$9:$G$16,6,0) -> 134135 | AC6: 0 | AD6: 0 | AE6: 0 | AF6: =ROUND(J6/26*AE6,0) -> 0 | AG6: =IFERROR(VLOOKUP(B6,[20]Incentive!$B$9:$H$11,7,0),0) -> 0 | AH6: =SUMIF([20]Others!$B$8:$B$15,$B6,[20]Others!$F$8:$F$15) -> #VALUE! | AI6: 0 | AJ6: =AI6+AH6+AG6+AF6+AD6+AC6+AB6+AA6+Z6+U6+R6+BN6 -> #VALUE! | AK6: =VLOOKUP(B6,'[20]OT '!$B$7:$T$14,19,0) -> 3740865 | AL6: =VLOOKUP(B6,[20]NS!$B$9:$I$16,8,0) -> 134135 | AM6: =AI6 -> 0 | AN6: =IF(BT6=1,0,15500000) -> 15500000 | AO6: 1 | AP6: =AO6*$AP$3 -> 6200000 | AQ6: =BF6*$AQ$3 -> 668000 | AR6: =BF6*$AR$3 -> 125250 | AS6: =BG6*$AS$3 -> 83500 | AT6: =+AS6+AR6+AQ6 -> 876750 | AU6: =IF(BT6=1,0,MIN(Y6,730000)) -> 730000 | AV6: =AJ6-AK6-AL6-AM6-AU6 -> #VALUE! | AW6: =MAX(AV6-AN6-AP6-AT6,0) -> #VALUE! | AX6: =IF(BT6=1,10%,IF(AW6>0,IF(AW6>80000000,0.35,IF(AW6>52000000,0.3,IF(AW6>32000000,0.25,IF(AW6>18000000,0.2,IF(AW6>10000000,0.15,IF(AW6>5000000,0.1,0.05)))))),0)) -> #VALUE! | AY6: =IF(BT6=1,0,IF(AW6>80000000,9850000,IF(AW6>52000000,5850000,IF(AW6>32000000,3250000,IF(AW6>18000000,1650000,IF(AW6>10000000,750000,IF(AW6>5000000,250000,0))))))) -> #VALUE! | AZ6: =ROUND(AW6*AX6-AY6,0) -> #VALUE! | BA6: =BF6*$BA$3 -> 1419500 | BB6: =BF6*$BB$3 -> 250500 | BC6: =BG6*$BC$3 -> 83500 | BD6: =BG6*$BD$3 -> 41750 | BE6: =SUM(BA6:BD6) -> 1795250 | BF6: =MIN((IF(BS6=1,K6,0)),$BF$3) -> 8350000 | BG6: =MIN((IF(BS6=1,K6,0)),$BG$3) -> 8350000 | BH6: 0 | BI6: 0 | BJ6: =IF(BS6=1,BF6*2%,0) -> 167000 | BK6: =IF(BU6=1,40000,0) -> 40000 | BL6: =IF(BV6=0,0,IF(J6<11000000,5000,IF(J6<25000000,10000,IF(J6<40000000,15000,20000)))*BW6) -> 300000 | BM6: =AJ6-AT6-AZ6-BK6-BL6-BN6-BO6-BP6 -> #VALUE! | BN6: =IFERROR(VLOOKUP(B6,'[20]Benefit tính thuế'!$B$2:$H$5,7,0),0) -> 2000000 | BO6: 0 | BP6: 0 | BQ6: =AN6+AP6+AU6 -> 22430000 | BR6: =+AZ6+AT6 -> #VALUE! | BS6: 1 | BT6: 0 | BU6: 1 | BV6: 1 | BW6: 20
A7: 1 | B7: PVT2500113 | D7: Nguyễn Văn Quân | E7: 24/10/2022 | F7: PVT - Operation | G7: PP. Center | H7: Staff | I7: Shipper Staff | J7: 10448000 | K7: 7570000 | L7: =J7-K7 -> 2878000 | M7: 26 | N7: =IFERROR(VLOOKUP(B7,' TimeTB 1'!$B$4:$P$5,5,0),0) -> 0 | O7: =VLOOKUP(B7,'TimeTB 2'!$B$4:$O$11,14,0) -> 0 | P7: =ROUND((K7/M7*N7),0) -> 0 | Q7: =ROUND(K7/M7*O7,0) -> 0 | R7: =SUM(P7:Q7) -> 0 | S7: =ROUND(L7/26*N7,0) -> 0 | T7: =ROUND(L7/26*O7,0) -> 0 | U7: =SUM(S7:T7) -> 0 | V7: 0 | W7: 0 | X7: 0 | Y7: =VLOOKUP(B7,'[20]PC cơm '!$B$7:$L$15,11,0) -> 960000 | Z7: =SUM(V7:Y7) -> 960000 | AA7: =VLOOKUP(B7,'[20]OT '!$B$7:$R$14,17,0) -> 307663 | AB7: =VLOOKUP(B7,[20]NS!$B$9:$G$16,6,0) -> 60277 | AC7: 0 | AD7: 0 | AE7: 0 | AF7: =ROUND(J7/26*AE7,0) -> 0 | AG7: =IFERROR(VLOOKUP(B7,[20]Incentive!$B$9:$H$11,7,0),0) -> 0 | AH7: =SUMIF([20]Others!$B$8:$B$15,$B7,[20]Others!$F$8:$F$15) -> #VALUE! | AI7: 0 | AJ7: =AI7+AH7+AG7+AF7+AD7+AC7+AB7+AA7+Z7+U7+R7+BN7 -> #VALUE! | AK7: =VLOOKUP(B7,'[20]OT '!$B$7:$T$14,19,0) -> 156971 | AL7: =VLOOKUP(B7,[20]NS!$B$9:$I$16,8,0) -> 60277 | AM7: =AI7 -> 0 | AN7: =IF(BT7=1,0,15500000) -> 15500000 | AO7: 0 | AP7: =AO7*$AP$3 -> 0 | AQ7: =BF7*$AQ$3 -> 605600 | AR7: =BF7*$AR$3 -> 113550 | AS7: =BG7*$AS$3 -> 75700 | AT7: =+AS7+AR7+AQ7 -> 794850 | AU7: =IF(BT7=1,0,MIN(Y7,730000)) -> 730000 | AV7: =AJ7-AK7-AL7-AM7-AU7 -> #VALUE! | AW7: =MAX(AV7-AN7-AP7-AT7,0) -> #VALUE! | AX7: =IF(BT7=1,10%,IF(AW7>0,IF(AW7>80000000,0.35,IF(AW7>52000000,0.3,IF(AW7>32000000,0.25,IF(AW7>18000000,0.2,IF(AW7>10000000,0.15,IF(AW7>5000000,0.1,0.05)))))),0)) -> #VALUE! | AY7: =IF(BT7=1,0,IF(AW7>80000000,9850000,IF(AW7>52000000,5850000,IF(AW7>32000000,3250000,IF(AW7>18000000,1650000,IF(AW7>10000000,750000,IF(AW7>5000000,250000,0))))))) -> #VALUE! | AZ7: =ROUND(AW7*AX7-AY7,0) -> #VALUE! | BA7: =BF7*$BA$3 -> 1286900 | BB7: =BF7*$BB$3 -> 227100 | BC7: =BG7*$BC$3 -> 75700 | BD7: =BG7*$BD$3 -> 37850 | BE7: =SUM(BA7:BD7) -> 1627550 | BF7: =MIN((IF(BS7=1,K7,0)),$BF$3) -> 7570000 | BG7: =MIN((IF(BS7=1,K7,0)),$BG$3) -> 7570000 | BH7: 0 | BI7: 0 | BJ7: =IF(BS7=1,BF7*2%,0) -> 151400 | BK7: =IF(BU7=1,40000,0) -> 40000 | BL7: =IF(BV7=0,0,IF(J7<11000000,5000,IF(J7<25000000,10000,IF(J7<40000000,15000,20000)))*BW7) -> 0 | BM7: =AJ7-AT7-AZ7-BK7-BL7-BN7-BO7-BP7 -> #VALUE! | BN7: =IFERROR(VLOOKUP(B7,'[20]Benefit tính thuế'!$B$2:$H$5,7,0),0) -> 1000000 | BO7: 0 | BP7: 0 | BQ7: =AN7+AP7+AU7 -> 16230000 | BR7: =+AZ7+AT7 -> #VALUE! | BS7: 1 | BT7: 0 | BU7: 1 | BV7: 0 | BW7: 20
A8: 2 | B8: PVT2500114 | D8: Nguyễn Đức Khánh | E8: 44562 | F8: PVT - Cashier | G8: Cashier | H8: Staff | I8: Cashier Staff | J8: 8000000 | K8: 5310000 | L8: =J8-K8 -> 2690000 | M8: 26 | N8: =IFERROR(VLOOKUP(B8,' TimeTB 1'!$B$4:$P$5,5,0),0) -> 0 | O8: =VLOOKUP(B8,'TimeTB 2'!$B$4:$O$11,14,0) -> 0 | P8: =ROUND((K8/M8*N8),0) -> 0 | Q8: =ROUND(K8/M8*O8,0) -> 0 | R8: =SUM(P8:Q8) -> 0 | S8: =ROUND(L8/26*N8,0) -> 0 | T8: =ROUND(L8/26*O8,0) -> 0 | U8: =SUM(S8:T8) -> 0 | V8: 0 | W8: 0 | X8: 0 | Y8: =VLOOKUP(B8,'[20]PC cơm '!$B$7:$L$15,11,0) -> 720000 | Z8: =SUM(V8:Y8) -> 720000 | AA8: =VLOOKUP(B8,'[20]OT '!$B$7:$R$14,17,0) -> 965384 | AB8: =VLOOKUP(B8,[20]NS!$B$9:$G$16,6,0) -> 17308 | AC8: 0 | AD8: 0 | AE8: 4 | AF8: =ROUND(J8/26*AE8,0) -> 1230769 | AG8: =IFERROR(VLOOKUP(B8,[20]Incentive!$B$9:$H$11,7,0),0) -> 0 | AH8: =SUMIF([20]Others!$B$8:$B$15,$B8,[20]Others!$F$8:$F$15) -> #VALUE! | AI8: 0 | AJ8: =AI8+AH8+AG8+AF8+AD8+AC8+AB8+AA8+Z8+U8+R8+BN8 -> #VALUE! | AK8: =VLOOKUP(B8,'[20]OT '!$B$7:$T$14,19,0) -> 657692 | AL8: =VLOOKUP(B8,[20]NS!$B$9:$I$16,8,0) -> 17308 | AM8: =AI8 -> 0 | AN8: =IF(BT8=1,0,15500000) -> 15500000 | AO8: 0 | AP8: =AO8*$AP$3 -> 0 | AQ8: =BF8*$AQ$3 -> 0 | AR8: =BF8*$AR$3 -> 0 | AS8: =BG8*$AS$3 -> 0 | AT8: =+AS8+AR8+AQ8 -> 0 | AU8: =IF(BT8=1,0,MIN(Y8,730000)) -> 720000 | AV8: =AJ8-AK8-AL8-AM8-AU8 -> #VALUE! | AW8: =MAX(AV8-AN8-AP8-AT8,0) -> #VALUE! | AX8: =IF(BT8=1,10%,IF(AW8>0,IF(AW8>80000000,0.35,IF(AW8>52000000,0.3,IF(AW8>32000000,0.25,IF(AW8>18000000,0.2,IF(AW8>10000000,0.15,IF(AW8>5000000,0.1,0.05)))))),0)) -> #VALUE! | AY8: =IF(BT8=1,0,IF(AW8>80000000,9850000,IF(AW8>52000000,5850000,IF(AW8>32000000,3250000,IF(AW8>18000000,1650000,IF(AW8>10000000,750000,IF(AW8>5000000,250000,0))))))) -> #VALUE! | AZ8: =ROUND(AW8*AX8-AY8,0) -> #VALUE! | BA8: =BF8*$BA$3 -> 0 | BB8: =BF8*$BB$3 -> 0 | BC8: =BG8*$BC$3 -> 0 | BD8: =BG8*$BD$3 -> 0 | BE8: =SUM(BA8:BD8) -> 0 | BF8: =MIN((IF(BS8=1,K8,0)),$BF$3) -> 0 | BG8: =MIN((IF(BS8=1,K8,0)),$BG$3) -> 0 | BH8: 0 | BI8: 0 | BJ8: =IF(BS8=1,BF8*2%,0) -> 0 | BK8: =IF(BU8=1,40000,0) -> 0 | BL8: =IF(BV8=0,0,IF(J8<11000000,5000,IF(J8<25000000,10000,IF(J8<40000000,15000,20000)))*BW8) -> 0 | BM8: =AJ8-AT8-AZ8-BK8-BL8-BN8-BO8-BP8 -> #VALUE! | BN8: =IFERROR(VLOOKUP(B8,'[20]Benefit tính thuế'!$B$2:$H$5,7,0),0) -> 1250000 | BO8: 0 | BP8: 0 | BQ8: =AN8+AP8+AU8 -> 16220000 | BR8: =+AZ8+AT8 -> #VALUE! | BS8: 0 | BT8: 0 | BU8: 0 | BV8: 0 | BW8: 20
A9: 3 | B9: PVT2500115 | D9: Nguyễn Sơn Tùng | E9: 45740 | F9: PVT - Cashier | G9: Cashier | H9: Staff | I9: Cashier Staff | J9: 8500000 | K9: 5310000 | L9: =J9-K9 -> 3190000 | M9: 26 | N9: =IFERROR(VLOOKUP(B9,' TimeTB 1'!$B$4:$P$5,5,0),0) -> 0 | O9: =VLOOKUP(B9,'TimeTB 2'!$B$4:$O$11,14,0) -> 0 | P9: =ROUND((K9/M9*N9),0) -> 0 | Q9: =ROUND(K9/M9*O9,0) -> 0 | R9: =SUM(P9:Q9) -> 0 | S9: =ROUND(L9/26*N9,0) -> 0 | T9: =ROUND(L9/26*O9,0) -> 0 | U9: =SUM(S9:T9) -> 0 | V9: 0 | W9: 0 | X9: 0 | Y9: =VLOOKUP(B9,'[20]PC cơm '!$B$7:$L$15,11,0) -> 1120000 | Z9: =SUM(V9:Y9) -> 1120000 | AA9: =VLOOKUP(B9,'[20]OT '!$B$7:$R$14,17,0) -> 980769 | AB9: =VLOOKUP(B9,[20]NS!$B$9:$G$16,6,0) -> 6130 | AC9: 0 | AD9: 0 | AE9: 0 | AF9: =ROUND(J9/26*AE9,0) -> 0 | AG9: =IFERROR(VLOOKUP(B9,[20]Incentive!$B$9:$H$11,7,0),0) -> 0 | AH9: =SUMIF([20]Others!$B$8:$B$15,$B9,[20]Others!$F$8:$F$15) -> #VALUE! | AI9: 0 | AJ9: =AI9+AH9+AG9+AF9+AD9+AC9+AB9+AA9+Z9+U9+R9+BN9 -> #VALUE! | AK9: =VLOOKUP(B9,'[20]OT '!$B$7:$T$14,19,0) -> 0 | AL9: =VLOOKUP(B9,[20]NS!$B$9:$I$16,8,0) -> 0 | AM9: =AI9 -> 0 | AN9: =IF(BT9=1,0,15500000) -> 0 | AO9: 0 | AP9: =AO9*$AP$3 -> 0 | AQ9: =BF9*$AQ$3 -> 0 | AR9: =BF9*$AR$3 -> 0 | AS9: =BG9*$AS$3 -> 0 | AT9: =+AS9+AR9+AQ9 -> 0 | AU9: =IF(BT9=1,0,MIN(Y9,730000)) -> 0 | AV9: =AJ9-AK9-AL9-AM9-AU9 -> #VALUE! | AW9: =MAX(AV9-AN9-AP9-AT9,0) -> #VALUE! | AX9: =IF(BT9=1,10%,IF(AW9>0,IF(AW9>80000000,0.35,IF(AW9>52000000,0.3,IF(AW9>32000000,0.25,IF(AW9>18000000,0.2,IF(AW9>10000000,0.15,IF(AW9>5000000,0.1,0.05)))))),0)) -> 0.1 | AY9: =IF(BT9=1,0,IF(AW9>80000000,9850000,IF(AW9>52000000,5850000,IF(AW9>32000000,3250000,IF(AW9>18000000,1650000,IF(AW9>10000000,750000,IF(AW9>5000000,250000,0))))))) -> 0 | AZ9: =ROUND(AW9*AX9-AY9,0) -> #VALUE! | BA9: =BF9*$BA$3 -> 0 | BB9: =BF9*$BB$3 -> 0 | BC9: =BG9*$BC$3 -> 0 | BD9: =BG9*$BD$3 -> 0 | BE9: =SUM(BA9:BD9) -> 0 | BF9: =MIN((IF(BS9=1,K9,0)),$BF$3) -> 0 | BG9: =MIN((IF(BS9=1,K9,0)),$BG$3) -> 0 | BH9: 0 | BI9: 0 | BJ9: =IF(BS9=1,BF9*2%,0) -> 0 | BK9: =IF(BU9=1,40000,0) -> 0 | BL9: =IF(BV9=0,0,IF(J9<11000000,5000,IF(J9<25000000,10000,IF(J9<40000000,15000,20000)))*BW9) -> 0 | BM9: =AJ9-AT9-AZ9-BK9-BL9-BN9-BO9-BP9 -> #VALUE! | BN9: =IFERROR(VLOOKUP(B9,'[20]Benefit tính thuế'!$B$2:$H$5,7,0),0) -> 0 | BO9: 0 | BP9: 0 | BQ9: =AN9+AP9+AU9 -> 0 | BR9: =+AZ9+AT9 -> #VALUE! | BS9: 0 | BT9: 1 | BU9: 0 | BV9: 0 | BW9: 20
A10: 1 | B10: PVT2500116 | D10: Nguyễn Quang Cường | E10: 12/10/2016 | F10: PVT - Quality Assurance | G10: Quality Assurance | H10: Assistant | I10: QA Assistant | J10: 7056000 | K10: 5310000 | L10: =J10-K10 -> 1746000 | M10: 26 | N10: =IFERROR(VLOOKUP(B10,' TimeTB 1'!$B$4:$P$5,5,0),0) -> 0 | O10: =VLOOKUP(B10,'TimeTB 2'!$B$4:$O$11,14,0) -> 0 | P10: =ROUND((K10/M10*N10),0) -> 0 | Q10: =ROUND(K10/M10*O10,0) -> 0 | R10: =SUM(P10:Q10) -> 0 | S10: =ROUND(L10/26*N10,0) -> 0 | T10: =ROUND(L10/26*O10,0) -> 0 | U10: =SUM(S10:T10) -> 0 | V10: 0 | W10: 0 | X10: 0 | Y10: =VLOOKUP(B10,'[20]PC cơm '!$B$7:$L$15,11,0) -> 1120000 | Z10: =SUM(V10:Y10) -> 1120000 | AA10: =VLOOKUP(B10,'[20]OT '!$B$7:$R$14,17,0) -> 1596081 | AB10: =VLOOKUP(B10,[20]NS!$B$9:$G$16,6,0) -> 10177 | AC10: 0 | AD10: 0 | AE10: 0 | AF10: =ROUND(J10/26*AE10,0) -> 0 | AG10: =IFERROR(VLOOKUP(B10,[20]Incentive!$B$9:$H$11,7,0),0) -> 2000000 | AH10: =SUMIF([20]Others!$B$8:$B$15,$B10,[20]Others!$F$8:$F$15) -> #VALUE! | AI10: 0 | AJ10: =AI10+AH10+AG10+AF10+AD10+AC10+AB10+AA10+Z10+U10+R10+BN10 -> #VALUE! | AK10: =VLOOKUP(B10,'[20]OT '!$B$7:$T$14,19,0) -> 985466 | AL10: =VLOOKUP(B10,[20]NS!$B$9:$I$16,8,0) -> 10177 | AM10: =AI10 -> 0 | AN10: =IF(BT10=1,0,15500000) -> 15500000 | AO10: 0 | AP10: =AO10*$AP$3 -> 0 | AQ10: =BF10*$AQ$3 -> 424800 | AR10: =BF10*$AR$3 -> 79650 | AS10: =BG10*$AS$3 -> 53100 | AT10: =+AS10+AR10+AQ10 -> 557550 | AU10: =IF(BT10=1,0,MIN(Y10,730000)) -> 730000 | AV10: =AJ10-AK10-AL10-AM10-AU10 -> #VALUE! | AW10: =MAX(AV10-AN10-AP10-AT10,0) -> #VALUE! | AX10: =IF(BT10=1,10%,IF(AW10>0,IF(AW10>80000000,0.35,IF(AW10>52000000,0.3,IF(AW10>32000000,0.25,IF(AW10>18000000,0.2,IF(AW10>10000000,0.15,IF(AW10>5000000,0.1,0.05)))))),0)) -> #VALUE! | AY10: =IF(BT10=1,0,IF(AW10>80000000,9850000,IF(AW10>52000000,5850000,IF(AW10>32000000,3250000,IF(AW10>18000000,1650000,IF(AW10>10000000,750000,IF(AW10>5000000,250000,0))))))) -> #VALUE! | AZ10: =ROUND(AW10*AX10-AY10,0) -> #VALUE! | BA10: =BF10*$BA$3 -> 902700 | BB10: =BF10*$BB$3 -> 159300 | BC10: =BG10*$BC$3 -> 53100 | BD10: =BG10*$BD$3 -> 26550 | BE10: =SUM(BA10:BD10) -> 1141650 | BF10: =MIN((IF(BS10=1,K10,0)),$BF$3) -> 5310000 | BG10: =MIN((IF(BS10=1,K10,0)),$BG$3) -> 5310000 | BH10: 0 | BI10: 0 | BJ10: =IF(BS10=1,BF10*2%,0) -> 106200 | BK10: =IF(BU10=1,40000,0) -> 40000 | BL10: =IF(BV10=0,0,IF(J10<11000000,5000,IF(J10<25000000,10000,IF(J10<40000000,15000,20000)))*BW10) -> 100000 | BM10: =AJ10-AT10-AZ10-BK10-BL10-BN10-BO10-BP10 -> #VALUE! | BN10: =IFERROR(VLOOKUP(B10,'[20]Benefit tính thuế'!$B$2:$H$5,7,0),0) -> 0 | BO10: 0 | BP10: 0 | BQ10: =AN10+AP10+AU10 -> 16230000 | BR10: =+AZ10+AT10 -> #VALUE! | BS10: 1 | BT10: 0 | BU10: 1 | BV10: 1 | BW10: 20
A11: 1 | B11: PVT2500117 | D11: Phạm Đức Kiên | E11: 22/06/2022 | F11: PVT - Security | G11: Security | H11: Staff | I11: Security Staff | J11: 6841000 | K11: 5310000 | L11: =J11-K11 -> 1531000 | M11: 26 | N11: =IFERROR(VLOOKUP(B11,' TimeTB 1'!$B$4:$P$5,5,0),0) -> 0 | O11: =VLOOKUP(B11,'TimeTB 2'!$B$4:$O$11,14,0) -> 0 | P11: =ROUND((K11/M11*N11),0) -> 0 | Q11: =ROUND(K11/M11*O11,0) -> 0 | R11: =SUM(P11:Q11) -> 0 | S11: =ROUND(L11/26*N11,0) -> 0 | T11: =ROUND(L11/26*O11,0) -> 0 | U11: =SUM(S11:T11) -> 0 | V11: 0 | W11: 0 | X11: 0 | Y11: =VLOOKUP(B11,'[20]PC cơm '!$B$7:$L$15,11,0) -> 960000 | Z11: =SUM(V11:Y11) -> 960000 | AA11: =VLOOKUP(B11,'[20]OT '!$B$7:$R$14,17,0) -> 0 | AB11: =VLOOKUP(B11,[20]NS!$B$9:$G$16,6,0) -> 49334 | AC11: 0 | AD11: 0 | AE11: 0 | AF11: =ROUND(J11/26*AE11,0) -> 0 | AG11: =IFERROR(VLOOKUP(B11,[20]Incentive!$B$9:$H$11,7,0),0) -> 2600000 | AH11: =SUMIF([20]Others!$B$8:$B$15,$B11,[20]Others!$F$8:$F$15) -> #VALUE! | AI11: 0 | AJ11: =AI11+AH11+AG11+AF11+AD11+AC11+AB11+AA11+Z11+U11+R11+BN11 -> #VALUE! | AK11: =VLOOKUP(B11,'[20]OT '!$B$7:$T$14,19,0) -> 0 | AL11: =VLOOKUP(B11,[20]NS!$B$9:$I$16,8,0) -> 49334 | AM11: =AI11 -> 0 | AN11: =IF(BT11=1,0,15500000) -> 15500000 | AO11: 0 | AP11: =AO11*$AP$3 -> 0 | AQ11: =BF11*$AQ$3 -> 424800 | AR11: =BF11*$AR$3 -> 79650 | AS11: =BG11*$AS$3 -> 53100 | AT11: =+AS11+AR11+AQ11 -> 557550 | AU11: =IF(BT11=1,0,MIN(Y11,730000)) -> 730000 | AV11: =AJ11-AK11-AL11-AM11-AU11 -> #VALUE! | AW11: =MAX(AV11-AN11-AP11-AT11,0) -> #VALUE! | AX11: =IF(BT11=1,10%,IF(AW11>0,IF(AW11>80000000,0.35,IF(AW11>52000000,0.3,IF(AW11>32000000,0.25,IF(AW11>18000000,0.2,IF(AW11>10000000,0.15,IF(AW11>5000000,0.1,0.05)))))),0)) -> #VALUE! | AY11: =IF(BT11=1,0,IF(AW11>80000000,9850000,IF(AW11>52000000,5850000,IF(AW11>32000000,3250000,IF(AW11>18000000,1650000,IF(AW11>10000000,750000,IF(AW11>5000000,250000,0))))))) -> #VALUE! | AZ11: =ROUND(AW11*AX11-AY11,0) -> #VALUE! | BA11: =BF11*$BA$3 -> 902700 | BB11: =BF11*$BB$3 -> 159300 | BC11: =BG11*$BC$3 -> 53100 | BD11: =BG11*$BD$3 -> 26550 | BE11: =SUM(BA11:BD11) -> 1141650 | BF11: =MIN((IF(BS11=1,K11,0)),$BF$3) -> 5310000 | BG11: =MIN((IF(BS11=1,K11,0)),$BG$3) -> 5310000 | BH11: 0 | BI11: 0 | BJ11: =IF(BS11=1,BF11*2%,0) -> 106200 | BK11: =IF(BU11=1,40000,0) -> 40000 | BL11: =IF(BV11=0,0,IF(J11<11000000,5000,IF(J11<25000000,10000,IF(J11<40000000,15000,20000)))*BW11) -> 0 | BM11: =AJ11-AT11-AZ11-BK11-BL11-BN11-BO11-BP11 -> #VALUE! | BN11: =IFERROR(VLOOKUP(B11,'[20]Benefit tính thuế'!$B$2:$H$5,7,0),0) -> 0 | BO11: 0 | BP11: 0 | BQ11: =AN11+AP11+AU11 -> 16230000 | BR11: =+AZ11+AT11 -> #VALUE! | BS11: 1 | BT11: 0 | BU11: 1 | BV11: 0 | BW11: 20
A12: 1 | B12: PVT2500118 | D12: Ngô Văn Tuấn | E12: 45738 | F12: PVT - Operation | G12: PP. Center | H12: Staff | I12: Shipper Staff | J12: 11000000 | K12: 5800000 | L12: =J12-K12 -> 5200000 | M12: 26 | N12: =IFERROR(VLOOKUP(B12,' TimeTB 1'!$B$4:$P$5,5,0),0) -> 0 | O12: =VLOOKUP(B12,'TimeTB 2'!$B$4:$O$11,14,0) -> 0 | P12: =ROUND((K12/M12*N12),0) -> 0 | Q12: =ROUND(K12/M12*O12,0) -> 0 | R12: =SUM(P12:Q12) -> 0 | S12: =ROUND(L12/26*N12,0) -> 0 | T12: =ROUND(L12/26*O12,0) -> 0 | U12: =SUM(S12:T12) -> 0 | V12: 0 | W12: 0 | X12: 0 | Y12: =VLOOKUP(B12,'[20]PC cơm '!$B$7:$L$15,11,0) -> 1120000 | Z12: =SUM(V12:Y12) -> 1120000 | AA12: =VLOOKUP(B12,'[20]OT '!$B$7:$R$14,17,0) -> 2488221 | AB12: =VLOOKUP(B12,[20]NS!$B$9:$G$16,6,0) -> 95192 | AC12: 0 | AD12: 0 | AE12: 0 | AF12: =ROUND(J12/26*AE12,0) -> 0 | AG12: =IFERROR(VLOOKUP(B12,[20]Incentive!$B$9:$H$11,7,0),0) -> 5610000 | AH12: =SUMIF([20]Others!$B$8:$B$15,$B12,[20]Others!$F$8:$F$15) -> #VALUE! | AI12: 0 | AJ12: =AI12+AH12+AG12+AF12+AD12+AC12+AB12+AA12+Z12+U12+R12+BN12 -> #VALUE! | AK12: =VLOOKUP(B12,'[20]OT '!$B$7:$T$14,19,0) -> 0 | AL12: =VLOOKUP(B12,[20]NS!$B$9:$I$16,8,0) -> 0 | AM12: =AI12 -> 0 | AN12: =IF(BT12=1,0,11000000) -> 0 | AO12: 0 | AP12: =AO12*$AP$3 -> 0 | AQ12: =BF12*$AQ$3 -> 0 | AR12: =BF12*$AR$3 -> 0 | AS12: =BG12*$AS$3 -> 0 | AT12: =+AS12+AR12+AQ12 -> 0 | AU12: =IF(BT12=1,0,MIN(Y12,730000)) -> 0 | AV12: =AJ12-AK12-AL12-AM12-AU12 -> #VALUE! | AW12: =MAX(AV12-AN12-AP12-AT12,0) -> #VALUE! | AX12: =IF(BT12=1,10%,IF(AW12>0,IF(AW12>80000000,0.35,IF(AW12>52000000,0.3,IF(AW12>32000000,0.25,IF(AW12>18000000,0.2,IF(AW12>10000000,0.15,IF(AW12>5000000,0.1,0.05)))))),0)) -> 0.1 | AY12: =IF(BT12=1,0,IF(AW12>80000000,9850000,IF(AW12>52000000,5850000,IF(AW12>32000000,3250000,IF(AW12>18000000,1650000,IF(AW12>10000000,750000,IF(AW12>5000000,250000,0))))))) -> 0 | AZ12: =ROUND(AW12*AX12-AY12,0) -> #VALUE! | BA12: =BF12*$BA$3 -> 0 | BB12: =BF12*$BB$3 -> 0 | BC12: =BG12*$BC$3 -> 0 | BD12: =BG12*$BD$3 -> 0 | BE12: =SUM(BA12:BD12) -> 0 | BF12: =MIN((IF(BS12=1,K12,0)),$BF$3) -> 0 | BG12: =MIN((IF(BS12=1,K12,0)),$BG$3) -> 0 | BH12: 0 | BI12: 0 | BJ12: =IF(BS12=1,BF12*2%,0) -> 0 | BK12: =IF(BU12=1,40000,0) -> 0 | BL12: =IF(BV12=0,0,IF(J12<11000000,5000,IF(J12<25000000,10000,IF(J12<40000000,15000,20000)))*BW12) -> 0 | BM12: =AJ12-AT12-AZ12-BK12-BL12-BN12-BO12-BP12 -> #VALUE! | BN12: =IFERROR(VLOOKUP(B12,'[20]Benefit tính thuế'!$B$2:$H$5,7,0),0) -> 0 | BO12: 0 | BP12: 0 | BQ12: =AN12+AP12+AU12 -> 0 | BR12: =+AZ12+AT12 -> #VALUE! | BS12: 0 | BT12: 1 | BU12: 0 | BV12: 0 | BW12: 20
BB24: =BF3/2 -> 23400000 | BD24: =BG3/2 -> 49600000

Sheet PC cơm 
A1: Emp. Code | B1: Full Name | C1: Join Date | D1: Dept/Div | E1: Actual work days (excl. Holidays) | F1: OT days ≥ 4 hours | G1: Work days on Holidays | H1: Amount for actual work days (excl. Holidays) | I1: Amount for OT days ≥ 4 hours | J1: Amount for work on Holidays | K1: Total Amount | L1: Notes
H2: 40000 | I2: 40000 | J2: 80000
A3: SLA2500111 | B3: Nguyễn Thị Hà | C3: 43466 | D3: Store Management | E3: =VLOOKUP($A3,'TimeTB 2'!$B$4:$P$11,15,0) -> 0 | F3: =VLOOKUP($A3,'TimeTB 2'!$B$4:$R$11,17,0) -> 0 | G3: =VLOOKUP($A3,'TimeTB 2'!$B$4:$R$11,16,0) -> 0 | H3: =E3*$H$2 -> 0 | I3: =F3*$I$2 -> 0 | J3: =G3*$J$2 -> 0 | K3: =SUM(H3:J3) -> 0
A4: PHI2500112 | B4: Phùng Mạnh Hà | C4: 43831 | D4: Cooperate Function | E4: =VLOOKUP($A4,'TimeTB 2'!$B$4:$P$11,15,0) -> 0 | F4: =VLOOKUP($A4,'TimeTB 2'!$B$4:$R$11,17,0) -> 0 | G4: =VLOOKUP($A4,'TimeTB 2'!$B$4:$R$11,16,0) -> 0 | H4: =E4*$H$2 -> 0 | I4: =F4*$I$2 -> 0 | J4: =G4*$J$2 -> 0 | K4: =SUM(H4:J4) -> 0
A5: PVT2500113 | B5: Nguyễn Đức Khánh | C5: 44197 | D5: PP. Center | E5: =VLOOKUP($A5,'TimeTB 2'!$B$4:$P$11,15,0) -> 0 | F5: =VLOOKUP($A5,'TimeTB 2'!$B$4:$R$11,17,0) -> 0 | G5: =VLOOKUP($A5,'TimeTB 2'!$B$4:$R$11,16,0) -> 0 | H5: =E5*$H$2 -> 0 | I5: =F5*$I$2 -> 0 | J5: =G5*$J$2 -> 0 | K5: =SUM(H5:J5) -> 0
A6: PVT2500114 | B6: Nguyễn Sơn Tùng | C6: 44562 | D6: Hr/Admin | E6: =VLOOKUP($A6,'TimeTB 2'!$B$4:$P$11,15,0) -> 0 | F6: =VLOOKUP($A6,'TimeTB 2'!$B$4:$R$11,17,0) -> 0 | G6: =VLOOKUP($A6,'TimeTB 2'!$B$4:$R$11,16,0) -> 0 | H6: =E6*$H$2 -> 0 | I6: =F6*$I$2 -> 0 | J6: =G6*$J$2 -> 0 | K6: =SUM(H6:J6) -> 0
A7: PVT2500115 | B7: Nguyễn Quang Cường | C7: 45740 | D7: Hr/Admin | E7: =VLOOKUP($A7,'TimeTB 2'!$B$4:$P$11,15,0) -> 0 | F7: =VLOOKUP($A7,'TimeTB 2'!$B$4:$R$11,17,0) -> 0 | G7: =VLOOKUP($A7,'TimeTB 2'!$B$4:$R$11,16,0) -> 0 | H7: =E7*$H$2 -> 0 | I7: =F7*$I$2 -> 0 | J7: =G7*$J$2 -> 0 | K7: =SUM(H7:J7) -> 0
A8: PVT2500116 | B8: Phạm Đức Kiên | C8: 44927 | D8: Cashier | E8: =VLOOKUP($A8,'TimeTB 2'!$B$4:$P$11,15,0) -> 0 | F8: =VLOOKUP($A8,'TimeTB 2'!$B$4:$R$11,17,0) -> 0 | G8: =VLOOKUP($A8,'TimeTB 2'!$B$4:$R$11,16,0) -> 0 | H8: =E8*$H$2 -> 0 | I8: =F8*$I$2 -> 0 | J8: =G8*$J$2 -> 0 | K8: =SUM(H8:J8) -> 0
A9: PVT2500117 | B9: Nguyễn Văn Quân | C9: 45292 | D9: Cashier | E9: =VLOOKUP($A9,'TimeTB 2'!$B$4:$P$11,15,0) -> 0 | F9: =VLOOKUP($A9,'TimeTB 2'!$B$4:$R$11,17,0) -> 0 | G9: =VLOOKUP($A9,'TimeTB 2'!$B$4:$R$11,16,0) -> 0 | H9: =E9*$H$2 -> 0 | I9: =F9*$I$2 -> 0 | J9: =G9*$J$2 -> 0 | K9: =SUM(H9:J9) -> 0
A10: PVT2500118 | B10: Ngô Văn Tuấn | C10: 45738 | D10: PP. Center | E10: =VLOOKUP($A10,'TimeTB 2'!$B$4:$P$11,15,0) -> 0 | F10: =VLOOKUP($A10,'TimeTB 2'!$B$4:$R$11,17,0) -> 0 | G10: =VLOOKUP($A10,'TimeTB 2'!$B$4:$R$11,16,0) -> 0 | H10: =E10*$H$2 -> 0 | I10: =F10*$I$2 -> 0 | J10: =G10*$J$2 -> 0 | K10: =SUM(H10:J10) -> 0

Sheet TimeTB 2
B1: Emp. Code | C1: Full Name | D1: Joinging date | E1: Dept | F1: Sub. Dept | G1: Job Title | H1: REMARK | I1: Total OFF days | J1: Unpaid leave | K1: Nghỉ hưởng lương (Nghỉ Phép/ Nghỉ Bù/ Nghỉ chế độ/ Nghỉ Lễ) | L1: Actual working days | M1: Total | N1: Work adjustment | O1: Total paid workdays | P1: Total working days paid regular meals | Q1: Total working days pay for meals during Tet holidays | R1: Total workdays pay for overtime meals | S1: Note
A4: 1 | B4: SLA2500111 | C4: Nguyễn Thị Hà | D4: 43466 | G4: Store Manager - Emart Phan Van Tri | M4: =+K4+L4 -> 0 | O4: =MIN((M4+N4),26) -> 0 | R4: 0
A5: =+A3+1 -> 1 | B5: PHI2500112 | C5: Phùng Mạnh Hà | D5: 43831 | G5: Corporate Function Manager | M5: =+K5+L5 -> 0 | O5: =MIN((M5+N5),26) -> 0 | R5: 0
A6: =+A5+1 -> 2 | B6: PVT2500113 | C6: Nguyễn Đức Khánh | D6: 44197 | G6: Admin Supervisor - Store Division | M6: =+K6+L6 -> 0 | O6: =MIN((M6+N6),26) -> 0 | R6: 0
A7: =+A6+1 -> 3 | B7: PVT2500114 | C7: Nguyễn Sơn Tùng | D7: 44562 | G7: HR Supervisor - Store Division | M7: =+K7+L7 -> 0 | O7: =MIN((M7+N7),26) -> 0 | R7: 0
A8: =+A7+1 -> 4 | B8: PVT2500115 | C8: Nguyễn Quang Cường | D8: 45740 | G8: HR Staff - Store Divison | M8: =+K8+L8 -> 0 | O8: =MIN((M8+N8),26) -> 0 | R8: 0
A9: =+A8+1 -> 5 | B9: PVT2500116 | C9: Phạm Đức Kiên | D9: 44927 | G9: QA Assistant | M9: =+K9+L9 -> 0 | O9: =MIN((M9+N9),26) -> 0 | R9: 0
A10: =+A9+1 -> 6 | B10: PVT2500117 | C10: Nguyễn Văn Quân | D10: 45292 | G10: Security Staff | M10: =+K10+L10 -> 0 | O10: =MIN((M10+N10),26) -> 0 | R10: 0
A11: =+A10+1 -> 7 | B11: PVT2500118 | C11: Ngô Văn Tuấn | D11: 45738 | G11: Treasury Staff | M11: =+K11+L11 -> 0 | O11: =MIN((M11+N11),26) -> 0 | R11: 0
B12: Quy định ký hiệu chấm công
B13: X | C13: Đi làm 01 ngày
B14: HL | C14: Nghĩ Lễ, Tết
B15: OFF | C15: Nghỉ 1 ngày OFFca hàng tuần
B16: AL | C16: Annual Leave/ Nghỉ phép năm 01 ngày
B17: 1/2AL | C17: 1/2 Annual Leave/ Nghỉ phép năm 1/2 ngày + Đi làm 1/2 ngày
B18: FP | C18: Full paid leave for personal affairs/Nghỉ việc riêng có hưởng lương 01 ngày (kết hôn, tang chế...)
B19: UP | C19: Unpaid leave/ Nghỉ việc riêng không hưởng lương 01 ngày
B20: 1/2UP | C20: 1/2 Unpaid leave/ Nghỉ việc không hưởng lương 1/2 ngày + Đi làm 1/2 ngày
B21: SL1 | C21: Sick leave / Nghỉ bệnh (hưởng BHXH)
B22: ML | C22: Maternity leave / Nghỉ thai sản
B23: CC | C23: Children care leave / Nghỉ con ốm/ vợ sinh (hưởng BHXH)
B24: LL | C24: Lactation leave/ Về sớm/đi trễ 1 tiếng/nghỉ 1 ngày sau 7 ngày làm việc
... B27: 1/2CL | C27: 1/2 Compensation leave ( in-lieu day-off)/ Nghỉ bù 1/2 ngày + Đi làm 1/2 ngày

Sheet  TimeTB 1
A1: Division | B1: Emp. Code | C1: Full Name | D1: Bộ Phận | E1: Joinging date | F1: SALARY CALCULATION DAYS | G1: Tổng ngày Off | H1: Total days/month | I1: Paid Leave (Annual Leave / Compensatory Leave / Policy Leave / Public Holiday) | J1: Total Paid Leave Days | K1: Total Unpaid Leave Days | L1: Holiday | M1: Compensation | N1: OT Sunday | O1: OT Holiday | P1: Actual Working Days
B4: PVT2500115 | C4: Nguyễn Văn Quân | E4: 45740 | F4: =IF(OR(P4=26,P4=26),26,P4) -> 0
B5: PVT2500118 | C5: Ngô Văn Tuấn | E5: 45738 | F5: =IF(OR(P5=26,P5=26),26,P5) -> 0 | S5: =VLOOKUP(B5,[21]Timetable_T03!$B$9:$AS$19,44,0) -> #N/A
F6: =IF(OR(P6=26,P6=26),26,P6) -> 0
F7: =IF(OR(P7=26,P7=26),26,P7) -> 0
F8: =IF(OR(P8=26,P8=26),26,P8) -> 0
F9: =IF(OR(P9=26,P9=26),26,P9) -> 0
F10: =IF(OR(P10=26,P10=26),26,P10) -> 0
B14: Quy định ký hiệu chấm công
B15: X | C15: Đi làm 01 ngày
B16: HL | C16: Nghĩ Lễ, Tết
B17: OFF | C17: Nghỉ 1 ngày OFFca hàng tuần
B18: AL | C18: Annual Leave/ Nghỉ phép năm 01 ngày
B19: 1/2AL | C19: 1/2 Annual Leave/ Nghỉ phép năm 1/2 ngày + Đi làm 1/2 ngày
B20: FP | C20: Full paid leave for personal affairs/Nghỉ việc riêng có hưởng lương 01 ngày (kết hôn, tang chế...)
B21: UP | C21: Unpaid leave/ Nghỉ việc riêng không hưởng lương 01 ngày
B22: 1/2UP | C22: 1/2 Unpaid leave/ Nghỉ việc không hưởng lương 1/2 ngày + Đi làm 1/2 ngày
B23: SL1 | C23: Sick leave / Nghỉ bệnh (hưởng BHXH)
B24: ML | C24: Maternity leave / Nghỉ thai sản
B25: CC | C25: Children care leave / Nghỉ con ốm/ vợ sinh (hưởng BHXH)
B26: LL | C26: Lactation leave/ Về sớm/đi trễ 1 tiếng/nghỉ 1 ngày sau 7 ngày làm việc
... B29: 1/2CL | C29: 1/2 Compensation leave ( in-lieu day-off)/ Nghỉ bù 1/2 ngày + Đi làm 1/2 ngày

Sheet OT
A1: Emp. Code | B1: Full name | C1: Joinging date | D1: Income salary | E1: Hour_150 | F1: Hour_215 | G1: Hour_200 | H1: Hour_280 | I1: Hour_300 | J1: Hour_410 | K1: OTPay_150 | L1: OTPay_215 | M1: OTPay_200 | N1: OTPay_280 | O1: OTPay_300 | P1: OTPay_410 | Q1: Total payment (VND) | R1: Overtime taxable | S1: OT.Untaxable
E2: 1.5 | F2: 2.15 | G2: 2 | H2: 2.8 | I2: 3 | J2: 4.1 | K2: 1.5 | L2: 2.15 | M2: 2 | N2: 2.8 | O2: 3 | P2: 4.1
A3: SLA2500111 | B3: Nguyễn Thị Hà | C3: 43466 | D3: =VLOOKUP(A3,'Template Payroll'!$B$5:$J$5,9,0) -> 47000000 | E3: 0 | F3: 0 | G3: 0 | H3: 0 | K3: =ROUND(D3/26/8*$K2*E3,0) -> 0 | L3: =ROUND(D3/26/8*$L2*F3,0) -> 0 | M3: =ROUND(D3/26/8*$M2*G3,0) -> 0 | N3: =ROUND(D3/26/8*$N2*H3,0) -> 0 | O3: =ROUND(D3/26/8*$O2*I3,0) -> 0 | P3: =ROUND(D3/26/8*$P2*J3,0) -> 0 | Q3: =ROUND(SUM(K3:P3),0) -> 0 | R3: =ROUND(SUM(E3:J3)*D3/26/8,0) -> 0 | S3: =ROUND(Q3-R3,0) -> 0
A4: PHI2500112 | B4: Phùng Mạnh Hà | C4: 43831 | D4: =VLOOKUP(A4,'[20]Template Payroll'!$B$6:$J$18,9,0) -> 31000000 | E4: 0 | F4: 6 | G4: 0 | H4: 0 | I4: 6 | J4: 2 | K4: =ROUND(D4/26/8*$K$5*E4,0) -> 0 | L4: =ROUND(D4/26/8*$L$5*F4,0) -> 1922596 | M4: =ROUND(D4/26/8*$M$5*G4,0) -> 0 | N4: =ROUND(D4/26/8*$N$5*H4,0) -> 0 | O4: =ROUND(D4/26/8*$O$5*I4,0) -> 2682692 | P4: =ROUND(D4/26/8*$P$5*J4,0) -> 1222115 | Q4: =ROUND(SUM(K4:P4),0) -> 5827403 | R4: =ROUND(SUM(E4:J4)*D4/26/8,0) -> 2086538 | S4: =ROUND(Q4-R4,0) -> 3740865
A5: PVT2500113 | B5: Nguyễn Đức Khánh | C5: 44197 | D5: =VLOOKUP(A5,'[20]Template Payroll'!$B$6:$J$18,9,0) -> 10448000 | E5: 0.5 | F5: 2.5 | G5: 0 | H5: 0 | I5: 0 | J5: 0 | K5: =ROUND(D5/26/8*$K$5*E5,0) -> 37673 | L5: =ROUND(D5/26/8*$L$5*F5,0) -> 269990 | M5: =ROUND(D5/26/8*$M$5*G5,0) -> 0 | N5: =ROUND(D5/26/8*$N$5*H5,0) -> 0 | O5: =ROUND(D5/26/8*$O$5*I5,0) -> 0 | P5: =ROUND(D5/26/8*$P$5*J5,0) -> 0 | Q5: =ROUND(SUM(K5:P5),0) -> 307663 | R5: =ROUND(SUM(E5:J5)*D5/26/8,0) -> 150692 | S5: =ROUND(Q5-R5,0) -> 156971
A6: PVT2500114 | B6: Nguyễn Sơn Tùng | C6: 44562 | D6: =VLOOKUP(A6,'[20]Template Payroll'!$B$6:$J$18,9,0) -> 8000000 | E6: 0 | F6: 0 | G6: 0 | H6: 0 | I6: 7 | J6: 1 | K6: =ROUND(D6/26/8*$K$5*E6,0) -> 0 | L6: =ROUND(D6/26/8*$L$5*F6,0) -> 0 | M6: =ROUND(D6/26/8*$M$5*G6,0) -> 0 | N6: =ROUND(D6/26/8*$N$5*H6,0) -> 0 | O6: =ROUND(D6/26/8*$O$5*I6,0) -> 807692 | P6: =ROUND(D6/26/8*$P$5*J6,0) -> 157692 | Q6: =ROUND(SUM(K6:P6),0) -> 965384 | R6: =ROUND(SUM(E6:J6)*D6/26/8,0) -> 307692 | S6: =ROUND(Q6-R6,0) -> 657692
A7: PVT2500115 | B7: Nguyễn Quang Cường | C7: 45740 | D7: =VLOOKUP(A7,'[20]Template Payroll'!$B$6:$J$18,9,0) -> 8500000 | E7: 0 | F7: 0 | G7: 0 | H7: 0 | I7: 8 | J7: 0 | K7: =ROUND(D7/26/8*$K$5*E7,0) -> 0 | L7: =ROUND(D7/26/8*$L$5*F7,0) -> 0 | M7: =ROUND(D7/26/8*$M$5*G7,0) -> 0 | N7: =ROUND(D7/26/8*$N$5*H7,0) -> 0 | O7: =ROUND(D7/26/8*$O$5*I7,0) -> 980769 | P7: =ROUND(D7/26/8*$P$5*J7,0) -> 0 | Q7: =ROUND(SUM(K7:P7),0) -> 980769 | R7: =Q7 -> 980769 | S7: 0
A8: PVT2500116 | B8: Phạm Đức Kiên | C8: 44927 | D8: =VLOOKUP(A8,'[20]Template Payroll'!$B$6:$J$18,9,0) -> 7056000 | E8: 1 | F8: 9 | G8: 0 | H8: 0 | I8: 6 | J8: 2 | K8: =ROUND(D8/26/8*$K$5*E8,0) -> 50885 | L8: =ROUND(D8/26/8*$L$5*F8,0) -> 656412 | M8: =ROUND(D8/26/8*$M$5*G8,0) -> 0 | N8: =ROUND(D8/26/8*$N$5*H8,0) -> 0 | O8: =ROUND(D8/26/8*$O$5*I8,0) -> 610615 | P8: =ROUND(D8/26/8*$P$5*J8,0) -> 278169 | Q8: =ROUND(SUM(K8:P8),0) -> 1596081 | R8: =ROUND(SUM(E8:J8)*D8/26/8,0) -> 610615 | S8: =ROUND(Q8-R8,0) -> 985466
A9: PVT2500117 | B9: Nguyễn Văn Quân | C9: 45292 | D9: =VLOOKUP(A9,'[20]Template Payroll'!$B$6:$J$18,9,0) -> 6841000 | E9: 0 | F9: 0 | G9: 0 | H9: 0 | I9: 0 | J9: 0 | K9: =ROUND(D9/26/8*$K$5*E9,0) -> 0 | L9: =ROUND(D9/26/8*$L$5*F9,0) -> 0 | M9: =ROUND(D9/26/8*$M$5*G9,0) -> 0 | N9: =ROUND(D9/26/8*$N$5*H9,0) -> 0 | O9: =ROUND(D9/26/8*$O$5*I9,0) -> 0 | P9: =ROUND(D9/26/8*$P$5*J9,0) -> 0 | Q9: =ROUND(SUM(K9:P9),0) -> 0 | R9: =ROUND(SUM(E9:J9)*D9/26/8,0) -> 0 | S9: =ROUND(Q9-R9,0) -> 0
A10: PVT2500118 | B10: Ngô Văn Tuấn | C10: 45738 | D10: =VLOOKUP(A10,'[20]Template Payroll'!$B$6:$J$18,9,0) -> 11000000 | E10: 1 | F10: 9 | G10: 0 | H10: 0 | I10: 6 | J10: 2 | K10: =ROUND(D10/26/8*$K$5*E10,0) -> 79327 | L10: =ROUND(D10/26/8*$L$5*F10,0) -> 1023317 | M10: =ROUND(D10/26/8*$M$5*G10,0) -> 0 | N10: =ROUND(D10/26/8*$N$5*H10,0) -> 0 | O10: =ROUND(D10/26/8*$O$5*I10,0) -> 951923 | P10: =ROUND(D10/26/8*$P$5*J10,0) -> 433654 | Q10: =ROUND(SUM(K10:P10),0) -> 2488221 | R10: =Q10 -> 2488221 | S10: 0

Sheet NS
A1: Emp. Code | B1: Full name | C1: Joinging date | D1: Income Salary | E1: Total hour night shift | F1: Payment night shift | G1: Night shift taxable | H1: Night shift untax
A2: SLA2500111 | B2: Nguyen Van A | C2: 43466 | D2: =IFERROR(VLOOKUP(A2,'Template Payroll'!$B$5:$J$12,9,0),0) -> 47000000 | E2: 2 | F2: =ROUND((D2/26/8)*30%*E2,0) -> 135577 | G2: =F2-H2 -> 0 | H2: =F2 -> 135577
A3: PHI2500112 | B3: Nguyen Van B | C3: 43831 | D3: =IFERROR(VLOOKUP(A3,'Template Payroll'!$B$5:$J$12,9,0),0) -> 31000000 | E3: 3 | F3: =ROUND((D3/26/8)*30%*E3,0) -> 134135 | G3: =F3-H3 -> 0 | H3: =F3 -> 134135
A4: PVT2500113 | B4: Nguyễn Đức Khánh | C4: 44197 | D4: =IFERROR(VLOOKUP(A4,'Template Payroll'!$B$5:$J$12,9,0),0) -> 10448000 | E4: 4 | F4: =ROUND((D4/26/8)*30%*E4,0) -> 60277 | G4: =F4-H4 -> 0 | H4: =F4 -> 60277
A5: PVT2500114 | B5: Nguyễn Sơn Tùng | C5: 44562 | D5: =IFERROR(VLOOKUP(A5,'Template Payroll'!$B$5:$J$12,9,0),0) -> 8000000 | E5: 1.5 | F5: =ROUND((D5/26/8)*30%*E5,0) -> 17308 | G5: =F5-H5 -> 0 | H5: =F5 -> 17308
A6: PVT2500115 | B6: Nguyễn Quang Cường | C6: 45740 | D6: =IFERROR(VLOOKUP(A6,'Template Payroll'!$B$5:$J$12,9,0),0) -> 8500000 | E6: 0.5 | F6: =ROUND((D6/26/8)*30%*E6,0) -> 6130 | G6: =F6-H6 -> 0 | H6: =F6 -> 6130
A7: PVT2500116 | B7: Phạm Đức Kiên | C7: 44927 | D7: =IFERROR(VLOOKUP(A7,'Template Payroll'!$B$5:$J$12,9,0),0) -> 7056000 | E7: 1 | F7: =ROUND((D7/26/8)*30%*E7,0) -> 10177 | G7: =F7-H7 -> 0 | H7: =F7 -> 10177
A8: PVT2500117 | B8: Nguyễn Văn Quân | C8: 45292 | D8: =IFERROR(VLOOKUP(A8,'Template Payroll'!$B$5:$J$12,9,0),0) -> 6841000 | E8: 5 | F8: =ROUND((D8/26/8)*30%*E8,0) -> 49334 | G8: =F8-H8 -> 0 | H8: =F8 -> 49334
A9: PVT2500118 | B9: Ngô Văn Tuấn | C9: 45738 | D9: =IFERROR(VLOOKUP(A9,'Template Payroll'!$B$5:$J$12,9,0),0) -> 11000000 | E9: 6 | F9: =ROUND((D9/26/8)*30%*E9,0) -> 95192 | G9: =F9-H9 -> 0 | H9: =F9 -> 95192

Sheet Others
A1: No. | B1: Emp. Code | C1: Full Name | D1: Phụ cấp điều phối | E1: Ngày công tính lương | F1: Amount
A4: 1 | B4: PVT2500113 | C4: Phùng Mạnh Hà | D4: 2000000 | E4: =VLOOKUP($B4,'TimeTB 2'!$B$4:$P$11,14,0) -> 0 | F4: =D4/26*E4 -> 0
F5: =E5*D5 -> 0
A6: 2. Thâm niên CASHIER
A7: No. | B7: Emp.Code | C7: Full Name | D7: Thâm niên CASHIER | E7: Thâm niên CASHIER bổ sung | F7: Amount
A8: 1 | B8: PVT2500114 | C8: Nguyễn Đức Khánh | D8: 500000 | F8: =D8+E8 -> 500000
A9: =1+A8 -> 2 | B9: PVT2500115 | C9: Nguyễn Sơn Tùng | D9: 500000 | F9: =D9+E9 -> 500000
A12: 3. Ngày phép/công bổ sung (AL payment)
A13: No. | B13: Code | C13: Name | D13: Gross | E13: ALs | F13: Amount
A22: =ROW()-85 -> -63 | C22: =VLOOKUP($B22,#REF!,3,0) -> #REF! | D22: =IFERROR(VLOOKUP(B22,#REF!,81,0),0) -> 0 | F22: =ROUND((D22/26*E22),0) -> 0 | G22: =VLOOKUP(B22,#REF!,74,0) -> #REF! | H22: =G22-E22 -> #REF!
A23: =ROW()-85 -> -62 | C23: =VLOOKUP($B23,#REF!,3,0) -> #REF! | D23: =IFERROR(VLOOKUP(B23,#REF!,81,0),0) -> 0 | F23: =ROUND((D23/26*E23),0) -> 0 | G23: =VLOOKUP(B23,#REF!,74,0) -> #REF! | H23: =G23-E23 -> #REF!
A24: =ROW()-85 -> -61 | C24: =VLOOKUP($B24,#REF!,3,0) -> #REF! | D24: =IFERROR(VLOOKUP(B24,#REF!,81,0),0) -> 0 | F24: =ROUND((D24/26*E24),0) -> 0 | G24: =VLOOKUP(B24,#REF!,74,0) -> #REF! | H24: =G24-E24 -> #REF!
A25: =ROW()-85 -> -60 | C25: =VLOOKUP($B25,#REF!,3,0) -> #REF! | D25: =IFERROR(VLOOKUP(B25,#REF!,81,0),0) -> 0 | F25: =ROUND((D25/26*E25),0) -> 0 | G25: =VLOOKUP(B25,#REF!,74,0) -> #REF! | H25: =G25-E25 -> #REF!
A26: =ROW()-85 -> -59
C27: Total | E27: =SUM(E14:E26) -> 0 | F27: =SUM(F14:F26) -> 0

Sheet Incentive
B1: 42004 | C1: 41974 | F1: c | G1: =SUBTOTAL(9,G4:G5) -> 4600000 | H1: =SUBTOTAL(9,H4:H5) -> 0 | I1: =SUBTOTAL(9,I4:I5) -> 4000000 | J1: =SUBTOTAL(9,J4:J5) -> 600000
C2: 44561 | E2: 42339 | F2: 364 | G2: =SUBTOTAL(9,G4:G7) -> 10210000 | H2: =SUBTOTAL(9,H4:H7) -> 5610000 | I2: =SUBTOTAL(9,I4:I7) -> 4000000 | J2: =SUBTOTAL(9,J4:J7) -> 600000
A3: Emp. Code | B3: Full Name | C3: Joining date | D3: Nghỉ việc | E3: Division | F3: Dept. | G3: Incentive | H3: PP.Shipper | I3: Cashier incentive | J3: Bill
A4: PVT2500116 | B4: Phạm Đức Kiên | F4: Cashier | G4: =ROUND(SUM($H4:$J4),0) -> 2000000 | H4: 0 | I4: 2000000 | J4: 0 | K4: =VLOOKUP(A4,#REF!,36,0) -> #REF! | L4: =K4=G4 -> #REF!
A5: PVT2500117 | B5: Nguyễn Văn Quân | F5: Cashier | G5: =ROUND(SUM($H5:$J5),0) -> 2600000 | H5: 0 | I5: 2000000 | J5: 600000 | K5: =VLOOKUP(A5,#REF!,36,0) -> #REF! | L5: =K5=G5 -> #REF!
A6: PVT2500118 | B6: Ngô Văn Tuấn | F6: PP. Center | G6: =ROUND(SUM($H6:$J6),0) -> 5610000 | H6: 5610000 | K6: =VLOOKUP(A6,#REF!,36,0) -> #REF! | L6: =K6=G6 -> #REF!

Sheet Benefit tính thuế
A1: Emp. Code | B1: Full name | C1: Monthly bonus | D1: Birthday (Company) | E1: Seniority | F1: Gift (10%) | G1: Total taxable benefits
A2: SLA2500111 | B2: Nguyễn Thị Hà | D2: 200000 | G2: =SUM(C2:F2) -> 200000
A3: PHI2500112 | B3: Phùng Mạnh Hà | E3: 2000000 | G3: =SUM(C3:F3) -> 2000000
A4: PVT2500113 | B4: Nguyễn Đức Khánh | F4: 1000000 | G4: =SUM(C4:F4) -> 1000000
A5: PVT2500114 | B5: Nguyễn Sơn Tùng | C5: 500000 | F5: 750000 | G5: =SUM(C5:F5) -> 1250000
