Workbook
Name _: "SQRT"
Name _____KDX3: [1]!_____KDX3
Name ____KDX3: #N/A
Name ___a10: #N/A
Name ___atn1: #REF!
Name ___atn10: #REF!
Name ___atn2: #REF!
Name ___atn3: #REF!
Name ___atn4: #REF!
Name ___atn5: #REF!
Name ___atn6: #REF!
Name ___atn7: #REF!
Name ___atn8: #REF!
Name ___atn9: #REF!
Name ___Bia1: #N/A
Name ___Bia2: #N/A
Name ___boi1: #REF!
Name ___boi2: #REF!
Name ___BTM150: #REF!
Name ___BTM250: #REF!
Name ___BTM300: #REF!
Name ___cao1: #REF!
Name ___cao2: #REF!
Name ___cao3: #REF!
Name ___cao4: #REF!
Name ___cao5: #REF!
Name ___cao6: #REF!
Name ___coc250: #REF!
Name ___coc300: #REF!
Name ___coc350: #REF!
Name ___CON1: #REF!
Name ___CON2: #REF!
Name ___cpd1: #REF!
Name ___cpd2: #REF!
Name ___Cus1: #N/A
Name ___dai1: #REF!
Name ___dai2: #REF!
Name ___dai3: #REF!
Name ___dai4: #REF!
Name ___dai5: #REF!
Name ___dai6: #REF!
Name ___dan1: #REF!
Name ___dan2: #REF!
Name ___ddn400: #REF!
Name ___ddn600: #REF!
Name ___deo1: #REF!
Name ___deo10: #REF!
Name ___deo2: #REF!
Name ___deo3: #REF!
Name ___deo4: #REF!
Name ___deo5: #REF!
Name ___deo6: #REF!
Name ___deo7: #REF!
Name ___deo8: #REF!
Name ___deo9: #REF!
Name ___E99999: #REF!
Name ___gon4: #N/A
Name ___hom2: #N/A
Name ___KDX3: #N/A
Name ___lap1: #REF!

Sheet Template Payroll
AP1: 4400000 | AQ1: 0.08 | AR1: 0.015 | AS1: 0.01 | BA1: 0.17 | BB1: 0.03 | BC1: 0.01 | BD1: 0.005 | BF1: =2340000*20 -> 46800000 | BG1: =4960000*20 -> 99200000 | BH1: Truy thu BHYT 3% | BI1: Truy thu BHYT 1.5%
A2: No | B2: Emp. Code | C2: ID No | D2: Full name | E2: Joning Date | F2: Division | G2: Department | H2: Position | I2: Job title | J2: Income Salary | K2: Basic Salary | L2: Efficiency salary | M2: Standard working day | N2: Working day last month (21-25) | O2: Working day current month | P2: Actual Basic Salary last month (21-25) | Q2: Actual Basic Salary current month | R2: Total Actual Basic Salary | S2: Efficiency salary Advance last month (21-25) | T2: Efficiency salary Advance current month | U2: Total Efficiency salary Advance | V2: Responsibility Allows | W2: Transportation Allows | X2: Mob Allows | Y2: Meal Allows | Z2: Total Actual All Allows | AA2: Overtime | AB2: Night shift | AC2: Bonus | AD2: Acting Allowance | AE2: AL Remain | AF2: Rest of annual leave | AG2: Incentives | AH2: Other Allowance | AI2: Severance pay | AJ2: Total Gross Salary | AK2: OT untaxable | AL2: Night shift untaxable | AM2: Severance pay untaxable | AN2: Self- deduction | AO2: Qty. | AP2: AMT | AQ2: Social Ins. 8% | AR2: Health Ins. 1.5% | AS2: Jobless Ins. 1% | AT2: Total Ins. Employees paid 10.5% | AU2: Lunch Max (730,000đ) | AV2: Taxable income | AW2: Assessable income | AX2: Tax rate | AY2: Min Tax | AZ2: Monthly PIT 개인소득세 | BA2: Social Ins. 17% | BB2: Health Ins. 3% | BC2: Jobless Ins. 1% | BD2: Accident & occupational disease 0.5% | BE2: Total Ins. Employer paid 21.5% | BF2: Insurance salary (SI & HI) | BG2: Insurance salary (Jobless) | BH2: Obligation Health Insurance Employer | BI2: Obligation Health Insurance Employee | BJ2: Trade Union (Company) | BK2: Trade Union (Employee) | BL2: Support Funeral Fund | BM2: Net salary | BN2: Benefit TAX | BO2: PIT payable last year | BP2: Government funds | BQ2: Total Reduction | BR2: Total obligation of employee | BS2: Tham gia BHXH | BT2: Đối tượng tính thuế TNCN | BU2: Tham gia Công đoàn | BV2: Tham gia Tang chế | BW2: Số đám tang phát sinh trong kỳ | BX2: Email
A3: 1 | B3: SLA2500111 | D3: Nguyễn Thị Hà | E3: 27/07/2015 | F3: PVT - Store Manager | G3: Store Management | H3: Manager | I3: Store Manager - Emart Phan Van Tri | J3: 47000000 | K3: 10870000 | L3: =J3-K3 -> 36130000 | M3: 26 | N3: =IFERROR(VLOOKUP(B3,' TimeTB 1'!$C$4:$AU$5,45,0),0) -> 0 | O3: =VLOOKUP(B3,'TimeTB 2'!$C$4:$AU$5,45,0) -> 26 | P3: =ROUND(K3/M3*N3,0) -> 0 | Q3: =ROUND(K3/M3*O3,0) -> 10870000 | R3: =SUM(P3:Q3) -> 10870000 | S3: =ROUND(L3/26*N3,0) -> 0 | T3: =ROUND(L3/26*O3,0) -> 36130000 | U3: =SUM(S3:T3) -> 36130000 | V3: 0 | W3: 0 | X3: 0 | Y3: =VLOOKUP(B3,'PC cơm '!$B$3:$L$4,11,0) -> 1000000 | Z3: =SUM(V3:Y3) -> 1000000 | AA3: =VLOOKUP(B3,'OT '!$B$3:$R$4,17,0) -> 5920193 | AB3: =VLOOKUP(B3,NS!$B$3:$G$6,6,0) -> 135577 | AC3: 0 | AD3: 0 | AE3: 0 | AF3: =ROUND(J3/26*AE3,0) -> 0 | AG3: =IFERROR(VLOOKUP(B3,Incentive!$B$4:$H$6,7,0),0) -> 0 | AH3: =SUMIF(Others!$B$3:$B$10,$B3,Others!$F$3:$F$10) -> 0 | AI3: 0 | AJ3: =AI3+AH3+AG3+AF3+AD3+AC3+AB3+AA3+Z3+U3+R3+BN3 -> 54255770 | AK3: =VLOOKUP(B3,'OT '!$B$3:$T$4,19,0) -> 4112501 | AL3: =VLOOKUP(B3,NS!$B$3:$I$6,8,0) -> 135577 | AM3: =AI3 -> 0 | AN3: =IF(BT3=1,0,11000000) -> 11000000 | AO3: 4 | AP3: =AO3*$AP$1 -> 17600000 | AQ3: =BF3*$AQ$1 -> 869600 | AR3: =BF3*$AR$1 -> 163050 | AS3: =BG3*$AS$1 -> 108700 | AT3: =+AS3+AR3+AQ3 -> 1141350 | AU3: =IF(BT3=1,0,MIN(Y3,730000)) -> 730000 | AV3: =AJ3-AK3-AL3-AM3-AU3 -> 49277692 | AW3: =MAX(AV3-AN3-AP3-AT3,0) -> 19536342 | AX3: =IF(BT3=1,10%,IF(AW3>0,IF(AW3>80000000,0.35,IF(AW3>52000000,0.3,IF(AW3>32000000,0.25,IF(AW3>18000000,0.2,IF(AW3>10000000,0.15,IF(AW3>5000000,0.1,0.05)))))),0)) -> 0.2 | AY3: =IF(BT3=1,0,IF(AW3>80000000,9850000,IF(AW3>52000000,5850000,IF(AW3>32000000,3250000,IF(AW3>18000000,1650000,IF(AW3>10000000,750000,IF(AW3>5000000,250000,0))))))) -> 1650000 | AZ3: =ROUND(AW3*AX3-AY3,0) -> 2257268 | BA3: =BF3*$BA$1 -> 1847900 | BB3: =BF3*$BB$1 -> 326100 | BC3: =BG3*$BC$1 -> 108700 | BD3: =BG3*$BD$1 -> 54350 | BE3: =SUM(BA3:BD3) -> 2337050 | BF3: =MIN((IF(BS3=1,K3,0)),$BF$1) -> 10870000 | BG3: =MIN((IF(BS3=1,K3,0)),$BG$1) -> 10870000 | BH3: 0 | BI3: 0 | BJ3: =IF(BS3=1,BF3*2%,0) -> 217400 | BK3: =IF(BU3=1,40000,0) -> 40000 | BL3: =IF(BV3=0,0,IF(J3<11000000,5000,IF(J3<25000000,10000,IF(J3<40000000,15000,20000)))*BW3) -> 0 | BM3: =AJ3-AT3-AZ3-BK3-BL3-BN3-BO3-BP3 -> 50617152 | BN3: =IFERROR(VLOOKUP(B3,'Benefit tính thuế'!$B$2:$H$5,7,0),0) -> 200000 | BO3: 0 | BP3: 0 | BQ3: =AN3+AP3+AU3 -> 29330000 | BR3: =+AZ3+AT3 -> 3398618 | BS3: 1 | BT3: 0 | BU3: 1 | BV3: 0 | BW3: 20

Sheet PC cơm 
A1: No | B1: Emp. Code | C1: Full Name | D1: Join Date | E1: Dept/Div | F1: Actual work days (excl. Holidays) | G1: OT days ≥ 4 hours | H1: Work days on Holidays | I1: Amount for actual work days (excl. Holidays) | J1: Amount for OT days ≥ 4 hours | K1: Amount for work on Holidays | L1: Total Amount | M1: Notes
I2: 40000 | J2: 40000 | K2: 80000
A3: =ROW()-6 -> -3 | B3: SLA2500111 | C3: Nguyễn Thị Hà | D3: 43466 | E3: Store Management | F3: =VLOOKUP($B3,'TimeTB 2'!$C$4:$AX$5,46,0) -> 25 | G3: =VLOOKUP($B3,'TimeTB 2'!$C$4:$AX$5,48,0) -> 0 | H3: =VLOOKUP($B3,'TimeTB 2'!$C$4:$AX$5,47,0) -> 0 | I3: =F3*$I$2 -> 1000000 | J3: =G3*$J$2 -> 0 | K3: =H3*$K$2 -> 0 | L3: =SUM(I3:K3) -> 1000000
A4: =ROW()-6 -> -2 | B4: PHI2500112 | C4: Phùng Mạnh Hà | D4: 43831 | E4: Cooperate Function | F4: =VLOOKUP(B4,'TimeTB 2'!$C$4:$AX$5,46,0) -> 26 | G4: =VLOOKUP($B4,'TimeTB 2'!$C$4:$AX$5,48,0) -> 0 | H4: =VLOOKUP($B4,'TimeTB 2'!$C$4:$AX$5,47,0) -> 1 | I4: =F4*$I$2 -> 1040000 | J4: =G4*$J$2 -> 0 | K4: =H4*$K$2 -> 80000 | L4: =SUM(I4:K4) -> 1120000

Sheet TimeTB 2
B1: TT | C1: Emp. Code | D1: Full Name | E1: Joinging date | F1: Dept | G1: Sub. Dept | H1: Job Title | I1: REMARK | J1: 45742 | M1: =EOMONTH(J1,0)+1 -> 45748 | AO1: Total OFF days | AP1: Unpaid leave | AQ1: Nghỉ hưởng lương (Nghỉ Phép/ Nghỉ Bù/ Nghỉ chế độ/ Nghỉ Lễ) | AR1: Actual working days | AS1: Total | AT1: Work adjustment | AU1: Total paid workdays | AV1: Total working days paid regular meals | AW1: Total working days pay for meals during Tet holidays | AX1: Total workdays pay for overtime meals | AY1: Note
J2: =J1 -> 45742 | K2: =+J2+1 -> 45743 | L2: =+K2+1 -> 45744 | M2: =+L2+1 -> 45745 | N2: =+M2+1 -> 45746 | O2: =+N2+1 -> 45747 | P2: =+O2+1 -> 45748 | Q2: =+P2+1 -> 45749 | R2: =+Q2+1 -> 45750 | ... AN2: =+AM2+1 -> 45772
J3: =TEXT(J2,"ddd") -> Wed | K3: =TEXT(K2,"ddd") -> Thu | L3: =TEXT(L2,"ddd") -> Fri | M3: =TEXT(M2,"ddd") -> Sat | N3: =TEXT(N2,"ddd") -> Sun | O3: =TEXT(O2,"ddd") -> Mon | P3: =TEXT(P2,"ddd") -> Tue | Q3: =TEXT(Q2,"ddd") -> Wed | ... AN3: =TEXT(AN2,"ddd") -> Fri
A4: 1 | B4: =ROW()-10 -> -6 | C4: SLA2500111 | D4: Nguyễn Thị Hà | E4: 43466 | H4: Store Manager - Emart Phan Van Tri | J4: X | K4: X | L4: OFF | M4: X | N4: X | O4: X | P4: X | Q4: X | R4: X | T4: OFF | U4: X | V4: HL | W4: X | X4: X | Y4: X | Z4: OFF | AA4: X | AB4: X | AC4: X | AD4: X | AE4: X | AF4: X | AG4: X | AH4: X | AI4: OFF | AJ4: X | AK4: X | AL4: X | AM4: X | AN4: X | AO4: =COUNTIFS($J4:$AN4,"OFF ")+COUNTIFS($J4:$AN4,"OFF") -> 4 | AP4: =+COUNTIF(J4:AN4,"UP")+0.5*COUNTIF(J4:AN4,"1/2UP")+COUNTIFS(J4:AN4,"SL1")+COUNTIFS(J4:AN4,"ML")+COUNTIFS(J4:AN4,"CC") -> 0 | AQ4: =COUNTIF($J4:$AN4,"AL")+0.5*(COUNTIF($J4:$AN4,"1/2AL"))+COUNTIF($J4:$AN4,"CL")+0.5*(COUNTIF($J4:$AN4,"1/2CL"))+COUNTIF($J4:$AN4,"LS")+COUNTIF($J4:$AN4,"HL") -> 1 | AR4: =COUNTIF(J4:AN4,"X")+(COUNTIF(J4:AN4,"FP"))+COUNTIF(J4:AN4,"SL2")+(COUNTIF(J4:AN4,"LL"))+0.5*COUNTIF(J4:AN4,"1/2AL")+0.5*COUNTIF(J4:AN4,"1/2CL")+0.5*COUNTIF(J4:AN4,"1/2UP") -> 25 | AS4: =+AQ4+AR4 -> 26 | AU4: =MIN((AS4+AT4),26) -> 26 | AV4: =COUNTIF(J4:AN4,"X") -> 25 | AW4: =COUNTIF(V4:V4,"X") -> 0 | AX4: 0
A5: =+A3+1 -> 1 | B5: =ROW()-10 -> -5 | C5: PHI2500112 | D5: Phùng Mạnh Hà | E5: 43831 | H5: Corporate Function Manager | J5: X | K5: X | L5: X | M5: OFF | N5: X | O5: X | P5: X | Q5: X | R5: X | S5: X | T5: X | U5: OFF | V5: X | W5: X | X5: X | Y5: X | Z5: X | AA5: OFF | AB5: X | AC5: X | AD5: X | AE5: X | AF5: X | AG5: X | AH5: OFF | AI5: X | AJ5: X | AK5: X | AL5: X | AM5: X | AN5: OFF | AO5: =COUNTIFS($J5:$AN5,"OFF ")+COUNTIFS($J5:$AN5,"OFF") -> 5 | AP5: =+COUNTIF(J5:AN5,"UP")+0.5*COUNTIF(J5:AN5,"1/2UP")+COUNTIFS(J5:AN5,"SL1")+COUNTIFS(J5:AN5,"ML")+COUNTIFS(J5:AN5,"CC") -> 0 | AQ5: =COUNTIF($J5:$AN5,"AL")+0.5*(COUNTIF($J5:$AN5,"1/2AL"))+COUNTIF($J5:$AN5,"CL")+0.5*(COUNTIF($J5:$AN5,"1/2CL"))+COUNTIF($J5:$AN5,"LS")+COUNTIF($J5:$AN5,"HL") -> 0 | AR5: =COUNTIF(J5:AN5,"X")+(COUNTIF(J5:AN5,"FP"))+COUNTIF(J5:AN5,"SL2")+(COUNTIF(J5:AN5,"LL"))+0.5*COUNTIF(J5:AN5,"1/2AL")+0.5*COUNTIF(J5:AN5,"1/2CL")+0.5*COUNTIF(J5:AN5,"1/2UP") -> 26 | AS5: =+AQ5+AR5 -> 26 | AU5: =MIN((AS5+AT5),26) -> 26 | AV5: =COUNTIF(J5:AN5,"X") -> 26 | AW5: =COUNTIF(V5:V5,"X") -> 1 | AX5: 0
C7: Quy định ký hiệu chấm công
C8: X | D8: Đi làm 01 ngày
C9: HL | D9: Nghĩ Lễ, Tết
C10: OFF | D10: Nghỉ 1 ngày OFFca hàng tuần
C11: AL | D11: Annual Leave/ Nghỉ phép năm 01 ngày
C12: 1/2AL | D12: 1/2 Annual Leave/ Nghỉ phép năm 1/2 ngày + Đi làm 1/2 ngày
C13: FP | D13: Full paid leave for personal affairs/Nghỉ việc riêng có hưởng lương 01 ngày (kết hôn, tang chế...)
C14: UP | D14: Unpaid leave/ Nghỉ việc riêng không hưởng lương 01 ngày
C15: 1/2UP | D15: 1/2 Unpaid leave/ Nghỉ việc không hưởng lương 1/2 ngày + Đi làm 1/2 ngày
C16: SL1 | D16: Sick leave / Nghỉ bệnh (hưởng BHXH)
C17: ML | D17: Maternity leave / Nghỉ thai sản
C18: CC | D18: Children care leave / Nghỉ con ốm/ vợ sinh (hưởng BHXH)
C19: LL | D19: Lactation leave/ Về sớm/đi trễ 1 tiếng/nghỉ 1 ngày sau 7 ngày làm việc
... C22: 1/2CL | D22: 1/2 Compensation leave ( in-lieu day-off)/ Nghỉ bù 1/2 ngày + Đi làm 1/2 ngày

Sheet  TimeTB 1
A1: TT | B1: Division | C1: Emp. Code | D1: Full Name | E1: Bộ Phận | F1: Joinging date | G1: 45444 | I1: 45689 | AK1: Tổng ngày Off | AL1: Total days/month | AM1: Paid Leave (Annual Leave / Compensatory Leave / Policy Leave / Public Holiday) | AN1: Total Paid Leave Days | AO1: Total Unpaid Leave Days | AP1: Holiday | AQ1: Compensation | AR1: OT Sunday | AS1: OT Holiday | AT1: Actual Working Days | AU1: SALARY CALCULATION DAYS
G2: 45411 | H2: 45412 | I2: 45566 | J2: 45567 | K2: 45568 | L2: 45569 | M2: 45570 | N2: 45571 | O2: 45572 | P2: 45573 | Q2: 45574 | R2: 45575 | S2: 45576 | T2: 45577 | U2: 45578 | V2: 45579 | W2: 45580 | X2: 45581 | Y2: 45582 | Z2: 45583 | AA2: 45584 | AB2: 45585 | AC2: 45586 | AD2: 45587 | AE2: 45588 | AF2: 45589 | AG2: 45590 | AH2: =1+AG2 -> 45591 | AI2: =1+AH2 -> 45592
G3: Sun | H3: Mon | I3: Tue | J3: Wed | K3: Thu | L3: Fri | M3: Sat | N3: Sun | O3: Mon | P3: Tue | Q3: Wed | R3: Thu | S3: Fri | T3: Sat | U3: Sun | V3: Mon | W3: Tue | X3: Wed | Y3: Thu | Z3: Fri | AA3: Sat | AB3: Sun | AC3: Mon | AD3: Tue | AE3: Wed | AF3: Thu | AG3: Fri | AH3: Mon | AI3: Mon | AJ3: Sat
A4: 1 | C4: PVT2500115 | D4: Nguyễn Văn Quân | F4: 45740 | G4: GV - PP. Center | H4: Staff | AF4: X | AG4: X | AK4: =COUNTIF(G4:AJ4,"OFF") -> 0 | AL4: =COUNTA(G4:AJ4) -> 4 | AM4: =COUNTIF(G4:AJ4,#REF!)+(COUNTIF(G4:AJ4,#REF!)/2) -> 0 | AN4: =COUNTIF(G4:AJ4,#REF!)+(COUNTIF(G4:AJ4,#REF!)/2) -> 0 | AO4: =COUNTIF(G4:AJ4,#REF!)+(COUNTIF(G4:AJ4,#REF!)/2)+COUNTIF(G4:AJ4,#REF!) -> 0 | AP4: =COUNTIF(G4:AJ4,#REF!) -> 0 | AQ4: =COUNTIF(G4:AJ4,#REF!)+(COUNTIF(G4:AJ4,#REF!)/2) -> 0 | AR4: =COUNTIF(G4:AJ4,#REF!)+(COUNTIF(G4:AJ4,#REF!)/2) -> 0 | AS4: =COUNTIF(G4:AJ4,#REF!)+(COUNTIF(G4:AJ4,#REF!)/2) -> 0 | AT4: =COUNTIF(G4:AG4,"X") -> 2 | AU4: =IF(OR(AT4=26,AT4=26),26,AT4) -> 2
A5: 2 | C5: PVT2500118 | D5: Ngô Văn Tuấn | F5: 45738 | G5: GV - PP. Center | H5: Staff | AD5: X | AE5: X | AF5: X | AG5: X | AK5: =COUNTIF(G5:AJ5,"OFF") -> 0 | AL5: =COUNTA(G5:AJ5) -> 6 | AM5: =COUNTIF(G5:AJ5,#REF!)+(COUNTIF(G5:AJ5,#REF!)/2) -> 0 | AN5: =COUNTIF(G5:AJ5,#REF!)+(COUNTIF(G5:AJ5,#REF!)/2) -> 0 | AO5: =COUNTIF(G5:AJ5,#REF!)+(COUNTIF(G5:AJ5,#REF!)/2)+COUNTIF(G5:AJ5,#REF!) -> 0 | AP5: =COUNTIF(G5:AJ5,#REF!) -> 0 | AQ5: =COUNTIF(G5:AJ5,#REF!)+(COUNTIF(G5:AJ5,#REF!)/2) -> 0 | AR5: =COUNTIF(G5:AJ5,#REF!)+(COUNTIF(G5:AJ5,#REF!)/2) -> 0 | AS5: =COUNTIF(G5:AJ5,#REF!)+(COUNTIF(G5:AJ5,#REF!)/2) -> 0 | AT5: =COUNTIF(G5:AG5,"X") -> 4 | AU5: =IF(OR(AT5=26,AT5=26),26,AT5) -> 4 | AX5: =VLOOKUP(C5,[20]Timetable_T03!$B$9:$AS$19,44,0) -> #N/A
A6: =ROW()-21 -> -15 | AK6: =COUNTIF(G6:AJ6,"OFF") -> 0 | AL6: =COUNTA(G6:AJ6) -> 0 | AM6: =COUNTIF(G6:AJ6,#REF!)+(COUNTIF(G6:AJ6,#REF!)/2) -> 0 | AN6: =COUNTIF(G6:AJ6,#REF!)+(COUNTIF(G6:AJ6,#REF!)/2) -> 0 | AO6: =COUNTIF(G6:AJ6,#REF!)+(COUNTIF(G6:AJ6,#REF!)/2)+COUNTIF(G6:AJ6,#REF!) -> 0 | AP6: =COUNTIF(G6:AJ6,#REF!) -> 0 | AQ6: =COUNTIF(G6:AJ6,#REF!)+(COUNTIF(G6:AJ6,#REF!)/2) -> 0 | AR6: =COUNTIF(G6:AJ6,#REF!)+(COUNTIF(G6:AJ6,#REF!)/2) -> 0 | AS6: =COUNTIF(G6:AJ6,#REF!)+(COUNTIF(G6:AJ6,#REF!)/2) -> 0 | AT6: =COUNTIF(G6:AG6,"X") -> 0 | AU6: =IF(OR(AT6=26,AT6=26),26,AT6) -> 0
A7: =ROW()-21 -> -14 | AK7: =COUNTIF(G7:AJ7,"OFF") -> 0 | AL7: =COUNTA(G7:AJ7) -> 0 | AM7: =COUNTIF(G7:AJ7,#REF!)+(COUNTIF(G7:AJ7,#REF!)/2) -> 0 | AN7: =COUNTIF(G7:AJ7,#REF!)+(COUNTIF(G7:AJ7,#REF!)/2) -> 0 | AO7: =COUNTIF(G7:AJ7,#REF!)+(COUNTIF(G7:AJ7,#REF!)/2)+COUNTIF(G7:AJ7,#REF!) -> 0 | AP7: =COUNTIF(G7:AJ7,#REF!) -> 0 | AQ7: =COUNTIF(G7:AJ7,#REF!)+(COUNTIF(G7:AJ7,#REF!)/2) -> 0 | AR7: =COUNTIF(G7:AJ7,#REF!)+(COUNTIF(G7:AJ7,#REF!)/2) -> 0 | AS7: =COUNTIF(G7:AJ7,#REF!)+(COUNTIF(G7:AJ7,#REF!)/2) -> 0 | AT7: =COUNTIF(G7:AG7,"X") -> 0 | AU7: =IF(OR(AT7=26,AT7=26),26,AT7) -> 0
A8: =ROW()-21 -> -13 | AK8: =COUNTIF(G8:AJ8,"OFF") -> 0 | AL8: =COUNTA(G8:AJ8) -> 0 | AM8: =COUNTIF(G8:AJ8,#REF!)+(COUNTIF(G8:AJ8,#REF!)/2) -> 0 | AN8: =COUNTIF(G8:AJ8,#REF!)+(COUNTIF(G8:AJ8,#REF!)/2) -> 0 | AO8: =COUNTIF(G8:AJ8,#REF!)+(COUNTIF(G8:AJ8,#REF!)/2)+COUNTIF(G8:AJ8,#REF!) -> 0 | AP8: =COUNTIF(G8:AJ8,#REF!) -> 0 | AQ8: =COUNTIF(G8:AJ8,#REF!)+(COUNTIF(G8:AJ8,#REF!)/2) -> 0 | AR8: =COUNTIF(G8:AJ8,#REF!)+(COUNTIF(G8:AJ8,#REF!)/2) -> 0 | AS8: =COUNTIF(G8:AJ8,#REF!)+(COUNTIF(G8:AJ8,#REF!)/2) -> 0 | AT8: =COUNTIF(G8:AG8,"X") -> 0 | AU8: =IF(OR(AT8=26,AT8=26),26,AT8) -> 0
A9: =ROW()-21 -> -12 | AK9: =COUNTIF(G9:AJ9,"OFF") -> 0 | AL9: =COUNTA(G9:AJ9) -> 0 | AM9: =COUNTIF(G9:AJ9,#REF!)+(COUNTIF(G9:AJ9,#REF!)/2) -> 0 | AN9: =COUNTIF(G9:AJ9,#REF!)+(COUNTIF(G9:AJ9,#REF!)/2) -> 0 | AO9: =COUNTIF(G9:AJ9,#REF!)+(COUNTIF(G9:AJ9,#REF!)/2)+COUNTIF(G9:AJ9,#REF!) -> 0 | AP9: =COUNTIF(G9:AJ9,#REF!) -> 0 | AQ9: =COUNTIF(G9:AJ9,#REF!)+(COUNTIF(G9:AJ9,#REF!)/2) -> 0 | AR9: =COUNTIF(G9:AJ9,#REF!)+(COUNTIF(G9:AJ9,#REF!)/2) -> 0 | AS9: =COUNTIF(G9:AJ9,#REF!)+(COUNTIF(G9:AJ9,#REF!)/2) -> 0 | AT9: =COUNTIF(G9:AG9,"X") -> 0 | AU9: =IF(OR(AT9=26,AT9=26),26,AT9) -> 0
A10: =ROW()-21 -> -11 | AH10: X | AK10: =COUNTIF(G10:AJ10,"OFF") -> 0 | AL10: =COUNTA(G10:AJ10) -> 1 | AM10: =COUNTIF(G10:AJ10,#REF!)+(COUNTIF(G10:AJ10,#REF!)/2) -> 0 | AN10: =COUNTIF(G10:AJ10,#REF!)+(COUNTIF(G10:AJ10,#REF!)/2) -> 0 | AO10: =COUNTIF(G10:AJ10,#REF!)+(COUNTIF(G10:AJ10,#REF!)/2)+COUNTIF(G10:AJ10,#REF!) -> 0 | AP10: =COUNTIF(G10:AJ10,#REF!) -> 0 | AQ10: =COUNTIF(G10:AJ10,#REF!)+(COUNTIF(G10:AJ10,#REF!)/2) -> 0 | AR10: =COUNTIF(G10:AJ10,#REF!)+(COUNTIF(G10:AJ10,#REF!)/2) -> 0 | AS10: =COUNTIF(G10:AJ10,#REF!)+(COUNTIF(G10:AJ10,#REF!)/2) -> 0 | AT10: =COUNTIF(G10:AG10,"X") -> 0 | AU10: =IF(OR(AT10=26,AT10=26),26,AT10) -> 0
A11: Total | AK11: =SUM(AK4:AK10) -> 0 | AL11: =SUM(AL4:AL10) -> 11 | AM11: =SUM(AM4:AM10) -> 0 | AN11: =SUM(AN4:AN10) -> 0 | AO11: =SUM(AO4:AO10) -> 0 | AP11: =SUM(AP4:AP10) -> 0 | AQ11: =SUM(AQ4:AQ10) -> 0 | AR11: =SUM(AR4:AR10) -> 0 | ... AU11: =SUM(AU4:AU10) -> 6 | AV11: =SUM(AV10:AV10) -> 0
C15: Quy định ký hiệu chấm công
C16: X | D16: Đi làm 01 ngày
C17: HL | D17: Nghĩ Lễ, Tết
C18: OFF | D18: Nghỉ 1 ngày OFFca hàng tuần
C19: AL | D19: Annual Leave/ Nghỉ phép năm 01 ngày
C20: 1/2AL | D20: 1/2 Annual Leave/ Nghỉ phép năm 1/2 ngày + Đi làm 1/2 ngày
C21: FP | D21: Full paid leave for personal affairs/Nghỉ việc riêng có hưởng lương 01 ngày (kết hôn, tang chế...)
C22: UP | D22: Unpaid leave/ Nghỉ việc riêng không hưởng lương 01 ngày
C23: 1/2UP | D23: 1/2 Unpaid leave/ Nghỉ việc không hưởng lương 1/2 ngày + Đi làm 1/2 ngày
C24: SL1 | D24: Sick leave / Nghỉ bệnh (hưởng BHXH)
C25: ML | D25: Maternity leave / Nghỉ thai sản
C26: CC | D26: Children care leave / Nghỉ con ốm/ vợ sinh (hưởng BHXH)
C27: LL | D27: Lactation leave/ Về sớm/đi trễ 1 tiếng/nghỉ 1 ngày sau 7 ngày làm việc
... C30: 1/2CL | D30: 1/2 Compensation leave ( in-lieu day-off)/ Nghỉ bù 1/2 ngày + Đi làm 1/2 ngày

Sheet OT 
E1: Income salary | F1: Hour | L1: Overtime payment per hour | R1: Total payment (VND) | S1: Overtime taxable | T1: OT.Untaxable
A2: No. | B2: Emp. Code | C2: Full name | D2: Joinging date | E2: VND | F2: 1.5 | G2: 2.15 | H2: 2 | I2: 2.8 | J2: 3 | K2: 4.1 | L2: 1.5 | M2: 2.15 | N2: 2 | O2: 2.8 | P2: 3 | Q2: 4.1
A3: =ROW()-6 -> -3 | B3: SLA2500111 | C3: Nguyễn Thị Hà | D3: 43466 | E3: =VLOOKUP(B3,'Template Payroll'!$B$3:$J$3,9,0) -> 47000000 | F3: 0 | G3: 0 | H3: 0 | I3: 0 | J3: 6 | K3: 2 | L3: =ROUND(E3/26/8*$L$2*F3,0) -> 0 | M3: =ROUND(E3/26/8*$M$2*G3,0) -> 0 | N3: =ROUND(E3/26/8*$N$2*H3,0) -> 0 | O3: =ROUND(E3/26/8*$O$2*I3,0) -> 0 | P3: =ROUND(E3/26/8*$P$2*J3,0) -> 4067308 | Q3: =ROUND(E3/26/8*$Q$2*K3,0) -> 1852885 | R3: =ROUND(SUM(L3:Q3),0) -> 5920193 | S3: =ROUND(SUM(F3:K3)*E3/26/8,0) -> 1807692 | T3: =ROUND(R3-S3,0) -> 4112501
A4: =ROW()-6 -> -2 | B4: PHI2500112 | C4: Phùng Mạnh Hà | D4: 43831 | E4: {=VLOOKUP(E9B4,'Template Payroll'!$B$3:$J$3,9,0)} -> #NAME? | F4: 0 | G4: 6 | H4: 0 | I4: 0 | J4: 6 | K4: 2 | L4: =ROUND(E4/26/8*$L$2*F4,0) -> #NAME? | M4: =ROUND(E4/26/8*$M$2*G4,0) -> #NAME? | N4: =ROUND(E4/26/8*$N$2*H4,0) -> #NAME? | O4: =ROUND(E4/26/8*$O$2*I4,0) -> #NAME? | P4: =ROUND(E4/26/8*$P$2*J4,0) -> #NAME? | Q4: =ROUND(E4/26/8*$Q$2*K4,0) -> #NAME? | R4: =ROUND(SUM(L4:Q4),0) -> #NAME? | S4: =ROUND(SUM(F4:K4)*E4/26/8,0) -> #NAME? | T4: =ROUND(R4-S4,0) -> #NAME?

Sheet NS
A1: No. | B1: Emp. Code | C1: Full name | D1: Joinging date | E1: Income Salary | F1: Total hour night shift | G1: Payment night shift | H1: Night shift taxable | I1: Night shift untax
B2: 1 | C2: =B2+1 -> 2 | D2: 3 | E2: =D2+1 -> 4 | F2: =E2+1 -> 5 | G2: =F2+1 -> 6 | H2: =G2+1 -> 7 | I2: =H2+1 -> 8
A3: =ROW()-8 -> -5 | B3: SLA2500111 | C3: Nguyen Van A | D3: 43466 | E3: =IFERROR(VLOOKUP(B3,'Template Payroll'!$B$3:$J$3,9,0),0) -> 47000000 | F3: 2 | G3: =ROUND((E3/26/8)*30%*F3,0) -> 135577 | H3: =G3-I3 -> 0 | I3: =G3 -> 135577
A4: =ROW()-8 -> -4 | B4: PHI2500112 | C4: Nguyen Van B | D4: 43831 | E4: =IFERROR(VLOOKUP(B4,'Template Payroll'!$B$3:$J$3,9,0),0) -> 0 | F4: 3 | G4: =ROUND((E4/26/8)*30%*F4,0) -> 0 | H4: =G4-I4 -> 0 | I4: =G4 -> 0
A5: =ROW()-8 -> -3 | B5: PVT2500113 | C5: Nguyễn Đức Khánh | D5: 44197 | E5: =IFERROR(VLOOKUP(B5,'Template Payroll'!$B$3:$J$3,9,0),0) -> 0 | F5: 4 | G5: =ROUND((E5/26/8)*30%*F5,0) -> 0 | H5: =G5-I5 -> 0 | I5: =G5 -> 0
A6: =ROW()-8 -> -2 | B6: PVT2500114 | C6: Nguyễn Sơn Tùng | D6: 44562 | E6: =IFERROR(VLOOKUP(B6,'Template Payroll'!$B$3:$J$3,9,0),0) -> 0 | F6: 1.5 | G6: =ROUND((E6/26/8)*30%*F6,0) -> 0 | H6: =G6-I6 -> 0 | I6: =G6 -> 0

Sheet Incentive
C1: 42004 | D1: 41974 | G1: c | H1: =SUBTOTAL(9,H4:H5) -> 4600000 | I1: =SUBTOTAL(9,I4:I5) -> 0 | J1: =SUBTOTAL(9,J4:J5) -> 4000000 | K1: =SUBTOTAL(9,K4:K5) -> 600000
D2: 44561 | F2: 42339 | G2: 364 | H2: =SUBTOTAL(9,H4:H7) -> 10210000 | I2: =SUBTOTAL(9,I4:I7) -> 5610000 | J2: =SUBTOTAL(9,J4:J7) -> 4000000 | K2: =SUBTOTAL(9,K4:K7) -> 600000
A3: No. | B3: Emp. Code | C3: Full Name | D3: Joining date | E3: Nghỉ việc | F3: Division | G3: Dept. | H3: Incentive | I3: PP.Shipper | J3: Cashier incentive | K3: Bill
A4: =SUBTOTAL(3,$B$4:B4) -> 1 | B4: PVT2500116 | C4: Phạm Đức Kiên | G4: Cashier | H4: =ROUND(SUM($I4:$K4),0) -> 2000000 | I4: 0 | J4: 2000000 | K4: 0 | L4: =VLOOKUP(B4,#REF!,36,0) -> #REF! | M4: =L4=H4 -> #REF!
A5: =SUBTOTAL(3,$B$4:B5) -> 2 | B5: PVT2500117 | C5: Nguyễn Văn Quân | G5: Cashier | H5: =ROUND(SUM($I5:$K5),0) -> 2600000 | I5: 0 | J5: 2000000 | K5: 600000 | L5: =VLOOKUP(B5,#REF!,36,0) -> #REF! | M5: =L5=H5 -> #REF!
A6: =SUBTOTAL(3,$B$4:B6) -> 3 | B6: PVT2500118 | C6: Ngô Văn Tuấn | G6: PP. Center | H6: =ROUND(SUM($I6:$K6),0) -> 5610000 | I6: 5610000 | L6: =VLOOKUP(B6,#REF!,36,0) -> #REF! | M6: =L6=H6 -> #REF!
A8: Total | H8: =SUM(H4:H7) -> 10210000 | I8: =SUM(I4:I7) -> 5610000 | J8: =SUM(J4:J7) -> 4000000 | K8: =SUM(K4:K7) -> 600000 | L8: =H8-I8-J8-K8 -> 0

Sheet Others
A1: No. | B1: Emp. Code | C1: Full Name | D1: Phụ cấp điều phối | E1: Ngày công tính lương | F1: Amount
A4: 1 | B4: PVT2500113 | C4: Phùng Mạnh Hà | D4: 2000000 | E4: =VLOOKUP(B4,'TimeTB 2'!$C$4:$AU$5,45,0) -> #N/A | F4: =D4/26*E4 -> #N/A
F5: =E5*D5 -> 0
C6: Total | D6: =SUM(D4:D5) -> 2000000 | F6: =SUM(F4:F5) -> #N/A
A7: 2. Thâm niên CASHIER
A8: No. | B8: Emp.Code | C8: Full Name | D8: Thâm niên CASHIER | E8: Thâm niên CASHIER bổ sung | F8: Amount
A9: 1 | B9: PVT2500114 | C9: Nguyễn Đức Khánh | D9: 500000 | F9: =D9+E9 -> 500000
A10: =1+A9 -> 2 | B10: PVT2500115 | C10: Nguyễn Sơn Tùng | D10: 500000 | F10: =D10+E10 -> 500000
C11: Total | F11: =SUM(F9:F10) -> 1000000
A14: 3. Ngày phép/công bổ sung (AL payment)
A15: No. | B15: Code | C15: Name | D15: Gross | E15: ALs | F15: Amount
A24: =ROW()-85 -> -61 | C24: =VLOOKUP($B24,#REF!,3,0) -> #REF! | D24: =IFERROR(VLOOKUP(B24,#REF!,81,0),0) -> 0 | F24: =ROUND((D24/26*E24),0) -> 0 | G24: =VLOOKUP(B24,#REF!,74,0) -> #REF! | H24: =G24-E24 -> #REF!
A25: =ROW()-85 -> -60 | C25: =VLOOKUP($B25,#REF!,3,0) -> #REF! | D25: =IFERROR(VLOOKUP(B25,#REF!,81,0),0) -> 0 | F25: =ROUND((D25/26*E25),0) -> 0 | G25: =VLOOKUP(B25,#REF!,74,0) -> #REF! | H25: =G25-E25 -> #REF!
A26: =ROW()-85 -> -59 | C26: =VLOOKUP($B26,#REF!,3,0) -> #REF! | D26: =IFERROR(VLOOKUP(B26,#REF!,81,0),0) -> 0 | F26: =ROUND((D26/26*E26),0) -> 0 | G26: =VLOOKUP(B26,#REF!,74,0) -> #REF! | H26: =G26-E26 -> #REF!
A27: =ROW()-85 -> -58 | C27: =VLOOKUP($B27,#REF!,3,0) -> #REF! | D27: =IFERROR(VLOOKUP(B27,#REF!,81,0),0) -> 0 | F27: =ROUND((D27/26*E27),0) -> 0 | G27: =VLOOKUP(B27,#REF!,74,0) -> #REF! | H27: =G27-E27 -> #REF!
A28: =ROW()-85 -> -57
C29: Total | E29: =SUM(E16:E28) -> 0 | F29: =SUM(F16:F28) -> 0

Sheet Benefit tính thuế
A1: TT | B1: Emp. Code | C1: Full name | D1: Monthly bonus | E1: Birthday (Company) | F1: Seniority | G1: Gift (10%) | H1: Total taxable benefits
A2: =ROW()-1 -> 1 | B2: SLA2500111 | C2: Nguyễn Thị Hà | E2: 200000 | H2: =SUM(D2:G2) -> 200000
A3: =ROW()-1 -> 2 | B3: PHI2500112 | C3: Phùng Mạnh Hà | F3: 2000000 | H3: =SUM(D3:G3) -> 2000000
A4: =ROW()-1 -> 3 | B4: PVT2500113 | C4: Nguyễn Đức Khánh | G4: 1000000 | H4: =SUM(D4:G4) -> 1000000
A5: =ROW()-1 -> 4 | B5: PVT2500114 | C5: Nguyễn Sơn Tùng | D5: 500000 | G5: 750000 | H5: =SUM(D5:G5) -> 1250000
D6: =SUM(D2:D5) -> 500000 | E6: =SUM(E2:E5) -> 200000 | F6: =SUM(F2:F5) -> 2000000 | G6: =SUM(G2:G5) -> 1750000 | H6: =SUM(H2:H5) -> 4450000
